Workbook

Sheet Underwriting Dashboard
B2: AUTO LOAN UNDERWRITING MODEL
B4: Consumer Credit Risk Assessment | Quanthaven Labs LLC
B6: ▸ BORROWER INPUTS | E6: ▸ CALCULATED RISK METRICS
B7: Credit Score | C7: 720 | E7: Loan Amount | F7: =C10-C11 -> 40000
B8: Annual Gross Income | C8: 72000 | E8: Monthly Interest Rate | F8: =C13/12 -> 0.0062416667
B9: Monthly Non-Auto Debt Payments | C9: 450 | E9: Est. Monthly Payment | F9: =IFERROR(PMT(F8,C12,-F7),0) -> 801.32788
B10: Vehicle Purchase Price | C10: 40000 | E10: Back-End DTI (incl. auto) | F10: =(C9+F9)/(C8/12) -> 0.20855465
B11: Down Payment | C11: 0 | E11: Loan-to-Value (LTV) | F11: =IFERROR(F7/C10,0) -> 1
B12: Loan Term (Months) | C12: 60 | E12: Credit Tier | F12: =IF(C7>=750,"Super-Prime",IF(C7>=700,"Prime",IF(C7>=650,"Near-Prime","Sub-Prime"))) -> Prime
B13: Annual Interest Rate (APR) | C13: 0.0749 | E13: Negative Equity at Funding? | F13: =IF(F11>1,"Yes — LTV exceeds 100%","No") -> No
B15: ▸ LENDER POLICY THRESHOLDS (editable) | E15: ▸ APPROVAL SCORECARD
B16: Max Back-End DTI | C16: 0.45 | E16: Credit Score Check | F16: =IF(C7>=C18,"✔ PASS","✘ FAIL") -> ✔ PASS
B17: Max LTV at Origination | C17: 1.1 | E17: DTI Check | F17: =IF(F10<=C16,"✔ PASS","✘ FAIL") -> ✔ PASS
B18: Min Credit Score | C18: 620 | E18: LTV Check | F18: =IF(F11<=C17,"✔ PASS","✘ FAIL") -> ✔ PASS
B19: Max Loan Term (Months) | C19: 72 | E19: Loan Term Check | F19: =IF(C12<=C19,"✔ PASS","✘ FAIL") -> ✔ PASS
B21: ▸ NOTES (blue = input | black = formula) | E21: ▸ OVERALL APPROVAL LIKELIHOOD
E22: =IF(AND(F16="✔ PASS",F17="✔ PASS",F18="✔ PASS",F19="✔ PASS"),"LIKELY APPROVED",IF(COUNTIF(F16:F19,"✘ FAIL")=1,"CONDITIONAL — REVIEW REQUIRED","LIKELY DECLINED")) -> LIKELY APPROVED

Sheet Amortization Schedule
B2: LOAN AMORTIZATION SCHEDULE
B4: Driven by Underwriting Dashboard inputs | Quanthaven Labs LLC
B6: Loan Amount | C6: Monthly Payment | D6: Total Interest | E6: Total Cost | F6: APR | G6: Term
B7: ='Underwriting Dashboard'!F7 -> 40000 | C7: ='Underwriting Dashboard'!F9 -> 801.32788 | D7: =IF(B7>0,C7*'Underwriting Dashboard'!C12-B7,0) -> 8079.6727 | E7: =C7*'Underwriting Dashboard'!C12 -> 48079.673 | F7: ='Underwriting Dashboard'!C13 -> 0.0749 | G7: ='Underwriting Dashboard'!C12&" mo" -> 60 mo
B9: # | C9: Payment Date | D9: Beginning Balance | E9: Payment | F9: Principal | G9: Interest | H9: Ending Balance
B10: =IF(1<='Underwriting Dashboard'!C12,1,"") -> 1 | C10: =IF(B10<>"",DATE(YEAR(TODAY()),MONTH(TODAY())+1,1),"") -> 46113 | D10: =IF(B10<>"",'Underwriting Dashboard'!F7,"") -> 40000 | E10: =IF(B10<>"",'Underwriting Dashboard'!F9,"") -> 801.32788 | F10: =IF(B10<>"",PPMT('Underwriting Dashboard'!F8,1,'Underwriting Dashboard'!C12,-'Underwriting Dashboard'!F7),"") -> 551.66121 | G10: =IF(B10<>"",IPMT('Underwriting Dashboard'!F8,1,'Underwriting Dashboard'!C12,-'Underwriting Dashboard'!F7),"") -> 249.66667 | H10: =IF(B10<>"",D10-F10,"") -> 39448.339
B11: =IF(2<='Underwriting Dashboard'!C12,2,"") -> 2 | C11: =IF(B11<>"",EDATE(C10,1),"") -> 46143 | D11: =IF(B11<>"",G10,"") -> 249.66667 | E11: =IF(B11<>"",'Underwriting Dashboard'!F9,"") -> 801.32788 | F11: =IF(B11<>"",PPMT('Underwriting Dashboard'!F8,2,'Underwriting Dashboard'!C12,-'Underwriting Dashboard'!F7),"") -> 555.1045 | G11: =IF(B11<>"",IPMT('Underwriting Dashboard'!F8,2,'Underwriting Dashboard'!C12,-'Underwriting Dashboard'!F7),"") -> 246.22338 | H11: =IF(B11<>"",D11-F11,"") -> -305.43783
B12: =IF(3<='Underwriting Dashboard'!C12,3,"") -> 3 | C12: =IF(B12<>"",EDATE(C11,1),"") -> 46174 | D12: =IF(B12<>"",G11,"") -> 246.22338 | E12: =IF(B12<>"",'Underwriting Dashboard'!F9,"") -> 801.32788 | F12: =IF(B12<>"",PPMT('Underwriting Dashboard'!F8,3,'Underwriting Dashboard'!C12,-'Underwriting Dashboard'!F7),"") -> 558.56927 | G12: =IF(B12<>"",IPMT('Underwriting Dashboard'!F8,3,'Underwriting Dashboard'!C12,-'Underwriting Dashboard'!F7),"") -> 242.7586 | H12: =IF(B12<>"",D12-F12,"") -> -312.34589
B13: =IF(4<='Underwriting Dashboard'!C12,4,"") -> 4 | C13: =IF(B13<>"",EDATE(C12,1),"") -> 46204 | D13: =IF(B13<>"",G12,"") -> 242.7586 | E13: =IF(B13<>"",'Underwriting Dashboard'!F9,"") -> 801.32788 | F13: =IF(B13<>"",PPMT('Underwriting Dashboard'!F8,4,'Underwriting Dashboard'!C12,-'Underwriting Dashboard'!F7),"") -> 562.05568 | G13: =IF(B13<>"",IPMT('Underwriting Dashboard'!F8,4,'Underwriting Dashboard'!C12,-'Underwriting Dashboard'!F7),"") -> 239.2722 | H13: =IF(B13<>"",D13-F13,"") -> -319.29707
B14: =IF(5<='Underwriting Dashboard'!C12,5,"") -> 5 | C14: =IF(B14<>"",EDATE(C13,1),"") -> 46235 | D14: =IF(B14<>"",G13,"") -> 239.2722 | E14: =IF(B14<>"",'Underwriting Dashboard'!F9,"") -> 801.32788 | F14: =IF(B14<>"",PPMT('Underwriting Dashboard'!F8,5,'Underwriting Dashboard'!C12,-'Underwriting Dashboard'!F7),"") -> 565.56384 | G14: =IF(B14<>"",IPMT('Underwriting Dashboard'!F8,5,'Underwriting Dashboard'!C12,-'Underwriting Dashboard'!F7),"") -> 235.76404 | H14: =IF(B14<>"",D14-F14,"") -> -326.29164
B15: =IF(6<='Underwriting Dashboard'!C12,6,"") -> 6 | C15: =IF(B15<>"",EDATE(C14,1),"") -> 46266 | D15: =IF(B15<>"",G14,"") -> 235.76404 | E15: =IF(B15<>"",'Underwriting Dashboard'!F9,"") -> 801.32788 | F15: =IF(B15<>"",PPMT('Underwriting Dashboard'!F8,6,'Underwriting Dashboard'!C12,-'Underwriting Dashboard'!F7),"") -> 569.0939 | G15: =IF(B15<>"",IPMT('Underwriting Dashboard'!F8,6,'Underwriting Dashboard'!C12,-'Underwriting Dashboard'!F7),"") -> 232.23398 | H15: =IF(B15<>"",D15-F15,"") -> -333.32987
B16: =IF(7<='Underwriting Dashboard'!C12,7,"") -> 7 | C16: =IF(B16<>"",EDATE(C15,1),"") -> 46296 | D16: =IF(B16<>"",G15,"") -> 232.23398 | E16: =IF(B16<>"",'Underwriting Dashboard'!F9,"") -> 801.32788 | F16: =IF(B16<>"",PPMT('Underwriting Dashboard'!F8,7,'Underwriting Dashboard'!C12,-'Underwriting Dashboard'!F7),"") -> 572.646 | G16: =IF(B16<>"",IPMT('Underwriting Dashboard'!F8,7,'Underwriting Dashboard'!C12,-'Underwriting Dashboard'!F7),"") -> 228.68188 | H16: =IF(B16<>"",D16-F16,"") -> -340.41202
B17: =IF(8<='Underwriting Dashboard'!C12,8,"") -> 8 | C17: =IF(B17<>"",EDATE(C16,1),"") -> 46327 | D17: =IF(B17<>"",G16,"") -> 228.68188 | E17: =IF(B17<>"",'Underwriting Dashboard'!F9,"") -> 801.32788 | F17: =IF(B17<>"",PPMT('Underwriting Dashboard'!F8,8,'Underwriting Dashboard'!C12,-'Underwriting Dashboard'!F7),"") -> 576.22026 | G17: =IF(B17<>"",IPMT('Underwriting Dashboard'!F8,8,'Underwriting Dashboard'!C12,-'Underwriting Dashboard'!F7),"") -> 225.10762 | H17: =IF(B17<>"",D17-F17,"") -> -347.53838
B18: =IF(9<='Underwriting Dashboard'!C12,9,"") -> 9 | C18: =IF(B18<>"",EDATE(C17,1),"") -> 46357 | D18: =IF(B18<>"",G17,"") -> 225.10762 | E18: =IF(B18<>"",'Underwriting Dashboard'!F9,"") -> 801.32788 | F18: =IF(B18<>"",PPMT('Underwriting Dashboard'!F8,9,'Underwriting Dashboard'!C12,-'Underwriting Dashboard'!F7),"") -> 579.81684 | G18: =IF(B18<>"",IPMT('Underwriting Dashboard'!F8,9,'Underwriting Dashboard'!C12,-'Underwriting Dashboard'!F7),"") -> 221.51104 | H18: =IF(B18<>"",D18-F18,"") -> -354.70922
B19: =IF(10<='Underwriting Dashboard'!C12,10,"") -> 10 | C19: =IF(B19<>"",EDATE(C18,1),"") -> 46388 | D19: =IF(B19<>"",G18,"") -> 221.51104 | E19: =IF(B19<>"",'Underwriting Dashboard'!F9,"") -> 801.32788 | F19: =IF(B19<>"",PPMT('Underwriting Dashboard'!F8,10,'Underwriting Dashboard'!C12,-'Underwriting Dashboard'!F7),"") -> 583.43586 | G19: =IF(B19<>"",IPMT('Underwriting Dashboard'!F8,10,'Underwriting Dashboard'!C12,-'Underwriting Dashboard'!F7),"") -> 217.89202 | H19: =IF(B19<>"",D19-F19,"") -> -361.92482
B20: =IF(11<='Underwriting Dashboard'!C12,11,"") -> 11 | C20: =IF(B20<>"",EDATE(C19,1),"") -> 46419 | D20: =IF(B20<>"",G19,"") -> 217.89202 | E20: =IF(B20<>"",'Underwriting Dashboard'!F9,"") -> 801.32788 | F20: =IF(B20<>"",PPMT('Underwriting Dashboard'!F8,11,'Underwriting Dashboard'!C12,-'Underwriting Dashboard'!F7),"") -> 587.07747 | G20: =IF(B20<>"",IPMT('Underwriting Dashboard'!F8,11,'Underwriting Dashboard'!C12,-'Underwriting Dashboard'!F7),"") -> 214.25041 | H20: =IF(B20<>"",D20-F20,"") -> -369.18546
B21: =IF(12<='Underwriting Dashboard'!C12,12,"") -> 12 | C21: =IF(B21<>"",EDATE(C20,1),"") -> 46447 | D21: =IF(B21<>"",G20,"") -> 214.25041 | E21: =IF(B21<>"",'Underwriting Dashboard'!F9,"") -> 801.32788 | F21: =IF(B21<>"",PPMT('Underwriting Dashboard'!F8,12,'Underwriting Dashboard'!C12,-'Underwriting Dashboard'!F7),"") -> 590.74182 | G21: =IF(B21<>"",IPMT('Underwriting Dashboard'!F8,12,'Underwriting Dashboard'!C12,-'Underwriting Dashboard'!F7),"") -> 210.58606 | H21: =IF(B21<>"",D21-F21,"") -> -376.49141
B22: =IF(13<='Underwriting Dashboard'!C12,13,"") -> 13 | C22: =IF(B22<>"",EDATE(C21,1),"") -> 46478 | D22: =IF(B22<>"",G21,"") -> 210.58606 | E22: =IF(B22<>"",'Underwriting Dashboard'!F9,"") -> 801.32788 | F22: =IF(B22<>"",PPMT('Underwriting Dashboard'!F8,13,'Underwriting Dashboard'!C12,-'Underwriting Dashboard'!F7),"") -> 594.42903 | G22: =IF(B22<>"",IPMT('Underwriting Dashboard'!F8,13,'Underwriting Dashboard'!C12,-'Underwriting Dashboard'!F7),"") -> 206.89885 | H22: =IF(B22<>"",D22-F22,"") -> -383.84297
B23: =IF(14<='Underwriting Dashboard'!C12,14,"") -> 14 | C23: =IF(B23<>"",EDATE(C22,1),"") -> 46508 | D23: =IF(B23<>"",G22,"") -> 206.89885 | E23: =IF(B23<>"",'Underwriting Dashboard'!F9,"") -> 801.32788 | F23: =IF(B23<>"",PPMT('Underwriting Dashboard'!F8,14,'Underwriting Dashboard'!C12,-'Underwriting Dashboard'!F7),"") -> 598.13926 | G23: =IF(B23<>"",IPMT('Underwriting Dashboard'!F8,14,'Underwriting Dashboard'!C12,-'Underwriting Dashboard'!F7),"") -> 203.18862 | H23: =IF(B23<>"",D23-F23,"") -> -391.24041
B24: =IF(15<='Underwriting Dashboard'!C12,15,"") -> 15 | C24: =IF(B24<>"",EDATE(C23,1),"") -> 46539 | D24: =IF(B24<>"",G23,"") -> 203.18862 | E24: =IF(B24<>"",'Underwriting Dashboard'!F9,"") -> 801.32788 | F24: =IF(B24<>"",PPMT('Underwriting Dashboard'!F8,15,'Underwriting Dashboard'!C12,-'Underwriting Dashboard'!F7),"") -> 601.87264 | G24: =IF(B24<>"",IPMT('Underwriting Dashboard'!F8,15,'Underwriting Dashboard'!C12,-'Underwriting Dashboard'!F7),"") -> 199.45524 | H24: =IF(B24<>"",D24-F24,"") -> -398.68402
B25: =IF(16<='Underwriting Dashboard'!C12,16,"") -> 16 | C25: =IF(B25<>"",EDATE(C24,1),"") -> 46569 | D25: =IF(B25<>"",G24,"") -> 199.45524 | E25: =IF(B25<>"",'Underwriting Dashboard'!F9,"") -> 801.32788 | F25: =IF(B25<>"",PPMT('Underwriting Dashboard'!F8,16,'Underwriting Dashboard'!C12,-'Underwriting Dashboard'!F7),"") -> 605.62933 | G25: =IF(B25<>"",IPMT('Underwriting Dashboard'!F8,16,'Underwriting Dashboard'!C12,-'Underwriting Dashboard'!F7),"") -> 195.69855 | H25: =IF(B25<>"",D25-F25,"") -> -406.17409
B26: =IF(17<='Underwriting Dashboard'!C12,17,"") -> 17 | C26: =IF(B26<>"",EDATE(C25,1),"") -> 46600 | D26: =IF(B26<>"",G25,"") -> 195.69855 | E26: =IF(B26<>"",'Underwriting Dashboard'!F9,"") -> 801.32788 | F26: =IF(B26<>"",PPMT('Underwriting Dashboard'!F8,17,'Underwriting Dashboard'!C12,-'Underwriting Dashboard'!F7),"") -> 609.40947 | G26: =IF(B26<>"",IPMT('Underwriting Dashboard'!F8,17,'Underwriting Dashboard'!C12,-'Underwriting Dashboard'!F7),"") -> 191.91841 | H26: =IF(B26<>"",D26-F26,"") -> -413.71092
B27: =IF(18<='Underwriting Dashboard'!C12,18,"") -> 18 | C27: =IF(B27<>"",EDATE(C26,1),"") -> 46631 | D27: =IF(B27<>"",G26,"") -> 191.91841 | E27: =IF(B27<>"",'Underwriting Dashboard'!F9,"") -> 801.32788 | F27: =IF(B27<>"",PPMT('Underwriting Dashboard'!F8,18,'Underwriting Dashboard'!C12,-'Underwriting Dashboard'!F7),"") -> 613.2132 | G27: =IF(B27<>"",IPMT('Underwriting Dashboard'!F8,18,'Underwriting Dashboard'!C12,-'Underwriting Dashboard'!F7),"") -> 188.11468 | H27: =IF(B27<>"",D27-F27,"") -> -421.29479
B28: =IF(19<='Underwriting Dashboard'!C12,19,"") -> 19 | C28: =IF(B28<>"",EDATE(C27,1),"") -> 46661 | D28: =IF(B28<>"",G27,"") -> 188.11468 | E28: =IF(B28<>"",'Underwriting Dashboard'!F9,"") -> 801.32788 | F28: =IF(B28<>"",PPMT('Underwriting Dashboard'!F8,19,'Underwriting Dashboard'!C12,-'Underwriting Dashboard'!F7),"") -> 617.04067 | G28: =IF(B28<>"",IPMT('Underwriting Dashboard'!F8,19,'Underwriting Dashboard'!C12,-'Underwriting Dashboard'!F7),"") -> 184.28721 | H28: =IF(B28<>"",D28-F28,"") -> -428.92599
B29: =IF(20<='Underwriting Dashboard'!C12,20,"") -> 20 | C29: =IF(B29<>"",EDATE(C28,1),"") -> 46692 | D29: =IF(B29<>"",G28,"") -> 184.28721 | E29: =IF(B29<>"",'Underwriting Dashboard'!F9,"") -> 801.32788 | F29: =IF(B29<>"",PPMT('Underwriting Dashboard'!F8,20,'Underwriting Dashboard'!C12,-'Underwriting Dashboard'!F7),"") -> 620.89203 | G29: =IF(B29<>"",IPMT('Underwriting Dashboard'!F8,20,'Underwriting Dashboard'!C12,-'Underwriting Dashboard'!F7),"") -> 180.43585 | H29: =IF(B29<>"",D29-F29,"") -> -436.60482
B30: =IF(21<='Underwriting Dashboard'!C12,21,"") -> 21 | C30: =IF(B30<>"",EDATE(C29,1),"") -> 46722 | D30: =IF(B30<>"",G29,"") -> 180.43585 | E30: =IF(B30<>"",'Underwriting Dashboard'!F9,"") -> 801.32788 | F30: =IF(B30<>"",PPMT('Underwriting Dashboard'!F8,21,'Underwriting Dashboard'!C12,-'Underwriting Dashboard'!F7),"") -> 624.76743 | G30: =IF(B30<>"",IPMT('Underwriting Dashboard'!F8,21,'Underwriting Dashboard'!C12,-'Underwriting Dashboard'!F7),"") -> 176.56045 | H30: =IF(B30<>"",D30-F30,"") -> -444.33159
B31: =IF(22<='Underwriting Dashboard'!C12,22,"") -> 22 | C31: =IF(B31<>"",EDATE(C30,1),"") -> 46753 | D31: =IF(B31<>"",G30,"") -> 176.56045 | E31: =IF(B31<>"",'Underwriting Dashboard'!F9,"") -> 801.32788 | F31: =IF(B31<>"",PPMT('Underwriting Dashboard'!F8,22,'Underwriting Dashboard'!C12,-'Underwriting Dashboard'!F7),"") -> 628.66702 | G31: =IF(B31<>"",IPMT('Underwriting Dashboard'!F8,22,'Underwriting Dashboard'!C12,-'Underwriting Dashboard'!F7),"") -> 172.66085 | H31: =IF(B31<>"",D31-F31,"") -> -452.10658
B32: =IF(23<='Underwriting Dashboard'!C12,23,"") -> 23 | C32: =IF(B32<>"",EDATE(C31,1),"") -> 46784 | D32: =IF(B32<>"",G31,"") -> 172.66085 | E32: =IF(B32<>"",'Underwriting Dashboard'!F9,"") -> 801.32788 | F32: =IF(B32<>"",PPMT('Underwriting Dashboard'!F8,23,'Underwriting Dashboard'!C12,-'Underwriting Dashboard'!F7),"") -> 632.59095 | G32: =IF(B32<>"",IPMT('Underwriting Dashboard'!F8,23,'Underwriting Dashboard'!C12,-'Underwriting Dashboard'!F7),"") -> 168.73692 | H32: =IF(B32<>"",D32-F32,"") -> -459.9301
B33: =IF(24<='Underwriting Dashboard'!C12,24,"") -> 24 | C33: =IF(B33<>"",EDATE(C32,1),"") -> 46813 | D33: =IF(B33<>"",G32,"") -> 168.73692 | E33: =IF(B33<>"",'Underwriting Dashboard'!F9,"") -> 801.32788 | F33: =IF(B33<>"",PPMT('Underwriting Dashboard'!F8,24,'Underwriting Dashboard'!C12,-'Underwriting Dashboard'!F7),"") -> 636.53938 | G33: =IF(B33<>"",IPMT('Underwriting Dashboard'!F8,24,'Underwriting Dashboard'!C12,-'Underwriting Dashboard'!F7),"") -> 164.7885 | H33: =IF(B33<>"",D33-F33,"") -> -467.80245
B34: =IF(25<='Underwriting Dashboard'!C12,25,"") -> 25 | C34: =IF(B34<>"",EDATE(C33,1),"") -> 46844 | D34: =IF(B34<>"",G33,"") -> 164.7885 | E34: =IF(B34<>"",'Underwriting Dashboard'!F9,"") -> 801.32788 | F34: =IF(B34<>"",PPMT('Underwriting Dashboard'!F8,25,'Underwriting Dashboard'!C12,-'Underwriting Dashboard'!F7),"") -> 640.51244 | G34: =IF(B34<>"",IPMT('Underwriting Dashboard'!F8,25,'Underwriting Dashboard'!C12,-'Underwriting Dashboard'!F7),"") -> 160.81544 | H34: =IF(B34<>"",D34-F34,"") -> -475.72394
B35: =IF(26<='Underwriting Dashboard'!C12,26,"") -> 26 | C35: =IF(B35<>"",EDATE(C34,1),"") -> 46874 | D35: =IF(B35<>"",G34,"") -> 160.81544 | E35: =IF(B35<>"",'Underwriting Dashboard'!F9,"") -> 801.32788 | F35: =IF(B35<>"",PPMT('Underwriting Dashboard'!F8,26,'Underwriting Dashboard'!C12,-'Underwriting Dashboard'!F7),"") -> 644.51031 | G35: =IF(B35<>"",IPMT('Underwriting Dashboard'!F8,26,'Underwriting Dashboard'!C12,-'Underwriting Dashboard'!F7),"") -> 156.81757 | H35: =IF(B35<>"",D35-F35,"") -> -483.69487
B36: =IF(27<='Underwriting Dashboard'!C12,27,"") -> 27 | C36: =IF(B36<>"",EDATE(C35,1),"") -> 46905 | D36: =IF(B36<>"",G35,"") -> 156.81757 | E36: =IF(B36<>"",'Underwriting Dashboard'!F9,"") -> 801.32788 | F36: =IF(B36<>"",PPMT('Underwriting Dashboard'!F8,27,'Underwriting Dashboard'!C12,-'Underwriting Dashboard'!F7),"") -> 648.53313 | G36: =IF(B36<>"",IPMT('Underwriting Dashboard'!F8,27,'Underwriting Dashboard'!C12,-'Underwriting Dashboard'!F7),"") -> 152.79475 | H36: =IF(B36<>"",D36-F36,"") -> -491.71555
B37: =IF(28<='Underwriting Dashboard'!C12,28,"") -> 28 | C37: =IF(B37<>"",EDATE(C36,1),"") -> 46935 | D37: =IF(B37<>"",G36,"") -> 152.79475 | E37: =IF(B37<>"",'Underwriting Dashboard'!F9,"") -> 801.32788 | F37: =IF(B37<>"",PPMT('Underwriting Dashboard'!F8,28,'Underwriting Dashboard'!C12,-'Underwriting Dashboard'!F7),"") -> 652.58105 | G37: =IF(B37<>"",IPMT('Underwriting Dashboard'!F8,28,'Underwriting Dashboard'!C12,-'Underwriting Dashboard'!F7),"") -> 148.74683 | H37: =IF(B37<>"",D37-F37,"") -> -499.7863
B38: =IF(29<='Underwriting Dashboard'!C12,29,"") -> 29 | C38: =IF(B38<>"",EDATE(C37,1),"") -> 46966 | D38: =IF(B38<>"",G37,"") -> 148.74683 | E38: =IF(B38<>"",'Underwriting Dashboard'!F9,"") -> 801.32788 | F38: =IF(B38<>"",PPMT('Underwriting Dashboard'!F8,29,'Underwriting Dashboard'!C12,-'Underwriting Dashboard'!F7),"") -> 656.65425 | G38: =IF(B38<>"",IPMT('Underwriting Dashboard'!F8,29,'Underwriting Dashboard'!C12,-'Underwriting Dashboard'!F7),"") -> 144.67363 | H38: =IF(B38<>"",D38-F38,"") -> -507.90742
B39: =IF(30<='Underwriting Dashboard'!C12,30,"") -> 30 | C39: =IF(B39<>"",EDATE(C38,1),"") -> 46997 | D39: =IF(B39<>"",G38,"") -> 144.67363 | E39: =IF(B39<>"",'Underwriting Dashboard'!F9,"") -> 801.32788 | F39: =IF(B39<>"",PPMT('Underwriting Dashboard'!F8,30,'Underwriting Dashboard'!C12,-'Underwriting Dashboard'!F7),"") -> 660.75286 | G39: =IF(B39<>"",IPMT('Underwriting Dashboard'!F8,30,'Underwriting Dashboard'!C12,-'Underwriting Dashboard'!F7),"") -> 140.57501 | H39: =IF(B39<>"",D39-F39,"") -> -516.07923
B40: =IF(31<='Underwriting Dashboard'!C12,31,"") -> 31 | C40: =IF(B40<>"",EDATE(C39,1),"") -> 47027 | D40: =IF(B40<>"",G39,"") -> 140.57501 | E40: =IF(B40<>"",'Underwriting Dashboard'!F9,"") -> 801.32788 | F40: =IF(B40<>"",PPMT('Underwriting Dashboard'!F8,31,'Underwriting Dashboard'!C12,-'Underwriting Dashboard'!F7),"") -> 664.87706 | G40: =IF(B40<>"",IPMT('Underwriting Dashboard'!F8,31,'Underwriting Dashboard'!C12,-'Underwriting Dashboard'!F7),"") -> 136.45082 | H40: =IF(B40<>"",D40-F40,"") -> -524.30205
B41: =IF(32<='Underwriting Dashboard'!C12,32,"") -> 32 | C41: =IF(B41<>"",EDATE(C40,1),"") -> 47058 | D41: =IF(B41<>"",G40,"") -> 136.45082 | E41: =IF(B41<>"",'Underwriting Dashboard'!F9,"") -> 801.32788 | F41: =IF(B41<>"",PPMT('Underwriting Dashboard'!F8,32,'Underwriting Dashboard'!C12,-'Underwriting Dashboard'!F7),"") -> 669.027 | G41: =IF(B41<>"",IPMT('Underwriting Dashboard'!F8,32,'Underwriting Dashboard'!C12,-'Underwriting Dashboard'!F7),"") -> 132.30087 | H41: =IF(B41<>"",D41-F41,"") -> -532.57619
B42: =IF(33<='Underwriting Dashboard'!C12,33,"") -> 33 | C42: =IF(B42<>"",EDATE(C41,1),"") -> 47088 | D42: =IF(B42<>"",G41,"") -> 132.30087 | E42: =IF(B42<>"",'Underwriting Dashboard'!F9,"") -> 801.32788 | F42: =IF(B42<>"",PPMT('Underwriting Dashboard'!F8,33,'Underwriting Dashboard'!C12,-'Underwriting Dashboard'!F7),"") -> 673.20285 | G42: =IF(B42<>"",IPMT('Underwriting Dashboard'!F8,33,'Underwriting Dashboard'!C12,-'Underwriting Dashboard'!F7),"") -> 128.12503 | H42: =IF(B42<>"",D42-F42,"") -> -540.90197
B43: =IF(34<='Underwriting Dashboard'!C12,34,"") -> 34 | C43: =IF(B43<>"",EDATE(C42,1),"") -> 47119 | D43: =IF(B43<>"",G42,"") -> 128.12503 | E43: =IF(B43<>"",'Underwriting Dashboard'!F9,"") -> 801.32788 | F43: =IF(B43<>"",PPMT('Underwriting Dashboard'!F8,34,'Underwriting Dashboard'!C12,-'Underwriting Dashboard'!F7),"") -> 677.40476 | G43: =IF(B43<>"",IPMT('Underwriting Dashboard'!F8,34,'Underwriting Dashboard'!C12,-'Underwriting Dashboard'!F7),"") -> 123.92312 | H43: =IF(B43<>"",D43-F43,"") -> -549.27972
B44: =IF(35<='Underwriting Dashboard'!C12,35,"") -> 35 | C44: =IF(B44<>"",EDATE(C43,1),"") -> 47150 | D44: =IF(B44<>"",G43,"") -> 123.92312 | E44: =IF(B44<>"",'Underwriting Dashboard'!F9,"") -> 801.32788 | F44: =IF(B44<>"",PPMT('Underwriting Dashboard'!F8,35,'Underwriting Dashboard'!C12,-'Underwriting Dashboard'!F7),"") -> 681.63289 | G44: =IF(B44<>"",IPMT('Underwriting Dashboard'!F8,35,'Underwriting Dashboard'!C12,-'Underwriting Dashboard'!F7),"") -> 119.69499 | H44: =IF(B44<>"",D44-F44,"") -> -557.70977
B45: =IF(36<='Underwriting Dashboard'!C12,36,"") -> 36 | C45: =IF(B45<>"",EDATE(C44,1),"") -> 47178 | D45: =IF(B45<>"",G44,"") -> 119.69499 | E45: =IF(B45<>"",'Underwriting Dashboard'!F9,"") -> 801.32788 | F45: =IF(B45<>"",PPMT('Underwriting Dashboard'!F8,36,'Underwriting Dashboard'!C12,-'Underwriting Dashboard'!F7),"") -> 685.88742 | G45: =IF(B45<>"",IPMT('Underwriting Dashboard'!F8,36,'Underwriting Dashboard'!C12,-'Underwriting Dashboard'!F7),"") -> 115.44046 | H45: =IF(B45<>"",D45-F45,"") -> -566.19243
B46: =IF(37<='Underwriting Dashboard'!C12,37,"") -> 37 | C46: =IF(B46<>"",EDATE(C45,1),"") -> 47209 | D46: =IF(B46<>"",G45,"") -> 115.44046 | E46: =IF(B46<>"",'Underwriting Dashboard'!F9,"") -> 801.32788 | F46: =IF(B46<>"",PPMT('Underwriting Dashboard'!F8,37,'Underwriting Dashboard'!C12,-'Underwriting Dashboard'!F7),"") -> 690.1685 | G46: =IF(B46<>"",IPMT('Underwriting Dashboard'!F8,37,'Underwriting Dashboard'!C12,-'Underwriting Dashboard'!F7),"") -> 111.15938 | H46: =IF(B46<>"",D46-F46,"") -> -574.72803
B47: =IF(38<='Underwriting Dashboard'!C12,38,"") -> 38 | C47: =IF(B47<>"",EDATE(C46,1),"") -> 47239 | D47: =IF(B47<>"",G46,"") -> 111.15938 | E47: =IF(B47<>"",'Underwriting Dashboard'!F9,"") -> 801.32788 | F47: =IF(B47<>"",PPMT('Underwriting Dashboard'!F8,38,'Underwriting Dashboard'!C12,-'Underwriting Dashboard'!F7),"") -> 694.4763 | G47: =IF(B47<>"",IPMT('Underwriting Dashboard'!F8,38,'Underwriting Dashboard'!C12,-'Underwriting Dashboard'!F7),"") -> 106.85158 | H47: =IF(B47<>"",D47-F47,"") -> -583.31691
B48: =IF(39<='Underwriting Dashboard'!C12,39,"") -> 39 | C48: =IF(B48<>"",EDATE(C47,1),"") -> 47270 | D48: =IF(B48<>"",G47,"") -> 106.85158 | E48: =IF(B48<>"",'Underwriting Dashboard'!F9,"") -> 801.32788 | F48: =IF(B48<>"",PPMT('Underwriting Dashboard'!F8,39,'Underwriting Dashboard'!C12,-'Underwriting Dashboard'!F7),"") -> 698.81099 | G48: =IF(B48<>"",IPMT('Underwriting Dashboard'!F8,39,'Underwriting Dashboard'!C12,-'Underwriting Dashboard'!F7),"") -> 102.51689 | H48: =IF(B48<>"",D48-F48,"") -> -591.95941
B49: =IF(40<='Underwriting Dashboard'!C12,40,"") -> 40 | C49: =IF(B49<>"",EDATE(C48,1),"") -> 47300 | D49: =IF(B49<>"",G48,"") -> 102.51689 | E49: =IF(B49<>"",'Underwriting Dashboard'!F9,"") -> 801.32788 | F49: =IF(B49<>"",PPMT('Underwriting Dashboard'!F8,40,'Underwriting Dashboard'!C12,-'Underwriting Dashboard'!F7),"") -> 703.17273 | G49: =IF(B49<>"",IPMT('Underwriting Dashboard'!F8,40,'Underwriting Dashboard'!C12,-'Underwriting Dashboard'!F7),"") -> 98.155146 | H49: =IF(B49<>"",D49-F49,"") -> -600.65584
B50: =IF(41<='Underwriting Dashboard'!C12,41,"") -> 41 | C50: =IF(B50<>"",EDATE(C49,1),"") -> 47331 | D50: =IF(B50<>"",G49,"") -> 98.155146 | E50: =IF(B50<>"",'Underwriting Dashboard'!F9,"") -> 801.32788 | F50: =IF(B50<>"",PPMT('Underwriting Dashboard'!F8,41,'Underwriting Dashboard'!C12,-'Underwriting Dashboard'!F7),"") -> 707.5617 | G50: =IF(B50<>"",IPMT('Underwriting Dashboard'!F8,41,'Underwriting Dashboard'!C12,-'Underwriting Dashboard'!F7),"") -> 93.766177 | H50: =IF(B50<>"",D50-F50,"") -> -609.40656
B51: =IF(42<='Underwriting Dashboard'!C12,42,"") -> 42 | C51: =IF(B51<>"",EDATE(C50,1),"") -> 47362 | D51: =IF(B51<>"",G50,"") -> 93.766177 | E51: =IF(B51<>"",'Underwriting Dashboard'!F9,"") -> 801.32788 | F51: =IF(B51<>"",PPMT('Underwriting Dashboard'!F8,42,'Underwriting Dashboard'!C12,-'Underwriting Dashboard'!F7),"") -> 711.97807 | G51: =IF(B51<>"",IPMT('Underwriting Dashboard'!F8,42,'Underwriting Dashboard'!C12,-'Underwriting Dashboard'!F7),"") -> 89.349812 | H51: =IF(B51<>"",D51-F51,"") -> -618.21189
B52: =IF(43<='Underwriting Dashboard'!C12,43,"") -> 43 | C52: =IF(B52<>"",EDATE(C51,1),"") -> 47392 | D52: =IF(B52<>"",G51,"") -> 89.349812 | E52: =IF(B52<>"",'Underwriting Dashboard'!F9,"") -> 801.32788 | F52: =IF(B52<>"",PPMT('Underwriting Dashboard'!F8,43,'Underwriting Dashboard'!C12,-'Underwriting Dashboard'!F7),"") -> 716.422 | G52: =IF(B52<>"",IPMT('Underwriting Dashboard'!F8,43,'Underwriting Dashboard'!C12,-'Underwriting Dashboard'!F7),"") -> 84.905883 | H52: =IF(B52<>"",D52-F52,"") -> -627.07218
B53: =IF(44<='Underwriting Dashboard'!C12,44,"") -> 44 | C53: =IF(B53<>"",EDATE(C52,1),"") -> 47423 | D53: =IF(B53<>"",G52,"") -> 84.905883 | E53: =IF(B53<>"",'Underwriting Dashboard'!F9,"") -> 801.32788 | F53: =IF(B53<>"",PPMT('Underwriting Dashboard'!F8,44,'Underwriting Dashboard'!C12,-'Underwriting Dashboard'!F7),"") -> 720.89366 | G53: =IF(B53<>"",IPMT('Underwriting Dashboard'!F8,44,'Underwriting Dashboard'!C12,-'Underwriting Dashboard'!F7),"") -> 80.434215 | H53: =IF(B53<>"",D53-F53,"") -> -635.98778
B54: =IF(45<='Underwriting Dashboard'!C12,45,"") -> 45 | C54: =IF(B54<>"",EDATE(C53,1),"") -> 47453 | D54: =IF(B54<>"",G53,"") -> 80.434215 | E54: =IF(B54<>"",'Underwriting Dashboard'!F9,"") -> 801.32788 | F54: =IF(B54<>"",PPMT('Underwriting Dashboard'!F8,45,'Underwriting Dashboard'!C12,-'Underwriting Dashboard'!F7),"") -> 725.39324 | G54: =IF(B54<>"",IPMT('Underwriting Dashboard'!F8,45,'Underwriting Dashboard'!C12,-'Underwriting Dashboard'!F7),"") -> 75.934637 | H54: =IF(B54<>"",D54-F54,"") -> -644.95903
B55: =IF(46<='Underwriting Dashboard'!C12,46,"") -> 46 | C55: =IF(B55<>"",EDATE(C54,1),"") -> 47484 | D55: =IF(B55<>"",G54,"") -> 75.934637 | E55: =IF(B55<>"",'Underwriting Dashboard'!F9,"") -> 801.32788 | F55: =IF(B55<>"",PPMT('Underwriting Dashboard'!F8,46,'Underwriting Dashboard'!C12,-'Underwriting Dashboard'!F7),"") -> 729.9209 | G55: =IF(B55<>"",IPMT('Underwriting Dashboard'!F8,46,'Underwriting Dashboard'!C12,-'Underwriting Dashboard'!F7),"") -> 71.406974 | H55: =IF(B55<>"",D55-F55,"") -> -653.98627
B56: =IF(47<='Underwriting Dashboard'!C12,47,"") -> 47 | C56: =IF(B56<>"",EDATE(C55,1),"") -> 47515 | D56: =IF(B56<>"",G55,"") -> 71.406974 | E56: =IF(B56<>"",'Underwriting Dashboard'!F9,"") -> 801.32788 | F56: =IF(B56<>"",PPMT('Underwriting Dashboard'!F8,47,'Underwriting Dashboard'!C12,-'Underwriting Dashboard'!F7),"") -> 734.47683 | G56: =IF(B56<>"",IPMT('Underwriting Dashboard'!F8,47,'Underwriting Dashboard'!C12,-'Underwriting Dashboard'!F7),"") -> 66.851051 | H56: =IF(B56<>"",D56-F56,"") -> -663.06985
B57: =IF(48<='Underwriting Dashboard'!C12,48,"") -> 48 | C57: =IF(B57<>"",EDATE(C56,1),"") -> 47543 | D57: =IF(B57<>"",G56,"") -> 66.851051 | E57: =IF(B57<>"",'Underwriting Dashboard'!F9,"") -> 801.32788 | F57: =IF(B57<>"",PPMT('Underwriting Dashboard'!F8,48,'Underwriting Dashboard'!C12,-'Underwriting Dashboard'!F7),"") -> 739.06119 | G57: =IF(B57<>"",IPMT('Underwriting Dashboard'!F8,48,'Underwriting Dashboard'!C12,-'Underwriting Dashboard'!F7),"") -> 62.266692 | H57: =IF(B57<>"",D57-F57,"") -> -672.21014
B58: =IF(49<='Underwriting Dashboard'!C12,49,"") -> 49 | C58: =IF(B58<>"",EDATE(C57,1),"") -> 47574 | D58: =IF(B58<>"",G57,"") -> 62.266692 | E58: =IF(B58<>"",'Underwriting Dashboard'!F9,"") -> 801.32788 | F58: =IF(B58<>"",PPMT('Underwriting Dashboard'!F8,49,'Underwriting Dashboard'!C12,-'Underwriting Dashboard'!F7),"") -> 743.67416 | G58: =IF(B58<>"",IPMT('Underwriting Dashboard'!F8,49,'Underwriting Dashboard'!C12,-'Underwriting Dashboard'!F7),"") -> 57.653718 | H58: =IF(B58<>"",D58-F58,"") -> -681.40747
B59: =IF(50<='Underwriting Dashboard'!C12,50,"") -> 50 | C59: =IF(B59<>"",EDATE(C58,1),"") -> 47604 | D59: =IF(B59<>"",G58,"") -> 57.653718 | E59: =IF(B59<>"",'Underwriting Dashboard'!F9,"") -> 801.32788 | F59: =IF(B59<>"",PPMT('Underwriting Dashboard'!F8,50,'Underwriting Dashboard'!C12,-'Underwriting Dashboard'!F7),"") -> 748.31593 | G59: =IF(B59<>"",IPMT('Underwriting Dashboard'!F8,50,'Underwriting Dashboard'!C12,-'Underwriting Dashboard'!F7),"") -> 53.011952 | H59: =IF(B59<>"",D59-F59,"") -> -690.66221
B60: =IF(51<='Underwriting Dashboard'!C12,51,"") -> 51 | C60: =IF(B60<>"",EDATE(C59,1),"") -> 47635 | D60: =IF(B60<>"",G59,"") -> 53.011952 | E60: =IF(B60<>"",'Underwriting Dashboard'!F9,"") -> 801.32788 | F60: =IF(B60<>"",PPMT('Underwriting Dashboard'!F8,51,'Underwriting Dashboard'!C12,-'Underwriting Dashboard'!F7),"") -> 752.98666 | G60: =IF(B60<>"",IPMT('Underwriting Dashboard'!F8,51,'Underwriting Dashboard'!C12,-'Underwriting Dashboard'!F7),"") -> 48.341214 | H60: =IF(B60<>"",D60-F60,"") -> -699.97471
B61: =IF(52<='Underwriting Dashboard'!C12,52,"") -> 52 | C61: =IF(B61<>"",EDATE(C60,1),"") -> 47665 | D61: =IF(B61<>"",G60,"") -> 48.341214 | E61: =IF(B61<>"",'Underwriting Dashboard'!F9,"") -> 801.32788 | F61: =IF(B61<>"",PPMT('Underwriting Dashboard'!F8,52,'Underwriting Dashboard'!C12,-'Underwriting Dashboard'!F7),"") -> 757.68656 | G61: =IF(B61<>"",IPMT('Underwriting Dashboard'!F8,52,'Underwriting Dashboard'!C12,-'Underwriting Dashboard'!F7),"") -> 43.641322 | H61: =IF(B61<>"",D61-F61,"") -> -709.34534
B62: =IF(53<='Underwriting Dashboard'!C12,53,"") -> 53 | C62: =IF(B62<>"",EDATE(C61,1),"") -> 47696 | D62: =IF(B62<>"",G61,"") -> 43.641322 | E62: =IF(B62<>"",'Underwriting Dashboard'!F9,"") -> 801.32788 | F62: =IF(B62<>"",PPMT('Underwriting Dashboard'!F8,53,'Underwriting Dashboard'!C12,-'Underwriting Dashboard'!F7),"") -> 762.41578 | G62: =IF(B62<>"",IPMT('Underwriting Dashboard'!F8,53,'Underwriting Dashboard'!C12,-'Underwriting Dashboard'!F7),"") -> 38.912095 | H62: =IF(B62<>"",D62-F62,"") -> -718.77446
B63: =IF(54<='Underwriting Dashboard'!C12,54,"") -> 54 | C63: =IF(B63<>"",EDATE(C62,1),"") -> 47727 | D63: =IF(B63<>"",G62,"") -> 38.912095 | E63: =IF(B63<>"",'Underwriting Dashboard'!F9,"") -> 801.32788 | F63: =IF(B63<>"",PPMT('Underwriting Dashboard'!F8,54,'Underwriting Dashboard'!C12,-'Underwriting Dashboard'!F7),"") -> 767.17453 | G63: =IF(B63<>"",IPMT('Underwriting Dashboard'!F8,54,'Underwriting Dashboard'!C12,-'Underwriting Dashboard'!F7),"") -> 34.15335 | H63: =IF(B63<>"",D63-F63,"") -> -728.26243
B64: =IF(55<='Underwriting Dashboard'!C12,55,"") -> 55 | C64: =IF(B64<>"",EDATE(C63,1),"") -> 47757 | D64: =IF(B64<>"",G63,"") -> 34.15335 | E64: =IF(B64<>"",'Underwriting Dashboard'!F9,"") -> 801.32788 | F64: =IF(B64<>"",PPMT('Underwriting Dashboard'!F8,55,'Underwriting Dashboard'!C12,-'Underwriting Dashboard'!F7),"") -> 771.96298 | G64: =IF(B64<>"",IPMT('Underwriting Dashboard'!F8,55,'Underwriting Dashboard'!C12,-'Underwriting Dashboard'!F7),"") -> 29.364902 | H64: =IF(B64<>"",D64-F64,"") -> -737.80963
B65: =IF(56<='Underwriting Dashboard'!C12,56,"") -> 56 | C65: =IF(B65<>"",EDATE(C64,1),"") -> 47788 | D65: =IF(B65<>"",G64,"") -> 29.364902 | E65: =IF(B65<>"",'Underwriting Dashboard'!F9,"") -> 801.32788 | F65: =IF(B65<>"",PPMT('Underwriting Dashboard'!F8,56,'Underwriting Dashboard'!C12,-'Underwriting Dashboard'!F7),"") -> 776.78131 | G65: =IF(B65<>"",IPMT('Underwriting Dashboard'!F8,56,'Underwriting Dashboard'!C12,-'Underwriting Dashboard'!F7),"") -> 24.546566 | H65: =IF(B65<>"",D65-F65,"") -> -747.41641
B66: =IF(57<='Underwriting Dashboard'!C12,57,"") -> 57 | C66: =IF(B66<>"",EDATE(C65,1),"") -> 47818 | D66: =IF(B66<>"",G65,"") -> 24.546566 | E66: =IF(B66<>"",'Underwriting Dashboard'!F9,"") -> 801.32788 | F66: =IF(B66<>"",PPMT('Underwriting Dashboard'!F8,57,'Underwriting Dashboard'!C12,-'Underwriting Dashboard'!F7),"") -> 781.62972 | G66: =IF(B66<>"",IPMT('Underwriting Dashboard'!F8,57,'Underwriting Dashboard'!C12,-'Underwriting Dashboard'!F7),"") -> 19.698156 | H66: =IF(B66<>"",D66-F66,"") -> -757.08316
B67: =IF(58<='Underwriting Dashboard'!C12,58,"") -> 58 | C67: =IF(B67<>"",EDATE(C66,1),"") -> 47849 | D67: =IF(B67<>"",G66,"") -> 19.698156 | E67: =IF(B67<>"",'Underwriting Dashboard'!F9,"") -> 801.32788 | F67: =IF(B67<>"",PPMT('Underwriting Dashboard'!F8,58,'Underwriting Dashboard'!C12,-'Underwriting Dashboard'!F7),"") -> 786.50839 | G67: =IF(B67<>"",IPMT('Underwriting Dashboard'!F8,58,'Underwriting Dashboard'!C12,-'Underwriting Dashboard'!F7),"") -> 14.819484 | H67: =IF(B67<>"",D67-F67,"") -> -766.81024
B68: =IF(59<='Underwriting Dashboard'!C12,59,"") -> 59 | C68: =IF(B68<>"",EDATE(C67,1),"") -> 47880 | D68: =IF(B68<>"",G67,"") -> 14.819484 | E68: =IF(B68<>"",'Underwriting Dashboard'!F9,"") -> 801.32788 | F68: =IF(B68<>"",PPMT('Underwriting Dashboard'!F8,59,'Underwriting Dashboard'!C12,-'Underwriting Dashboard'!F7),"") -> 791.41752 | G68: =IF(B68<>"",IPMT('Underwriting Dashboard'!F8,59,'Underwriting Dashboard'!C12,-'Underwriting Dashboard'!F7),"") -> 9.910361 | H68: =IF(B68<>"",D68-F68,"") -> -776.59803
B69: =IF(60<='Underwriting Dashboard'!C12,60,"") -> 60 | C69: =IF(B69<>"",EDATE(C68,1),"") -> 47908 | D69: =IF(B69<>"",G68,"") -> 9.910361 | E69: =IF(B69<>"",'Underwriting Dashboard'!F9,"") -> 801.32788 | F69: =IF(B69<>"",PPMT('Underwriting Dashboard'!F8,60,'Underwriting Dashboard'!C12,-'Underwriting Dashboard'!F7),"") -> 796.35728 | G69: =IF(B69<>"",IPMT('Underwriting Dashboard'!F8,60,'Underwriting Dashboard'!C12,-'Underwriting Dashboard'!F7),"") -> 4.9705967 | H69: =IF(B69<>"",D69-F69,"") -> -786.44692
B70: =IF(61<='Underwriting Dashboard'!C12,61,"") | C70: =IF(B70<>"",EDATE(C69,1),"") | D70: =IF(B70<>"",G69,"") | E70: =IF(B70<>"",'Underwriting Dashboard'!F9,"") | F70: =IF(B70<>"",PPMT('Underwriting Dashboard'!F8,61,'Underwriting Dashboard'!C12,-'Underwriting Dashboard'!F7),"") | G70: =IF(B70<>"",IPMT('Underwriting Dashboard'!F8,61,'Underwriting Dashboard'!C12,-'Underwriting Dashboard'!F7),"") | H70: =IF(B70<>"",D70-F70,"")
B71: =IF(62<='Underwriting Dashboard'!C12,62,"") | C71: =IF(B71<>"",EDATE(C70,1),"") | D71: =IF(B71<>"",G70,"") | E71: =IF(B71<>"",'Underwriting Dashboard'!F9,"") | F71: =IF(B71<>"",PPMT('Underwriting Dashboard'!F8,62,'Underwriting Dashboard'!C12,-'Underwriting Dashboard'!F7),"") | G71: =IF(B71<>"",IPMT('Underwriting Dashboard'!F8,62,'Underwriting Dashboard'!C12,-'Underwriting Dashboard'!F7),"") | H71: =IF(B71<>"",D71-F71,"")
B72: =IF(63<='Underwriting Dashboard'!C12,63,"") | C72: =IF(B72<>"",EDATE(C71,1),"") | D72: =IF(B72<>"",G71,"") | E72: =IF(B72<>"",'Underwriting Dashboard'!F9,"") | F72: =IF(B72<>"",PPMT('Underwriting Dashboard'!F8,63,'Underwriting Dashboard'!C12,-'Underwriting Dashboard'!F7),"") | G72: =IF(B72<>"",IPMT('Underwriting Dashboard'!F8,63,'Underwriting Dashboard'!C12,-'Underwriting Dashboard'!F7),"") | H72: =IF(B72<>"",D72-F72,"")
B73: =IF(64<='Underwriting Dashboard'!C12,64,"") | C73: =IF(B73<>"",EDATE(C72,1),"") | D73: =IF(B73<>"",G72,"") | E73: =IF(B73<>"",'Underwriting Dashboard'!F9,"") | F73: =IF(B73<>"",PPMT('Underwriting Dashboard'!F8,64,'Underwriting Dashboard'!C12,-'Underwriting Dashboard'!F7),"") | G73: =IF(B73<>"",IPMT('Underwriting Dashboard'!F8,64,'Underwriting Dashboard'!C12,-'Underwriting Dashboard'!F7),"") | H73: =IF(B73<>"",D73-F73,"")
B74: =IF(65<='Underwriting Dashboard'!C12,65,"") | C74: =IF(B74<>"",EDATE(C73,1),"") | D74: =IF(B74<>"",G73,"") | E74: =IF(B74<>"",'Underwriting Dashboard'!F9,"") | F74: =IF(B74<>"",PPMT('Underwriting Dashboard'!F8,65,'Underwriting Dashboard'!C12,-'Underwriting Dashboard'!F7),"") | G74: =IF(B74<>"",IPMT('Underwriting Dashboard'!F8,65,'Underwriting Dashboard'!C12,-'Underwriting Dashboard'!F7),"") | H74: =IF(B74<>"",D74-F74,"")
B75: =IF(66<='Underwriting Dashboard'!C12,66,"") | C75: =IF(B75<>"",EDATE(C74,1),"") | D75: =IF(B75<>"",G74,"") | E75: =IF(B75<>"",'Underwriting Dashboard'!F9,"") | F75: =IF(B75<>"",PPMT('Underwriting Dashboard'!F8,66,'Underwriting Dashboard'!C12,-'Underwriting Dashboard'!F7),"") | G75: =IF(B75<>"",IPMT('Underwriting Dashboard'!F8,66,'Underwriting Dashboard'!C12,-'Underwriting Dashboard'!F7),"") | H75: =IF(B75<>"",D75-F75,"")
B76: =IF(67<='Underwriting Dashboard'!C12,67,"") | C76: =IF(B76<>"",EDATE(C75,1),"") | D76: =IF(B76<>"",G75,"") | E76: =IF(B76<>"",'Underwriting Dashboard'!F9,"") | F76: =IF(B76<>"",PPMT('Underwriting Dashboard'!F8,67,'Underwriting Dashboard'!C12,-'Underwriting Dashboard'!F7),"") | G76: =IF(B76<>"",IPMT('Underwriting Dashboard'!F8,67,'Underwriting Dashboard'!C12,-'Underwriting Dashboard'!F7),"") | H76: =IF(B76<>"",D76-F76,"")
B77: =IF(68<='Underwriting Dashboard'!C12,68,"") | C77: =IF(B77<>"",EDATE(C76,1),"") | D77: =IF(B77<>"",G76,"") | E77: =IF(B77<>"",'Underwriting Dashboard'!F9,"") | F77: =IF(B77<>"",PPMT('Underwriting Dashboard'!F8,68,'Underwriting Dashboard'!C12,-'Underwriting Dashboard'!F7),"") | G77: =IF(B77<>"",IPMT('Underwriting Dashboard'!F8,68,'Underwriting Dashboard'!C12,-'Underwriting Dashboard'!F7),"") | H77: =IF(B77<>"",D77-F77,"")
B78: =IF(69<='Underwriting Dashboard'!C12,69,"") | C78: =IF(B78<>"",EDATE(C77,1),"") | D78: =IF(B78<>"",G77,"") | E78: =IF(B78<>"",'Underwriting Dashboard'!F9,"") | F78: =IF(B78<>"",PPMT('Underwriting Dashboard'!F8,69,'Underwriting Dashboard'!C12,-'Underwriting Dashboard'!F7),"") | G78: =IF(B78<>"",IPMT('Underwriting Dashboard'!F8,69,'Underwriting Dashboard'!C12,-'Underwriting Dashboard'!F7),"") | H78: =IF(B78<>"",D78-F78,"")
B79: =IF(70<='Underwriting Dashboard'!C12,70,"") | C79: =IF(B79<>"",EDATE(C78,1),"") | D79: =IF(B79<>"",G78,"") | E79: =IF(B79<>"",'Underwriting Dashboard'!F9,"") | F79: =IF(B79<>"",PPMT('Underwriting Dashboard'!F8,70,'Underwriting Dashboard'!C12,-'Underwriting Dashboard'!F7),"") | G79: =IF(B79<>"",IPMT('Underwriting Dashboard'!F8,70,'Underwriting Dashboard'!C12,-'Underwriting Dashboard'!F7),"") | H79: =IF(B79<>"",D79-F79,"")
B80: =IF(71<='Underwriting Dashboard'!C12,71,"") | C80: =IF(B80<>"",EDATE(C79,1),"") | D80: =IF(B80<>"",G79,"") | E80: =IF(B80<>"",'Underwriting Dashboard'!F9,"") | F80: =IF(B80<>"",PPMT('Underwriting Dashboard'!F8,71,'Underwriting Dashboard'!C12,-'Underwriting Dashboard'!F7),"") | G80: =IF(B80<>"",IPMT('Underwriting Dashboard'!F8,71,'Underwriting Dashboard'!C12,-'Underwriting Dashboard'!F7),"") | H80: =IF(B80<>"",D80-F80,"")
B81: =IF(72<='Underwriting Dashboard'!C12,72,"") | C81: =IF(B81<>"",EDATE(C80,1),"") | D81: =IF(B81<>"",G80,"") | E81: =IF(B81<>"",'Underwriting Dashboard'!F9,"") | F81: =IF(B81<>"",PPMT('Underwriting Dashboard'!F8,72,'Underwriting Dashboard'!C12,-'Underwriting Dashboard'!F7),"") | G81: =IF(B81<>"",IPMT('Underwriting Dashboard'!F8,72,'Underwriting Dashboard'!C12,-'Underwriting Dashboard'!F7),"") | H81: =IF(B81<>"",D81-F81,"")
B82: =IF(73<='Underwriting Dashboard'!C12,73,"") | C82: =IF(B82<>"",EDATE(C81,1),"") | D82: =IF(B82<>"",G81,"") | E82: =IF(B82<>"",'Underwriting Dashboard'!F9,"") | F82: =IF(B82<>"",PPMT('Underwriting Dashboard'!F8,73,'Underwriting Dashboard'!C12,-'Underwriting Dashboard'!F7),"") | G82: =IF(B82<>"",IPMT('Underwriting Dashboard'!F8,73,'Underwriting Dashboard'!C12,-'Underwriting Dashboard'!F7),"") | H82: =IF(B82<>"",D82-F82,"")
B83: =IF(74<='Underwriting Dashboard'!C12,74,"") | C83: =IF(B83<>"",EDATE(C82,1),"") | D83: =IF(B83<>"",G82,"") | E83: =IF(B83<>"",'Underwriting Dashboard'!F9,"") | F83: =IF(B83<>"",PPMT('Underwriting Dashboard'!F8,74,'Underwriting Dashboard'!C12,-'Underwriting Dashboard'!F7),"") | G83: =IF(B83<>"",IPMT('Underwriting Dashboard'!F8,74,'Underwriting Dashboard'!C12,-'Underwriting Dashboard'!F7),"") | H83: =IF(B83<>"",D83-F83,"")
B84: =IF(75<='Underwriting Dashboard'!C12,75,"") | C84: =IF(B84<>"",EDATE(C83,1),"") | D84: =IF(B84<>"",G83,"") | E84: =IF(B84<>"",'Underwriting Dashboard'!F9,"") | F84: =IF(B84<>"",PPMT('Underwriting Dashboard'!F8,75,'Underwriting Dashboard'!C12,-'Underwriting Dashboard'!F7),"") | G84: =IF(B84<>"",IPMT('Underwriting Dashboard'!F8,75,'Underwriting Dashboard'!C12,-'Underwriting Dashboard'!F7),"") | H84: =IF(B84<>"",D84-F84,"")
B85: =IF(76<='Underwriting Dashboard'!C12,76,"") | C85: =IF(B85<>"",EDATE(C84,1),"") | D85: =IF(B85<>"",G84,"") | E85: =IF(B85<>"",'Underwriting Dashboard'!F9,"") | F85: =IF(B85<>"",PPMT('Underwriting Dashboard'!F8,76,'Underwriting Dashboard'!C12,-'Underwriting Dashboard'!F7),"") | G85: =IF(B85<>"",IPMT('Underwriting Dashboard'!F8,76,'Underwriting Dashboard'!C12,-'Underwriting Dashboard'!F7),"") | H85: =IF(B85<>"",D85-F85,"")
B86: =IF(77<='Underwriting Dashboard'!C12,77,"") | C86: =IF(B86<>"",EDATE(C85,1),"") | D86: =IF(B86<>"",G85,"") | E86: =IF(B86<>"",'Underwriting Dashboard'!F9,"") | F86: =IF(B86<>"",PPMT('Underwriting Dashboard'!F8,77,'Underwriting Dashboard'!C12,-'Underwriting Dashboard'!F7),"") | G86: =IF(B86<>"",IPMT('Underwriting Dashboard'!F8,77,'Underwriting Dashboard'!C12,-'Underwriting Dashboard'!F7),"") | H86: =IF(B86<>"",D86-F86,"")
B87: =IF(78<='Underwriting Dashboard'!C12,78,"") | C87: =IF(B87<>"",EDATE(C86,1),"") | D87: =IF(B87<>"",G86,"") | E87: =IF(B87<>"",'Underwriting Dashboard'!F9,"") | F87: =IF(B87<>"",PPMT('Underwriting Dashboard'!F8,78,'Underwriting Dashboard'!C12,-'Underwriting Dashboard'!F7),"") | G87: =IF(B87<>"",IPMT('Underwriting Dashboard'!F8,78,'Underwriting Dashboard'!C12,-'Underwriting Dashboard'!F7),"") | H87: =IF(B87<>"",D87-F87,"")
B88: =IF(79<='Underwriting Dashboard'!C12,79,"") | C88: =IF(B88<>"",EDATE(C87,1),"") | D88: =IF(B88<>"",G87,"") | E88: =IF(B88<>"",'Underwriting Dashboard'!F9,"") | F88: =IF(B88<>"",PPMT('Underwriting Dashboard'!F8,79,'Underwriting Dashboard'!C12,-'Underwriting Dashboard'!F7),"") | G88: =IF(B88<>"",IPMT('Underwriting Dashboard'!F8,79,'Underwriting Dashboard'!C12,-'Underwriting Dashboard'!F7),"") | H88: =IF(B88<>"",D88-F88,"")
B89: =IF(80<='Underwriting Dashboard'!C12,80,"") | C89: =IF(B89<>"",EDATE(C88,1),"") | D89: =IF(B89<>"",G88,"") | E89: =IF(B89<>"",'Underwriting Dashboard'!F9,"") | F89: =IF(B89<>"",PPMT('Underwriting Dashboard'!F8,80,'Underwriting Dashboard'!C12,-'Underwriting Dashboard'!F7),"") | G89: =IF(B89<>"",IPMT('Underwriting Dashboard'!F8,80,'Underwriting Dashboard'!C12,-'Underwriting Dashboard'!F7),"") | H89: =IF(B89<>"",D89-F89,"")
B90: =IF(81<='Underwriting Dashboard'!C12,81,"") | C90: =IF(B90<>"",EDATE(C89,1),"") | D90: =IF(B90<>"",G89,"") | E90: =IF(B90<>"",'Underwriting Dashboard'!F9,"") | F90: =IF(B90<>"",PPMT('Underwriting Dashboard'!F8,81,'Underwriting Dashboard'!C12,-'Underwriting Dashboard'!F7),"") | G90: =IF(B90<>"",IPMT('Underwriting Dashboard'!F8,81,'Underwriting Dashboard'!C12,-'Underwriting Dashboard'!F7),"") | H90: =IF(B90<>"",D90-F90,"")
B91: =IF(82<='Underwriting Dashboard'!C12,82,"") | C91: =IF(B91<>"",EDATE(C90,1),"") | D91: =IF(B91<>"",G90,"") | E91: =IF(B91<>"",'Underwriting Dashboard'!F9,"") | F91: =IF(B91<>"",PPMT('Underwriting Dashboard'!F8,82,'Underwriting Dashboard'!C12,-'Underwriting Dashboard'!F7),"") | G91: =IF(B91<>"",IPMT('Underwriting Dashboard'!F8,82,'Underwriting Dashboard'!C12,-'Underwriting Dashboard'!F7),"") | H91: =IF(B91<>"",D91-F91,"")
B92: =IF(83<='Underwriting Dashboard'!C12,83,"") | C92: =IF(B92<>"",EDATE(C91,1),"") | D92: =IF(B92<>"",G91,"") | E92: =IF(B92<>"",'Underwriting Dashboard'!F9,"") | F92: =IF(B92<>"",PPMT('Underwriting Dashboard'!F8,83,'Underwriting Dashboard'!C12,-'Underwriting Dashboard'!F7),"") | G92: =IF(B92<>"",IPMT('Underwriting Dashboard'!F8,83,'Underwriting Dashboard'!C12,-'Underwriting Dashboard'!F7),"") | H92: =IF(B92<>"",D92-F92,"")
B93: =IF(84<='Underwriting Dashboard'!C12,84,"") | C93: =IF(B93<>"",EDATE(C92,1),"") | D93: =IF(B93<>"",G92,"") | E93: =IF(B93<>"",'Underwriting Dashboard'!F9,"") | F93: =IF(B93<>"",PPMT('Underwriting Dashboard'!F8,84,'Underwriting Dashboard'!C12,-'Underwriting Dashboard'!F7),"") | G93: =IF(B93<>"",IPMT('Underwriting Dashboard'!F8,84,'Underwriting Dashboard'!C12,-'Underwriting Dashboard'!F7),"") | H93: =IF(B93<>"",D93-F93,"")
B94: TOTALS | E94: =SUM(E10:E93) -> 48079.673 | F94: =SUM(F10:F93) -> 40000 | G94: =SUM(G10:G93) -> 8079.6727
