Workbook

Sheet 📋 Instructions
B1: 📋 HOW TO USE THIS DASHBOARD
B3: COLOR CODING
B4: Blue text | C4: Input cells — enter or update your data here
B5: Black text | C5: Calculated formulas — do not overwrite
B6: Green text | C6: Cross-sheet links pulling from other tabs
B8: NAVIGATION
B9: 📊 Dashboard | C9: Master summary view — all KPIs, monthly table. Start here.
B10: 📥 Income | C10: Enter all income sources by month. Add rows as needed.
B11: 💸 Expenses | C11: Enter all monthly expenses by category. Column Q = annual budget.
B12: 💰 Goals | C12: Track savings goals, target amounts, and monthly allocations.
B13: 📊 Budget vs Actual | C13: Automatic variance analysis — no inputs needed.
B15: WORKFLOW
B16: Step 1 | C16: Go to 📥 Income — enter your monthly income by source (blue cells)
B17: Step 2 | C17: Go to 💸 Expenses — enter monthly spending. Set annual budgets in column Q.
B18: Step 3 | C18: Go to 💰 Goals — enter your financial goals and savings allocations.
B19: Step 4 | C19: Return to 📊 Dashboard — all charts and KPIs update automatically.
B20: Step 5 | C20: Review 📊 Budget vs Actual to see where you stand against targets.
B22: TIPS
B23: Do not delete rows | C23: Add new rows above the TOTAL rows to preserve formulas
B24: Monthly updates | C24: Update expense actuals at month-end; income posts when received
B25: Budget column | C25: Column Q on Expenses tab = annual budget; divide by 12 for monthly

Sheet 📊 Dashboard
B2: PERSONAL BUDGET DASHBOARD
B3: Fiscal Year 2025 | Real-Time Financial Snapshot
B6: TOTAL INCOME | D6: TOTAL EXPENSES | F6: NET SAVINGS | H6: SAVINGS RATE | J6: BUDGET VARIANCE
B7: =C25 -> 110500 | D7: =D25 -> 55125 | F7: =E25 -> 55375 | H7: =IF(B7=0,0,F7/B7) -> 0.50113122 | J7: ='📊 Budget vs Actual'!N5 -> 5
B11: 📅 MONTHLY SUMMARY
B12: Month | C12: Income | D12: Expenses | E12: Net Savings | F12: Savings Rate | G12: Cumul. Savings | H12: Housing | I12: Food | J12: Transport | K12: Health | L12: Other
B13: Jan | C13: ='📥 Income'!C11 -> 8700 | D13: ='💸 Expenses'!C29 -> 4415 | E13: =C13-D13 -> 4285 | F13: =IF(C13=0,0,E13/C13) -> 0.49252874 | G13: =E13 -> 4285 | H13: =SUM('💸 Expenses'!C6:C9) -> 2190 | I13: =SUM('💸 Expenses'!C11:C13) -> 750 | J13: =SUM('💸 Expenses'!C15:C18) -> 760 | K13: =SUM('💸 Expenses'!C20:C22) -> 350 | L13: =SUM('💸 Expenses'!C24:C28) -> 365
B14: Feb | C14: ='📥 Income'!D11 -> 8500 | D14: ='💸 Expenses'!D29 -> 4275 | E14: =C14-D14 -> 4225 | F14: =IF(C14=0,0,E14/C14) -> 0.49705882 | G14: =G13+E14 -> 8510 | H14: =SUM('💸 Expenses'!D6:D9) -> 2170 | I14: =SUM('💸 Expenses'!D11:D13) -> 680 | J14: =SUM('💸 Expenses'!D15:D18) -> 750 | K14: =SUM('💸 Expenses'!D20:D22) -> 350 | L14: =SUM('💸 Expenses'!D24:D28) -> 325
B15: Mar | C15: ='📥 Income'!E11 -> 9000 | D15: ='💸 Expenses'!E29 -> 4815 | E15: =C15-D15 -> 4185 | F15: =IF(C15=0,0,E15/C15) -> 0.465 | G15: =G14+E15 -> 12695 | H15: =SUM('💸 Expenses'!E6:E9) -> 2160 | I15: =SUM('💸 Expenses'!E11:E13) -> 785 | J15: =SUM('💸 Expenses'!E15:E18) -> 765 | K15: =SUM('💸 Expenses'!E20:E22) -> 500 | L15: =SUM('💸 Expenses'!E24:E28) -> 605
B16: Apr | C16: ='📥 Income'!F11 -> 8600 | D16: ='💸 Expenses'!F29 -> 4330 | E16: =C16-D16 -> 4270 | F16: =IF(C16=0,0,E16/C16) -> 0.49651163 | G16: =G15+E16 -> 16965 | H16: =SUM('💸 Expenses'!F6:F9) -> 2165 | I16: =SUM('💸 Expenses'!F11:F13) -> 715 | J16: =SUM('💸 Expenses'!F15:F18) -> 755 | K16: =SUM('💸 Expenses'!F20:F22) -> 350 | L16: =SUM('💸 Expenses'!F24:F28) -> 345
B17: May | C17: ='📥 Income'!G11 -> 8700 | D17: ='💸 Expenses'!G29 -> 4440 | E17: =C17-D17 -> 4260 | F17: =IF(C17=0,0,E17/C17) -> 0.48965517 | G17: =G16+E17 -> 21225 | H17: =SUM('💸 Expenses'!G6:G9) -> 2150 | I17: =SUM('💸 Expenses'!G11:G13) -> 675 | J17: =SUM('💸 Expenses'!G15:G18) -> 740 | K17: =SUM('💸 Expenses'!G20:G22) -> 350 | L17: =SUM('💸 Expenses'!G24:G28) -> 525
B18: Jun | C18: ='📥 Income'!H11 -> 11600 | D18: ='💸 Expenses'!H29 -> 4820 | E18: =C18-D18 -> 6780 | F18: =IF(C18=0,0,E18/C18) -> 0.58448276 | G18: =G17+E18 -> 28005 | H18: =SUM('💸 Expenses'!H6:H9) -> 2155 | I18: =SUM('💸 Expenses'!H11:H13) -> 850 | J18: =SUM('💸 Expenses'!H15:H18) -> 770 | K18: =SUM('💸 Expenses'!H20:H22) -> 550 | L18: =SUM('💸 Expenses'!H24:H28) -> 495
B19: Jul | C19: ='📥 Income'!I11 -> 8500 | D19: ='💸 Expenses'!I29 -> 5035 | E19: =C19-D19 -> 3465 | F19: =IF(C19=0,0,E19/C19) -> 0.40764706 | G19: =G18+E19 -> 31470 | H19: =SUM('💸 Expenses'!I6:I9) -> 2170 | I19: =SUM('💸 Expenses'!I11:I13) -> 910 | J19: =SUM('💸 Expenses'!I15:I18) -> 780 | K19: =SUM('💸 Expenses'!I20:I22) -> 350 | L19: =SUM('💸 Expenses'!I24:I28) -> 825
B20: Aug | C20: ='📥 Income'!J11 -> 8650 | D20: ='💸 Expenses'!J29 -> 4535 | E20: =C20-D20 -> 4115 | F20: =IF(C20=0,0,E20/C20) -> 0.47572254 | G20: =G19+E20 -> 35585 | H20: =SUM('💸 Expenses'!J6:J9) -> 2180 | I20: =SUM('💸 Expenses'!J11:J13) -> 835 | J20: =SUM('💸 Expenses'!J15:J18) -> 775 | K20: =SUM('💸 Expenses'!J20:J22) -> 350 | L20: =SUM('💸 Expenses'!J24:J28) -> 395
B21: Sep | C21: ='📥 Income'!K11 -> 8800 | D21: ='💸 Expenses'!K29 -> 4500 | E21: =C21-D21 -> 4300 | F21: =IF(C21=0,0,E21/C21) -> 0.48863636 | G21: =G20+E21 -> 39885 | H21: =SUM('💸 Expenses'!K6:K9) -> 2175 | I21: =SUM('💸 Expenses'!K11:K13) -> 750 | J21: =SUM('💸 Expenses'!K15:K18) -> 765 | K21: =SUM('💸 Expenses'!K20:K22) -> 450 | L21: =SUM('💸 Expenses'!K24:K28) -> 360
B22: Oct | C22: ='📥 Income'!L11 -> 8550 | D22: ='💸 Expenses'!L29 -> 4470 | E22: =C22-D22 -> 4080 | F22: =IF(C22=0,0,E22/C22) -> 0.47719298 | G22: =G21+E22 -> 43965 | H22: =SUM('💸 Expenses'!L6:L9) -> 2165 | I22: =SUM('💸 Expenses'!L11:L13) -> 710 | J22: =SUM('💸 Expenses'!L15:L18) -> 755 | K22: =SUM('💸 Expenses'!L20:L22) -> 350 | L22: =SUM('💸 Expenses'!L24:L28) -> 490
B23: Nov | C23: ='📥 Income'!M11 -> 8900 | D23: ='💸 Expenses'!M29 -> 4485 | E23: =C23-D23 -> 4415 | F23: =IF(C23=0,0,E23/C23) -> 0.49606742 | G23: =G22+E23 -> 48380 | H23: =SUM('💸 Expenses'!M6:M9) -> 2185 | I23: =SUM('💸 Expenses'!M11:M13) -> 785 | J23: =SUM('💸 Expenses'!M15:M18) -> 770 | K23: =SUM('💸 Expenses'!M20:M22) -> 350 | L23: =SUM('💸 Expenses'!M24:M28) -> 395
B24: Dec | C24: ='📥 Income'!N11 -> 12000 | D24: ='💸 Expenses'!N29 -> 5005 | E24: =C24-D24 -> 6995 | F24: =IF(C24=0,0,E24/C24) -> 0.58291667 | G24: =G23+E24 -> 55375 | H24: =SUM('💸 Expenses'!N6:N9) -> 2200 | I24: =SUM('💸 Expenses'!N11:N13) -> 955 | J24: =SUM('💸 Expenses'!N15:N18) -> 785 | K24: =SUM('💸 Expenses'!N20:N22) -> 350 | L24: =SUM('💸 Expenses'!N24:N28) -> 715
B25: TOTAL | C25: =SUM(C13:C24) -> 110500 | D25: =SUM(D13:D24) -> 55125 | E25: =SUM(E13:E24) -> 55375 | F25: =IF(C25=0,0,E25/C25) -> 0.50113122 | G25: =G24 -> 55375 | H25: =SUM(H13:H24) -> 26065 | I25: =SUM(I13:I24) -> 9400 | J25: =SUM(J13:J24) -> 9170 | K25: =SUM(K13:K24) -> 4650 | L25: =SUM(L13:L24) -> 5840
B27: 📈 VISUAL ANALYTICS

Sheet 📥 Income
B1: 📥 INCOME TRACKER
B2: Enter all income sources below. Blue cells = inputs. Totals calculate automatically.
B4: Income Source | C4: Jan | D4: Feb | E4: Mar | F4: Apr | G4: May | H4: Jun | I4: Jul | J4: Aug | K4: Sep | L4: Oct | M4: Nov | N4: Dec | O4: Annual Total | P4: % of Total
B5: Primary Salary | C5: 6500 | D5: 6500 | E5: 6500 | F5: 6500 | G5: 6500 | H5: 6500 | I5: 6500 | J5: 6500 | K5: 6500 | L5: 6500 | M5: 6500 | N5: 6500 | O5: =SUM(C5:N5) -> 78000 | P5: =IF(O16=0,0,O5/O16) -> 0
B6: Bonus / Commission | C6: 0 | D6: 0 | E6: 0 | F6: 0 | G6: 0 | H6: 2500 | I6: 0 | J6: 0 | K6: 0 | L6: 0 | M6: 0 | N6: 3000 | O6: =SUM(C6:N6) -> 5500 | P6: =IF(O16=0,0,O6/O16) -> 0
B7: Freelance / Side Gig | C7: 800 | D7: 600 | E7: 950 | F7: 700 | G7: 800 | H7: 1200 | I7: 600 | J7: 750 | K7: 900 | L7: 650 | M7: 800 | N7: 1100 | O7: =SUM(C7:N7) -> 9850 | P7: =IF(O16=0,0,O7/O16) -> 0
B8: Investment Income | C8: 200 | D8: 200 | E8: 200 | F8: 200 | G8: 200 | H8: 200 | I8: 200 | J8: 200 | K8: 200 | L8: 200 | M8: 200 | N8: 200 | O8: =SUM(C8:N8) -> 2400 | P8: =IF(O16=0,0,O8/O16) -> 0
B9: Rental Income | C9: 1200 | D9: 1200 | E9: 1200 | F9: 1200 | G9: 1200 | H9: 1200 | I9: 1200 | J9: 1200 | K9: 1200 | L9: 1200 | M9: 1200 | N9: 1200 | O9: =SUM(C9:N9) -> 14400 | P9: =IF(O16=0,0,O9/O16) -> 0
B10: Other Income | C10: 0 | D10: 0 | E10: 150 | F10: 0 | G10: 0 | H10: 0 | I10: 0 | J10: 0 | K10: 0 | L10: 0 | M10: 200 | N10: 0 | O10: =SUM(C10:N10) -> 350 | P10: =IF(O16=0,0,O10/O16) -> 0
B11: TOTAL INCOME | C11: =SUM(C5:C10) -> 8700 | D11: =SUM(D5:D10) -> 8500 | E11: =SUM(E5:E10) -> 9000 | F11: =SUM(F5:F10) -> 8600 | G11: =SUM(G5:G10) -> 8700 | H11: =SUM(H5:H10) -> 11600 | I11: =SUM(I5:I10) -> 8500 | J11: =SUM(J5:J10) -> 8650 | ... O11: =SUM(O5:O10) -> 110500 | P11: 100.0%

Sheet 💸 Expenses
B1: 💸 EXPENSE TRACKER
B2: Track all monthly expenses by category. Blue = inputs. Column Q = annual budget for variance analysis.
B4: Category | C4: Jan | D4: Feb | E4: Mar | F4: Apr | G4: May | H4: Jun | I4: Jul | J4: Aug | K4: Sep | L4: Oct | M4: Nov | N4: Dec | O4: Annual Total | P4: % of Total | Q4: Annual Budget
B5: ── HOUSING ──
B6: Rent / Mortgage | C6: 1800 | D6: 1800 | E6: 1800 | F6: 1800 | G6: 1800 | H6: 1800 | I6: 1800 | J6: 1800 | K6: 1800 | L6: 1800 | M6: 1800 | N6: 1800 | O6: =SUM(C6:N6) -> 21600 | P6: =IF(O29=0,0,O6/O29) -> 0.39183673 | Q6: 21600
B7: Utilities | C7: 180 | D7: 160 | E7: 150 | F7: 155 | G7: 140 | H7: 145 | I7: 160 | J7: 170 | K7: 165 | L7: 155 | M7: 175 | N7: 190 | O7: =SUM(C7:N7) -> 1945 | P7: =IF(O29=0,0,O7/O29) -> 0.035283447 | Q7: 1950
B8: Internet / Cable | C8: 90 | D8: 90 | E8: 90 | F8: 90 | G8: 90 | H8: 90 | I8: 90 | J8: 90 | K8: 90 | L8: 90 | M8: 90 | N8: 90 | O8: =SUM(C8:N8) -> 1080 | P8: =IF(O29=0,0,O8/O29) -> 0.019591837 | Q8: 1080
B9: Insurance (Home) | C9: 120 | D9: 120 | E9: 120 | F9: 120 | G9: 120 | H9: 120 | I9: 120 | J9: 120 | K9: 120 | L9: 120 | M9: 120 | N9: 120 | O9: =SUM(C9:N9) -> 1440 | P9: =IF(O29=0,0,O9/O29) -> 0.026122449 | Q9: 1440
B10: ── FOOD ──
B11: Groceries | C11: 450 | D11: 430 | E11: 460 | F11: 440 | G11: 420 | H11: 480 | I11: 500 | J11: 490 | K11: 455 | L11: 445 | M11: 470 | N11: 510 | O11: =SUM(C11:N11) -> 5550 | P11: =IF(O29=0,0,O11/O29) -> 0.10068027 | Q11: 5550
B12: Dining Out | C12: 220 | D12: 180 | E12: 240 | F12: 200 | G12: 190 | H12: 280 | I12: 310 | J12: 260 | K12: 215 | L12: 195 | M12: 230 | N12: 350 | O12: =SUM(C12:N12) -> 2870 | P12: =IF(O29=0,0,O12/O29) -> 0.052063492 | Q12: 2870
B13: Coffee / Snacks | C13: 80 | D13: 70 | E13: 85 | F13: 75 | G13: 65 | H13: 90 | I13: 100 | J13: 85 | K13: 80 | L13: 70 | M13: 85 | N13: 95 | O13: =SUM(C13:N13) -> 980 | P13: =IF(O29=0,0,O13/O29) -> 0.017777778 | Q13: 980
B14: ── TRANSPORTATION ──
B15: Car Payment | C15: 450 | D15: 450 | E15: 450 | F15: 450 | G15: 450 | H15: 450 | I15: 450 | J15: 450 | K15: 450 | L15: 450 | M15: 450 | N15: 450 | O15: =SUM(C15:N15) -> 5400 | P15: =IF(O29=0,0,O15/O29) -> 0.097959184 | Q15: 5400
B16: Gas | C16: 140 | D16: 130 | E16: 145 | F16: 135 | G16: 120 | H16: 150 | I16: 160 | J16: 155 | K16: 145 | L16: 135 | M16: 150 | N16: 165 | O16: =SUM(C16:N16) -> 1730 | P16: =IF(O29=0,0,O16/O29) -> 0.03138322 | Q16: 1730
B17: Insurance (Auto) | C17: 110 | D17: 110 | E17: 110 | F17: 110 | G17: 110 | H17: 110 | I17: 110 | J17: 110 | K17: 110 | L17: 110 | M17: 110 | N17: 110 | O17: =SUM(C17:N17) -> 1320 | P17: =IF(O29=0,0,O17/O29) -> 0.023945578 | Q17: 1320
B18: Public Transit | C18: 60 | D18: 60 | E18: 60 | F18: 60 | G18: 60 | H18: 60 | I18: 60 | J18: 60 | K18: 60 | L18: 60 | M18: 60 | N18: 60 | O18: =SUM(C18:N18) -> 720 | P18: =IF(O29=0,0,O18/O29) -> 0.013061224 | Q18: 720
B19: ── HEALTH ──
B20: Health Insurance | C20: 300 | D20: 300 | E20: 300 | F20: 300 | G20: 300 | H20: 300 | I20: 300 | J20: 300 | K20: 300 | L20: 300 | M20: 300 | N20: 300 | O20: =SUM(C20:N20) -> 3600 | P20: =IF(O29=0,0,O20/O29) -> 0.065306122 | Q20: 3600
B21: Gym / Fitness | C21: 50 | D21: 50 | E21: 50 | F21: 50 | G21: 50 | H21: 50 | I21: 50 | J21: 50 | K21: 50 | L21: 50 | M21: 50 | N21: 50 | O21: =SUM(C21:N21) -> 600 | P21: =IF(O29=0,0,O21/O29) -> 0.010884354 | Q21: 600
B22: Medical / Dental | C22: 0 | D22: 0 | E22: 150 | F22: 0 | G22: 0 | H22: 200 | I22: 0 | J22: 0 | K22: 100 | L22: 0 | M22: 0 | N22: 0 | O22: =SUM(C22:N22) -> 450 | P22: =IF(O29=0,0,O22/O29) -> 0.0081632653 | Q22: 450
B23: ── LIFESTYLE & OTHER ──
B24: Entertainment | C24: 120 | D24: 100 | E24: 140 | F24: 110 | G24: 130 | H24: 200 | I24: 180 | J24: 150 | K24: 125 | L24: 115 | M24: 140 | N24: 220 | O24: =SUM(C24:N24) -> 1730 | P24: =IF(O29=0,0,O24/O29) -> 0.03138322 | Q24: 1730
B25: Clothing | C25: 0 | D25: 0 | E25: 200 | F25: 0 | G25: 150 | H25: 0 | I25: 300 | J25: 0 | K25: 0 | L25: 150 | M25: 0 | N25: 200 | O25: =SUM(C25:N25) -> 1000 | P25: =IF(O29=0,0,O25/O29) -> 0.01814059 | Q25: 1000
B26: Personal Care | C26: 60 | D26: 60 | E26: 60 | F26: 60 | G26: 60 | H26: 60 | I26: 60 | J26: 60 | K26: 60 | L26: 60 | M26: 60 | N26: 60 | O26: =SUM(C26:N26) -> 720 | P26: =IF(O29=0,0,O26/O29) -> 0.013061224 | Q26: 720
B27: Subscriptions | C27: 85 | D27: 85 | E27: 85 | F27: 85 | G27: 85 | H27: 85 | I27: 85 | J27: 85 | K27: 85 | L27: 85 | M27: 85 | N27: 85 | O27: =SUM(C27:N27) -> 1020 | P27: =IF(O29=0,0,O27/O29) -> 0.018503401 | Q27: 1020
B28: Miscellaneous | C28: 100 | D28: 80 | E28: 120 | F28: 90 | G28: 100 | H28: 150 | I28: 200 | J28: 100 | K28: 90 | L28: 80 | M28: 110 | N28: 150 | O28: =SUM(C28:N28) -> 1370 | P28: =IF(O29=0,0,O28/O29) -> 0.024852608 | Q28: 1370
B29: TOTAL EXPENSES | C29: =SUM(C5:C28) -> 4415 | D29: =SUM(D5:D28) -> 4275 | E29: =SUM(E5:E28) -> 4815 | F29: =SUM(F5:F28) -> 4330 | G29: =SUM(G5:G28) -> 4440 | H29: =SUM(H5:H28) -> 4820 | I29: =SUM(I5:I28) -> 5035 | J29: =SUM(J5:J28) -> 4535 | ... O29: =SUM(O5:O28) -> 55125 | Q29: =SUM(Q5:Q28) -> 55130

Sheet 💰 Goals
B1: 💰 SAVINGS & FINANCIAL GOALS
B3: FINANCIAL GOALS TRACKER
B4: Goal Name | C4: Target Amount | D4: Current Saved | E4: Monthly Contribution | F4: Target Date | G4: % Complete | H4: Status
B5: Emergency Fund | C5: 15000 | D5: 8500 | E5: 500 | F5: Dec-2025 | G5: =IF(C5=0,0,D5/C5) -> 0.56666667 | H5: =IF(G5>=1,"✅ Complete",IF(G5>=0.75,"🟡 On Track","🔴 Behind")) -> 🔴 Behind
B6: Vacation / Travel | C6: 5000 | D6: 1200 | E6: 300 | F6: Jun-2025 | G6: =IF(C6=0,0,D6/C6) -> 0.24 | H6: =IF(G6>=1,"✅ Complete",IF(G6>=0.75,"🟡 On Track","🔴 Behind")) -> 🔴 Behind
B7: New Car | C7: 12000 | D7: 3000 | E7: 400 | F7: Mar-2026 | G7: =IF(C7=0,0,D7/C7) -> 0.25 | H7: =IF(G7>=1,"✅ Complete",IF(G7>=0.75,"🟡 On Track","🔴 Behind")) -> 🔴 Behind
B8: Home Down Payment | C8: 60000 | D8: 18000 | E8: 1200 | F8: Dec-2027 | G8: =IF(C8=0,0,D8/C8) -> 0.3 | H8: =IF(G8>=1,"✅ Complete",IF(G8>=0.75,"🟡 On Track","🔴 Behind")) -> 🔴 Behind
B9: Retirement (IRA) | C9: 7000 | D9: 4500 | E9: 500 | F9: Dec-2025 | G9: =IF(C9=0,0,D9/C9) -> 0.64285714 | H9: =IF(G9>=1,"✅ Complete",IF(G9>=0.75,"🟡 On Track","🔴 Behind")) -> 🔴 Behind
B10: Education / Cert. | C10: 3000 | D10: 500 | E10: 200 | F10: Sep-2025 | G10: =IF(C10=0,0,D10/C10) -> 0.16666667 | H10: =IF(G10>=1,"✅ Complete",IF(G10>=0.75,"🟡 On Track","🔴 Behind")) -> 🔴 Behind
B11: TOTAL GOALS | C11: =SUM(C5:C10) -> 102000 | D11: =SUM(D5:D10) -> 35700 | E11: =SUM(E5:E10) -> 3100 | G11: =IF(C11=0,0,D11/C11) -> 0.35
B13: MONTHLY SAVINGS ALLOCATION
B14: Account / Fund | C14: Monthly Deposit | D14: Current Balance | E14: Annual Target | F14: YTD Progress | G14: Notes
B15: Emergency Fund | C15: 500 | D15: 8500 | E15: 6000 | F15: =IF(E15=0,0,D15/E15) -> 1.4166667 | G15: High priority
B16: Roth IRA | C16: 500 | D16: 4500 | E16: 7000 | F16: =IF(E16=0,0,D16/E16) -> 0.64285714 | G16: Max contribution
B17: 401(k) / Retirement | C17: 650 | D17: 18000 | E17: 7800 | F17: =IF(E17=0,0,D17/E17) -> 2.3076923 | G17: Employer match 4%
B18: Brokerage / Invest. | C18: 300 | D18: 5200 | E18: 3600 | F18: =IF(E18=0,0,D18/E18) -> 1.4444444 | G18: Index funds
B19: Vacation Fund | C19: 300 | D19: 1200 | E19: 3600 | F19: =IF(E19=0,0,D19/E19) -> 0.33333333 | G19: Trip in June
B20: Sinking Fund | C20: 200 | D20: 800 | E20: 2400 | F20: =IF(E20=0,0,D20/E20) -> 0.33333333 | G20: Car repair / irregular
B21: TOTAL MONTHLY SAVINGS | C21: =SUM(C15:C20) -> 2450 | D21: =SUM(D15:D20) -> 38200 | E21: =SUM(E15:E20) -> 30400

Sheet 📊 Budget vs Actual
B1: 📊 BUDGET vs. ACTUAL ANALYSIS
B2: Annual budget set on the Expenses sheet. Variance = Budget – Actual. Positive = under budget.
B4: Category | C4: Annual Budget | D4: YTD Actual | E4: Variance ($) | F4: Variance (%)
B5: Housing | C5: =SUM('💸 Expenses'!Q6:Q9) -> 26070 | D5: =SUM('💸 Expenses'!O6:O9) -> 26065 | E5: =C5-D5 -> 5 | F5: =IF(C5=0,0,E5/C5) -> 0.00019179133 | N5: =E10 -> 5
B6: Food | C6: =SUM('💸 Expenses'!Q11:Q13) -> 9400 | D6: =SUM('💸 Expenses'!O11:O13) -> 9400 | E6: =C6-D6 -> 0 | F6: =IF(C6=0,0,E6/C6) -> 0
B7: Transportation | C7: =SUM('💸 Expenses'!Q15:Q18) -> 9170 | D7: =SUM('💸 Expenses'!O15:O18) -> 9170 | E7: =C7-D7 -> 0 | F7: =IF(C7=0,0,E7/C7) -> 0
B8: Health | C8: =SUM('💸 Expenses'!Q20:Q22) -> 4650 | D8: =SUM('💸 Expenses'!O20:O22) -> 4650 | E8: =C8-D8 -> 0 | F8: =IF(C8=0,0,E8/C8) -> 0
B9: Lifestyle/Other | C9: =SUM('💸 Expenses'!Q24:Q28) -> 5840 | D9: =SUM('💸 Expenses'!O24:O28) -> 5840 | E9: =C9-D9 -> 0 | F9: =IF(C9=0,0,E9/C9) -> 0
B10: TOTAL | C10: =SUM(C5:C9) -> 55130 | D10: =SUM(D5:D9) -> 55125 | E10: =C10-D10 -> 5 | F10: =IF(C10=0,0,E10/C10) -> 9.0694722e-05
B12: INCOME: BUDGET vs ACTUAL
B13: Category | C13: Annual Budget | D13: YTD Actual | E13: Variance ($) | F13: Variance (%)
B14: Primary Salary | C14: ='📥 Income'!O5 -> 78000 | D14: ='📥 Income'!O5 -> 78000 | E14: =C14-D14 -> 0 | F14: =IF(C14=0,0,E14/C14) -> 0
B15: Bonus / Commission | C15: ='📥 Income'!O6 -> 5500 | D15: ='📥 Income'!O6 -> 5500 | E15: =C15-D15 -> 0 | F15: =IF(C15=0,0,E15/C15) -> 0
B16: Freelance | C16: ='📥 Income'!O7 -> 9850 | D16: ='📥 Income'!O7 -> 9850 | E16: =C16-D16 -> 0 | F16: =IF(C16=0,0,E16/C16) -> 0
B17: Investment Income | C17: ='📥 Income'!O8 -> 2400 | D17: ='📥 Income'!O8 -> 2400 | E17: =C17-D17 -> 0 | F17: =IF(C17=0,0,E17/C17) -> 0
B18: Rental Income | C18: ='📥 Income'!O9 -> 14400 | D18: ='📥 Income'!O9 -> 14400 | E18: =C18-D18 -> 0 | F18: =IF(C18=0,0,E18/C18) -> 0
B19: Other Income | C19: ='📥 Income'!O10 -> 350 | D19: ='📥 Income'!O10 -> 350 | E19: =C19-D19 -> 0 | F19: =IF(C19=0,0,E19/C19) -> 0
B20: TOTAL INCOME | C20: =SUM(C14:C19) -> 110500 | D20: =SUM(D14:D19) -> 110500 | E20: =SUM(E14:E19) -> 0 | F20: =IF(C20=0,0,E20/C20) -> 0
B22: NET (Income – Expenses) | C22: =C20-C10 -> 55370 | D22: =D20-D10 -> 55375 | E22: =E20-E10 -> -5 | F22: =IF(C22=0,0,E22/C22) -> -9.0301607e-05
