Workbook

Sheet Cover
B8: SaaS Financial Plan
B9: Enterprise Edition · Multi-Tier · Full 3-Statement Model
B10: Built by Quanthaven Labs LLC
B12: ✓ 3-Tier Pricing (Starter / Growth / Enterprise)
B14: ✓ Acquisition Funnel (Organic / Paid / Partner channels)
B16: ✓ Annual vs. Monthly Billing + Deferred Revenue
B18: ✓ Full 3-Statement Model (P&L · Balance Sheet · Cash Flow)
B20: ✓ SaaS KPI Dashboard with Benchmark Flags
B22: ✓ Scenario Toggle (Base / Upside / Downside)
B24: ✓ Burn Rate & Runway Tracker
B26: ✓ 36-Month Rolling Forecast (3 Years)
B31: ="Version 1.0 · Model Start: "&TEXT(Controls!$B$6,"mmmm yyyy")&" · Forecast Horizon: 36 Months" -> Version 1.0 · Model Start: January 2026 · Forecast Horizon: 36 Months
B33: START HERE → Controls → Revenue → Headcount → OpEx → P&L · Balance Sheet · Cash Flow · KPI Dashboard

Sheet Instructions
A2: HOW TO USE THIS MODEL · Step-by-Step Guide
A4: 1 | B4: Controls Tab | C4: Start here. Set your tax rate, scenario (Base/Upside/Downside), opening cash balance, payroll tax rate, and benefits rate. These feed the entire model.
A6: 2 | B6: Revenue Tab – Pricing | C6: Enter your ARPU for each tier (Starter / Growth / Enterprise) and the % of customers expected to choose annual billing per tier.
A8: 3 | B8: Revenue Tab – Acquisition Funnel | C8: Set Month 1 website visitors and traffic growth rate. Set trial and conversion rates. Set Month 1 paid marketing budget, CAC, partner leads, and close rate. The model computes monthly new customers from all three channels.
A10: 4 | B10: Revenue Tab – Customer Mix & Churn | C10: Set the % of new customers going to each tier (must sum to 100%). Set monthly gross churn rates per tier. Expansion MRR rates are pre-filled — adjust as needed.
A12: 5 | B12: Revenue Tab – Services Revenue | C12: Row 104: Pre-filled monthly professional services revenue. Overwrite with your own actuals or projections.
A14: 6 | B14: Headcount Tab | C14: Enter monthly base salary cost by department. Benefits and payroll tax are applied automatically from your Controls assumptions.
A16: 7 | B16: OpEx Tab | C16: Enter non-wage operating expenses by department and category. Categories are pre-filled with reasonable starting assumptions — adjust to match your cost structure.
A18: 8 | B18: P&L Tab | C18: Read-only (calculated). Review your SaaS income statement: Subscription revenue, COGS, Gross Profit, EBITDA, EBIT, and Net Income with margin percentages.
A20: 9 | B20: Balance Sheet Tab | C20: Read-only (calculated). End-of-period balance sheet. Review assets (cash, AR), liabilities (AP, deferred revenue), and equity.
A22: 10 | B22: Cash Flow Tab | C22: Read-only (calculated). Indirect-method cash flow statement. Monitor FCF, monthly burn rate, and runway in months.
A24: 11 | B24: KPI Dashboard | C24: Read-only (calculated). All key SaaS metrics: MRR, ARR, NRR, Gross Margin, EBITDA, ARPA, LTV, CAC, LTV:CAC, CAC Payback, Magic Number, Rule of 40. Benchmark reference guide included.
A26: 12 | B26: Scenario Analysis | C26: Change the "Active Scenario" in Controls!B12 between Base, Upside, and Downside. The revenue multiplier and churn multiplier are applied automatically. Compare outputs in the KPI Dashboard.

Sheet Controls
A1: GLOBAL CONTROLS
A2: All blue cells below are user inputs — changes flow through the entire model
A3: Setting | B3: Value | C3: Notes
A5: MODEL SETTINGS
A6: Model Start Date | B6: 46023 | C6: Enter as an actual date — Excel will display as mmm-yy (e.g. Jan-25). All headers auto-update.
A7: Forecast Horizon (Months) | B7: 36 | C7: Active months: 12–60. Columns beyond this show gray/zero. Annual cols auto-adjust.
A8: Tax Rate | B8: 0.25 | C8: Effective corp income tax rate
A9: Base Currency | B9: USD
A10: SCENARIO TOGGLE
A11: Scenario Instructions | C11: Type "Base", "Upside", or "Downside" in B12
A12: Active Scenario | B12: Base | C12: Base | Upside | Downside
A13: Upside Rev Multiplier | B13: 1.25 | C13: Applied to new customer counts
A14: Downside Rev Multiplier | B14: 0.75 | C14: Applied to new customer counts
A15: Upside Churn Multiplier | B15: 0.8 | C15: Lower churn in upside (e.g. 0.80 = 20% better)
A16: Downside Churn Multiplier | B16: 1.3 | C16: Higher churn in downside (e.g. 1.30 = 30% worse)
A17: FINANCING
A18: Financing Instructions | C18: Enter opening cash balance and any debt raised at model start
A19: Opening Cash Balance ($) | B19: 1000000 | C19: Cash on hand at model start (seed / Series A proceeds)
A20: Debt Raised ($) | B20: 0 | C20: Term loan or convertible note principal
A21: Annual Interest Rate | B21: 0.08 | C21: Interest on outstanding debt
A22: EXPENSE ASSUMPTIONS
A23: Expense Instructions | C23: These rates are applied globally in Headcount tab
A24: Employer Payroll Tax Rate | B24: 0.0765 | C24: Federal FICA — adjust for state
A25: Benefits Rate (% Salary) | B25: 0.18 | C25: Health, dental, vision, 401k match
A26: CapEx Depr Life (Years) | B26: 3 | C26: Straight-line useful life for CapEx
A29: COLOR KEY
A30: Sample Text | B30: Blue text on yellow → User input — safe to change
A31: Sample Text | B31: Black text → Formula — do not manually overwrite
A32: Sample Text | B32: Green text → Linked from another tab
A33: Sample Text | B33: Gray italic → Descriptive label or instruction

Sheet Revenue
A1: REVENUE MODEL · 3-Tier SaaS Subscription + Acquisition Funnel
A3: Label | B3: Unit | C3: =TEXT(EDATE(Controls!$B$6,0),"mmm-yy") -> Jan-26 | D3: =TEXT(EDATE(Controls!$B$6,1),"mmm-yy") -> Feb-26 | E3: =TEXT(EDATE(Controls!$B$6,2),"mmm-yy") -> Mar-26 | F3: =TEXT(EDATE(Controls!$B$6,3),"mmm-yy") -> Apr-26 | G3: =TEXT(EDATE(Controls!$B$6,4),"mmm-yy") -> May-26 | H3: =TEXT(EDATE(Controls!$B$6,5),"mmm-yy") -> Jun-26 | I3: =TEXT(EDATE(Controls!$B$6,6),"mmm-yy") -> Jul-26 | J3: =TEXT(EDATE(Controls!$B$6,7),"mmm-yy") -> Aug-26 | K3: =TEXT(EDATE(Controls!$B$6,8),"mmm-yy") -> Sep-26 | L3: =TEXT(EDATE(Controls!$B$6,9),"mmm-yy") -> Oct-26 | M3: =TEXT(EDATE(Controls!$B$6,10),"mmm-yy") -> Nov-26 | N3: =TEXT(EDATE(Controls!$B$6,11),"mmm-yy") -> Dec-26 | O3: =TEXT(EDATE(Controls!$B$6,12),"mmm-yy") -> Jan-27 | P3: =TEXT(EDATE(Controls!$B$6,13),"mmm-yy") -> Feb-27 | Q3: =TEXT(EDATE(Controls!$B$6,14),"mmm-yy") -> Mar-27 | R3: =TEXT(EDATE(Controls!$B$6,15),"mmm-yy") -> Apr-27 | S3: =TEXT(EDATE(Controls!$B$6,16),"mmm-yy") -> May-27 | T3: =TEXT(EDATE(Controls!$B$6,17),"mmm-yy") -> Jun-27 | U3: =TEXT(EDATE(Controls!$B$6,18),"mmm-yy") -> Jul-27 | V3: =TEXT(EDATE(Controls!$B$6,19),"mmm-yy") -> Aug-27 | W3: =TEXT(EDATE(Controls!$B$6,20),"mmm-yy") -> Sep-27 | X3: =TEXT(EDATE(Controls!$B$6,21),"mmm-yy") -> Oct-27 | Y3: =TEXT(EDATE(Controls!$B$6,22),"mmm-yy") -> Nov-27 | Z3: =TEXT(EDATE(Controls!$B$6,23),"mmm-yy") -> Dec-27 | AA3: =TEXT(EDATE(Controls!$B$6,24),"mmm-yy") -> Jan-28 | AB3: =TEXT(EDATE(Controls!$B$6,25),"mmm-yy") -> Feb-28 | AC3: =TEXT(EDATE(Controls!$B$6,26),"mmm-yy") -> Mar-28 | AD3: =TEXT(EDATE(Controls!$B$6,27),"mmm-yy") -> Apr-28 | AE3: =TEXT(EDATE(Controls!$B$6,28),"mmm-yy") -> May-28 | AF3: =TEXT(EDATE(Controls!$B$6,29),"mmm-yy") -> Jun-28 | AG3: =TEXT(EDATE(Controls!$B$6,30),"mmm-yy") -> Jul-28 | AH3: =TEXT(EDATE(Controls!$B$6,31),"mmm-yy") -> Aug-28 | AI3: =TEXT(EDATE(Controls!$B$6,32),"mmm-yy") -> Sep-28 | AJ3: =TEXT(EDATE(Controls!$B$6,33),"mmm-yy") -> Oct-28 | AK3: =TEXT(EDATE(Controls!$B$6,34),"mmm-yy") -> Nov-28 | AL3: =TEXT(EDATE(Controls!$B$6,35),"mmm-yy") -> Dec-28 | AM3: =TEXT(EDATE(Controls!$B$6,36),"mmm-yy") -> Jan-29 | AN3: =TEXT(EDATE(Controls!$B$6,37),"mmm-yy") -> Feb-29 | AO3: =TEXT(EDATE(Controls!$B$6,38),"mmm-yy") -> Mar-29 | AP3: =TEXT(EDATE(Controls!$B$6,39),"mmm-yy") -> Apr-29 | AQ3: =TEXT(EDATE(Controls!$B$6,40),"mmm-yy") -> May-29 | AR3: =TEXT(EDATE(Controls!$B$6,41),"mmm-yy") -> Jun-29 | AS3: =TEXT(EDATE(Controls!$B$6,42),"mmm-yy") -> Jul-29 | AT3: =TEXT(EDATE(Controls!$B$6,43),"mmm-yy") -> Aug-29 | AU3: =TEXT(EDATE(Controls!$B$6,44),"mmm-yy") -> Sep-29 | AV3: =TEXT(EDATE(Controls!$B$6,45),"mmm-yy") -> Oct-29 | AW3: =TEXT(EDATE(Controls!$B$6,46),"mmm-yy") -> Nov-29 | AX3: =TEXT(EDATE(Controls!$B$6,47),"mmm-yy") -> Dec-29 | AY3: =TEXT(EDATE(Controls!$B$6,48),"mmm-yy") -> Jan-30 | AZ3: =TEXT(EDATE(Controls!$B$6,49),"mmm-yy") -> Feb-30 | BA3: =TEXT(EDATE(Controls!$B$6,50),"mmm-yy") -> Mar-30 | BB3: =TEXT(EDATE(Controls!$B$6,51),"mmm-yy") -> Apr-30 | BC3: =TEXT(EDATE(Controls!$B$6,52),"mmm-yy") -> May-30 | BD3: =TEXT(EDATE(Controls!$B$6,53),"mmm-yy") -> Jun-30 | BE3: =TEXT(EDATE(Controls!$B$6,54),"mmm-yy") -> Jul-30 | BF3: =TEXT(EDATE(Controls!$B$6,55),"mmm-yy") -> Aug-30 | BG3: =TEXT(EDATE(Controls!$B$6,56),"mmm-yy") -> Sep-30 | BH3: =TEXT(EDATE(Controls!$B$6,57),"mmm-yy") -> Oct-30 | BI3: =TEXT(EDATE(Controls!$B$6,58),"mmm-yy") -> Nov-30 | BJ3: =TEXT(EDATE(Controls!$B$6,59),"mmm-yy") -> Dec-30 | BK3: ="FY "&(YEAR(Controls!$B$6)+0) -> FY 2026 | BL3: ="FY "&(YEAR(Controls!$B$6)+1) -> FY 2027 | BM3: ="FY "&(YEAR(Controls!$B$6)+2) -> FY 2028 | BN3: ="FY "&(YEAR(Controls!$B$6)+3) -> FY 2029 | BO3: ="FY "&(YEAR(Controls!$B$6)+4) -> FY 2030 | BP3: ="FY "&(YEAR(Controls!$B$6)+5) -> FY 2031
A5: PRICING ASSUMPTIONS
A6: Starter ARPU (Monthly) | B6: $/mo | C6: 49 | D6: ← Single-cell inputs (col C). Copy right if you want tier-specific monthly variation.
A7: Growth ARPU (Monthly) | B7: $/mo | C7: 149
A8: Enterprise ARPU (Monthly) | B8: $/mo | C8: 499
A9: % on Annual Plan – Starter | B9: % | C9: 0.2
A10: % on Annual Plan – Growth | B10: % | C10: 0.35
A11: % on Annual Plan – Enterprise | B11: % | C11: 0.6
A13: ACQUISITION FUNNEL · Organic / Paid / Partner
A14: Organic Channel
A15: Month 1 Website Visitors (Input) | B15: # | C15: 5000
A16: MoM Traffic Growth Rate | B16: % | C16: 0.05
A17: Monthly Website Visitors | B17: # | C17: =C15 -> 5000 | D17: =IF(COLUMN()-2<=Controls!$B$7,C17*(1+$C$16),0) -> 5250 | E17: =IF(COLUMN()-2<=Controls!$B$7,D17*(1+$C$16),0) -> 5512.5 | F17: =IF(COLUMN()-2<=Controls!$B$7,E17*(1+$C$16),0) -> 5788.125 | G17: =IF(COLUMN()-2<=Controls!$B$7,F17*(1+$C$16),0) -> 6077.5312 | H17: =IF(COLUMN()-2<=Controls!$B$7,G17*(1+$C$16),0) -> 6381.4078 | I17: =IF(COLUMN()-2<=Controls!$B$7,H17*(1+$C$16),0) -> 6700.4782 | J17: =IF(COLUMN()-2<=Controls!$B$7,I17*(1+$C$16),0) -> 7035.5021 | K17: =IF(COLUMN()-2<=Controls!$B$7,J17*(1+$C$16),0) -> 7387.2772 | ... BJ17: =IF(COLUMN()-2<=Controls!$B$7,BI17*(1+$C$16),0) -> 0 | BK17: =SUMPRODUCT((YEAR(EDATE(Controls!$B$6,COLUMN($C$1:$BJ$1)-COLUMN($C$1)))=YEAR(Controls!$B$6)+0)*(COLUMN($C$1:$BJ$1)-COLUMN($C$1)<Controls!$B$7)*$C$17:$BJ$17) -> 79585.633 | BL17: =SUMPRODUCT((YEAR(EDATE(Controls!$B$6,COLUMN($C$1:$BJ$1)-COLUMN($C$1)))=YEAR(Controls!$B$6)+1)*(COLUMN($C$1:$BJ$1)-COLUMN($C$1)<Controls!$B$7)*$C$17:$BJ$17) -> 142924.36 | BM17: =SUMPRODUCT((YEAR(EDATE(Controls!$B$6,COLUMN($C$1:$BJ$1)-COLUMN($C$1)))=YEAR(Controls!$B$6)+2)*(COLUMN($C$1:$BJ$1)-COLUMN($C$1)<Controls!$B$7)*$C$17:$BJ$17) -> 256671.62 | BN17: =SUMPRODUCT((YEAR(EDATE(Controls!$B$6,COLUMN($C$1:$BJ$1)-COLUMN($C$1)))=YEAR(Controls!$B$6)+3)*(COLUMN($C$1:$BJ$1)-COLUMN($C$1)<Controls!$B$7)*$C$17:$BJ$17) -> 0 | BO17: =SUMPRODUCT((YEAR(EDATE(Controls!$B$6,COLUMN($C$1:$BJ$1)-COLUMN($C$1)))=YEAR(Controls!$B$6)+4)*(COLUMN($C$1:$BJ$1)-COLUMN($C$1)<Controls!$B$7)*$C$17:$BJ$17) -> 0 | BP17: =SUMPRODUCT((YEAR(EDATE(Controls!$B$6,COLUMN($C$1:$BJ$1)-COLUMN($C$1)))=YEAR(Controls!$B$6)+5)*(COLUMN($C$1:$BJ$1)-COLUMN($C$1)<Controls!$B$7)*$C$17:$BJ$17) -> 0
A18: Trial Sign-Up Rate | B18: % | C18: 0.03
A19: Trial-to-Paid Conversion | B19: % | C19: 0.25
A20: New Customers – Organic | B20: # | C20: =ROUND(C17*$C$18*$C$19,0) -> 38 | D20: =ROUND(D17*$C$18*$C$19,0) -> 39 | E20: =ROUND(E17*$C$18*$C$19,0) -> 41 | F20: =ROUND(F17*$C$18*$C$19,0) -> 43 | G20: =ROUND(G17*$C$18*$C$19,0) -> 46 | H20: =ROUND(H17*$C$18*$C$19,0) -> 48 | I20: =ROUND(I17*$C$18*$C$19,0) -> 50 | J20: =ROUND(J17*$C$18*$C$19,0) -> 53 | ... BJ20: =ROUND(BJ17*$C$18*$C$19,0) -> 0 | BK20: =SUMPRODUCT((YEAR(EDATE(Controls!$B$6,COLUMN($C$1:$BJ$1)-COLUMN($C$1)))=YEAR(Controls!$B$6)+0)*(COLUMN($C$1:$BJ$1)-COLUMN($C$1)<Controls!$B$7)*$C$20:$BJ$20) -> 596 | BL20: =SUMPRODUCT((YEAR(EDATE(Controls!$B$6,COLUMN($C$1:$BJ$1)-COLUMN($C$1)))=YEAR(Controls!$B$6)+1)*(COLUMN($C$1:$BJ$1)-COLUMN($C$1)<Controls!$B$7)*$C$20:$BJ$20) -> 1071 | BM20: =SUMPRODUCT((YEAR(EDATE(Controls!$B$6,COLUMN($C$1:$BJ$1)-COLUMN($C$1)))=YEAR(Controls!$B$6)+2)*(COLUMN($C$1:$BJ$1)-COLUMN($C$1)<Controls!$B$7)*$C$20:$BJ$20) -> 1925 | BN20: =SUMPRODUCT((YEAR(EDATE(Controls!$B$6,COLUMN($C$1:$BJ$1)-COLUMN($C$1)))=YEAR(Controls!$B$6)+3)*(COLUMN($C$1:$BJ$1)-COLUMN($C$1)<Controls!$B$7)*$C$20:$BJ$20) -> 0 | BO20: =SUMPRODUCT((YEAR(EDATE(Controls!$B$6,COLUMN($C$1:$BJ$1)-COLUMN($C$1)))=YEAR(Controls!$B$6)+4)*(COLUMN($C$1:$BJ$1)-COLUMN($C$1)<Controls!$B$7)*$C$20:$BJ$20) -> 0 | BP20: =SUMPRODUCT((YEAR(EDATE(Controls!$B$6,COLUMN($C$1:$BJ$1)-COLUMN($C$1)))=YEAR(Controls!$B$6)+5)*(COLUMN($C$1:$BJ$1)-COLUMN($C$1)<Controls!$B$7)*$C$20:$BJ$20) -> 0
A22: Paid Channel
A23: Month 1 Paid Marketing Budget | B23: $ | C23: 10000
A24: MoM Budget Growth Rate | B24: % | C24: 0.08
A25: Monthly Paid Budget | B25: $ | C25: =C23 -> 10000 | D25: =IF(COLUMN()-2<=Controls!$B$7,C25*(1+$C$24),0) -> 10800 | E25: =IF(COLUMN()-2<=Controls!$B$7,D25*(1+$C$24),0) -> 11664 | F25: =IF(COLUMN()-2<=Controls!$B$7,E25*(1+$C$24),0) -> 12597.12 | G25: =IF(COLUMN()-2<=Controls!$B$7,F25*(1+$C$24),0) -> 13604.89 | H25: =IF(COLUMN()-2<=Controls!$B$7,G25*(1+$C$24),0) -> 14693.281 | I25: =IF(COLUMN()-2<=Controls!$B$7,H25*(1+$C$24),0) -> 15868.743 | J25: =IF(COLUMN()-2<=Controls!$B$7,I25*(1+$C$24),0) -> 17138.243 | K25: =IF(COLUMN()-2<=Controls!$B$7,J25*(1+$C$24),0) -> 18509.302 | ... BJ25: =IF(COLUMN()-2<=Controls!$B$7,BI25*(1+$C$24),0) -> 0 | BK25: =SUMPRODUCT((YEAR(EDATE(Controls!$B$6,COLUMN($C$1:$BJ$1)-COLUMN($C$1)))=YEAR(Controls!$B$6)+0)*(COLUMN($C$1:$BJ$1)-COLUMN($C$1)<Controls!$B$7)*$C$25:$BJ$25) -> 189771.26 | BL25: =SUMPRODUCT((YEAR(EDATE(Controls!$B$6,COLUMN($C$1:$BJ$1)-COLUMN($C$1)))=YEAR(Controls!$B$6)+1)*(COLUMN($C$1:$BJ$1)-COLUMN($C$1)<Controls!$B$7)*$C$25:$BJ$25) -> 477876.33 | BM25: =SUMPRODUCT((YEAR(EDATE(Controls!$B$6,COLUMN($C$1:$BJ$1)-COLUMN($C$1)))=YEAR(Controls!$B$6)+2)*(COLUMN($C$1:$BJ$1)-COLUMN($C$1)<Controls!$B$7)*$C$25:$BJ$25) -> 1203373.9 | BN25: =SUMPRODUCT((YEAR(EDATE(Controls!$B$6,COLUMN($C$1:$BJ$1)-COLUMN($C$1)))=YEAR(Controls!$B$6)+3)*(COLUMN($C$1:$BJ$1)-COLUMN($C$1)<Controls!$B$7)*$C$25:$BJ$25) -> 0 | BO25: =SUMPRODUCT((YEAR(EDATE(Controls!$B$6,COLUMN($C$1:$BJ$1)-COLUMN($C$1)))=YEAR(Controls!$B$6)+4)*(COLUMN($C$1:$BJ$1)-COLUMN($C$1)<Controls!$B$7)*$C$25:$BJ$25) -> 0 | BP25: =SUMPRODUCT((YEAR(EDATE(Controls!$B$6,COLUMN($C$1:$BJ$1)-COLUMN($C$1)))=YEAR(Controls!$B$6)+5)*(COLUMN($C$1:$BJ$1)-COLUMN($C$1)<Controls!$B$7)*$C$25:$BJ$25) -> 0
A26: Blended Paid CAC | B26: $ | C26: 450
A27: New Customers – Paid | B27: # | C27: =IFERROR(ROUND(C25/$C$26,0),0) -> 22 | D27: =IFERROR(ROUND(D25/$C$26,0),0) -> 24 | E27: =IFERROR(ROUND(E25/$C$26,0),0) -> 26 | F27: =IFERROR(ROUND(F25/$C$26,0),0) -> 28 | G27: =IFERROR(ROUND(G25/$C$26,0),0) -> 30 | H27: =IFERROR(ROUND(H25/$C$26,0),0) -> 33 | I27: =IFERROR(ROUND(I25/$C$26,0),0) -> 35 | J27: =IFERROR(ROUND(J25/$C$26,0),0) -> 38 | ... BJ27: =IFERROR(ROUND(BJ25/$C$26,0),0) -> 0 | BK27: =SUMPRODUCT((YEAR(EDATE(Controls!$B$6,COLUMN($C$1:$BJ$1)-COLUMN($C$1)))=YEAR(Controls!$B$6)+0)*(COLUMN($C$1:$BJ$1)-COLUMN($C$1)<Controls!$B$7)*$C$27:$BJ$27) -> 421 | BL27: =SUMPRODUCT((YEAR(EDATE(Controls!$B$6,COLUMN($C$1:$BJ$1)-COLUMN($C$1)))=YEAR(Controls!$B$6)+1)*(COLUMN($C$1:$BJ$1)-COLUMN($C$1)<Controls!$B$7)*$C$27:$BJ$27) -> 1061 | BM27: =SUMPRODUCT((YEAR(EDATE(Controls!$B$6,COLUMN($C$1:$BJ$1)-COLUMN($C$1)))=YEAR(Controls!$B$6)+2)*(COLUMN($C$1:$BJ$1)-COLUMN($C$1)<Controls!$B$7)*$C$27:$BJ$27) -> 2676 | BN27: =SUMPRODUCT((YEAR(EDATE(Controls!$B$6,COLUMN($C$1:$BJ$1)-COLUMN($C$1)))=YEAR(Controls!$B$6)+3)*(COLUMN($C$1:$BJ$1)-COLUMN($C$1)<Controls!$B$7)*$C$27:$BJ$27) -> 0 | BO27: =SUMPRODUCT((YEAR(EDATE(Controls!$B$6,COLUMN($C$1:$BJ$1)-COLUMN($C$1)))=YEAR(Controls!$B$6)+4)*(COLUMN($C$1:$BJ$1)-COLUMN($C$1)<Controls!$B$7)*$C$27:$BJ$27) -> 0 | BP27: =SUMPRODUCT((YEAR(EDATE(Controls!$B$6,COLUMN($C$1:$BJ$1)-COLUMN($C$1)))=YEAR(Controls!$B$6)+5)*(COLUMN($C$1:$BJ$1)-COLUMN($C$1)<Controls!$B$7)*$C$27:$BJ$27) -> 0
A29: Partner / Referral Channel
A30: Month 1 Partner Leads | B30: # | C30: 15
A31: MoM Leads Growth Rate | B31: % | C31: 0.05
A32: Monthly Partner Leads | B32: # | C32: =C30 -> 15 | D32: =IF(COLUMN()-2<=Controls!$B$7,C32*(1+$C$31),0) -> 15.75 | E32: =IF(COLUMN()-2<=Controls!$B$7,D32*(1+$C$31),0) -> 16.5375 | F32: =IF(COLUMN()-2<=Controls!$B$7,E32*(1+$C$31),0) -> 17.364375 | G32: =IF(COLUMN()-2<=Controls!$B$7,F32*(1+$C$31),0) -> 18.232594 | H32: =IF(COLUMN()-2<=Controls!$B$7,G32*(1+$C$31),0) -> 19.144223 | I32: =IF(COLUMN()-2<=Controls!$B$7,H32*(1+$C$31),0) -> 20.101435 | J32: =IF(COLUMN()-2<=Controls!$B$7,I32*(1+$C$31),0) -> 21.106506 | K32: =IF(COLUMN()-2<=Controls!$B$7,J32*(1+$C$31),0) -> 22.161832 | ... BJ32: =IF(COLUMN()-2<=Controls!$B$7,BI32*(1+$C$31),0) -> 0 | BK32: =SUMPRODUCT((YEAR(EDATE(Controls!$B$6,COLUMN($C$1:$BJ$1)-COLUMN($C$1)))=YEAR(Controls!$B$6)+0)*(COLUMN($C$1:$BJ$1)-COLUMN($C$1)<Controls!$B$7)*$C$32:$BJ$32) -> 238.7569 | BL32: =SUMPRODUCT((YEAR(EDATE(Controls!$B$6,COLUMN($C$1:$BJ$1)-COLUMN($C$1)))=YEAR(Controls!$B$6)+1)*(COLUMN($C$1:$BJ$1)-COLUMN($C$1)<Controls!$B$7)*$C$32:$BJ$32) -> 428.77309 | BM32: =SUMPRODUCT((YEAR(EDATE(Controls!$B$6,COLUMN($C$1:$BJ$1)-COLUMN($C$1)))=YEAR(Controls!$B$6)+2)*(COLUMN($C$1:$BJ$1)-COLUMN($C$1)<Controls!$B$7)*$C$32:$BJ$32) -> 770.01486 | BN32: =SUMPRODUCT((YEAR(EDATE(Controls!$B$6,COLUMN($C$1:$BJ$1)-COLUMN($C$1)))=YEAR(Controls!$B$6)+3)*(COLUMN($C$1:$BJ$1)-COLUMN($C$1)<Controls!$B$7)*$C$32:$BJ$32) -> 0 | BO32: =SUMPRODUCT((YEAR(EDATE(Controls!$B$6,COLUMN($C$1:$BJ$1)-COLUMN($C$1)))=YEAR(Controls!$B$6)+4)*(COLUMN($C$1:$BJ$1)-COLUMN($C$1)<Controls!$B$7)*$C$32:$BJ$32) -> 0 | BP32: =SUMPRODUCT((YEAR(EDATE(Controls!$B$6,COLUMN($C$1:$BJ$1)-COLUMN($C$1)))=YEAR(Controls!$B$6)+5)*(COLUMN($C$1:$BJ$1)-COLUMN($C$1)<Controls!$B$7)*$C$32:$BJ$32) -> 0
A33: Partner Close Rate | B33: % | C33: 0.15
A34: New Customers – Partner | B34: # | C34: =ROUND(C32*$C$33,0) -> 2 | D34: =ROUND(D32*$C$33,0) -> 2 | E34: =ROUND(E32*$C$33,0) -> 2 | F34: =ROUND(F32*$C$33,0) -> 3 | G34: =ROUND(G32*$C$33,0) -> 3 | H34: =ROUND(H32*$C$33,0) -> 3 | I34: =ROUND(I32*$C$33,0) -> 3 | J34: =ROUND(J32*$C$33,0) -> 3 | ... BJ34: =ROUND(BJ32*$C$33,0) -> 0 | BK34: =SUMPRODUCT((YEAR(EDATE(Controls!$B$6,COLUMN($C$1:$BJ$1)-COLUMN($C$1)))=YEAR(Controls!$B$6)+0)*(COLUMN($C$1:$BJ$1)-COLUMN($C$1)<Controls!$B$7)*$C$34:$BJ$34) -> 35 | BL34: =SUMPRODUCT((YEAR(EDATE(Controls!$B$6,COLUMN($C$1:$BJ$1)-COLUMN($C$1)))=YEAR(Controls!$B$6)+1)*(COLUMN($C$1:$BJ$1)-COLUMN($C$1)<Controls!$B$7)*$C$34:$BJ$34) -> 64 | BM34: =SUMPRODUCT((YEAR(EDATE(Controls!$B$6,COLUMN($C$1:$BJ$1)-COLUMN($C$1)))=YEAR(Controls!$B$6)+2)*(COLUMN($C$1:$BJ$1)-COLUMN($C$1)<Controls!$B$7)*$C$34:$BJ$34) -> 115 | BN34: =SUMPRODUCT((YEAR(EDATE(Controls!$B$6,COLUMN($C$1:$BJ$1)-COLUMN($C$1)))=YEAR(Controls!$B$6)+3)*(COLUMN($C$1:$BJ$1)-COLUMN($C$1)<Controls!$B$7)*$C$34:$BJ$34) -> 0 | BO34: =SUMPRODUCT((YEAR(EDATE(Controls!$B$6,COLUMN($C$1:$BJ$1)-COLUMN($C$1)))=YEAR(Controls!$B$6)+4)*(COLUMN($C$1:$BJ$1)-COLUMN($C$1)<Controls!$B$7)*$C$34:$BJ$34) -> 0 | BP34: =SUMPRODUCT((YEAR(EDATE(Controls!$B$6,COLUMN($C$1:$BJ$1)-COLUMN($C$1)))=YEAR(Controls!$B$6)+5)*(COLUMN($C$1:$BJ$1)-COLUMN($C$1)<Controls!$B$7)*$C$34:$BJ$34) -> 0
A36: Scenario Multiplier | B36: x | C36: =IF(Controls!$B$12="Upside",Controls!$B$13,IF(Controls!$B$12="Downside",Controls!$B$14,1)) -> 1 | D36: =IF(Controls!$B$12="Upside",Controls!$B$13,IF(Controls!$B$12="Downside",Controls!$B$14,1)) -> 1 | E36: =IF(Controls!$B$12="Upside",Controls!$B$13,IF(Controls!$B$12="Downside",Controls!$B$14,1)) -> 1 | F36: =IF(Controls!$B$12="Upside",Controls!$B$13,IF(Controls!$B$12="Downside",Controls!$B$14,1)) -> 1 | G36: =IF(Controls!$B$12="Upside",Controls!$B$13,IF(Controls!$B$12="Downside",Controls!$B$14,1)) -> 1 | H36: =IF(Controls!$B$12="Upside",Controls!$B$13,IF(Controls!$B$12="Downside",Controls!$B$14,1)) -> 1 | I36: =IF(Controls!$B$12="Upside",Controls!$B$13,IF(Controls!$B$12="Downside",Controls!$B$14,1)) -> 1 | J36: =IF(Controls!$B$12="Upside",Controls!$B$13,IF(Controls!$B$12="Downside",Controls!$B$14,1)) -> 1 | ... BJ36: =IF(Controls!$B$12="Upside",Controls!$B$13,IF(Controls!$B$12="Downside",Controls!$B$14,1)) -> 1 | BK36: =IFERROR(SUMPRODUCT((YEAR(EDATE(Controls!$B$6,COLUMN($C$1:$BJ$1)-COLUMN($C$1)))=YEAR(Controls!$B$6)+0)*(COLUMN($C$1:$BJ$1)-COLUMN($C$1)<Controls!$B$7)*$C$36:$BJ$36)/SUMPRODUCT((YEAR(EDATE(Controls!$B$6,COLUMN($C$1:$BJ$1)-COLUMN($C$1)))=YEAR(Controls!$B$6)+0)*(COLUMN($C$1:$BJ$1)-COLUMN($C$1)<Controls!$B$7)*1),0) -> 1 | BL36: =IFERROR(SUMPRODUCT((YEAR(EDATE(Controls!$B$6,COLUMN($C$1:$BJ$1)-COLUMN($C$1)))=YEAR(Controls!$B$6)+1)*(COLUMN($C$1:$BJ$1)-COLUMN($C$1)<Controls!$B$7)*$C$36:$BJ$36)/SUMPRODUCT((YEAR(EDATE(Controls!$B$6,COLUMN($C$1:$BJ$1)-COLUMN($C$1)))=YEAR(Controls!$B$6)+1)*(COLUMN($C$1:$BJ$1)-COLUMN($C$1)<Controls!$B$7)*1),0) -> 1 | BM36: =IFERROR(SUMPRODUCT((YEAR(EDATE(Controls!$B$6,COLUMN($C$1:$BJ$1)-COLUMN($C$1)))=YEAR(Controls!$B$6)+2)*(COLUMN($C$1:$BJ$1)-COLUMN($C$1)<Controls!$B$7)*$C$36:$BJ$36)/SUMPRODUCT((YEAR(EDATE(Controls!$B$6,COLUMN($C$1:$BJ$1)-COLUMN($C$1)))=YEAR(Controls!$B$6)+2)*(COLUMN($C$1:$BJ$1)-COLUMN($C$1)<Controls!$B$7)*1),0) -> 1 | BN36: =IFERROR(SUMPRODUCT((YEAR(EDATE(Controls!$B$6,COLUMN($C$1:$BJ$1)-COLUMN($C$1)))=YEAR(Controls!$B$6)+3)*(COLUMN($C$1:$BJ$1)-COLUMN($C$1)<Controls!$B$7)*$C$36:$BJ$36)/SUMPRODUCT((YEAR(EDATE(Controls!$B$6,COLUMN($C$1:$BJ$1)-COLUMN($C$1)))=YEAR(Controls!$B$6)+3)*(COLUMN($C$1:$BJ$1)-COLUMN($C$1)<Controls!$B$7)*1),0) -> 0 | BO36: =IFERROR(SUMPRODUCT((YEAR(EDATE(Controls!$B$6,COLUMN($C$1:$BJ$1)-COLUMN($C$1)))=YEAR(Controls!$B$6)+4)*(COLUMN($C$1:$BJ$1)-COLUMN($C$1)<Controls!$B$7)*$C$36:$BJ$36)/SUMPRODUCT((YEAR(EDATE(Controls!$B$6,COLUMN($C$1:$BJ$1)-COLUMN($C$1)))=YEAR(Controls!$B$6)+4)*(COLUMN($C$1:$BJ$1)-COLUMN($C$1)<Controls!$B$7)*1),0) -> 0 | BP36: =IFERROR(SUMPRODUCT((YEAR(EDATE(Controls!$B$6,COLUMN($C$1:$BJ$1)-COLUMN($C$1)))=YEAR(Controls!$B$6)+5)*(COLUMN($C$1:$BJ$1)-COLUMN($C$1)<Controls!$B$7)*$C$36:$BJ$36)/SUMPRODUCT((YEAR(EDATE(Controls!$B$6,COLUMN($C$1:$BJ$1)-COLUMN($C$1)))=YEAR(Controls!$B$6)+5)*(COLUMN($C$1:$BJ$1)-COLUMN($C$1)<Controls!$B$7)*1),0) -> 0
A37: TOTAL NEW CUSTOMERS | B37: # | C37: =ROUND((C20+C27+C34)*C36,0) -> 62 | D37: =ROUND((D20+D27+D34)*D36,0) -> 65 | E37: =ROUND((E20+E27+E34)*E36,0) -> 69 | F37: =ROUND((F20+F27+F34)*F36,0) -> 74 | G37: =ROUND((G20+G27+G34)*G36,0) -> 79 | H37: =ROUND((H20+H27+H34)*H36,0) -> 84 | I37: =ROUND((I20+I27+I34)*I36,0) -> 88 | J37: =ROUND((J20+J27+J34)*J36,0) -> 94 | ... BJ37: =ROUND((BJ20+BJ27+BJ34)*BJ36,0) -> 0 | BK37: =SUMPRODUCT((YEAR(EDATE(Controls!$B$6,COLUMN($C$1:$BJ$1)-COLUMN($C$1)))=YEAR(Controls!$B$6)+0)*(COLUMN($C$1:$BJ$1)-COLUMN($C$1)<Controls!$B$7)*$C$37:$BJ$37) -> 1052 | BL37: =SUMPRODUCT((YEAR(EDATE(Controls!$B$6,COLUMN($C$1:$BJ$1)-COLUMN($C$1)))=YEAR(Controls!$B$6)+1)*(COLUMN($C$1:$BJ$1)-COLUMN($C$1)<Controls!$B$7)*$C$37:$BJ$37) -> 2196 | BM37: =SUMPRODUCT((YEAR(EDATE(Controls!$B$6,COLUMN($C$1:$BJ$1)-COLUMN($C$1)))=YEAR(Controls!$B$6)+2)*(COLUMN($C$1:$BJ$1)-COLUMN($C$1)<Controls!$B$7)*$C$37:$BJ$37) -> 4716 | BN37: =SUMPRODUCT((YEAR(EDATE(Controls!$B$6,COLUMN($C$1:$BJ$1)-COLUMN($C$1)))=YEAR(Controls!$B$6)+3)*(COLUMN($C$1:$BJ$1)-COLUMN($C$1)<Controls!$B$7)*$C$37:$BJ$37) -> 0 | BO37: =SUMPRODUCT((YEAR(EDATE(Controls!$B$6,COLUMN($C$1:$BJ$1)-COLUMN($C$1)))=YEAR(Controls!$B$6)+4)*(COLUMN($C$1:$BJ$1)-COLUMN($C$1)<Controls!$B$7)*$C$37:$BJ$37) -> 0 | BP37: =SUMPRODUCT((YEAR(EDATE(Controls!$B$6,COLUMN($C$1:$BJ$1)-COLUMN($C$1)))=YEAR(Controls!$B$6)+5)*(COLUMN($C$1:$BJ$1)-COLUMN($C$1)<Controls!$B$7)*$C$37:$BJ$37) -> 0
A39: CUSTOMER MIX BY TIER
A40: New Customer Mix – Starter | B40: % | C40: 0.6
A41: New Customer Mix – Growth | B41: % | C41: 0.3
A42: New Customer Mix – Enterprise | B42: % | C42: 0.1
A43: Mix Total (must = 100%) | B43: % | C43: =C40+C41+C42 -> 1
A45: CUSTOMER WATERFALL – STARTER
A46: Beginning Customers – Starter | B46: # | C46: =5 -> 5 | D46: =C49 -> 42 | E46: =D49 -> 80 | F46: =E49 -> 119 | G46: =F49 -> 159 | H46: =G49 -> 201 | I46: =H49 -> 245 | J46: =I49 -> 291 | K46: =J49 -> 338 | ... BJ46: =BI49 -> 1749
A47: + New Customers – Starter | B47: # | C47: =ROUND(C37*$C$40,0) -> 37 | D47: =ROUND(D37*$C$40,0) -> 39 | E47: =ROUND(E37*$C$40,0) -> 41 | F47: =ROUND(F37*$C$40,0) -> 44 | G47: =ROUND(G37*$C$40,0) -> 47 | H47: =ROUND(H37*$C$40,0) -> 50 | I47: =ROUND(I37*$C$40,0) -> 53 | J47: =ROUND(J37*$C$40,0) -> 56 | ... BJ47: =ROUND(BJ37*$C$40,0) -> 0 | BK47: =SUMPRODUCT((YEAR(EDATE(Controls!$B$6,COLUMN($C$1:$BJ$1)-COLUMN($C$1)))=YEAR(Controls!$B$6)+0)*(COLUMN($C$1:$BJ$1)-COLUMN($C$1)<Controls!$B$7)*$C$47:$BJ$47) -> 629 | BL47: =SUMPRODUCT((YEAR(EDATE(Controls!$B$6,COLUMN($C$1:$BJ$1)-COLUMN($C$1)))=YEAR(Controls!$B$6)+1)*(COLUMN($C$1:$BJ$1)-COLUMN($C$1)<Controls!$B$7)*$C$47:$BJ$47) -> 1317 | BM47: =SUMPRODUCT((YEAR(EDATE(Controls!$B$6,COLUMN($C$1:$BJ$1)-COLUMN($C$1)))=YEAR(Controls!$B$6)+2)*(COLUMN($C$1:$BJ$1)-COLUMN($C$1)<Controls!$B$7)*$C$47:$BJ$47) -> 2831 | BN47: =SUMPRODUCT((YEAR(EDATE(Controls!$B$6,COLUMN($C$1:$BJ$1)-COLUMN($C$1)))=YEAR(Controls!$B$6)+3)*(COLUMN($C$1:$BJ$1)-COLUMN($C$1)<Controls!$B$7)*$C$47:$BJ$47) -> 0 | BO47: =SUMPRODUCT((YEAR(EDATE(Controls!$B$6,COLUMN($C$1:$BJ$1)-COLUMN($C$1)))=YEAR(Controls!$B$6)+4)*(COLUMN($C$1:$BJ$1)-COLUMN($C$1)<Controls!$B$7)*$C$47:$BJ$47) -> 0 | BP47: =SUMPRODUCT((YEAR(EDATE(Controls!$B$6,COLUMN($C$1:$BJ$1)-COLUMN($C$1)))=YEAR(Controls!$B$6)+5)*(COLUMN($C$1:$BJ$1)-COLUMN($C$1)<Controls!$B$7)*$C$47:$BJ$47) -> 0
A48: – Churned Customers – Starter | B48: # | C48: =-ROUND(C46*$C$50*IF(Controls!$B$12="Upside",Controls!$B$15,IF(Controls!$B$12="Downside",Controls!$B$16,1)),0) -> 0 | D48: =-ROUND(D46*$C$50*IF(Controls!$B$12="Upside",Controls!$B$15,IF(Controls!$B$12="Downside",Controls!$B$16,1)),0) -> -1 | E48: =-ROUND(E46*$C$50*IF(Controls!$B$12="Upside",Controls!$B$15,IF(Controls!$B$12="Downside",Controls!$B$16,1)),0) -> -2 | F48: =-ROUND(F46*$C$50*IF(Controls!$B$12="Upside",Controls!$B$15,IF(Controls!$B$12="Downside",Controls!$B$16,1)),0) -> -4 | G48: =-ROUND(G46*$C$50*IF(Controls!$B$12="Upside",Controls!$B$15,IF(Controls!$B$12="Downside",Controls!$B$16,1)),0) -> -5 | H48: =-ROUND(H46*$C$50*IF(Controls!$B$12="Upside",Controls!$B$15,IF(Controls!$B$12="Downside",Controls!$B$16,1)),0) -> -6 | I48: =-ROUND(I46*$C$50*IF(Controls!$B$12="Upside",Controls!$B$15,IF(Controls!$B$12="Downside",Controls!$B$16,1)),0) -> -7 | J48: =-ROUND(J46*$C$50*IF(Controls!$B$12="Upside",Controls!$B$15,IF(Controls!$B$12="Downside",Controls!$B$16,1)),0) -> -9 | ... BJ48: =-ROUND(BJ46*$C$50*IF(Controls!$B$12="Upside",Controls!$B$15,IF(Controls!$B$12="Downside",Controls!$B$16,1)),0) -> -52 | BK48: =SUMPRODUCT((YEAR(EDATE(Controls!$B$6,COLUMN($C$1:$BJ$1)-COLUMN($C$1)))=YEAR(Controls!$B$6)+0)*(COLUMN($C$1:$BJ$1)-COLUMN($C$1)<Controls!$B$7)*$C$48:$BJ$48) -> -84 | BL48: =SUMPRODUCT((YEAR(EDATE(Controls!$B$6,COLUMN($C$1:$BJ$1)-COLUMN($C$1)))=YEAR(Controls!$B$6)+1)*(COLUMN($C$1:$BJ$1)-COLUMN($C$1)<Controls!$B$7)*$C$48:$BJ$48) -> -340 | BM48: =SUMPRODUCT((YEAR(EDATE(Controls!$B$6,COLUMN($C$1:$BJ$1)-COLUMN($C$1)))=YEAR(Controls!$B$6)+2)*(COLUMN($C$1:$BJ$1)-COLUMN($C$1)<Controls!$B$7)*$C$48:$BJ$48) -> -834 | BN48: =SUMPRODUCT((YEAR(EDATE(Controls!$B$6,COLUMN($C$1:$BJ$1)-COLUMN($C$1)))=YEAR(Controls!$B$6)+3)*(COLUMN($C$1:$BJ$1)-COLUMN($C$1)<Controls!$B$7)*$C$48:$BJ$48) -> 0 | BO48: =SUMPRODUCT((YEAR(EDATE(Controls!$B$6,COLUMN($C$1:$BJ$1)-COLUMN($C$1)))=YEAR(Controls!$B$6)+4)*(COLUMN($C$1:$BJ$1)-COLUMN($C$1)<Controls!$B$7)*$C$48:$BJ$48) -> 0 | BP48: =SUMPRODUCT((YEAR(EDATE(Controls!$B$6,COLUMN($C$1:$BJ$1)-COLUMN($C$1)))=YEAR(Controls!$B$6)+5)*(COLUMN($C$1:$BJ$1)-COLUMN($C$1)<Controls!$B$7)*$C$48:$BJ$48) -> 0
A49: = Ending Customers – Starter | B49: # | C49: =C46+C47+C48 -> 42 | D49: =D46+D47+D48 -> 80 | E49: =E46+E47+E48 -> 119 | F49: =F46+F47+F48 -> 159 | G49: =G46+G47+G48 -> 201 | H49: =H46+H47+H48 -> 245 | I49: =I46+I47+I48 -> 291 | J49: =J46+J47+J48 -> 338 | ... BJ49: =BJ46+BJ47+BJ48 -> 1697 | BK49: =IFERROR(LOOKUP(2,1/((YEAR(EDATE(Controls!$B$6,COLUMN($C$1:$BJ$1)-COLUMN($C$1)))=YEAR(Controls!$B$6)+0)*(COLUMN($C$1:$BJ$1)-COLUMN($C$1)<Controls!$B$7)),$C$49:$BJ$49),0) -> 550 | BL49: =IFERROR(LOOKUP(2,1/((YEAR(EDATE(Controls!$B$6,COLUMN($C$1:$BJ$1)-COLUMN($C$1)))=YEAR(Controls!$B$6)+1)*(COLUMN($C$1:$BJ$1)-COLUMN($C$1)<Controls!$B$7)),$C$49:$BJ$49),0) -> 1527 | BM49: =IFERROR(LOOKUP(2,1/((YEAR(EDATE(Controls!$B$6,COLUMN($C$1:$BJ$1)-COLUMN($C$1)))=YEAR(Controls!$B$6)+2)*(COLUMN($C$1:$BJ$1)-COLUMN($C$1)<Controls!$B$7)),$C$49:$BJ$49),0) -> 3524 | BN49: =IFERROR(LOOKUP(2,1/((YEAR(EDATE(Controls!$B$6,COLUMN($C$1:$BJ$1)-COLUMN($C$1)))=YEAR(Controls!$B$6)+3)*(COLUMN($C$1:$BJ$1)-COLUMN($C$1)<Controls!$B$7)),$C$49:$BJ$49),0) -> 0 | BO49: =IFERROR(LOOKUP(2,1/((YEAR(EDATE(Controls!$B$6,COLUMN($C$1:$BJ$1)-COLUMN($C$1)))=YEAR(Controls!$B$6)+4)*(COLUMN($C$1:$BJ$1)-COLUMN($C$1)<Controls!$B$7)),$C$49:$BJ$49),0) -> 0 | BP49: =IFERROR(LOOKUP(2,1/((YEAR(EDATE(Controls!$B$6,COLUMN($C$1:$BJ$1)-COLUMN($C$1)))=YEAR(Controls!$B$6)+5)*(COLUMN($C$1:$BJ$1)-COLUMN($C$1)<Controls!$B$7)),$C$49:$BJ$49),0) -> 0
A50: Gross Churn Rate – Starter | B50: %/mo | C50: 0.03
A52: CUSTOMER WATERFALL – GROWTH
A53: Beginning Customers – Growth | B53: # | C53: =2 -> 2 | D53: =C56 -> 21 | E53: =D56 -> 41 | F53: =E56 -> 61 | G53: =F56 -> 82 | H53: =G56 -> 104 | I53: =H56 -> 127 | J53: =I56 -> 150 | K53: =J56 -> 175 | ... BJ53: =BI56 -> 1218
A54: + New Customers – Growth | B54: # | C54: =ROUND(C37*$C$41,0) -> 19 | D54: =ROUND(D37*$C$41,0) -> 20 | E54: =ROUND(E37*$C$41,0) -> 21 | F54: =ROUND(F37*$C$41,0) -> 22 | G54: =ROUND(G37*$C$41,0) -> 24 | H54: =ROUND(H37*$C$41,0) -> 25 | I54: =ROUND(I37*$C$41,0) -> 26 | J54: =ROUND(J37*$C$41,0) -> 28 | ... BJ54: =ROUND(BJ37*$C$41,0) -> 0 | BK54: =SUMPRODUCT((YEAR(EDATE(Controls!$B$6,COLUMN($C$1:$BJ$1)-COLUMN($C$1)))=YEAR(Controls!$B$6)+0)*(COLUMN($C$1:$BJ$1)-COLUMN($C$1)<Controls!$B$7)*$C$54:$BJ$54) -> 317 | BL54: =SUMPRODUCT((YEAR(EDATE(Controls!$B$6,COLUMN($C$1:$BJ$1)-COLUMN($C$1)))=YEAR(Controls!$B$6)+1)*(COLUMN($C$1:$BJ$1)-COLUMN($C$1)<Controls!$B$7)*$C$54:$BJ$54) -> 660 | BM54: =SUMPRODUCT((YEAR(EDATE(Controls!$B$6,COLUMN($C$1:$BJ$1)-COLUMN($C$1)))=YEAR(Controls!$B$6)+2)*(COLUMN($C$1:$BJ$1)-COLUMN($C$1)<Controls!$B$7)*$C$54:$BJ$54) -> 1415 | BN54: =SUMPRODUCT((YEAR(EDATE(Controls!$B$6,COLUMN($C$1:$BJ$1)-COLUMN($C$1)))=YEAR(Controls!$B$6)+3)*(COLUMN($C$1:$BJ$1)-COLUMN($C$1)<Controls!$B$7)*$C$54:$BJ$54) -> 0 | BO54: =SUMPRODUCT((YEAR(EDATE(Controls!$B$6,COLUMN($C$1:$BJ$1)-COLUMN($C$1)))=YEAR(Controls!$B$6)+4)*(COLUMN($C$1:$BJ$1)-COLUMN($C$1)<Controls!$B$7)*$C$54:$BJ$54) -> 0 | BP54: =SUMPRODUCT((YEAR(EDATE(Controls!$B$6,COLUMN($C$1:$BJ$1)-COLUMN($C$1)))=YEAR(Controls!$B$6)+5)*(COLUMN($C$1:$BJ$1)-COLUMN($C$1)<Controls!$B$7)*$C$54:$BJ$54) -> 0
A55: – Churned Customers – Growth | B55: # | C55: =-ROUND(C53*$C$57*IF(Controls!$B$12="Upside",Controls!$B$15,IF(Controls!$B$12="Downside",Controls!$B$16,1)),0) -> 0 | D55: =-ROUND(D53*$C$57*IF(Controls!$B$12="Upside",Controls!$B$15,IF(Controls!$B$12="Downside",Controls!$B$16,1)),0) -> 0 | E55: =-ROUND(E53*$C$57*IF(Controls!$B$12="Upside",Controls!$B$15,IF(Controls!$B$12="Downside",Controls!$B$16,1)),0) -> -1 | F55: =-ROUND(F53*$C$57*IF(Controls!$B$12="Upside",Controls!$B$15,IF(Controls!$B$12="Downside",Controls!$B$16,1)),0) -> -1 | G55: =-ROUND(G53*$C$57*IF(Controls!$B$12="Upside",Controls!$B$15,IF(Controls!$B$12="Downside",Controls!$B$16,1)),0) -> -2 | H55: =-ROUND(H53*$C$57*IF(Controls!$B$12="Upside",Controls!$B$15,IF(Controls!$B$12="Downside",Controls!$B$16,1)),0) -> -2 | I55: =-ROUND(I53*$C$57*IF(Controls!$B$12="Upside",Controls!$B$15,IF(Controls!$B$12="Downside",Controls!$B$16,1)),0) -> -3 | J55: =-ROUND(J53*$C$57*IF(Controls!$B$12="Upside",Controls!$B$15,IF(Controls!$B$12="Downside",Controls!$B$16,1)),0) -> -3 | ... BJ55: =-ROUND(BJ53*$C$57*IF(Controls!$B$12="Upside",Controls!$B$15,IF(Controls!$B$12="Downside",Controls!$B$16,1)),0) -> -24 | BK55: =SUMPRODUCT((YEAR(EDATE(Controls!$B$6,COLUMN($C$1:$BJ$1)-COLUMN($C$1)))=YEAR(Controls!$B$6)+0)*(COLUMN($C$1:$BJ$1)-COLUMN($C$1)<Controls!$B$7)*$C$55:$BJ$55) -> -30 | BL55: =SUMPRODUCT((YEAR(EDATE(Controls!$B$6,COLUMN($C$1:$BJ$1)-COLUMN($C$1)))=YEAR(Controls!$B$6)+1)*(COLUMN($C$1:$BJ$1)-COLUMN($C$1)<Controls!$B$7)*$C$55:$BJ$55) -> -120 | BM55: =SUMPRODUCT((YEAR(EDATE(Controls!$B$6,COLUMN($C$1:$BJ$1)-COLUMN($C$1)))=YEAR(Controls!$B$6)+2)*(COLUMN($C$1:$BJ$1)-COLUMN($C$1)<Controls!$B$7)*$C$55:$BJ$55) -> -305 | BN55: =SUMPRODUCT((YEAR(EDATE(Controls!$B$6,COLUMN($C$1:$BJ$1)-COLUMN($C$1)))=YEAR(Controls!$B$6)+3)*(COLUMN($C$1:$BJ$1)-COLUMN($C$1)<Controls!$B$7)*$C$55:$BJ$55) -> 0 | BO55: =SUMPRODUCT((YEAR(EDATE(Controls!$B$6,COLUMN($C$1:$BJ$1)-COLUMN($C$1)))=YEAR(Controls!$B$6)+4)*(COLUMN($C$1:$BJ$1)-COLUMN($C$1)<Controls!$B$7)*$C$55:$BJ$55) -> 0 | BP55: =SUMPRODUCT((YEAR(EDATE(Controls!$B$6,COLUMN($C$1:$BJ$1)-COLUMN($C$1)))=YEAR(Controls!$B$6)+5)*(COLUMN($C$1:$BJ$1)-COLUMN($C$1)<Controls!$B$7)*$C$55:$BJ$55) -> 0
A56: = Ending Customers – Growth | B56: # | C56: =C53+C54+C55 -> 21 | D56: =D53+D54+D55 -> 41 | E56: =E53+E54+E55 -> 61 | F56: =F53+F54+F55 -> 82 | G56: =G53+G54+G55 -> 104 | H56: =H53+H54+H55 -> 127 | I56: =I53+I54+I55 -> 150 | J56: =J53+J54+J55 -> 175 | ... BJ56: =BJ53+BJ54+BJ55 -> 1194 | BK56: =IFERROR(LOOKUP(2,1/((YEAR(EDATE(Controls!$B$6,COLUMN($C$1:$BJ$1)-COLUMN($C$1)))=YEAR(Controls!$B$6)+0)*(COLUMN($C$1:$BJ$1)-COLUMN($C$1)<Controls!$B$7)),$C$56:$BJ$56),0) -> 289 | BL56: =IFERROR(LOOKUP(2,1/((YEAR(EDATE(Controls!$B$6,COLUMN($C$1:$BJ$1)-COLUMN($C$1)))=YEAR(Controls!$B$6)+1)*(COLUMN($C$1:$BJ$1)-COLUMN($C$1)<Controls!$B$7)),$C$56:$BJ$56),0) -> 829 | BM56: =IFERROR(LOOKUP(2,1/((YEAR(EDATE(Controls!$B$6,COLUMN($C$1:$BJ$1)-COLUMN($C$1)))=YEAR(Controls!$B$6)+2)*(COLUMN($C$1:$BJ$1)-COLUMN($C$1)<Controls!$B$7)),$C$56:$BJ$56),0) -> 1939 | BN56: =IFERROR(LOOKUP(2,1/((YEAR(EDATE(Controls!$B$6,COLUMN($C$1:$BJ$1)-COLUMN($C$1)))=YEAR(Controls!$B$6)+3)*(COLUMN($C$1:$BJ$1)-COLUMN($C$1)<Controls!$B$7)),$C$56:$BJ$56),0) -> 0 | BO56: =IFERROR(LOOKUP(2,1/((YEAR(EDATE(Controls!$B$6,COLUMN($C$1:$BJ$1)-COLUMN($C$1)))=YEAR(Controls!$B$6)+4)*(COLUMN($C$1:$BJ$1)-COLUMN($C$1)<Controls!$B$7)),$C$56:$BJ$56),0) -> 0 | BP56: =IFERROR(LOOKUP(2,1/((YEAR(EDATE(Controls!$B$6,COLUMN($C$1:$BJ$1)-COLUMN($C$1)))=YEAR(Controls!$B$6)+5)*(COLUMN($C$1:$BJ$1)-COLUMN($C$1)<Controls!$B$7)),$C$56:$BJ$56),0) -> 0
A57: Gross Churn Rate – Growth | B57: %/mo | C57: 0.02
A59: CUSTOMER WATERFALL – ENTERPRISE
A60: Beginning Customers – Enterprise | B60: # | C60: =1 -> 1 | D60: =C63 -> 7 | E60: =D63 -> 14 | F60: =E63 -> 21 | G60: =F63 -> 28 | H60: =G63 -> 36 | I60: =H63 -> 44 | J60: =I63 -> 53 | K60: =J63 -> 61 | ... BJ60: =BI63 -> 568
A61: + New Customers – Enterprise | B61: # | C61: =ROUND(C37*$C$42,0) -> 6 | D61: =ROUND(D37*$C$42,0) -> 7 | E61: =ROUND(E37*$C$42,0) -> 7 | F61: =ROUND(F37*$C$42,0) -> 7 | G61: =ROUND(G37*$C$42,0) -> 8 | H61: =ROUND(H37*$C$42,0) -> 8 | I61: =ROUND(I37*$C$42,0) -> 9 | J61: =ROUND(J37*$C$42,0) -> 9 | ... BJ61: =ROUND(BJ37*$C$42,0) -> 0 | BK61: =SUMPRODUCT((YEAR(EDATE(Controls!$B$6,COLUMN($C$1:$BJ$1)-COLUMN($C$1)))=YEAR(Controls!$B$6)+0)*(COLUMN($C$1:$BJ$1)-COLUMN($C$1)<Controls!$B$7)*$C$61:$BJ$61) -> 105 | BL61: =SUMPRODUCT((YEAR(EDATE(Controls!$B$6,COLUMN($C$1:$BJ$1)-COLUMN($C$1)))=YEAR(Controls!$B$6)+1)*(COLUMN($C$1:$BJ$1)-COLUMN($C$1)<Controls!$B$7)*$C$61:$BJ$61) -> 219 | BM61: =SUMPRODUCT((YEAR(EDATE(Controls!$B$6,COLUMN($C$1:$BJ$1)-COLUMN($C$1)))=YEAR(Controls!$B$6)+2)*(COLUMN($C$1:$BJ$1)-COLUMN($C$1)<Controls!$B$7)*$C$61:$BJ$61) -> 473 | BN61: =SUMPRODUCT((YEAR(EDATE(Controls!$B$6,COLUMN($C$1:$BJ$1)-COLUMN($C$1)))=YEAR(Controls!$B$6)+3)*(COLUMN($C$1:$BJ$1)-COLUMN($C$1)<Controls!$B$7)*$C$61:$BJ$61) -> 0 | BO61: =SUMPRODUCT((YEAR(EDATE(Controls!$B$6,COLUMN($C$1:$BJ$1)-COLUMN($C$1)))=YEAR(Controls!$B$6)+4)*(COLUMN($C$1:$BJ$1)-COLUMN($C$1)<Controls!$B$7)*$C$61:$BJ$61) -> 0 | BP61: =SUMPRODUCT((YEAR(EDATE(Controls!$B$6,COLUMN($C$1:$BJ$1)-COLUMN($C$1)))=YEAR(Controls!$B$6)+5)*(COLUMN($C$1:$BJ$1)-COLUMN($C$1)<Controls!$B$7)*$C$61:$BJ$61) -> 0
A62: – Churned Customers – Enterprise | B62: # | C62: =-ROUND(C60*$C$64*IF(Controls!$B$12="Upside",Controls!$B$15,IF(Controls!$B$12="Downside",Controls!$B$16,1)),0) -> 0 | D62: =-ROUND(D60*$C$64*IF(Controls!$B$12="Upside",Controls!$B$15,IF(Controls!$B$12="Downside",Controls!$B$16,1)),0) -> 0 | E62: =-ROUND(E60*$C$64*IF(Controls!$B$12="Upside",Controls!$B$15,IF(Controls!$B$12="Downside",Controls!$B$16,1)),0) -> 0 | F62: =-ROUND(F60*$C$64*IF(Controls!$B$12="Upside",Controls!$B$15,IF(Controls!$B$12="Downside",Controls!$B$16,1)),0) -> 0 | G62: =-ROUND(G60*$C$64*IF(Controls!$B$12="Upside",Controls!$B$15,IF(Controls!$B$12="Downside",Controls!$B$16,1)),0) -> 0 | H62: =-ROUND(H60*$C$64*IF(Controls!$B$12="Upside",Controls!$B$15,IF(Controls!$B$12="Downside",Controls!$B$16,1)),0) -> 0 | I62: =-ROUND(I60*$C$64*IF(Controls!$B$12="Upside",Controls!$B$15,IF(Controls!$B$12="Downside",Controls!$B$16,1)),0) -> 0 | J62: =-ROUND(J60*$C$64*IF(Controls!$B$12="Upside",Controls!$B$15,IF(Controls!$B$12="Downside",Controls!$B$16,1)),0) -> -1 | ... BJ62: =-ROUND(BJ60*$C$64*IF(Controls!$B$12="Upside",Controls!$B$15,IF(Controls!$B$12="Downside",Controls!$B$16,1)),0) -> -6 | BK62: =SUMPRODUCT((YEAR(EDATE(Controls!$B$6,COLUMN($C$1:$BJ$1)-COLUMN($C$1)))=YEAR(Controls!$B$6)+0)*(COLUMN($C$1:$BJ$1)-COLUMN($C$1)<Controls!$B$7)*$C$62:$BJ$62) -> -5 | BL62: =SUMPRODUCT((YEAR(EDATE(Controls!$B$6,COLUMN($C$1:$BJ$1)-COLUMN($C$1)))=YEAR(Controls!$B$6)+1)*(COLUMN($C$1:$BJ$1)-COLUMN($C$1)<Controls!$B$7)*$C$62:$BJ$62) -> -22 | BM62: =SUMPRODUCT((YEAR(EDATE(Controls!$B$6,COLUMN($C$1:$BJ$1)-COLUMN($C$1)))=YEAR(Controls!$B$6)+2)*(COLUMN($C$1:$BJ$1)-COLUMN($C$1)<Controls!$B$7)*$C$62:$BJ$62) -> -55 | BN62: =SUMPRODUCT((YEAR(EDATE(Controls!$B$6,COLUMN($C$1:$BJ$1)-COLUMN($C$1)))=YEAR(Controls!$B$6)+3)*(COLUMN($C$1:$BJ$1)-COLUMN($C$1)<Controls!$B$7)*$C$62:$BJ$62) -> 0 | BO62: =SUMPRODUCT((YEAR(EDATE(Controls!$B$6,COLUMN($C$1:$BJ$1)-COLUMN($C$1)))=YEAR(Controls!$B$6)+4)*(COLUMN($C$1:$BJ$1)-COLUMN($C$1)<Controls!$B$7)*$C$62:$BJ$62) -> 0 | BP62: =SUMPRODUCT((YEAR(EDATE(Controls!$B$6,COLUMN($C$1:$BJ$1)-COLUMN($C$1)))=YEAR(Controls!$B$6)+5)*(COLUMN($C$1:$BJ$1)-COLUMN($C$1)<Controls!$B$7)*$C$62:$BJ$62) -> 0
A63: = Ending Customers – Enterprise | B63: # | C63: =C60+C61+C62 -> 7 | D63: =D60+D61+D62 -> 14 | E63: =E60+E61+E62 -> 21 | F63: =F60+F61+F62 -> 28 | G63: =G60+G61+G62 -> 36 | H63: =H60+H61+H62 -> 44 | I63: =I60+I61+I62 -> 53 | J63: =J60+J61+J62 -> 61 | ... BJ63: =BJ60+BJ61+BJ62 -> 562 | BK63: =IFERROR(LOOKUP(2,1/((YEAR(EDATE(Controls!$B$6,COLUMN($C$1:$BJ$1)-COLUMN($C$1)))=YEAR(Controls!$B$6)+0)*(COLUMN($C$1:$BJ$1)-COLUMN($C$1)<Controls!$B$7)),$C$63:$BJ$63),0) -> 101 | BL63: =IFERROR(LOOKUP(2,1/((YEAR(EDATE(Controls!$B$6,COLUMN($C$1:$BJ$1)-COLUMN($C$1)))=YEAR(Controls!$B$6)+1)*(COLUMN($C$1:$BJ$1)-COLUMN($C$1)<Controls!$B$7)),$C$63:$BJ$63),0) -> 298 | BM63: =IFERROR(LOOKUP(2,1/((YEAR(EDATE(Controls!$B$6,COLUMN($C$1:$BJ$1)-COLUMN($C$1)))=YEAR(Controls!$B$6)+2)*(COLUMN($C$1:$BJ$1)-COLUMN($C$1)<Controls!$B$7)),$C$63:$BJ$63),0) -> 716 | BN63: =IFERROR(LOOKUP(2,1/((YEAR(EDATE(Controls!$B$6,COLUMN($C$1:$BJ$1)-COLUMN($C$1)))=YEAR(Controls!$B$6)+3)*(COLUMN($C$1:$BJ$1)-COLUMN($C$1)<Controls!$B$7)),$C$63:$BJ$63),0) -> 0 | BO63: =IFERROR(LOOKUP(2,1/((YEAR(EDATE(Controls!$B$6,COLUMN($C$1:$BJ$1)-COLUMN($C$1)))=YEAR(Controls!$B$6)+4)*(COLUMN($C$1:$BJ$1)-COLUMN($C$1)<Controls!$B$7)),$C$63:$BJ$63),0) -> 0 | BP63: =IFERROR(LOOKUP(2,1/((YEAR(EDATE(Controls!$B$6,COLUMN($C$1:$BJ$1)-COLUMN($C$1)))=YEAR(Controls!$B$6)+5)*(COLUMN($C$1:$BJ$1)-COLUMN($C$1)<Controls!$B$7)),$C$63:$BJ$63),0) -> 0
A64: Gross Churn Rate – Enterprise | B64: %/mo | C64: 0.01
A66: TOTAL ACTIVE CUSTOMERS | B66: # | C66: =C49+C56+C63 -> 70 | D66: =D49+D56+D63 -> 135 | E66: =E49+E56+E63 -> 201 | F66: =F49+F56+F63 -> 269 | G66: =G49+G56+G63 -> 341 | H66: =H49+H56+H63 -> 416 | I66: =I49+I56+I63 -> 494 | J66: =J49+J56+J63 -> 574 | ... BJ66: =BJ49+BJ56+BJ63 -> 3453 | BK66: =IFERROR(LOOKUP(2,1/((YEAR(EDATE(Controls!$B$6,COLUMN($C$1:$BJ$1)-COLUMN($C$1)))=YEAR(Controls!$B$6)+0)*(COLUMN($C$1:$BJ$1)-COLUMN($C$1)<Controls!$B$7)),$C$66:$BJ$66),0) -> 940 | BL66: =IFERROR(LOOKUP(2,1/((YEAR(EDATE(Controls!$B$6,COLUMN($C$1:$BJ$1)-COLUMN($C$1)))=YEAR(Controls!$B$6)+1)*(COLUMN($C$1:$BJ$1)-COLUMN($C$1)<Controls!$B$7)),$C$66:$BJ$66),0) -> 2654 | BM66: =IFERROR(LOOKUP(2,1/((YEAR(EDATE(Controls!$B$6,COLUMN($C$1:$BJ$1)-COLUMN($C$1)))=YEAR(Controls!$B$6)+2)*(COLUMN($C$1:$BJ$1)-COLUMN($C$1)<Controls!$B$7)),$C$66:$BJ$66),0) -> 6179 | BN66: =IFERROR(LOOKUP(2,1/((YEAR(EDATE(Controls!$B$6,COLUMN($C$1:$BJ$1)-COLUMN($C$1)))=YEAR(Controls!$B$6)+3)*(COLUMN($C$1:$BJ$1)-COLUMN($C$1)<Controls!$B$7)),$C$66:$BJ$66),0) -> 0 | BO66: =IFERROR(LOOKUP(2,1/((YEAR(EDATE(Controls!$B$6,COLUMN($C$1:$BJ$1)-COLUMN($C$1)))=YEAR(Controls!$B$6)+4)*(COLUMN($C$1:$BJ$1)-COLUMN($C$1)<Controls!$B$7)),$C$66:$BJ$66),0) -> 0 | BP66: =IFERROR(LOOKUP(2,1/((YEAR(EDATE(Controls!$B$6,COLUMN($C$1:$BJ$1)-COLUMN($C$1)))=YEAR(Controls!$B$6)+5)*(COLUMN($C$1:$BJ$1)-COLUMN($C$1)<Controls!$B$7)),$C$66:$BJ$66),0) -> 0
A68: MRR WATERFALL · New · Expansion · Churn
A69: Net Expansion Rate – Starter | B69: %/mo | C69: 0.005
A70: Net Expansion Rate – Growth | B70: %/mo | C70: 0.008
A71: Net Expansion Rate – Enterprise | B71: %/mo | C71: 0.015
A73: Beginning MRR – Starter | B73: $ | C73: =C46*$C$6 -> 245 | D73: =C77 -> 2059.225 | E73: =D77 -> 3931.5211 | F73: =E77 -> 5862.1787 | G73: =F77 -> 7851.4896 | H73: =G77 -> 9948.7471 | I73: =H77 -> 12154.491 | J73: =I77 -> 14469.263 | K73: =J77 -> 16844.61 | ... BJ73: =BI77 -> 113216.88
A74: + New MRR – Starter | B74: $ | C74: =C47*$C$6 -> 1813 | D74: =D47*$C$6 -> 1911 | E74: =E47*$C$6 -> 2009 | F74: =F47*$C$6 -> 2156 | G74: =G47*$C$6 -> 2303 | H74: =H47*$C$6 -> 2450 | I74: =I47*$C$6 -> 2597 | J74: =J47*$C$6 -> 2744 | ... BJ74: =BJ47*$C$6 -> 0
A75: + Expansion MRR – Starter | B75: $ | C75: =C73*$C$69 -> 1.225 | D75: =D73*$C$69 -> 10.296125 | E75: =E73*$C$69 -> 19.657606 | F75: =F73*$C$69 -> 29.310894 | G75: =G73*$C$69 -> 39.257448 | H75: =H73*$C$69 -> 49.743735 | I75: =I73*$C$69 -> 60.772454 | J75: =J73*$C$69 -> 72.346316 | ... BJ75: =BJ73*$C$69 -> 566.08439
A76: – Churned MRR – Starter | B76: $ | C76: =C48*$C$6 -> 0 | D76: =D48*$C$6 -> -49 | E76: =E48*$C$6 -> -98 | F76: =F48*$C$6 -> -196 | G76: =G48*$C$6 -> -245 | H76: =H48*$C$6 -> -294 | I76: =I48*$C$6 -> -343 | J76: =J48*$C$6 -> -441 | ... BJ76: =BJ48*$C$6 -> -2548
A77: = Ending MRR – Starter | B77: $ | C77: =C73+C74+C75+C76 -> 2059.225 | D77: =D73+D74+D75+D76 -> 3931.5211 | E77: =E73+E74+E75+E76 -> 5862.1787 | F77: =F73+F74+F75+F76 -> 7851.4896 | G77: =G73+G74+G75+G76 -> 9948.7471 | H77: =H73+H74+H75+H76 -> 12154.491 | I77: =I73+I74+I75+I76 -> 14469.263 | J77: =J73+J74+J75+J76 -> 16844.61 | ... BJ77: =BJ73+BJ74+BJ75+BJ76 -> 111234.96 | BK77: =IFERROR(LOOKUP(2,1/((YEAR(EDATE(Controls!$B$6,COLUMN($C$1:$BJ$1)-COLUMN($C$1)))=YEAR(Controls!$B$6)+0)*(COLUMN($C$1:$BJ$1)-COLUMN($C$1)<Controls!$B$7)),$C$77:$BJ$77),0) -> 27646.76 | BL77: =IFERROR(LOOKUP(2,1/((YEAR(EDATE(Controls!$B$6,COLUMN($C$1:$BJ$1)-COLUMN($C$1)))=YEAR(Controls!$B$6)+1)*(COLUMN($C$1:$BJ$1)-COLUMN($C$1)<Controls!$B$7)),$C$77:$BJ$77),0) -> 78404.875 | BM77: =IFERROR(LOOKUP(2,1/((YEAR(EDATE(Controls!$B$6,COLUMN($C$1:$BJ$1)-COLUMN($C$1)))=YEAR(Controls!$B$6)+2)*(COLUMN($C$1:$BJ$1)-COLUMN($C$1)<Controls!$B$7)),$C$77:$BJ$77),0) -> 183457.4 | BN77: =IFERROR(LOOKUP(2,1/((YEAR(EDATE(Controls!$B$6,COLUMN($C$1:$BJ$1)-COLUMN($C$1)))=YEAR(Controls!$B$6)+3)*(COLUMN($C$1:$BJ$1)-COLUMN($C$1)<Controls!$B$7)),$C$77:$BJ$77),0) -> 0 | BO77: =IFERROR(LOOKUP(2,1/((YEAR(EDATE(Controls!$B$6,COLUMN($C$1:$BJ$1)-COLUMN($C$1)))=YEAR(Controls!$B$6)+4)*(COLUMN($C$1:$BJ$1)-COLUMN($C$1)<Controls!$B$7)),$C$77:$BJ$77),0) -> 0 | BP77: =IFERROR(LOOKUP(2,1/((YEAR(EDATE(Controls!$B$6,COLUMN($C$1:$BJ$1)-COLUMN($C$1)))=YEAR(Controls!$B$6)+5)*(COLUMN($C$1:$BJ$1)-COLUMN($C$1)<Controls!$B$7)),$C$77:$BJ$77),0) -> 0
A79: Beginning MRR – Growth | B79: $ | C79: =C53*$C$7 -> 298 | D79: =C83 -> 3131.384 | E79: =D83 -> 6136.4351 | F79: =E83 -> 9165.5266 | G79: =F83 -> 12367.851 | H79: =G83 -> 15744.794 | I79: =H83 -> 19297.752 | J79: =I83 -> 22879.134 | K79: =J83 -> 26787.167 | ... BJ79: =BI83 -> 263884.71
A80: + New MRR – Growth | B80: $ | C80: =C54*$C$7 -> 2831 | D80: =D54*$C$7 -> 2980 | E80: =E54*$C$7 -> 3129 | F80: =F54*$C$7 -> 3278 | G80: =G54*$C$7 -> 3576 | H80: =H54*$C$7 -> 3725 | I80: =I54*$C$7 -> 3874 | J80: =J54*$C$7 -> 4172 | ... BJ80: =BJ54*$C$7 -> 0
A81: + Expansion MRR – Growth | B81: $ | C81: =C79*$C$70 -> 2.384 | D81: =D79*$C$70 -> 25.051072 | E81: =E79*$C$70 -> 49.091481 | F81: =F79*$C$70 -> 73.324212 | G81: =G79*$C$70 -> 98.942806 | H81: =H79*$C$70 -> 125.95835 | I81: =I79*$C$70 -> 154.38202 | J81: =J79*$C$70 -> 183.03307 | ... BJ81: =BJ79*$C$70 -> 2111.0777
A82: – Churned MRR – Growth | B82: $ | C82: =C55*$C$7 -> 0 | D82: =D55*$C$7 -> 0 | E82: =E55*$C$7 -> -149 | F82: =F55*$C$7 -> -149 | G82: =G55*$C$7 -> -298 | H82: =H55*$C$7 -> -298 | I82: =I55*$C$7 -> -447 | J82: =J55*$C$7 -> -447 | ... BJ82: =BJ55*$C$7 -> -3576
A83: = Ending MRR – Growth | B83: $ | C83: =C79+C80+C81+C82 -> 3131.384 | D83: =D79+D80+D81+D82 -> 6136.4351 | E83: =E79+E80+E81+E82 -> 9165.5266 | F83: =F79+F80+F81+F82 -> 12367.851 | G83: =G79+G80+G81+G82 -> 15744.794 | H83: =H79+H80+H81+H82 -> 19297.752 | I83: =I79+I80+I81+I82 -> 22879.134 | J83: =J79+J80+J81+J82 -> 26787.167 | ... BJ83: =BJ79+BJ80+BJ81+BJ82 -> 262419.79 | BK83: =IFERROR(LOOKUP(2,1/((YEAR(EDATE(Controls!$B$6,COLUMN($C$1:$BJ$1)-COLUMN($C$1)))=YEAR(Controls!$B$6)+0)*(COLUMN($C$1:$BJ$1)-COLUMN($C$1)<Controls!$B$7)),$C$83:$BJ$83),0) -> 44836.006 | BL83: =IFERROR(LOOKUP(2,1/((YEAR(EDATE(Controls!$B$6,COLUMN($C$1:$BJ$1)-COLUMN($C$1)))=YEAR(Controls!$B$6)+1)*(COLUMN($C$1:$BJ$1)-COLUMN($C$1)<Controls!$B$7)),$C$83:$BJ$83),0) -> 132976.41 | BM83: =IFERROR(LOOKUP(2,1/((YEAR(EDATE(Controls!$B$6,COLUMN($C$1:$BJ$1)-COLUMN($C$1)))=YEAR(Controls!$B$6)+2)*(COLUMN($C$1:$BJ$1)-COLUMN($C$1)<Controls!$B$7)),$C$83:$BJ$83),0) -> 318161.49 | BN83: =IFERROR(LOOKUP(2,1/((YEAR(EDATE(Controls!$B$6,COLUMN($C$1:$BJ$1)-COLUMN($C$1)))=YEAR(Controls!$B$6)+3)*(COLUMN($C$1:$BJ$1)-COLUMN($C$1)<Controls!$B$7)),$C$83:$BJ$83),0) -> 0 | BO83: =IFERROR(LOOKUP(2,1/((YEAR(EDATE(Controls!$B$6,COLUMN($C$1:$BJ$1)-COLUMN($C$1)))=YEAR(Controls!$B$6)+4)*(COLUMN($C$1:$BJ$1)-COLUMN($C$1)<Controls!$B$7)),$C$83:$BJ$83),0) -> 0 | BP83: =IFERROR(LOOKUP(2,1/((YEAR(EDATE(Controls!$B$6,COLUMN($C$1:$BJ$1)-COLUMN($C$1)))=YEAR(Controls!$B$6)+5)*(COLUMN($C$1:$BJ$1)-COLUMN($C$1)<Controls!$B$7)),$C$83:$BJ$83),0) -> 0
A85: Beginning MRR – Enterprise | B85: $ | C85: =C60*$C$8 -> 499 | D85: =C89 -> 3500.485 | E85: =D89 -> 7045.9923 | F85: =E89 -> 10644.682 | G85: =F89 -> 14297.352 | H85: =G89 -> 18503.813 | I85: =H89 -> 22773.37 | J85: =I89 -> 27605.97 | K85: =J89 -> 32012.06 | ... BJ85: =BI89 -> 515338.9
A86: + New MRR – Enterprise | B86: $ | C86: =C61*$C$8 -> 2994 | D86: =D61*$C$8 -> 3493 | E86: =E61*$C$8 -> 3493 | F86: =F61*$C$8 -> 3493 | G86: =G61*$C$8 -> 3992 | H86: =H61*$C$8 -> 3992 | I86: =I61*$C$8 -> 4491 | J86: =J61*$C$8 -> 4491 | ... BJ86: =BJ61*$C$8 -> 0
A87: + Expansion MRR – Enterprise | B87: $ | C87: =C85*$C$71 -> 7.485 | D87: =D85*$C$71 -> 52.507275 | E87: =E85*$C$71 -> 105.68988 | F87: =F85*$C$71 -> 159.67023 | G87: =G85*$C$71 -> 214.46029 | H87: =H85*$C$71 -> 277.55719 | I87: =I85*$C$71 -> 341.60055 | J87: =J85*$C$71 -> 414.08956 | ... BJ87: =BJ85*$C$71 -> 7730.0836
A88: – Churned MRR – Enterprise | B88: $ | C88: =C62*$C$8 -> 0 | D88: =D62*$C$8 -> 0 | E88: =E62*$C$8 -> 0 | F88: =F62*$C$8 -> 0 | G88: =G62*$C$8 -> 0 | H88: =H62*$C$8 -> 0 | I88: =I62*$C$8 -> 0 | J88: =J62*$C$8 -> -499 | ... BJ88: =BJ62*$C$8 -> -2994
A89: = Ending MRR – Enterprise | B89: $ | C89: =C85+C86+C87+C88 -> 3500.485 | D89: =D85+D86+D87+D88 -> 7045.9923 | E89: =E85+E86+E87+E88 -> 10644.682 | F89: =F85+F86+F87+F88 -> 14297.352 | G89: =G85+G86+G87+G88 -> 18503.813 | H89: =H85+H86+H87+H88 -> 22773.37 | I89: =I85+I86+I87+I88 -> 27605.97 | J89: =J85+J86+J87+J88 -> 32012.06 | ... BJ89: =BJ85+BJ86+BJ87+BJ88 -> 520074.99 | BK89: =IFERROR(LOOKUP(2,1/((YEAR(EDATE(Controls!$B$6,COLUMN($C$1:$BJ$1)-COLUMN($C$1)))=YEAR(Controls!$B$6)+0)*(COLUMN($C$1:$BJ$1)-COLUMN($C$1)<Controls!$B$7)),$C$89:$BJ$89),0) -> 54367.248 | BL89: =IFERROR(LOOKUP(2,1/((YEAR(EDATE(Controls!$B$6,COLUMN($C$1:$BJ$1)-COLUMN($C$1)))=YEAR(Controls!$B$6)+1)*(COLUMN($C$1:$BJ$1)-COLUMN($C$1)<Controls!$B$7)),$C$89:$BJ$89),0) -> 170753.21 | BM89: =IFERROR(LOOKUP(2,1/((YEAR(EDATE(Controls!$B$6,COLUMN($C$1:$BJ$1)-COLUMN($C$1)))=YEAR(Controls!$B$6)+2)*(COLUMN($C$1:$BJ$1)-COLUMN($C$1)<Controls!$B$7)),$C$89:$BJ$89),0) -> 428388.2 | BN89: =IFERROR(LOOKUP(2,1/((YEAR(EDATE(Controls!$B$6,COLUMN($C$1:$BJ$1)-COLUMN($C$1)))=YEAR(Controls!$B$6)+3)*(COLUMN($C$1:$BJ$1)-COLUMN($C$1)<Controls!$B$7)),$C$89:$BJ$89),0) -> 0 | BO89: =IFERROR(LOOKUP(2,1/((YEAR(EDATE(Controls!$B$6,COLUMN($C$1:$BJ$1)-COLUMN($C$1)))=YEAR(Controls!$B$6)+4)*(COLUMN($C$1:$BJ$1)-COLUMN($C$1)<Controls!$B$7)),$C$89:$BJ$89),0) -> 0 | BP89: =IFERROR(LOOKUP(2,1/((YEAR(EDATE(Controls!$B$6,COLUMN($C$1:$BJ$1)-COLUMN($C$1)))=YEAR(Controls!$B$6)+5)*(COLUMN($C$1:$BJ$1)-COLUMN($C$1)<Controls!$B$7)),$C$89:$BJ$89),0) -> 0
A91: TOTAL MRR | B91: $ | C91: =C77+C83+C89 -> 8691.094 | D91: =D77+D83+D89 -> 17113.948 | E91: =E77+E83+E89 -> 25672.387 | F91: =F77+F83+F89 -> 34516.693 | G91: =G77+G83+G89 -> 44197.353 | H91: =H77+H83+H89 -> 54225.613 | I91: =I77+I83+I89 -> 64954.368 | J91: =J77+J83+J89 -> 75643.837 | ... BJ91: =BJ77+BJ83+BJ89 -> 893729.74 | BK91: =IFERROR(LOOKUP(2,1/((YEAR(EDATE(Controls!$B$6,COLUMN($C$1:$BJ$1)-COLUMN($C$1)))=YEAR(Controls!$B$6)+0)*(COLUMN($C$1:$BJ$1)-COLUMN($C$1)<Controls!$B$7)),$C$91:$BJ$91),0) -> 126850.01 | BL91: =IFERROR(LOOKUP(2,1/((YEAR(EDATE(Controls!$B$6,COLUMN($C$1:$BJ$1)-COLUMN($C$1)))=YEAR(Controls!$B$6)+1)*(COLUMN($C$1:$BJ$1)-COLUMN($C$1)<Controls!$B$7)),$C$91:$BJ$91),0) -> 382134.5 | BM91: =IFERROR(LOOKUP(2,1/((YEAR(EDATE(Controls!$B$6,COLUMN($C$1:$BJ$1)-COLUMN($C$1)))=YEAR(Controls!$B$6)+2)*(COLUMN($C$1:$BJ$1)-COLUMN($C$1)<Controls!$B$7)),$C$91:$BJ$91),0) -> 930007.09 | BN91: =IFERROR(LOOKUP(2,1/((YEAR(EDATE(Controls!$B$6,COLUMN($C$1:$BJ$1)-COLUMN($C$1)))=YEAR(Controls!$B$6)+3)*(COLUMN($C$1:$BJ$1)-COLUMN($C$1)<Controls!$B$7)),$C$91:$BJ$91),0) -> 0 | BO91: =IFERROR(LOOKUP(2,1/((YEAR(EDATE(Controls!$B$6,COLUMN($C$1:$BJ$1)-COLUMN($C$1)))=YEAR(Controls!$B$6)+4)*(COLUMN($C$1:$BJ$1)-COLUMN($C$1)<Controls!$B$7)),$C$91:$BJ$91),0) -> 0 | BP91: =IFERROR(LOOKUP(2,1/((YEAR(EDATE(Controls!$B$6,COLUMN($C$1:$BJ$1)-COLUMN($C$1)))=YEAR(Controls!$B$6)+5)*(COLUMN($C$1:$BJ$1)-COLUMN($C$1)<Controls!$B$7)),$C$91:$BJ$91),0) -> 0
A92: ARR (MRR×12) | B92: $ | C92: =C91*12 -> 104293.13 | D92: =D91*12 -> 205367.38 | E92: =E91*12 -> 308068.65 | F92: =F91*12 -> 414200.31 | G92: =G91*12 -> 530368.24 | H92: =H91*12 -> 650707.35 | I92: =I91*12 -> 779452.41 | J92: =J91*12 -> 907726.04 | ... BJ92: =BJ91*12 -> 10724757 | BK92: =IFERROR(LOOKUP(2,1/((YEAR(EDATE(Controls!$B$6,COLUMN($C$1:$BJ$1)-COLUMN($C$1)))=YEAR(Controls!$B$6)+0)*(COLUMN($C$1:$BJ$1)-COLUMN($C$1)<Controls!$B$7)),$C$92:$BJ$92),0) -> 1522200.2 | BL92: =IFERROR(LOOKUP(2,1/((YEAR(EDATE(Controls!$B$6,COLUMN($C$1:$BJ$1)-COLUMN($C$1)))=YEAR(Controls!$B$6)+1)*(COLUMN($C$1:$BJ$1)-COLUMN($C$1)<Controls!$B$7)),$C$92:$BJ$92),0) -> 4585614 | BM92: =IFERROR(LOOKUP(2,1/((YEAR(EDATE(Controls!$B$6,COLUMN($C$1:$BJ$1)-COLUMN($C$1)))=YEAR(Controls!$B$6)+2)*(COLUMN($C$1:$BJ$1)-COLUMN($C$1)<Controls!$B$7)),$C$92:$BJ$92),0) -> 11160085 | BN92: =IFERROR(LOOKUP(2,1/((YEAR(EDATE(Controls!$B$6,COLUMN($C$1:$BJ$1)-COLUMN($C$1)))=YEAR(Controls!$B$6)+3)*(COLUMN($C$1:$BJ$1)-COLUMN($C$1)<Controls!$B$7)),$C$92:$BJ$92),0) -> 0 | BO92: =IFERROR(LOOKUP(2,1/((YEAR(EDATE(Controls!$B$6,COLUMN($C$1:$BJ$1)-COLUMN($C$1)))=YEAR(Controls!$B$6)+4)*(COLUMN($C$1:$BJ$1)-COLUMN($C$1)<Controls!$B$7)),$C$92:$BJ$92),0) -> 0 | BP92: =IFERROR(LOOKUP(2,1/((YEAR(EDATE(Controls!$B$6,COLUMN($C$1:$BJ$1)-COLUMN($C$1)))=YEAR(Controls!$B$6)+5)*(COLUMN($C$1:$BJ$1)-COLUMN($C$1)<Controls!$B$7)),$C$92:$BJ$92),0) -> 0
A93: Net Revenue Retention (NRR) | B93: % | C93: =IFERROR((C73+C79+C85+C75+C81+C87+C76+C82+C88)/(C73+C79+C85),0) -> 1.0106468 | D93: =IFERROR((D73+D79+D85+D75+D81+D87+D76+D82+D88)/(D73+D79+D85),0) -> 1.0044706 | E93: =IFERROR((E73+E79+E85+E75+E81+E87+E76+E82+E88)/(E73+E79+E85),0) -> 0.99576012 | F93: =IFERROR((F73+F79+F85+F75+F81+F87+F76+F82+F88)/(F73+F79+F85),0) -> 0.99677885 | G93: =IFERROR((G73+G79+G85+G75+G81+G87+G76+G82+G88)/(G73+G79+G85),0) -> 0.99448558 | H93: =IFERROR((H73+H79+H85+H75+H81+H87+H76+H82+H88)/(H73+H79+H85),0) -> 0.99686088 | I93: =IFERROR((I73+I79+I85+I75+I81+I87+I76+I82+I88)/(I73+I79+I85),0) -> 0.99569862 | J93: =IFERROR((J73+J79+J85+J75+J81+J87+J76+J82+J88)/(J73+J79+J85),0) -> 0.98895331 | ... BJ93: =IFERROR((BJ73+BJ79+BJ85+BJ75+BJ81+BJ87+BJ76+BJ82+BJ88)/(BJ73+BJ79+BJ85),0) -> 1.0014446 | BK93: =IFERROR(SUMPRODUCT((YEAR(EDATE(Controls!$B$6,COLUMN($C$1:$BJ$1)-COLUMN($C$1)))=YEAR(Controls!$B$6)+0)*(COLUMN($C$1:$BJ$1)-COLUMN($C$1)<Controls!$B$7)*$C$93:$BJ$93)/SUMPRODUCT((YEAR(EDATE(Controls!$B$6,COLUMN($C$1:$BJ$1)-COLUMN($C$1)))=YEAR(Controls!$B$6)+0)*(COLUMN($C$1:$BJ$1)-COLUMN($C$1)<Controls!$B$7)*1),0) -> 0.99568737 | BL93: =IFERROR(SUMPRODUCT((YEAR(EDATE(Controls!$B$6,COLUMN($C$1:$BJ$1)-COLUMN($C$1)))=YEAR(Controls!$B$6)+1)*(COLUMN($C$1:$BJ$1)-COLUMN($C$1)<Controls!$B$7)*$C$93:$BJ$93)/SUMPRODUCT((YEAR(EDATE(Controls!$B$6,COLUMN($C$1:$BJ$1)-COLUMN($C$1)))=YEAR(Controls!$B$6)+1)*(COLUMN($C$1:$BJ$1)-COLUMN($C$1)<Controls!$B$7)*1),0) -> 0.99380359 | BM93: =IFERROR(SUMPRODUCT((YEAR(EDATE(Controls!$B$6,COLUMN($C$1:$BJ$1)-COLUMN($C$1)))=YEAR(Controls!$B$6)+2)*(COLUMN($C$1:$BJ$1)-COLUMN($C$1)<Controls!$B$7)*$C$93:$BJ$93)/SUMPRODUCT((YEAR(EDATE(Controls!$B$6,COLUMN($C$1:$BJ$1)-COLUMN($C$1)))=YEAR(Controls!$B$6)+2)*(COLUMN($C$1:$BJ$1)-COLUMN($C$1)<Controls!$B$7)*1),0) -> 0.99470825 | BN93: =IFERROR(SUMPRODUCT((YEAR(EDATE(Controls!$B$6,COLUMN($C$1:$BJ$1)-COLUMN($C$1)))=YEAR(Controls!$B$6)+3)*(COLUMN($C$1:$BJ$1)-COLUMN($C$1)<Controls!$B$7)*$C$93:$BJ$93)/SUMPRODUCT((YEAR(EDATE(Controls!$B$6,COLUMN($C$1:$BJ$1)-COLUMN($C$1)))=YEAR(Controls!$B$6)+3)*(COLUMN($C$1:$BJ$1)-COLUMN($C$1)<Controls!$B$7)*1),0) -> 0 | BO93: =IFERROR(SUMPRODUCT((YEAR(EDATE(Controls!$B$6,COLUMN($C$1:$BJ$1)-COLUMN($C$1)))=YEAR(Controls!$B$6)+4)*(COLUMN($C$1:$BJ$1)-COLUMN($C$1)<Controls!$B$7)*$C$93:$BJ$93)/SUMPRODUCT((YEAR(EDATE(Controls!$B$6,COLUMN($C$1:$BJ$1)-COLUMN($C$1)))=YEAR(Controls!$B$6)+4)*(COLUMN($C$1:$BJ$1)-COLUMN($C$1)<Controls!$B$7)*1),0) -> 0 | BP93: =IFERROR(SUMPRODUCT((YEAR(EDATE(Controls!$B$6,COLUMN($C$1:$BJ$1)-COLUMN($C$1)))=YEAR(Controls!$B$6)+5)*(COLUMN($C$1:$BJ$1)-COLUMN($C$1)<Controls!$B$7)*$C$93:$BJ$93)/SUMPRODUCT((YEAR(EDATE(Controls!$B$6,COLUMN($C$1:$BJ$1)-COLUMN($C$1)))=YEAR(Controls!$B$6)+5)*(COLUMN($C$1:$BJ$1)-COLUMN($C$1)<Controls!$B$7)*1),0) -> 0
A95: REVENUE RECOGNITION · Monthly + Annual Billing + Deferred Revenue
A96: Monthly Billing Revenue (Recognized) | B96: $ | C96: =C91*(1-IFERROR((C77*$C$9+C83*$C$10+C89*$C$11)/C91,0)) -> 5082.9736 | D96: =D91*(1-IFERROR((D77*$C$9+D83*$C$10+D89*$C$11)/D91,0)) -> 9952.2966 | E96: =E91*(1-IFERROR((E77*$C$9+E83*$C$10+E89*$C$11)/E91,0)) -> 14905.208 | F96: =F91*(1-IFERROR((F77*$C$9+F83*$C$10+F89*$C$11)/F91,0)) -> 20039.236 | G96: =G91*(1-IFERROR((G77*$C$9+G83*$C$10+G89*$C$11)/G91,0)) -> 25594.639 | H96: =H91*(1-IFERROR((H77*$C$9+H83*$C$10+H89*$C$11)/H91,0)) -> 31376.479 | I96: =I91*(1-IFERROR((I77*$C$9+I83*$C$10+I89*$C$11)/I91,0)) -> 37489.236 | J96: =J91*(1-IFERROR((J77*$C$9+J83*$C$10+J89*$C$11)/J91,0)) -> 43692.17 | ... BJ96: =BJ91*(1-IFERROR((BJ77*$C$9+BJ83*$C$10+BJ89*$C$11)/BJ91,0)) -> 467590.83 | BK96: =SUMPRODUCT((YEAR(EDATE(Controls!$B$6,COLUMN($C$1:$BJ$1)-COLUMN($C$1)))=YEAR(Controls!$B$6)+0)*(COLUMN($C$1:$BJ$1)-COLUMN($C$1)<Controls!$B$7)*$C$96:$BJ$96) -> 433939.19 | BL96: =SUMPRODUCT((YEAR(EDATE(Controls!$B$6,COLUMN($C$1:$BJ$1)-COLUMN($C$1)))=YEAR(Controls!$B$6)+1)*(COLUMN($C$1:$BJ$1)-COLUMN($C$1)<Controls!$B$7)*$C$96:$BJ$96) -> 1712315.6 | BM96: =SUMPRODUCT((YEAR(EDATE(Controls!$B$6,COLUMN($C$1:$BJ$1)-COLUMN($C$1)))=YEAR(Controls!$B$6)+2)*(COLUMN($C$1:$BJ$1)-COLUMN($C$1)<Controls!$B$7)*$C$96:$BJ$96) -> 4375819.8 | BN96: =SUMPRODUCT((YEAR(EDATE(Controls!$B$6,COLUMN($C$1:$BJ$1)-COLUMN($C$1)))=YEAR(Controls!$B$6)+3)*(COLUMN($C$1:$BJ$1)-COLUMN($C$1)<Controls!$B$7)*$C$96:$BJ$96) -> 0 | BO96: =SUMPRODUCT((YEAR(EDATE(Controls!$B$6,COLUMN($C$1:$BJ$1)-COLUMN($C$1)))=YEAR(Controls!$B$6)+4)*(COLUMN($C$1:$BJ$1)-COLUMN($C$1)<Controls!$B$7)*$C$96:$BJ$96) -> 0 | BP96: =SUMPRODUCT((YEAR(EDATE(Controls!$B$6,COLUMN($C$1:$BJ$1)-COLUMN($C$1)))=YEAR(Controls!$B$6)+5)*(COLUMN($C$1:$BJ$1)-COLUMN($C$1)<Controls!$B$7)*$C$96:$BJ$96) -> 0
A97: Annual Billing – Cash Invoiced | B97: $ | C97: =C91*IFERROR((C77*$C$9+C83*$C$10+C89*$C$11)/C91,0)*12 -> 43297.445 | D97: =D91*IFERROR((D77*$C$9+D83*$C$10+D89*$C$11)/D91,0)*12 -> 85939.822 | E97: =E91*IFERROR((E77*$C$9+E83*$C$10+E89*$C$11)/E91,0)*12 -> 129206.15 | F97: =F91*IFERROR((F77*$C$9+F83*$C$10+F89*$C$11)/F91,0)*12 -> 173729.49 | G97: =G91*IFERROR((G77*$C$9+G83*$C$10+G89*$C$11)/G91,0)*12 -> 223232.58 | H97: =H91*IFERROR((H77*$C$9+H83*$C$10+H89*$C$11)/H91,0)*12 -> 274189.6 | I97: =I91*IFERROR((I77*$C$9+I83*$C$10+I89*$C$11)/I91,0)*12 -> 329581.58 | J97: =J91*IFERROR((J77*$C$9+J83*$C$10+J89*$C$11)/J91,0)*12 -> 383420 | ... BJ97: =BJ91*IFERROR((BJ77*$C$9+BJ83*$C$10+BJ89*$C$11)/BJ91,0)*12 -> 5113666.9 | BK97: =SUMPRODUCT((YEAR(EDATE(Controls!$B$6,COLUMN($C$1:$BJ$1)-COLUMN($C$1)))=YEAR(Controls!$B$6)+0)*(COLUMN($C$1:$BJ$1)-COLUMN($C$1)<Controls!$B$7)*$C$97:$BJ$97) -> 3811757.3 | BL97: =SUMPRODUCT((YEAR(EDATE(Controls!$B$6,COLUMN($C$1:$BJ$1)-COLUMN($C$1)))=YEAR(Controls!$B$6)+1)*(COLUMN($C$1:$BJ$1)-COLUMN($C$1)<Controls!$B$7)*$C$97:$BJ$97) -> 15426877 | BM97: =SUMPRODUCT((YEAR(EDATE(Controls!$B$6,COLUMN($C$1:$BJ$1)-COLUMN($C$1)))=YEAR(Controls!$B$6)+2)*(COLUMN($C$1:$BJ$1)-COLUMN($C$1)<Controls!$B$7)*$C$97:$BJ$97) -> 40278497 | BN97: =SUMPRODUCT((YEAR(EDATE(Controls!$B$6,COLUMN($C$1:$BJ$1)-COLUMN($C$1)))=YEAR(Controls!$B$6)+3)*(COLUMN($C$1:$BJ$1)-COLUMN($C$1)<Controls!$B$7)*$C$97:$BJ$97) -> 0 | BO97: =SUMPRODUCT((YEAR(EDATE(Controls!$B$6,COLUMN($C$1:$BJ$1)-COLUMN($C$1)))=YEAR(Controls!$B$6)+4)*(COLUMN($C$1:$BJ$1)-COLUMN($C$1)<Controls!$B$7)*$C$97:$BJ$97) -> 0 | BP97: =SUMPRODUCT((YEAR(EDATE(Controls!$B$6,COLUMN($C$1:$BJ$1)-COLUMN($C$1)))=YEAR(Controls!$B$6)+5)*(COLUMN($C$1:$BJ$1)-COLUMN($C$1)<Controls!$B$7)*$C$97:$BJ$97) -> 0
A98: Deferred Revenue – Beginning Balance | B98: $ | C98: =0 -> 0 | D98: =C101 -> 39689.324 | E98: =D101 -> 114859.37 | F98: =E101 -> 222856.59 | G98: =F101 -> 361848.92 | H98: =G101 -> 533583.43 | I98: =H101 -> 736416.31 | J98: =I101 -> 971585.82 | K98: =J101 -> 1234728.2 | ... BJ98: =BI101 -> 47715186
A99: + Annual Invoiced (New Deferred) | B99: $ | C99: =C97 -> 43297.445 | D99: =D97 -> 85939.822 | E99: =E97 -> 129206.15 | F99: =F97 -> 173729.49 | G99: =G97 -> 223232.58 | H99: =H97 -> 274189.6 | I99: =I97 -> 329581.58 | J99: =J97 -> 383420 | ... BJ99: =BJ97 -> 5113666.9
A100: – Recognized from Deferred (1/12/mo) | B100: $ | C100: =-IFERROR(C98/11,0)-C99/12 -> -3608.1204 | D100: =-IFERROR(D98/11,0)-D99/12 -> -10769.772 | E100: =-IFERROR(E98/11,0)-E99/12 -> -21208.941 | F100: =-IFERROR(F98/11,0)-F99/12 -> -34737.147 | G100: =-IFERROR(G98/11,0)-G99/12 -> -51498.072 | H100: =-IFERROR(H98/11,0)-H99/12 -> -71356.718 | I100: =-IFERROR(I98/11,0)-I99/12 -> -94412.069 | J100: =-IFERROR(J98/11,0)-J99/12 -> -120277.65 | ... BJ100: =-IFERROR(BJ98/11,0)-BJ99/12 -> -4763883.1
A101: = Deferred Revenue – Ending Balance | B101: $ | C101: =C98+C99+C100 -> 39689.324 | D101: =D98+D99+D100 -> 114859.37 | E101: =E98+E99+E100 -> 222856.59 | F101: =F98+F99+F100 -> 361848.92 | G101: =G98+G99+G100 -> 533583.43 | H101: =H98+H99+H100 -> 736416.31 | I101: =I98+I99+I100 -> 971585.82 | J101: =J98+J99+J100 -> 1234728.2 | ... BJ101: =BJ98+BJ99+BJ100 -> 48064970 | BK101: =IFERROR(LOOKUP(2,1/((YEAR(EDATE(Controls!$B$6,COLUMN($C$1:$BJ$1)-COLUMN($C$1)))=YEAR(Controls!$B$6)+0)*(COLUMN($C$1:$BJ$1)-COLUMN($C$1)<Controls!$B$7)),$C$101:$BJ$101),0) -> 2602422.6 | BL101: =IFERROR(LOOKUP(2,1/((YEAR(EDATE(Controls!$B$6,COLUMN($C$1:$BJ$1)-COLUMN($C$1)))=YEAR(Controls!$B$6)+1)*(COLUMN($C$1:$BJ$1)-COLUMN($C$1)<Controls!$B$7)),$C$101:$BJ$101),0) -> 10536492 | BM101: =IFERROR(LOOKUP(2,1/((YEAR(EDATE(Controls!$B$6,COLUMN($C$1:$BJ$1)-COLUMN($C$1)))=YEAR(Controls!$B$6)+2)*(COLUMN($C$1:$BJ$1)-COLUMN($C$1)<Controls!$B$7)),$C$101:$BJ$101),0) -> 28321416 | BN101: =IFERROR(LOOKUP(2,1/((YEAR(EDATE(Controls!$B$6,COLUMN($C$1:$BJ$1)-COLUMN($C$1)))=YEAR(Controls!$B$6)+3)*(COLUMN($C$1:$BJ$1)-COLUMN($C$1)<Controls!$B$7)),$C$101:$BJ$101),0) -> 0 | BO101: =IFERROR(LOOKUP(2,1/((YEAR(EDATE(Controls!$B$6,COLUMN($C$1:$BJ$1)-COLUMN($C$1)))=YEAR(Controls!$B$6)+4)*(COLUMN($C$1:$BJ$1)-COLUMN($C$1)<Controls!$B$7)),$C$101:$BJ$101),0) -> 0 | BP101: =IFERROR(LOOKUP(2,1/((YEAR(EDATE(Controls!$B$6,COLUMN($C$1:$BJ$1)-COLUMN($C$1)))=YEAR(Controls!$B$6)+5)*(COLUMN($C$1:$BJ$1)-COLUMN($C$1)<Controls!$B$7)),$C$101:$BJ$101),0) -> 0
A102: TOTAL RECOGNIZED SUBSCRIPTION REVENUE | B102: $ | C102: =C96-C100 -> 8691.094 | D102: =D96-D100 -> 20722.069 | E102: =E96-E100 -> 36114.149 | F102: =F96-F100 -> 54776.382 | G102: =G96-G100 -> 77092.71 | H102: =H96-H100 -> 102733.2 | I102: =I96-I100 -> 131901.31 | J102: =J96-J100 -> 163969.82 | ... BJ102: =BJ96-BJ100 -> 5231473.9 | BK102: =SUMPRODUCT((YEAR(EDATE(Controls!$B$6,COLUMN($C$1:$BJ$1)-COLUMN($C$1)))=YEAR(Controls!$B$6)+0)*(COLUMN($C$1:$BJ$1)-COLUMN($C$1)<Controls!$B$7)*$C$102:$BJ$102) -> 1643273.9 | BL102: =SUMPRODUCT((YEAR(EDATE(Controls!$B$6,COLUMN($C$1:$BJ$1)-COLUMN($C$1)))=YEAR(Controls!$B$6)+1)*(COLUMN($C$1:$BJ$1)-COLUMN($C$1)<Controls!$B$7)*$C$102:$BJ$102) -> 9205123.1 | BM102: =SUMPRODUCT((YEAR(EDATE(Controls!$B$6,COLUMN($C$1:$BJ$1)-COLUMN($C$1)))=YEAR(Controls!$B$6)+2)*(COLUMN($C$1:$BJ$1)-COLUMN($C$1)<Controls!$B$7)*$C$102:$BJ$102) -> 26869393 | BN102: =SUMPRODUCT((YEAR(EDATE(Controls!$B$6,COLUMN($C$1:$BJ$1)-COLUMN($C$1)))=YEAR(Controls!$B$6)+3)*(COLUMN($C$1:$BJ$1)-COLUMN($C$1)<Controls!$B$7)*$C$102:$BJ$102) -> 0 | BO102: =SUMPRODUCT((YEAR(EDATE(Controls!$B$6,COLUMN($C$1:$BJ$1)-COLUMN($C$1)))=YEAR(Controls!$B$6)+4)*(COLUMN($C$1:$BJ$1)-COLUMN($C$1)<Controls!$B$7)*$C$102:$BJ$102) -> 0 | BP102: =SUMPRODUCT((YEAR(EDATE(Controls!$B$6,COLUMN($C$1:$BJ$1)-COLUMN($C$1)))=YEAR(Controls!$B$6)+5)*(COLUMN($C$1:$BJ$1)-COLUMN($C$1)<Controls!$B$7)*$C$102:$BJ$102) -> 0
A104: Professional Services Revenue | B104: $ | C104: 5000 | D104: 5500 | E104: 6000 | F104: 6500 | G104: 7000 | H104: 7500 | I104: 8000 | J104: 8500 | K104: 9000 | L104: 9500 | M104: 10000 | N104: 10000 | O104: 10000 | P104: 11000 | Q104: 11000 | R104: 12000 | S104: 12000 | T104: 12000 | U104: 13000 | V104: 13000 | W104: 14000 | X104: 14000 | Y104: 15000 | Z104: 15000 | AA104: 15000 | AB104: 16000 | AC104: 16000 | AD104: 17000 | AE104: 17000 | AF104: 18000 | AG104: 18000 | AH104: 19000 | AI104: 19000 | AJ104: 20000 | AK104: 20000 | AL104: 20000 | AM104: 20000 | AN104: 21000 | AO104: 21000 | AP104: 22000 | AQ104: 22000 | AR104: 23000 | AS104: 23000 | AT104: 24000 | AU104: 24000 | AV104: 25000 | AW104: 25000 | AX104: 25000 | AY104: 25000 | AZ104: 26000 | BA104: 27000 | BB104: 27000 | BC104: 28000 | BD104: 28000 | BE104: 29000 | BF104: 30000 | BG104: 30000 | BH104: 31000 | BI104: 32000 | BJ104: 32000 | BK104: =SUMPRODUCT((YEAR(EDATE(Controls!$B$6,COLUMN($C$1:$BJ$1)-COLUMN($C$1)))=YEAR(Controls!$B$6)+0)*(COLUMN($C$1:$BJ$1)-COLUMN($C$1)<Controls!$B$7)*$C$104:$BJ$104) -> 92500 | BL104: =SUMPRODUCT((YEAR(EDATE(Controls!$B$6,COLUMN($C$1:$BJ$1)-COLUMN($C$1)))=YEAR(Controls!$B$6)+1)*(COLUMN($C$1:$BJ$1)-COLUMN($C$1)<Controls!$B$7)*$C$104:$BJ$104) -> 152000 | BM104: =SUMPRODUCT((YEAR(EDATE(Controls!$B$6,COLUMN($C$1:$BJ$1)-COLUMN($C$1)))=YEAR(Controls!$B$6)+2)*(COLUMN($C$1:$BJ$1)-COLUMN($C$1)<Controls!$B$7)*$C$104:$BJ$104) -> 215000 | BN104: =SUMPRODUCT((YEAR(EDATE(Controls!$B$6,COLUMN($C$1:$BJ$1)-COLUMN($C$1)))=YEAR(Controls!$B$6)+3)*(COLUMN($C$1:$BJ$1)-COLUMN($C$1)<Controls!$B$7)*$C$104:$BJ$104) -> 0 | BO104: =SUMPRODUCT((YEAR(EDATE(Controls!$B$6,COLUMN($C$1:$BJ$1)-COLUMN($C$1)))=YEAR(Controls!$B$6)+4)*(COLUMN($C$1:$BJ$1)-COLUMN($C$1)<Controls!$B$7)*$C$104:$BJ$104) -> 0 | BP104: =SUMPRODUCT((YEAR(EDATE(Controls!$B$6,COLUMN($C$1:$BJ$1)-COLUMN($C$1)))=YEAR(Controls!$B$6)+5)*(COLUMN($C$1:$BJ$1)-COLUMN($C$1)<Controls!$B$7)*$C$104:$BJ$104) -> 0
A105: TOTAL RECOGNIZED REVENUE | B105: $ | C105: =C102+C104 -> 13691.094 | D105: =D102+D104 -> 26222.069 | E105: =E102+E104 -> 42114.149 | F105: =F102+F104 -> 61276.382 | G105: =G102+G104 -> 84092.71 | H105: =H102+H104 -> 110233.2 | I105: =I102+I104 -> 139901.31 | J105: =J102+J104 -> 172469.82 | ... BJ105: =BJ102+BJ104 -> 5263473.9 | BK105: =SUMPRODUCT((YEAR(EDATE(Controls!$B$6,COLUMN($C$1:$BJ$1)-COLUMN($C$1)))=YEAR(Controls!$B$6)+0)*(COLUMN($C$1:$BJ$1)-COLUMN($C$1)<Controls!$B$7)*$C$105:$BJ$105) -> 1735773.9 | BL105: =SUMPRODUCT((YEAR(EDATE(Controls!$B$6,COLUMN($C$1:$BJ$1)-COLUMN($C$1)))=YEAR(Controls!$B$6)+1)*(COLUMN($C$1:$BJ$1)-COLUMN($C$1)<Controls!$B$7)*$C$105:$BJ$105) -> 9357123.1 | BM105: =SUMPRODUCT((YEAR(EDATE(Controls!$B$6,COLUMN($C$1:$BJ$1)-COLUMN($C$1)))=YEAR(Controls!$B$6)+2)*(COLUMN($C$1:$BJ$1)-COLUMN($C$1)<Controls!$B$7)*$C$105:$BJ$105) -> 27084393 | BN105: =SUMPRODUCT((YEAR(EDATE(Controls!$B$6,COLUMN($C$1:$BJ$1)-COLUMN($C$1)))=YEAR(Controls!$B$6)+3)*(COLUMN($C$1:$BJ$1)-COLUMN($C$1)<Controls!$B$7)*$C$105:$BJ$105) -> 0 | BO105: =SUMPRODUCT((YEAR(EDATE(Controls!$B$6,COLUMN($C$1:$BJ$1)-COLUMN($C$1)))=YEAR(Controls!$B$6)+4)*(COLUMN($C$1:$BJ$1)-COLUMN($C$1)<Controls!$B$7)*$C$105:$BJ$105) -> 0 | BP105: =SUMPRODUCT((YEAR(EDATE(Controls!$B$6,COLUMN($C$1:$BJ$1)-COLUMN($C$1)))=YEAR(Controls!$B$6)+5)*(COLUMN($C$1:$BJ$1)-COLUMN($C$1)<Controls!$B$7)*$C$105:$BJ$105) -> 0

Sheet Charts
A1: SaaS Financial Plan · Key Metrics Dashboard · 36-Month Forecast

Sheet Headcount
A1: HEADCOUNT PLAN · Role-Level Wage Forecast · Includes Benefits & Payroll Taxes
A3: Label | B3: Unit | C3: =TEXT(EDATE(Controls!$B$6,0),"mmm-yy") -> Jan-26 | D3: =TEXT(EDATE(Controls!$B$6,1),"mmm-yy") -> Feb-26 | E3: =TEXT(EDATE(Controls!$B$6,2),"mmm-yy") -> Mar-26 | F3: =TEXT(EDATE(Controls!$B$6,3),"mmm-yy") -> Apr-26 | G3: =TEXT(EDATE(Controls!$B$6,4),"mmm-yy") -> May-26 | H3: =TEXT(EDATE(Controls!$B$6,5),"mmm-yy") -> Jun-26 | I3: =TEXT(EDATE(Controls!$B$6,6),"mmm-yy") -> Jul-26 | J3: =TEXT(EDATE(Controls!$B$6,7),"mmm-yy") -> Aug-26 | K3: =TEXT(EDATE(Controls!$B$6,8),"mmm-yy") -> Sep-26 | L3: =TEXT(EDATE(Controls!$B$6,9),"mmm-yy") -> Oct-26 | M3: =TEXT(EDATE(Controls!$B$6,10),"mmm-yy") -> Nov-26 | N3: =TEXT(EDATE(Controls!$B$6,11),"mmm-yy") -> Dec-26 | O3: =TEXT(EDATE(Controls!$B$6,12),"mmm-yy") -> Jan-27 | P3: =TEXT(EDATE(Controls!$B$6,13),"mmm-yy") -> Feb-27 | Q3: =TEXT(EDATE(Controls!$B$6,14),"mmm-yy") -> Mar-27 | R3: =TEXT(EDATE(Controls!$B$6,15),"mmm-yy") -> Apr-27 | S3: =TEXT(EDATE(Controls!$B$6,16),"mmm-yy") -> May-27 | T3: =TEXT(EDATE(Controls!$B$6,17),"mmm-yy") -> Jun-27 | U3: =TEXT(EDATE(Controls!$B$6,18),"mmm-yy") -> Jul-27 | V3: =TEXT(EDATE(Controls!$B$6,19),"mmm-yy") -> Aug-27 | W3: =TEXT(EDATE(Controls!$B$6,20),"mmm-yy") -> Sep-27 | X3: =TEXT(EDATE(Controls!$B$6,21),"mmm-yy") -> Oct-27 | Y3: =TEXT(EDATE(Controls!$B$6,22),"mmm-yy") -> Nov-27 | Z3: =TEXT(EDATE(Controls!$B$6,23),"mmm-yy") -> Dec-27 | AA3: =TEXT(EDATE(Controls!$B$6,24),"mmm-yy") -> Jan-28 | AB3: =TEXT(EDATE(Controls!$B$6,25),"mmm-yy") -> Feb-28 | AC3: =TEXT(EDATE(Controls!$B$6,26),"mmm-yy") -> Mar-28 | AD3: =TEXT(EDATE(Controls!$B$6,27),"mmm-yy") -> Apr-28 | AE3: =TEXT(EDATE(Controls!$B$6,28),"mmm-yy") -> May-28 | AF3: =TEXT(EDATE(Controls!$B$6,29),"mmm-yy") -> Jun-28 | AG3: =TEXT(EDATE(Controls!$B$6,30),"mmm-yy") -> Jul-28 | AH3: =TEXT(EDATE(Controls!$B$6,31),"mmm-yy") -> Aug-28 | AI3: =TEXT(EDATE(Controls!$B$6,32),"mmm-yy") -> Sep-28 | AJ3: =TEXT(EDATE(Controls!$B$6,33),"mmm-yy") -> Oct-28 | AK3: =TEXT(EDATE(Controls!$B$6,34),"mmm-yy") -> Nov-28 | AL3: =TEXT(EDATE(Controls!$B$6,35),"mmm-yy") -> Dec-28 | AM3: =TEXT(EDATE(Controls!$B$6,36),"mmm-yy") -> Jan-29 | AN3: =TEXT(EDATE(Controls!$B$6,37),"mmm-yy") -> Feb-29 | AO3: =TEXT(EDATE(Controls!$B$6,38),"mmm-yy") -> Mar-29 | AP3: =TEXT(EDATE(Controls!$B$6,39),"mmm-yy") -> Apr-29 | AQ3: =TEXT(EDATE(Controls!$B$6,40),"mmm-yy") -> May-29 | AR3: =TEXT(EDATE(Controls!$B$6,41),"mmm-yy") -> Jun-29 | AS3: =TEXT(EDATE(Controls!$B$6,42),"mmm-yy") -> Jul-29 | AT3: =TEXT(EDATE(Controls!$B$6,43),"mmm-yy") -> Aug-29 | AU3: =TEXT(EDATE(Controls!$B$6,44),"mmm-yy") -> Sep-29 | AV3: =TEXT(EDATE(Controls!$B$6,45),"mmm-yy") -> Oct-29 | AW3: =TEXT(EDATE(Controls!$B$6,46),"mmm-yy") -> Nov-29 | AX3: =TEXT(EDATE(Controls!$B$6,47),"mmm-yy") -> Dec-29 | AY3: =TEXT(EDATE(Controls!$B$6,48),"mmm-yy") -> Jan-30 | AZ3: =TEXT(EDATE(Controls!$B$6,49),"mmm-yy") -> Feb-30 | BA3: =TEXT(EDATE(Controls!$B$6,50),"mmm-yy") -> Mar-30 | BB3: =TEXT(EDATE(Controls!$B$6,51),"mmm-yy") -> Apr-30 | BC3: =TEXT(EDATE(Controls!$B$6,52),"mmm-yy") -> May-30 | BD3: =TEXT(EDATE(Controls!$B$6,53),"mmm-yy") -> Jun-30 | BE3: =TEXT(EDATE(Controls!$B$6,54),"mmm-yy") -> Jul-30 | BF3: =TEXT(EDATE(Controls!$B$6,55),"mmm-yy") -> Aug-30 | BG3: =TEXT(EDATE(Controls!$B$6,56),"mmm-yy") -> Sep-30 | BH3: =TEXT(EDATE(Controls!$B$6,57),"mmm-yy") -> Oct-30 | BI3: =TEXT(EDATE(Controls!$B$6,58),"mmm-yy") -> Nov-30 | BJ3: =TEXT(EDATE(Controls!$B$6,59),"mmm-yy") -> Dec-30 | BK3: ="FY "&(YEAR(Controls!$B$6)+0) -> FY 2026 | BL3: ="FY "&(YEAR(Controls!$B$6)+1) -> FY 2027 | BM3: ="FY "&(YEAR(Controls!$B$6)+2) -> FY 2028 | BN3: ="FY "&(YEAR(Controls!$B$6)+3) -> FY 2029 | BO3: ="FY "&(YEAR(Controls!$B$6)+4) -> FY 2030 | BP3: ="FY "&(YEAR(Controls!$B$6)+5) -> FY 2031
A5: HEADCOUNT WAGES BY DEPARTMENT (Benefits & Payroll Tax Built In)
A6: Year 1 (months 1–12): enter base salary cost directly. Years 2–3 auto-calculate from the rolling 12-month prior period × (1 + YoY growth rate). Growth kicks in exactly 12 months after model start — not on a calendar-year boundary.
A7: COGS – Customer Success
A8: YoY Headcount Cost Growth Rate – COGS – Customer Success | B8: %/yr | C8: 0.2 | D8: ↑ Applies to months 13–36 (rolling 12-mo, not calendar year)
A9: Base Salary Cost – COGS – Customer Success | B9: $/mo | C9: 8000 | D9: 8000 | E9: 8000 | F9: 8000 | G9: 8000 | H9: 8000 | I9: 8000 | J9: 8000 | K9: 8000 | L9: 8000 | M9: 8000 | N9: 8000 | O9: =IF(COLUMN()-2<=Controls!$B$7,C9*(1+$C$8),0) -> 9600 | P9: =IF(COLUMN()-2<=Controls!$B$7,D9*(1+$C$8),0) -> 9600 | Q9: =IF(COLUMN()-2<=Controls!$B$7,E9*(1+$C$8),0) -> 9600 | R9: =IF(COLUMN()-2<=Controls!$B$7,F9*(1+$C$8),0) -> 9600 | S9: =IF(COLUMN()-2<=Controls!$B$7,G9*(1+$C$8),0) -> 9600 | T9: =IF(COLUMN()-2<=Controls!$B$7,H9*(1+$C$8),0) -> 9600 | U9: =IF(COLUMN()-2<=Controls!$B$7,I9*(1+$C$8),0) -> 9600 | V9: =IF(COLUMN()-2<=Controls!$B$7,J9*(1+$C$8),0) -> 9600 | ... BJ9: =IF(COLUMN()-2<=Controls!$B$7,AX9*(1+$C$8),0) -> 0 | BK9: =SUMPRODUCT((YEAR(EDATE(Controls!$B$6,COLUMN($C$1:$BJ$1)-COLUMN($C$1)))=YEAR(Controls!$B$6)+0)*(COLUMN($C$1:$BJ$1)-COLUMN($C$1)<Controls!$B$7)*$C$9:$BJ$9) -> 96000 | BL9: =SUMPRODUCT((YEAR(EDATE(Controls!$B$6,COLUMN($C$1:$BJ$1)-COLUMN($C$1)))=YEAR(Controls!$B$6)+1)*(COLUMN($C$1:$BJ$1)-COLUMN($C$1)<Controls!$B$7)*$C$9:$BJ$9) -> 115200 | BM9: =SUMPRODUCT((YEAR(EDATE(Controls!$B$6,COLUMN($C$1:$BJ$1)-COLUMN($C$1)))=YEAR(Controls!$B$6)+2)*(COLUMN($C$1:$BJ$1)-COLUMN($C$1)<Controls!$B$7)*$C$9:$BJ$9) -> 138240 | BN9: =SUMPRODUCT((YEAR(EDATE(Controls!$B$6,COLUMN($C$1:$BJ$1)-COLUMN($C$1)))=YEAR(Controls!$B$6)+3)*(COLUMN($C$1:$BJ$1)-COLUMN($C$1)<Controls!$B$7)*$C$9:$BJ$9) -> 0 | BO9: =SUMPRODUCT((YEAR(EDATE(Controls!$B$6,COLUMN($C$1:$BJ$1)-COLUMN($C$1)))=YEAR(Controls!$B$6)+4)*(COLUMN($C$1:$BJ$1)-COLUMN($C$1)<Controls!$B$7)*$C$9:$BJ$9) -> 0 | BP9: =SUMPRODUCT((YEAR(EDATE(Controls!$B$6,COLUMN($C$1:$BJ$1)-COLUMN($C$1)))=YEAR(Controls!$B$6)+5)*(COLUMN($C$1:$BJ$1)-COLUMN($C$1)<Controls!$B$7)*$C$9:$BJ$9) -> 0
A10: Total Loaded Cost – COGS – Customer Success (incl. benefits & taxes) | B10: $/mo | C10: =C9*(1+Controls!$B$25+Controls!$B$24) -> 10052 | D10: =D9*(1+Controls!$B$25+Controls!$B$24) -> 10052 | E10: =E9*(1+Controls!$B$25+Controls!$B$24) -> 10052 | F10: =F9*(1+Controls!$B$25+Controls!$B$24) -> 10052 | G10: =G9*(1+Controls!$B$25+Controls!$B$24) -> 10052 | H10: =H9*(1+Controls!$B$25+Controls!$B$24) -> 10052 | I10: =I9*(1+Controls!$B$25+Controls!$B$24) -> 10052 | J10: =J9*(1+Controls!$B$25+Controls!$B$24) -> 10052 | ... BJ10: =BJ9*(1+Controls!$B$25+Controls!$B$24) -> 0 | BK10: =SUMPRODUCT((YEAR(EDATE(Controls!$B$6,COLUMN($C$1:$BJ$1)-COLUMN($C$1)))=YEAR(Controls!$B$6)+0)*(COLUMN($C$1:$BJ$1)-COLUMN($C$1)<Controls!$B$7)*$C$10:$BJ$10) -> 120624 | BL10: =SUMPRODUCT((YEAR(EDATE(Controls!$B$6,COLUMN($C$1:$BJ$1)-COLUMN($C$1)))=YEAR(Controls!$B$6)+1)*(COLUMN($C$1:$BJ$1)-COLUMN($C$1)<Controls!$B$7)*$C$10:$BJ$10) -> 144748.8 | BM10: =SUMPRODUCT((YEAR(EDATE(Controls!$B$6,COLUMN($C$1:$BJ$1)-COLUMN($C$1)))=YEAR(Controls!$B$6)+2)*(COLUMN($C$1:$BJ$1)-COLUMN($C$1)<Controls!$B$7)*$C$10:$BJ$10) -> 173698.56 | BN10: =SUMPRODUCT((YEAR(EDATE(Controls!$B$6,COLUMN($C$1:$BJ$1)-COLUMN($C$1)))=YEAR(Controls!$B$6)+3)*(COLUMN($C$1:$BJ$1)-COLUMN($C$1)<Controls!$B$7)*$C$10:$BJ$10) -> 0 | BO10: =SUMPRODUCT((YEAR(EDATE(Controls!$B$6,COLUMN($C$1:$BJ$1)-COLUMN($C$1)))=YEAR(Controls!$B$6)+4)*(COLUMN($C$1:$BJ$1)-COLUMN($C$1)<Controls!$B$7)*$C$10:$BJ$10) -> 0 | BP10: =SUMPRODUCT((YEAR(EDATE(Controls!$B$6,COLUMN($C$1:$BJ$1)-COLUMN($C$1)))=YEAR(Controls!$B$6)+5)*(COLUMN($C$1:$BJ$1)-COLUMN($C$1)<Controls!$B$7)*$C$10:$BJ$10) -> 0
A12: Sales & Marketing
A13: YoY Headcount Cost Growth Rate – Sales & Marketing | B13: %/yr | C13: 0.3 | D13: ↑ Applies to months 13–36 (rolling 12-mo, not calendar year)
A14: Base Salary Cost – Sales & Marketing | B14: $/mo | C14: 15000 | D14: 15000 | E14: 15000 | F14: 15000 | G14: 15000 | H14: 15000 | I14: 15000 | J14: 15000 | K14: 15000 | L14: 15000 | M14: 15000 | N14: 15000 | O14: =IF(COLUMN()-2<=Controls!$B$7,C14*(1+$C$13),0) -> 19500 | P14: =IF(COLUMN()-2<=Controls!$B$7,D14*(1+$C$13),0) -> 19500 | Q14: =IF(COLUMN()-2<=Controls!$B$7,E14*(1+$C$13),0) -> 19500 | R14: =IF(COLUMN()-2<=Controls!$B$7,F14*(1+$C$13),0) -> 19500 | S14: =IF(COLUMN()-2<=Controls!$B$7,G14*(1+$C$13),0) -> 19500 | T14: =IF(COLUMN()-2<=Controls!$B$7,H14*(1+$C$13),0) -> 19500 | U14: =IF(COLUMN()-2<=Controls!$B$7,I14*(1+$C$13),0) -> 19500 | V14: =IF(COLUMN()-2<=Controls!$B$7,J14*(1+$C$13),0) -> 19500 | ... BJ14: =IF(COLUMN()-2<=Controls!$B$7,AX14*(1+$C$13),0) -> 0 | BK14: =SUMPRODUCT((YEAR(EDATE(Controls!$B$6,COLUMN($C$1:$BJ$1)-COLUMN($C$1)))=YEAR(Controls!$B$6)+0)*(COLUMN($C$1:$BJ$1)-COLUMN($C$1)<Controls!$B$7)*$C$14:$BJ$14) -> 180000 | BL14: =SUMPRODUCT((YEAR(EDATE(Controls!$B$6,COLUMN($C$1:$BJ$1)-COLUMN($C$1)))=YEAR(Controls!$B$6)+1)*(COLUMN($C$1:$BJ$1)-COLUMN($C$1)<Controls!$B$7)*$C$14:$BJ$14) -> 234000 | BM14: =SUMPRODUCT((YEAR(EDATE(Controls!$B$6,COLUMN($C$1:$BJ$1)-COLUMN($C$1)))=YEAR(Controls!$B$6)+2)*(COLUMN($C$1:$BJ$1)-COLUMN($C$1)<Controls!$B$7)*$C$14:$BJ$14) -> 304200 | BN14: =SUMPRODUCT((YEAR(EDATE(Controls!$B$6,COLUMN($C$1:$BJ$1)-COLUMN($C$1)))=YEAR(Controls!$B$6)+3)*(COLUMN($C$1:$BJ$1)-COLUMN($C$1)<Controls!$B$7)*$C$14:$BJ$14) -> 0 | BO14: =SUMPRODUCT((YEAR(EDATE(Controls!$B$6,COLUMN($C$1:$BJ$1)-COLUMN($C$1)))=YEAR(Controls!$B$6)+4)*(COLUMN($C$1:$BJ$1)-COLUMN($C$1)<Controls!$B$7)*$C$14:$BJ$14) -> 0 | BP14: =SUMPRODUCT((YEAR(EDATE(Controls!$B$6,COLUMN($C$1:$BJ$1)-COLUMN($C$1)))=YEAR(Controls!$B$6)+5)*(COLUMN($C$1:$BJ$1)-COLUMN($C$1)<Controls!$B$7)*$C$14:$BJ$14) -> 0
A15: Total Loaded Cost – Sales & Marketing (incl. benefits & taxes) | B15: $/mo | C15: =C14*(1+Controls!$B$25+Controls!$B$24) -> 18847.5 | D15: =D14*(1+Controls!$B$25+Controls!$B$24) -> 18847.5 | E15: =E14*(1+Controls!$B$25+Controls!$B$24) -> 18847.5 | F15: =F14*(1+Controls!$B$25+Controls!$B$24) -> 18847.5 | G15: =G14*(1+Controls!$B$25+Controls!$B$24) -> 18847.5 | H15: =H14*(1+Controls!$B$25+Controls!$B$24) -> 18847.5 | I15: =I14*(1+Controls!$B$25+Controls!$B$24) -> 18847.5 | J15: =J14*(1+Controls!$B$25+Controls!$B$24) -> 18847.5 | ... BJ15: =BJ14*(1+Controls!$B$25+Controls!$B$24) -> 0 | BK15: =SUMPRODUCT((YEAR(EDATE(Controls!$B$6,COLUMN($C$1:$BJ$1)-COLUMN($C$1)))=YEAR(Controls!$B$6)+0)*(COLUMN($C$1:$BJ$1)-COLUMN($C$1)<Controls!$B$7)*$C$15:$BJ$15) -> 226170 | BL15: =SUMPRODUCT((YEAR(EDATE(Controls!$B$6,COLUMN($C$1:$BJ$1)-COLUMN($C$1)))=YEAR(Controls!$B$6)+1)*(COLUMN($C$1:$BJ$1)-COLUMN($C$1)<Controls!$B$7)*$C$15:$BJ$15) -> 294021 | BM15: =SUMPRODUCT((YEAR(EDATE(Controls!$B$6,COLUMN($C$1:$BJ$1)-COLUMN($C$1)))=YEAR(Controls!$B$6)+2)*(COLUMN($C$1:$BJ$1)-COLUMN($C$1)<Controls!$B$7)*$C$15:$BJ$15) -> 382227.3 | BN15: =SUMPRODUCT((YEAR(EDATE(Controls!$B$6,COLUMN($C$1:$BJ$1)-COLUMN($C$1)))=YEAR(Controls!$B$6)+3)*(COLUMN($C$1:$BJ$1)-COLUMN($C$1)<Controls!$B$7)*$C$15:$BJ$15) -> 0 | BO15: =SUMPRODUCT((YEAR(EDATE(Controls!$B$6,COLUMN($C$1:$BJ$1)-COLUMN($C$1)))=YEAR(Controls!$B$6)+4)*(COLUMN($C$1:$BJ$1)-COLUMN($C$1)<Controls!$B$7)*$C$15:$BJ$15) -> 0 | BP15: =SUMPRODUCT((YEAR(EDATE(Controls!$B$6,COLUMN($C$1:$BJ$1)-COLUMN($C$1)))=YEAR(Controls!$B$6)+5)*(COLUMN($C$1:$BJ$1)-COLUMN($C$1)<Controls!$B$7)*$C$15:$BJ$15) -> 0
A17: R&D / Engineering
A18: YoY Headcount Cost Growth Rate – R&D / Engineering | B18: %/yr | C18: 0.25 | D18: ↑ Applies to months 13–36 (rolling 12-mo, not calendar year)
A19: Base Salary Cost – R&D / Engineering | B19: $/mo | C19: 20000 | D19: 20000 | E19: 20000 | F19: 20000 | G19: 20000 | H19: 20000 | I19: 20000 | J19: 20000 | K19: 20000 | L19: 20000 | M19: 20000 | N19: 20000 | O19: =IF(COLUMN()-2<=Controls!$B$7,C19*(1+$C$18),0) -> 25000 | P19: =IF(COLUMN()-2<=Controls!$B$7,D19*(1+$C$18),0) -> 25000 | Q19: =IF(COLUMN()-2<=Controls!$B$7,E19*(1+$C$18),0) -> 25000 | R19: =IF(COLUMN()-2<=Controls!$B$7,F19*(1+$C$18),0) -> 25000 | S19: =IF(COLUMN()-2<=Controls!$B$7,G19*(1+$C$18),0) -> 25000 | T19: =IF(COLUMN()-2<=Controls!$B$7,H19*(1+$C$18),0) -> 25000 | U19: =IF(COLUMN()-2<=Controls!$B$7,I19*(1+$C$18),0) -> 25000 | V19: =IF(COLUMN()-2<=Controls!$B$7,J19*(1+$C$18),0) -> 25000 | ... BJ19: =IF(COLUMN()-2<=Controls!$B$7,AX19*(1+$C$18),0) -> 0 | BK19: =SUMPRODUCT((YEAR(EDATE(Controls!$B$6,COLUMN($C$1:$BJ$1)-COLUMN($C$1)))=YEAR(Controls!$B$6)+0)*(COLUMN($C$1:$BJ$1)-COLUMN($C$1)<Controls!$B$7)*$C$19:$BJ$19) -> 240000 | BL19: =SUMPRODUCT((YEAR(EDATE(Controls!$B$6,COLUMN($C$1:$BJ$1)-COLUMN($C$1)))=YEAR(Controls!$B$6)+1)*(COLUMN($C$1:$BJ$1)-COLUMN($C$1)<Controls!$B$7)*$C$19:$BJ$19) -> 300000 | BM19: =SUMPRODUCT((YEAR(EDATE(Controls!$B$6,COLUMN($C$1:$BJ$1)-COLUMN($C$1)))=YEAR(Controls!$B$6)+2)*(COLUMN($C$1:$BJ$1)-COLUMN($C$1)<Controls!$B$7)*$C$19:$BJ$19) -> 375000 | BN19: =SUMPRODUCT((YEAR(EDATE(Controls!$B$6,COLUMN($C$1:$BJ$1)-COLUMN($C$1)))=YEAR(Controls!$B$6)+3)*(COLUMN($C$1:$BJ$1)-COLUMN($C$1)<Controls!$B$7)*$C$19:$BJ$19) -> 0 | BO19: =SUMPRODUCT((YEAR(EDATE(Controls!$B$6,COLUMN($C$1:$BJ$1)-COLUMN($C$1)))=YEAR(Controls!$B$6)+4)*(COLUMN($C$1:$BJ$1)-COLUMN($C$1)<Controls!$B$7)*$C$19:$BJ$19) -> 0 | BP19: =SUMPRODUCT((YEAR(EDATE(Controls!$B$6,COLUMN($C$1:$BJ$1)-COLUMN($C$1)))=YEAR(Controls!$B$6)+5)*(COLUMN($C$1:$BJ$1)-COLUMN($C$1)<Controls!$B$7)*$C$19:$BJ$19) -> 0
A20: Total Loaded Cost – R&D / Engineering (incl. benefits & taxes) | B20: $/mo | C20: =C19*(1+Controls!$B$25+Controls!$B$24) -> 25130 | D20: =D19*(1+Controls!$B$25+Controls!$B$24) -> 25130 | E20: =E19*(1+Controls!$B$25+Controls!$B$24) -> 25130 | F20: =F19*(1+Controls!$B$25+Controls!$B$24) -> 25130 | G20: =G19*(1+Controls!$B$25+Controls!$B$24) -> 25130 | H20: =H19*(1+Controls!$B$25+Controls!$B$24) -> 25130 | I20: =I19*(1+Controls!$B$25+Controls!$B$24) -> 25130 | J20: =J19*(1+Controls!$B$25+Controls!$B$24) -> 25130 | ... BJ20: =BJ19*(1+Controls!$B$25+Controls!$B$24) -> 0 | BK20: =SUMPRODUCT((YEAR(EDATE(Controls!$B$6,COLUMN($C$1:$BJ$1)-COLUMN($C$1)))=YEAR(Controls!$B$6)+0)*(COLUMN($C$1:$BJ$1)-COLUMN($C$1)<Controls!$B$7)*$C$20:$BJ$20) -> 301560 | BL20: =SUMPRODUCT((YEAR(EDATE(Controls!$B$6,COLUMN($C$1:$BJ$1)-COLUMN($C$1)))=YEAR(Controls!$B$6)+1)*(COLUMN($C$1:$BJ$1)-COLUMN($C$1)<Controls!$B$7)*$C$20:$BJ$20) -> 376950 | BM20: =SUMPRODUCT((YEAR(EDATE(Controls!$B$6,COLUMN($C$1:$BJ$1)-COLUMN($C$1)))=YEAR(Controls!$B$6)+2)*(COLUMN($C$1:$BJ$1)-COLUMN($C$1)<Controls!$B$7)*$C$20:$BJ$20) -> 471187.5 | BN20: =SUMPRODUCT((YEAR(EDATE(Controls!$B$6,COLUMN($C$1:$BJ$1)-COLUMN($C$1)))=YEAR(Controls!$B$6)+3)*(COLUMN($C$1:$BJ$1)-COLUMN($C$1)<Controls!$B$7)*$C$20:$BJ$20) -> 0 | BO20: =SUMPRODUCT((YEAR(EDATE(Controls!$B$6,COLUMN($C$1:$BJ$1)-COLUMN($C$1)))=YEAR(Controls!$B$6)+4)*(COLUMN($C$1:$BJ$1)-COLUMN($C$1)<Controls!$B$7)*$C$20:$BJ$20) -> 0 | BP20: =SUMPRODUCT((YEAR(EDATE(Controls!$B$6,COLUMN($C$1:$BJ$1)-COLUMN($C$1)))=YEAR(Controls!$B$6)+5)*(COLUMN($C$1:$BJ$1)-COLUMN($C$1)<Controls!$B$7)*$C$20:$BJ$20) -> 0
A22: G&A
A23: YoY Headcount Cost Growth Rate – G&A | B23: %/yr | C23: 0.15 | D23: ↑ Applies to months 13–36 (rolling 12-mo, not calendar year)
A24: Base Salary Cost – G&A | B24: $/mo | C24: 10000 | D24: 10000 | E24: 10000 | F24: 10000 | G24: 10000 | H24: 10000 | I24: 10000 | J24: 10000 | K24: 10000 | L24: 10000 | M24: 10000 | N24: 10000 | O24: =IF(COLUMN()-2<=Controls!$B$7,C24*(1+$C$23),0) -> 11500 | P24: =IF(COLUMN()-2<=Controls!$B$7,D24*(1+$C$23),0) -> 11500 | Q24: =IF(COLUMN()-2<=Controls!$B$7,E24*(1+$C$23),0) -> 11500 | R24: =IF(COLUMN()-2<=Controls!$B$7,F24*(1+$C$23),0) -> 11500 | S24: =IF(COLUMN()-2<=Controls!$B$7,G24*(1+$C$23),0) -> 11500 | T24: =IF(COLUMN()-2<=Controls!$B$7,H24*(1+$C$23),0) -> 11500 | U24: =IF(COLUMN()-2<=Controls!$B$7,I24*(1+$C$23),0) -> 11500 | V24: =IF(COLUMN()-2<=Controls!$B$7,J24*(1+$C$23),0) -> 11500 | ... BJ24: =IF(COLUMN()-2<=Controls!$B$7,AX24*(1+$C$23),0) -> 0 | BK24: =SUMPRODUCT((YEAR(EDATE(Controls!$B$6,COLUMN($C$1:$BJ$1)-COLUMN($C$1)))=YEAR(Controls!$B$6)+0)*(COLUMN($C$1:$BJ$1)-COLUMN($C$1)<Controls!$B$7)*$C$24:$BJ$24) -> 120000 | BL24: =SUMPRODUCT((YEAR(EDATE(Controls!$B$6,COLUMN($C$1:$BJ$1)-COLUMN($C$1)))=YEAR(Controls!$B$6)+1)*(COLUMN($C$1:$BJ$1)-COLUMN($C$1)<Controls!$B$7)*$C$24:$BJ$24) -> 138000 | BM24: =SUMPRODUCT((YEAR(EDATE(Controls!$B$6,COLUMN($C$1:$BJ$1)-COLUMN($C$1)))=YEAR(Controls!$B$6)+2)*(COLUMN($C$1:$BJ$1)-COLUMN($C$1)<Controls!$B$7)*$C$24:$BJ$24) -> 158700 | BN24: =SUMPRODUCT((YEAR(EDATE(Controls!$B$6,COLUMN($C$1:$BJ$1)-COLUMN($C$1)))=YEAR(Controls!$B$6)+3)*(COLUMN($C$1:$BJ$1)-COLUMN($C$1)<Controls!$B$7)*$C$24:$BJ$24) -> 0 | BO24: =SUMPRODUCT((YEAR(EDATE(Controls!$B$6,COLUMN($C$1:$BJ$1)-COLUMN($C$1)))=YEAR(Controls!$B$6)+4)*(COLUMN($C$1:$BJ$1)-COLUMN($C$1)<Controls!$B$7)*$C$24:$BJ$24) -> 0 | BP24: =SUMPRODUCT((YEAR(EDATE(Controls!$B$6,COLUMN($C$1:$BJ$1)-COLUMN($C$1)))=YEAR(Controls!$B$6)+5)*(COLUMN($C$1:$BJ$1)-COLUMN($C$1)<Controls!$B$7)*$C$24:$BJ$24) -> 0
A25: Total Loaded Cost – G&A (incl. benefits & taxes) | B25: $/mo | C25: =C24*(1+Controls!$B$25+Controls!$B$24) -> 12565 | D25: =D24*(1+Controls!$B$25+Controls!$B$24) -> 12565 | E25: =E24*(1+Controls!$B$25+Controls!$B$24) -> 12565 | F25: =F24*(1+Controls!$B$25+Controls!$B$24) -> 12565 | G25: =G24*(1+Controls!$B$25+Controls!$B$24) -> 12565 | H25: =H24*(1+Controls!$B$25+Controls!$B$24) -> 12565 | I25: =I24*(1+Controls!$B$25+Controls!$B$24) -> 12565 | J25: =J24*(1+Controls!$B$25+Controls!$B$24) -> 12565 | ... BJ25: =BJ24*(1+Controls!$B$25+Controls!$B$24) -> 0 | BK25: =SUMPRODUCT((YEAR(EDATE(Controls!$B$6,COLUMN($C$1:$BJ$1)-COLUMN($C$1)))=YEAR(Controls!$B$6)+0)*(COLUMN($C$1:$BJ$1)-COLUMN($C$1)<Controls!$B$7)*$C$25:$BJ$25) -> 150780 | BL25: =SUMPRODUCT((YEAR(EDATE(Controls!$B$6,COLUMN($C$1:$BJ$1)-COLUMN($C$1)))=YEAR(Controls!$B$6)+1)*(COLUMN($C$1:$BJ$1)-COLUMN($C$1)<Controls!$B$7)*$C$25:$BJ$25) -> 173397 | BM25: =SUMPRODUCT((YEAR(EDATE(Controls!$B$6,COLUMN($C$1:$BJ$1)-COLUMN($C$1)))=YEAR(Controls!$B$6)+2)*(COLUMN($C$1:$BJ$1)-COLUMN($C$1)<Controls!$B$7)*$C$25:$BJ$25) -> 199406.55 | BN25: =SUMPRODUCT((YEAR(EDATE(Controls!$B$6,COLUMN($C$1:$BJ$1)-COLUMN($C$1)))=YEAR(Controls!$B$6)+3)*(COLUMN($C$1:$BJ$1)-COLUMN($C$1)<Controls!$B$7)*$C$25:$BJ$25) -> 0 | BO25: =SUMPRODUCT((YEAR(EDATE(Controls!$B$6,COLUMN($C$1:$BJ$1)-COLUMN($C$1)))=YEAR(Controls!$B$6)+4)*(COLUMN($C$1:$BJ$1)-COLUMN($C$1)<Controls!$B$7)*$C$25:$BJ$25) -> 0 | BP25: =SUMPRODUCT((YEAR(EDATE(Controls!$B$6,COLUMN($C$1:$BJ$1)-COLUMN($C$1)))=YEAR(Controls!$B$6)+5)*(COLUMN($C$1:$BJ$1)-COLUMN($C$1)<Controls!$B$7)*$C$25:$BJ$25) -> 0
A27: TOTAL LOADED WAGES (All Departments) | B27: $/mo | C27: =C10+C15+C20+C25 -> 66594.5 | D27: =D10+D15+D20+D25 -> 66594.5 | E27: =E10+E15+E20+E25 -> 66594.5 | F27: =F10+F15+F20+F25 -> 66594.5 | G27: =G10+G15+G20+G25 -> 66594.5 | H27: =H10+H15+H20+H25 -> 66594.5 | I27: =I10+I15+I20+I25 -> 66594.5 | J27: =J10+J15+J20+J25 -> 66594.5 | ... BJ27: =BJ10+BJ15+BJ20+BJ25 -> 0 | BK27: =SUMPRODUCT((YEAR(EDATE(Controls!$B$6,COLUMN($C$1:$BJ$1)-COLUMN($C$1)))=YEAR(Controls!$B$6)+0)*(COLUMN($C$1:$BJ$1)-COLUMN($C$1)<Controls!$B$7)*$C$27:$BJ$27) -> 799134 | BL27: =SUMPRODUCT((YEAR(EDATE(Controls!$B$6,COLUMN($C$1:$BJ$1)-COLUMN($C$1)))=YEAR(Controls!$B$6)+1)*(COLUMN($C$1:$BJ$1)-COLUMN($C$1)<Controls!$B$7)*$C$27:$BJ$27) -> 989116.8 | BM27: =SUMPRODUCT((YEAR(EDATE(Controls!$B$6,COLUMN($C$1:$BJ$1)-COLUMN($C$1)))=YEAR(Controls!$B$6)+2)*(COLUMN($C$1:$BJ$1)-COLUMN($C$1)<Controls!$B$7)*$C$27:$BJ$27) -> 1226519.9 | BN27: =SUMPRODUCT((YEAR(EDATE(Controls!$B$6,COLUMN($C$1:$BJ$1)-COLUMN($C$1)))=YEAR(Controls!$B$6)+3)*(COLUMN($C$1:$BJ$1)-COLUMN($C$1)<Controls!$B$7)*$C$27:$BJ$27) -> 0 | BO27: =SUMPRODUCT((YEAR(EDATE(Controls!$B$6,COLUMN($C$1:$BJ$1)-COLUMN($C$1)))=YEAR(Controls!$B$6)+4)*(COLUMN($C$1:$BJ$1)-COLUMN($C$1)<Controls!$B$7)*$C$27:$BJ$27) -> 0 | BP27: =SUMPRODUCT((YEAR(EDATE(Controls!$B$6,COLUMN($C$1:$BJ$1)-COLUMN($C$1)))=YEAR(Controls!$B$6)+5)*(COLUMN($C$1:$BJ$1)-COLUMN($C$1)<Controls!$B$7)*$C$27:$BJ$27) -> 0

Sheet OpEx
A1: NON-WAGE OPERATING EXPENSES · By Department
A3: Label | B3: Unit | C3: =TEXT(EDATE(Controls!$B$6,0),"mmm-yy") -> Jan-26 | D3: =TEXT(EDATE(Controls!$B$6,1),"mmm-yy") -> Feb-26 | E3: =TEXT(EDATE(Controls!$B$6,2),"mmm-yy") -> Mar-26 | F3: =TEXT(EDATE(Controls!$B$6,3),"mmm-yy") -> Apr-26 | G3: =TEXT(EDATE(Controls!$B$6,4),"mmm-yy") -> May-26 | H3: =TEXT(EDATE(Controls!$B$6,5),"mmm-yy") -> Jun-26 | I3: =TEXT(EDATE(Controls!$B$6,6),"mmm-yy") -> Jul-26 | J3: =TEXT(EDATE(Controls!$B$6,7),"mmm-yy") -> Aug-26 | K3: =TEXT(EDATE(Controls!$B$6,8),"mmm-yy") -> Sep-26 | L3: =TEXT(EDATE(Controls!$B$6,9),"mmm-yy") -> Oct-26 | M3: =TEXT(EDATE(Controls!$B$6,10),"mmm-yy") -> Nov-26 | N3: =TEXT(EDATE(Controls!$B$6,11),"mmm-yy") -> Dec-26 | O3: =TEXT(EDATE(Controls!$B$6,12),"mmm-yy") -> Jan-27 | P3: =TEXT(EDATE(Controls!$B$6,13),"mmm-yy") -> Feb-27 | Q3: =TEXT(EDATE(Controls!$B$6,14),"mmm-yy") -> Mar-27 | R3: =TEXT(EDATE(Controls!$B$6,15),"mmm-yy") -> Apr-27 | S3: =TEXT(EDATE(Controls!$B$6,16),"mmm-yy") -> May-27 | T3: =TEXT(EDATE(Controls!$B$6,17),"mmm-yy") -> Jun-27 | U3: =TEXT(EDATE(Controls!$B$6,18),"mmm-yy") -> Jul-27 | V3: =TEXT(EDATE(Controls!$B$6,19),"mmm-yy") -> Aug-27 | W3: =TEXT(EDATE(Controls!$B$6,20),"mmm-yy") -> Sep-27 | X3: =TEXT(EDATE(Controls!$B$6,21),"mmm-yy") -> Oct-27 | Y3: =TEXT(EDATE(Controls!$B$6,22),"mmm-yy") -> Nov-27 | Z3: =TEXT(EDATE(Controls!$B$6,23),"mmm-yy") -> Dec-27 | AA3: =TEXT(EDATE(Controls!$B$6,24),"mmm-yy") -> Jan-28 | AB3: =TEXT(EDATE(Controls!$B$6,25),"mmm-yy") -> Feb-28 | AC3: =TEXT(EDATE(Controls!$B$6,26),"mmm-yy") -> Mar-28 | AD3: =TEXT(EDATE(Controls!$B$6,27),"mmm-yy") -> Apr-28 | AE3: =TEXT(EDATE(Controls!$B$6,28),"mmm-yy") -> May-28 | AF3: =TEXT(EDATE(Controls!$B$6,29),"mmm-yy") -> Jun-28 | AG3: =TEXT(EDATE(Controls!$B$6,30),"mmm-yy") -> Jul-28 | AH3: =TEXT(EDATE(Controls!$B$6,31),"mmm-yy") -> Aug-28 | AI3: =TEXT(EDATE(Controls!$B$6,32),"mmm-yy") -> Sep-28 | AJ3: =TEXT(EDATE(Controls!$B$6,33),"mmm-yy") -> Oct-28 | AK3: =TEXT(EDATE(Controls!$B$6,34),"mmm-yy") -> Nov-28 | AL3: =TEXT(EDATE(Controls!$B$6,35),"mmm-yy") -> Dec-28 | AM3: =TEXT(EDATE(Controls!$B$6,36),"mmm-yy") -> Jan-29 | AN3: =TEXT(EDATE(Controls!$B$6,37),"mmm-yy") -> Feb-29 | AO3: =TEXT(EDATE(Controls!$B$6,38),"mmm-yy") -> Mar-29 | AP3: =TEXT(EDATE(Controls!$B$6,39),"mmm-yy") -> Apr-29 | AQ3: =TEXT(EDATE(Controls!$B$6,40),"mmm-yy") -> May-29 | AR3: =TEXT(EDATE(Controls!$B$6,41),"mmm-yy") -> Jun-29 | AS3: =TEXT(EDATE(Controls!$B$6,42),"mmm-yy") -> Jul-29 | AT3: =TEXT(EDATE(Controls!$B$6,43),"mmm-yy") -> Aug-29 | AU3: =TEXT(EDATE(Controls!$B$6,44),"mmm-yy") -> Sep-29 | AV3: =TEXT(EDATE(Controls!$B$6,45),"mmm-yy") -> Oct-29 | AW3: =TEXT(EDATE(Controls!$B$6,46),"mmm-yy") -> Nov-29 | AX3: =TEXT(EDATE(Controls!$B$6,47),"mmm-yy") -> Dec-29 | AY3: =TEXT(EDATE(Controls!$B$6,48),"mmm-yy") -> Jan-30 | AZ3: =TEXT(EDATE(Controls!$B$6,49),"mmm-yy") -> Feb-30 | BA3: =TEXT(EDATE(Controls!$B$6,50),"mmm-yy") -> Mar-30 | BB3: =TEXT(EDATE(Controls!$B$6,51),"mmm-yy") -> Apr-30 | BC3: =TEXT(EDATE(Controls!$B$6,52),"mmm-yy") -> May-30 | BD3: =TEXT(EDATE(Controls!$B$6,53),"mmm-yy") -> Jun-30 | BE3: =TEXT(EDATE(Controls!$B$6,54),"mmm-yy") -> Jul-30 | BF3: =TEXT(EDATE(Controls!$B$6,55),"mmm-yy") -> Aug-30 | BG3: =TEXT(EDATE(Controls!$B$6,56),"mmm-yy") -> Sep-30 | BH3: =TEXT(EDATE(Controls!$B$6,57),"mmm-yy") -> Oct-30 | BI3: =TEXT(EDATE(Controls!$B$6,58),"mmm-yy") -> Nov-30 | BJ3: =TEXT(EDATE(Controls!$B$6,59),"mmm-yy") -> Dec-30 | BK3: ="FY "&(YEAR(Controls!$B$6)+0) -> FY 2026 | BL3: ="FY "&(YEAR(Controls!$B$6)+1) -> FY 2027 | BM3: ="FY "&(YEAR(Controls!$B$6)+2) -> FY 2028 | BN3: ="FY "&(YEAR(Controls!$B$6)+3) -> FY 2029 | BO3: ="FY "&(YEAR(Controls!$B$6)+4) -> FY 2030 | BP3: ="FY "&(YEAR(Controls!$B$6)+5) -> FY 2031
A5: NON-WAGE OPEX · Enter Year 1 monthly amounts — Years 2 & 3 auto-grow by dept YoY rate
A6: COGS – Non-Wage
A7: YoY Growth Rate – COGS – Non-Wage | B7: %/yr | C7: 0.2 | D7: ↑ Applies to months 13–36 (rolling 12-mo from model start, not calendar year)
A8: Cloud Hosting & Infrastructure | B8: $/mo | C8: 3000 | D8: 3000 | E8: 3000 | F8: 3000 | G8: 3000 | H8: 3000 | I8: 3000 | J8: 3000 | K8: 3000 | L8: 3000 | M8: 3000 | N8: 3000 | O8: =IF(COLUMN()-2<=Controls!$B$7,C8*(1+$C$7),0) -> 3600 | P8: =IF(COLUMN()-2<=Controls!$B$7,D8*(1+$C$7),0) -> 3600 | Q8: =IF(COLUMN()-2<=Controls!$B$7,E8*(1+$C$7),0) -> 3600 | R8: =IF(COLUMN()-2<=Controls!$B$7,F8*(1+$C$7),0) -> 3600 | S8: =IF(COLUMN()-2<=Controls!$B$7,G8*(1+$C$7),0) -> 3600 | T8: =IF(COLUMN()-2<=Controls!$B$7,H8*(1+$C$7),0) -> 3600 | U8: =IF(COLUMN()-2<=Controls!$B$7,I8*(1+$C$7),0) -> 3600 | V8: =IF(COLUMN()-2<=Controls!$B$7,J8*(1+$C$7),0) -> 3600 | ... BJ8: =IF(COLUMN()-2<=Controls!$B$7,AX8*(1+$C$7),0) -> 0 | BK8: =SUMPRODUCT((YEAR(EDATE(Controls!$B$6,COLUMN($C$1:$BJ$1)-COLUMN($C$1)))=YEAR(Controls!$B$6)+0)*(COLUMN($C$1:$BJ$1)-COLUMN($C$1)<Controls!$B$7)*$C$8:$BJ$8) -> 36000 | BL8: =SUMPRODUCT((YEAR(EDATE(Controls!$B$6,COLUMN($C$1:$BJ$1)-COLUMN($C$1)))=YEAR(Controls!$B$6)+1)*(COLUMN($C$1:$BJ$1)-COLUMN($C$1)<Controls!$B$7)*$C$8:$BJ$8) -> 43200 | BM8: =SUMPRODUCT((YEAR(EDATE(Controls!$B$6,COLUMN($C$1:$BJ$1)-COLUMN($C$1)))=YEAR(Controls!$B$6)+2)*(COLUMN($C$1:$BJ$1)-COLUMN($C$1)<Controls!$B$7)*$C$8:$BJ$8) -> 51840 | BN8: =SUMPRODUCT((YEAR(EDATE(Controls!$B$6,COLUMN($C$1:$BJ$1)-COLUMN($C$1)))=YEAR(Controls!$B$6)+3)*(COLUMN($C$1:$BJ$1)-COLUMN($C$1)<Controls!$B$7)*$C$8:$BJ$8) -> 0 | BO8: =SUMPRODUCT((YEAR(EDATE(Controls!$B$6,COLUMN($C$1:$BJ$1)-COLUMN($C$1)))=YEAR(Controls!$B$6)+4)*(COLUMN($C$1:$BJ$1)-COLUMN($C$1)<Controls!$B$7)*$C$8:$BJ$8) -> 0 | BP8: =SUMPRODUCT((YEAR(EDATE(Controls!$B$6,COLUMN($C$1:$BJ$1)-COLUMN($C$1)))=YEAR(Controls!$B$6)+5)*(COLUMN($C$1:$BJ$1)-COLUMN($C$1)<Controls!$B$7)*$C$8:$BJ$8) -> 0
A9: Other COGS (Support Tools, Ops) | B9: $/mo | C9: 1000 | D9: 1000 | E9: 1000 | F9: 1000 | G9: 1000 | H9: 1000 | I9: 1000 | J9: 1000 | K9: 1000 | L9: 1000 | M9: 1000 | N9: 1000 | O9: =IF(COLUMN()-2<=Controls!$B$7,C9*(1+$C$7),0) -> 1200 | P9: =IF(COLUMN()-2<=Controls!$B$7,D9*(1+$C$7),0) -> 1200 | Q9: =IF(COLUMN()-2<=Controls!$B$7,E9*(1+$C$7),0) -> 1200 | R9: =IF(COLUMN()-2<=Controls!$B$7,F9*(1+$C$7),0) -> 1200 | S9: =IF(COLUMN()-2<=Controls!$B$7,G9*(1+$C$7),0) -> 1200 | T9: =IF(COLUMN()-2<=Controls!$B$7,H9*(1+$C$7),0) -> 1200 | U9: =IF(COLUMN()-2<=Controls!$B$7,I9*(1+$C$7),0) -> 1200 | V9: =IF(COLUMN()-2<=Controls!$B$7,J9*(1+$C$7),0) -> 1200 | ... BJ9: =IF(COLUMN()-2<=Controls!$B$7,AX9*(1+$C$7),0) -> 0 | BK9: =SUMPRODUCT((YEAR(EDATE(Controls!$B$6,COLUMN($C$1:$BJ$1)-COLUMN($C$1)))=YEAR(Controls!$B$6)+0)*(COLUMN($C$1:$BJ$1)-COLUMN($C$1)<Controls!$B$7)*$C$9:$BJ$9) -> 12000 | BL9: =SUMPRODUCT((YEAR(EDATE(Controls!$B$6,COLUMN($C$1:$BJ$1)-COLUMN($C$1)))=YEAR(Controls!$B$6)+1)*(COLUMN($C$1:$BJ$1)-COLUMN($C$1)<Controls!$B$7)*$C$9:$BJ$9) -> 14400 | BM9: =SUMPRODUCT((YEAR(EDATE(Controls!$B$6,COLUMN($C$1:$BJ$1)-COLUMN($C$1)))=YEAR(Controls!$B$6)+2)*(COLUMN($C$1:$BJ$1)-COLUMN($C$1)<Controls!$B$7)*$C$9:$BJ$9) -> 17280 | BN9: =SUMPRODUCT((YEAR(EDATE(Controls!$B$6,COLUMN($C$1:$BJ$1)-COLUMN($C$1)))=YEAR(Controls!$B$6)+3)*(COLUMN($C$1:$BJ$1)-COLUMN($C$1)<Controls!$B$7)*$C$9:$BJ$9) -> 0 | BO9: =SUMPRODUCT((YEAR(EDATE(Controls!$B$6,COLUMN($C$1:$BJ$1)-COLUMN($C$1)))=YEAR(Controls!$B$6)+4)*(COLUMN($C$1:$BJ$1)-COLUMN($C$1)<Controls!$B$7)*$C$9:$BJ$9) -> 0 | BP9: =SUMPRODUCT((YEAR(EDATE(Controls!$B$6,COLUMN($C$1:$BJ$1)-COLUMN($C$1)))=YEAR(Controls!$B$6)+5)*(COLUMN($C$1:$BJ$1)-COLUMN($C$1)<Controls!$B$7)*$C$9:$BJ$9) -> 0
A10: S&M – Non-Wage
A11: YoY Growth Rate – S&M – Non-Wage | B11: %/yr | C11: 0.35 | D11: ↑ Applies to months 13–36 (rolling 12-mo from model start, not calendar year)
A12: Digital Marketing & Advertising | B12: $/mo | C12: 8000 | D12: 8000 | E12: 8000 | F12: 8000 | G12: 8000 | H12: 8000 | I12: 8000 | J12: 8000 | K12: 8000 | L12: 8000 | M12: 8000 | N12: 8000 | O12: =IF(COLUMN()-2<=Controls!$B$7,C12*(1+$C$11),0) -> 10800 | P12: =IF(COLUMN()-2<=Controls!$B$7,D12*(1+$C$11),0) -> 10800 | Q12: =IF(COLUMN()-2<=Controls!$B$7,E12*(1+$C$11),0) -> 10800 | R12: =IF(COLUMN()-2<=Controls!$B$7,F12*(1+$C$11),0) -> 10800 | S12: =IF(COLUMN()-2<=Controls!$B$7,G12*(1+$C$11),0) -> 10800 | T12: =IF(COLUMN()-2<=Controls!$B$7,H12*(1+$C$11),0) -> 10800 | U12: =IF(COLUMN()-2<=Controls!$B$7,I12*(1+$C$11),0) -> 10800 | V12: =IF(COLUMN()-2<=Controls!$B$7,J12*(1+$C$11),0) -> 10800 | ... BJ12: =IF(COLUMN()-2<=Controls!$B$7,AX12*(1+$C$11),0) -> 0 | BK12: =SUMPRODUCT((YEAR(EDATE(Controls!$B$6,COLUMN($C$1:$BJ$1)-COLUMN($C$1)))=YEAR(Controls!$B$6)+0)*(COLUMN($C$1:$BJ$1)-COLUMN($C$1)<Controls!$B$7)*$C$12:$BJ$12) -> 96000 | BL12: =SUMPRODUCT((YEAR(EDATE(Controls!$B$6,COLUMN($C$1:$BJ$1)-COLUMN($C$1)))=YEAR(Controls!$B$6)+1)*(COLUMN($C$1:$BJ$1)-COLUMN($C$1)<Controls!$B$7)*$C$12:$BJ$12) -> 129600 | BM12: =SUMPRODUCT((YEAR(EDATE(Controls!$B$6,COLUMN($C$1:$BJ$1)-COLUMN($C$1)))=YEAR(Controls!$B$6)+2)*(COLUMN($C$1:$BJ$1)-COLUMN($C$1)<Controls!$B$7)*$C$12:$BJ$12) -> 174960 | BN12: =SUMPRODUCT((YEAR(EDATE(Controls!$B$6,COLUMN($C$1:$BJ$1)-COLUMN($C$1)))=YEAR(Controls!$B$6)+3)*(COLUMN($C$1:$BJ$1)-COLUMN($C$1)<Controls!$B$7)*$C$12:$BJ$12) -> 0 | BO12: =SUMPRODUCT((YEAR(EDATE(Controls!$B$6,COLUMN($C$1:$BJ$1)-COLUMN($C$1)))=YEAR(Controls!$B$6)+4)*(COLUMN($C$1:$BJ$1)-COLUMN($C$1)<Controls!$B$7)*$C$12:$BJ$12) -> 0 | BP12: =SUMPRODUCT((YEAR(EDATE(Controls!$B$6,COLUMN($C$1:$BJ$1)-COLUMN($C$1)))=YEAR(Controls!$B$6)+5)*(COLUMN($C$1:$BJ$1)-COLUMN($C$1)<Controls!$B$7)*$C$12:$BJ$12) -> 0
A13: Sales Tools (CRM, Outreach) | B13: $/mo | C13: 1500 | D13: 1500 | E13: 1500 | F13: 1500 | G13: 1500 | H13: 1500 | I13: 1500 | J13: 1500 | K13: 1500 | L13: 1500 | M13: 1500 | N13: 1500 | O13: =IF(COLUMN()-2<=Controls!$B$7,C13*(1+$C$11),0) -> 2025 | P13: =IF(COLUMN()-2<=Controls!$B$7,D13*(1+$C$11),0) -> 2025 | Q13: =IF(COLUMN()-2<=Controls!$B$7,E13*(1+$C$11),0) -> 2025 | R13: =IF(COLUMN()-2<=Controls!$B$7,F13*(1+$C$11),0) -> 2025 | S13: =IF(COLUMN()-2<=Controls!$B$7,G13*(1+$C$11),0) -> 2025 | T13: =IF(COLUMN()-2<=Controls!$B$7,H13*(1+$C$11),0) -> 2025 | U13: =IF(COLUMN()-2<=Controls!$B$7,I13*(1+$C$11),0) -> 2025 | V13: =IF(COLUMN()-2<=Controls!$B$7,J13*(1+$C$11),0) -> 2025 | ... BJ13: =IF(COLUMN()-2<=Controls!$B$7,AX13*(1+$C$11),0) -> 0 | BK13: =SUMPRODUCT((YEAR(EDATE(Controls!$B$6,COLUMN($C$1:$BJ$1)-COLUMN($C$1)))=YEAR(Controls!$B$6)+0)*(COLUMN($C$1:$BJ$1)-COLUMN($C$1)<Controls!$B$7)*$C$13:$BJ$13) -> 18000 | BL13: =SUMPRODUCT((YEAR(EDATE(Controls!$B$6,COLUMN($C$1:$BJ$1)-COLUMN($C$1)))=YEAR(Controls!$B$6)+1)*(COLUMN($C$1:$BJ$1)-COLUMN($C$1)<Controls!$B$7)*$C$13:$BJ$13) -> 24300 | BM13: =SUMPRODUCT((YEAR(EDATE(Controls!$B$6,COLUMN($C$1:$BJ$1)-COLUMN($C$1)))=YEAR(Controls!$B$6)+2)*(COLUMN($C$1:$BJ$1)-COLUMN($C$1)<Controls!$B$7)*$C$13:$BJ$13) -> 32805 | BN13: =SUMPRODUCT((YEAR(EDATE(Controls!$B$6,COLUMN($C$1:$BJ$1)-COLUMN($C$1)))=YEAR(Controls!$B$6)+3)*(COLUMN($C$1:$BJ$1)-COLUMN($C$1)<Controls!$B$7)*$C$13:$BJ$13) -> 0 | BO13: =SUMPRODUCT((YEAR(EDATE(Controls!$B$6,COLUMN($C$1:$BJ$1)-COLUMN($C$1)))=YEAR(Controls!$B$6)+4)*(COLUMN($C$1:$BJ$1)-COLUMN($C$1)<Controls!$B$7)*$C$13:$BJ$13) -> 0 | BP13: =SUMPRODUCT((YEAR(EDATE(Controls!$B$6,COLUMN($C$1:$BJ$1)-COLUMN($C$1)))=YEAR(Controls!$B$6)+5)*(COLUMN($C$1:$BJ$1)-COLUMN($C$1)<Controls!$B$7)*$C$13:$BJ$13) -> 0
A14: Other S&M (Events, Content) | B14: $/mo | C14: 2000 | D14: 2000 | E14: 2000 | F14: 2000 | G14: 2000 | H14: 2000 | I14: 2000 | J14: 2000 | K14: 2000 | L14: 2000 | M14: 2000 | N14: 2000 | O14: =IF(COLUMN()-2<=Controls!$B$7,C14*(1+$C$11),0) -> 2700 | P14: =IF(COLUMN()-2<=Controls!$B$7,D14*(1+$C$11),0) -> 2700 | Q14: =IF(COLUMN()-2<=Controls!$B$7,E14*(1+$C$11),0) -> 2700 | R14: =IF(COLUMN()-2<=Controls!$B$7,F14*(1+$C$11),0) -> 2700 | S14: =IF(COLUMN()-2<=Controls!$B$7,G14*(1+$C$11),0) -> 2700 | T14: =IF(COLUMN()-2<=Controls!$B$7,H14*(1+$C$11),0) -> 2700 | U14: =IF(COLUMN()-2<=Controls!$B$7,I14*(1+$C$11),0) -> 2700 | V14: =IF(COLUMN()-2<=Controls!$B$7,J14*(1+$C$11),0) -> 2700 | ... BJ14: =IF(COLUMN()-2<=Controls!$B$7,AX14*(1+$C$11),0) -> 0 | BK14: =SUMPRODUCT((YEAR(EDATE(Controls!$B$6,COLUMN($C$1:$BJ$1)-COLUMN($C$1)))=YEAR(Controls!$B$6)+0)*(COLUMN($C$1:$BJ$1)-COLUMN($C$1)<Controls!$B$7)*$C$14:$BJ$14) -> 24000 | BL14: =SUMPRODUCT((YEAR(EDATE(Controls!$B$6,COLUMN($C$1:$BJ$1)-COLUMN($C$1)))=YEAR(Controls!$B$6)+1)*(COLUMN($C$1:$BJ$1)-COLUMN($C$1)<Controls!$B$7)*$C$14:$BJ$14) -> 32400 | BM14: =SUMPRODUCT((YEAR(EDATE(Controls!$B$6,COLUMN($C$1:$BJ$1)-COLUMN($C$1)))=YEAR(Controls!$B$6)+2)*(COLUMN($C$1:$BJ$1)-COLUMN($C$1)<Controls!$B$7)*$C$14:$BJ$14) -> 43740 | BN14: =SUMPRODUCT((YEAR(EDATE(Controls!$B$6,COLUMN($C$1:$BJ$1)-COLUMN($C$1)))=YEAR(Controls!$B$6)+3)*(COLUMN($C$1:$BJ$1)-COLUMN($C$1)<Controls!$B$7)*$C$14:$BJ$14) -> 0 | BO14: =SUMPRODUCT((YEAR(EDATE(Controls!$B$6,COLUMN($C$1:$BJ$1)-COLUMN($C$1)))=YEAR(Controls!$B$6)+4)*(COLUMN($C$1:$BJ$1)-COLUMN($C$1)<Controls!$B$7)*$C$14:$BJ$14) -> 0 | BP14: =SUMPRODUCT((YEAR(EDATE(Controls!$B$6,COLUMN($C$1:$BJ$1)-COLUMN($C$1)))=YEAR(Controls!$B$6)+5)*(COLUMN($C$1:$BJ$1)-COLUMN($C$1)<Controls!$B$7)*$C$14:$BJ$14) -> 0
A15: R&D – Non-Wage
A16: YoY Growth Rate – R&D – Non-Wage | B16: %/yr | C16: 0.25 | D16: ↑ Applies to months 13–36 (rolling 12-mo from model start, not calendar year)
A17: Cloud Compute & Dev Infra | B17: $/mo | C17: 2000 | D17: 2000 | E17: 2000 | F17: 2000 | G17: 2000 | H17: 2000 | I17: 2000 | J17: 2000 | K17: 2000 | L17: 2000 | M17: 2000 | N17: 2000 | O17: =IF(COLUMN()-2<=Controls!$B$7,C17*(1+$C$16),0) -> 2500 | P17: =IF(COLUMN()-2<=Controls!$B$7,D17*(1+$C$16),0) -> 2500 | Q17: =IF(COLUMN()-2<=Controls!$B$7,E17*(1+$C$16),0) -> 2500 | R17: =IF(COLUMN()-2<=Controls!$B$7,F17*(1+$C$16),0) -> 2500 | S17: =IF(COLUMN()-2<=Controls!$B$7,G17*(1+$C$16),0) -> 2500 | T17: =IF(COLUMN()-2<=Controls!$B$7,H17*(1+$C$16),0) -> 2500 | U17: =IF(COLUMN()-2<=Controls!$B$7,I17*(1+$C$16),0) -> 2500 | V17: =IF(COLUMN()-2<=Controls!$B$7,J17*(1+$C$16),0) -> 2500 | ... BJ17: =IF(COLUMN()-2<=Controls!$B$7,AX17*(1+$C$16),0) -> 0 | BK17: =SUMPRODUCT((YEAR(EDATE(Controls!$B$6,COLUMN($C$1:$BJ$1)-COLUMN($C$1)))=YEAR(Controls!$B$6)+0)*(COLUMN($C$1:$BJ$1)-COLUMN($C$1)<Controls!$B$7)*$C$17:$BJ$17) -> 24000 | BL17: =SUMPRODUCT((YEAR(EDATE(Controls!$B$6,COLUMN($C$1:$BJ$1)-COLUMN($C$1)))=YEAR(Controls!$B$6)+1)*(COLUMN($C$1:$BJ$1)-COLUMN($C$1)<Controls!$B$7)*$C$17:$BJ$17) -> 30000 | BM17: =SUMPRODUCT((YEAR(EDATE(Controls!$B$6,COLUMN($C$1:$BJ$1)-COLUMN($C$1)))=YEAR(Controls!$B$6)+2)*(COLUMN($C$1:$BJ$1)-COLUMN($C$1)<Controls!$B$7)*$C$17:$BJ$17) -> 37500 | BN17: =SUMPRODUCT((YEAR(EDATE(Controls!$B$6,COLUMN($C$1:$BJ$1)-COLUMN($C$1)))=YEAR(Controls!$B$6)+3)*(COLUMN($C$1:$BJ$1)-COLUMN($C$1)<Controls!$B$7)*$C$17:$BJ$17) -> 0 | BO17: =SUMPRODUCT((YEAR(EDATE(Controls!$B$6,COLUMN($C$1:$BJ$1)-COLUMN($C$1)))=YEAR(Controls!$B$6)+4)*(COLUMN($C$1:$BJ$1)-COLUMN($C$1)<Controls!$B$7)*$C$17:$BJ$17) -> 0 | BP17: =SUMPRODUCT((YEAR(EDATE(Controls!$B$6,COLUMN($C$1:$BJ$1)-COLUMN($C$1)))=YEAR(Controls!$B$6)+5)*(COLUMN($C$1:$BJ$1)-COLUMN($C$1)<Controls!$B$7)*$C$17:$BJ$17) -> 0
A18: Dev Tools & Licenses | B18: $/mo | C18: 1000 | D18: 1000 | E18: 1000 | F18: 1000 | G18: 1000 | H18: 1000 | I18: 1000 | J18: 1000 | K18: 1000 | L18: 1000 | M18: 1000 | N18: 1000 | O18: =IF(COLUMN()-2<=Controls!$B$7,C18*(1+$C$16),0) -> 1250 | P18: =IF(COLUMN()-2<=Controls!$B$7,D18*(1+$C$16),0) -> 1250 | Q18: =IF(COLUMN()-2<=Controls!$B$7,E18*(1+$C$16),0) -> 1250 | R18: =IF(COLUMN()-2<=Controls!$B$7,F18*(1+$C$16),0) -> 1250 | S18: =IF(COLUMN()-2<=Controls!$B$7,G18*(1+$C$16),0) -> 1250 | T18: =IF(COLUMN()-2<=Controls!$B$7,H18*(1+$C$16),0) -> 1250 | U18: =IF(COLUMN()-2<=Controls!$B$7,I18*(1+$C$16),0) -> 1250 | V18: =IF(COLUMN()-2<=Controls!$B$7,J18*(1+$C$16),0) -> 1250 | ... BJ18: =IF(COLUMN()-2<=Controls!$B$7,AX18*(1+$C$16),0) -> 0 | BK18: =SUMPRODUCT((YEAR(EDATE(Controls!$B$6,COLUMN($C$1:$BJ$1)-COLUMN($C$1)))=YEAR(Controls!$B$6)+0)*(COLUMN($C$1:$BJ$1)-COLUMN($C$1)<Controls!$B$7)*$C$18:$BJ$18) -> 12000 | BL18: =SUMPRODUCT((YEAR(EDATE(Controls!$B$6,COLUMN($C$1:$BJ$1)-COLUMN($C$1)))=YEAR(Controls!$B$6)+1)*(COLUMN($C$1:$BJ$1)-COLUMN($C$1)<Controls!$B$7)*$C$18:$BJ$18) -> 15000 | BM18: =SUMPRODUCT((YEAR(EDATE(Controls!$B$6,COLUMN($C$1:$BJ$1)-COLUMN($C$1)))=YEAR(Controls!$B$6)+2)*(COLUMN($C$1:$BJ$1)-COLUMN($C$1)<Controls!$B$7)*$C$18:$BJ$18) -> 18750 | BN18: =SUMPRODUCT((YEAR(EDATE(Controls!$B$6,COLUMN($C$1:$BJ$1)-COLUMN($C$1)))=YEAR(Controls!$B$6)+3)*(COLUMN($C$1:$BJ$1)-COLUMN($C$1)<Controls!$B$7)*$C$18:$BJ$18) -> 0 | BO18: =SUMPRODUCT((YEAR(EDATE(Controls!$B$6,COLUMN($C$1:$BJ$1)-COLUMN($C$1)))=YEAR(Controls!$B$6)+4)*(COLUMN($C$1:$BJ$1)-COLUMN($C$1)<Controls!$B$7)*$C$18:$BJ$18) -> 0 | BP18: =SUMPRODUCT((YEAR(EDATE(Controls!$B$6,COLUMN($C$1:$BJ$1)-COLUMN($C$1)))=YEAR(Controls!$B$6)+5)*(COLUMN($C$1:$BJ$1)-COLUMN($C$1)<Controls!$B$7)*$C$18:$BJ$18) -> 0
A19: Other R&D | B19: $/mo | C19: 500 | D19: 500 | E19: 500 | F19: 500 | G19: 500 | H19: 500 | I19: 500 | J19: 500 | K19: 500 | L19: 500 | M19: 500 | N19: 500 | O19: =IF(COLUMN()-2<=Controls!$B$7,C19*(1+$C$16),0) -> 625 | P19: =IF(COLUMN()-2<=Controls!$B$7,D19*(1+$C$16),0) -> 625 | Q19: =IF(COLUMN()-2<=Controls!$B$7,E19*(1+$C$16),0) -> 625 | R19: =IF(COLUMN()-2<=Controls!$B$7,F19*(1+$C$16),0) -> 625 | S19: =IF(COLUMN()-2<=Controls!$B$7,G19*(1+$C$16),0) -> 625 | T19: =IF(COLUMN()-2<=Controls!$B$7,H19*(1+$C$16),0) -> 625 | U19: =IF(COLUMN()-2<=Controls!$B$7,I19*(1+$C$16),0) -> 625 | V19: =IF(COLUMN()-2<=Controls!$B$7,J19*(1+$C$16),0) -> 625 | ... BJ19: =IF(COLUMN()-2<=Controls!$B$7,AX19*(1+$C$16),0) -> 0 | BK19: =SUMPRODUCT((YEAR(EDATE(Controls!$B$6,COLUMN($C$1:$BJ$1)-COLUMN($C$1)))=YEAR(Controls!$B$6)+0)*(COLUMN($C$1:$BJ$1)-COLUMN($C$1)<Controls!$B$7)*$C$19:$BJ$19) -> 6000 | BL19: =SUMPRODUCT((YEAR(EDATE(Controls!$B$6,COLUMN($C$1:$BJ$1)-COLUMN($C$1)))=YEAR(Controls!$B$6)+1)*(COLUMN($C$1:$BJ$1)-COLUMN($C$1)<Controls!$B$7)*$C$19:$BJ$19) -> 7500 | BM19: =SUMPRODUCT((YEAR(EDATE(Controls!$B$6,COLUMN($C$1:$BJ$1)-COLUMN($C$1)))=YEAR(Controls!$B$6)+2)*(COLUMN($C$1:$BJ$1)-COLUMN($C$1)<Controls!$B$7)*$C$19:$BJ$19) -> 9375 | BN19: =SUMPRODUCT((YEAR(EDATE(Controls!$B$6,COLUMN($C$1:$BJ$1)-COLUMN($C$1)))=YEAR(Controls!$B$6)+3)*(COLUMN($C$1:$BJ$1)-COLUMN($C$1)<Controls!$B$7)*$C$19:$BJ$19) -> 0 | BO19: =SUMPRODUCT((YEAR(EDATE(Controls!$B$6,COLUMN($C$1:$BJ$1)-COLUMN($C$1)))=YEAR(Controls!$B$6)+4)*(COLUMN($C$1:$BJ$1)-COLUMN($C$1)<Controls!$B$7)*$C$19:$BJ$19) -> 0 | BP19: =SUMPRODUCT((YEAR(EDATE(Controls!$B$6,COLUMN($C$1:$BJ$1)-COLUMN($C$1)))=YEAR(Controls!$B$6)+5)*(COLUMN($C$1:$BJ$1)-COLUMN($C$1)<Controls!$B$7)*$C$19:$BJ$19) -> 0
A20: G&A – Non-Wage
A21: YoY Growth Rate – G&A – Non-Wage | B21: %/yr | C21: 0.15 | D21: ↑ Applies to months 13–36 (rolling 12-mo from model start, not calendar year)
A22: Legal & Compliance | B22: $/mo | C22: 2500 | D22: 2500 | E22: 2500 | F22: 2500 | G22: 2500 | H22: 2500 | I22: 2500 | J22: 2500 | K22: 2500 | L22: 2500 | M22: 2500 | N22: 2500 | O22: =IF(COLUMN()-2<=Controls!$B$7,C22*(1+$C$21),0) -> 2875 | P22: =IF(COLUMN()-2<=Controls!$B$7,D22*(1+$C$21),0) -> 2875 | Q22: =IF(COLUMN()-2<=Controls!$B$7,E22*(1+$C$21),0) -> 2875 | R22: =IF(COLUMN()-2<=Controls!$B$7,F22*(1+$C$21),0) -> 2875 | S22: =IF(COLUMN()-2<=Controls!$B$7,G22*(1+$C$21),0) -> 2875 | T22: =IF(COLUMN()-2<=Controls!$B$7,H22*(1+$C$21),0) -> 2875 | U22: =IF(COLUMN()-2<=Controls!$B$7,I22*(1+$C$21),0) -> 2875 | V22: =IF(COLUMN()-2<=Controls!$B$7,J22*(1+$C$21),0) -> 2875 | ... BJ22: =IF(COLUMN()-2<=Controls!$B$7,AX22*(1+$C$21),0) -> 0 | BK22: =SUMPRODUCT((YEAR(EDATE(Controls!$B$6,COLUMN($C$1:$BJ$1)-COLUMN($C$1)))=YEAR(Controls!$B$6)+0)*(COLUMN($C$1:$BJ$1)-COLUMN($C$1)<Controls!$B$7)*$C$22:$BJ$22) -> 30000 | BL22: =SUMPRODUCT((YEAR(EDATE(Controls!$B$6,COLUMN($C$1:$BJ$1)-COLUMN($C$1)))=YEAR(Controls!$B$6)+1)*(COLUMN($C$1:$BJ$1)-COLUMN($C$1)<Controls!$B$7)*$C$22:$BJ$22) -> 34500 | BM22: =SUMPRODUCT((YEAR(EDATE(Controls!$B$6,COLUMN($C$1:$BJ$1)-COLUMN($C$1)))=YEAR(Controls!$B$6)+2)*(COLUMN($C$1:$BJ$1)-COLUMN($C$1)<Controls!$B$7)*$C$22:$BJ$22) -> 39675 | BN22: =SUMPRODUCT((YEAR(EDATE(Controls!$B$6,COLUMN($C$1:$BJ$1)-COLUMN($C$1)))=YEAR(Controls!$B$6)+3)*(COLUMN($C$1:$BJ$1)-COLUMN($C$1)<Controls!$B$7)*$C$22:$BJ$22) -> 0 | BO22: =SUMPRODUCT((YEAR(EDATE(Controls!$B$6,COLUMN($C$1:$BJ$1)-COLUMN($C$1)))=YEAR(Controls!$B$6)+4)*(COLUMN($C$1:$BJ$1)-COLUMN($C$1)<Controls!$B$7)*$C$22:$BJ$22) -> 0 | BP22: =SUMPRODUCT((YEAR(EDATE(Controls!$B$6,COLUMN($C$1:$BJ$1)-COLUMN($C$1)))=YEAR(Controls!$B$6)+5)*(COLUMN($C$1:$BJ$1)-COLUMN($C$1)<Controls!$B$7)*$C$22:$BJ$22) -> 0
A23: Finance, Accounting, Audit | B23: $/mo | C23: 1500 | D23: 1500 | E23: 1500 | F23: 1500 | G23: 1500 | H23: 1500 | I23: 1500 | J23: 1500 | K23: 1500 | L23: 1500 | M23: 1500 | N23: 1500 | O23: =IF(COLUMN()-2<=Controls!$B$7,C23*(1+$C$21),0) -> 1725 | P23: =IF(COLUMN()-2<=Controls!$B$7,D23*(1+$C$21),0) -> 1725 | Q23: =IF(COLUMN()-2<=Controls!$B$7,E23*(1+$C$21),0) -> 1725 | R23: =IF(COLUMN()-2<=Controls!$B$7,F23*(1+$C$21),0) -> 1725 | S23: =IF(COLUMN()-2<=Controls!$B$7,G23*(1+$C$21),0) -> 1725 | T23: =IF(COLUMN()-2<=Controls!$B$7,H23*(1+$C$21),0) -> 1725 | U23: =IF(COLUMN()-2<=Controls!$B$7,I23*(1+$C$21),0) -> 1725 | V23: =IF(COLUMN()-2<=Controls!$B$7,J23*(1+$C$21),0) -> 1725 | ... BJ23: =IF(COLUMN()-2<=Controls!$B$7,AX23*(1+$C$21),0) -> 0 | BK23: =SUMPRODUCT((YEAR(EDATE(Controls!$B$6,COLUMN($C$1:$BJ$1)-COLUMN($C$1)))=YEAR(Controls!$B$6)+0)*(COLUMN($C$1:$BJ$1)-COLUMN($C$1)<Controls!$B$7)*$C$23:$BJ$23) -> 18000 | BL23: =SUMPRODUCT((YEAR(EDATE(Controls!$B$6,COLUMN($C$1:$BJ$1)-COLUMN($C$1)))=YEAR(Controls!$B$6)+1)*(COLUMN($C$1:$BJ$1)-COLUMN($C$1)<Controls!$B$7)*$C$23:$BJ$23) -> 20700 | BM23: =SUMPRODUCT((YEAR(EDATE(Controls!$B$6,COLUMN($C$1:$BJ$1)-COLUMN($C$1)))=YEAR(Controls!$B$6)+2)*(COLUMN($C$1:$BJ$1)-COLUMN($C$1)<Controls!$B$7)*$C$23:$BJ$23) -> 23805 | BN23: =SUMPRODUCT((YEAR(EDATE(Controls!$B$6,COLUMN($C$1:$BJ$1)-COLUMN($C$1)))=YEAR(Controls!$B$6)+3)*(COLUMN($C$1:$BJ$1)-COLUMN($C$1)<Controls!$B$7)*$C$23:$BJ$23) -> 0 | BO23: =SUMPRODUCT((YEAR(EDATE(Controls!$B$6,COLUMN($C$1:$BJ$1)-COLUMN($C$1)))=YEAR(Controls!$B$6)+4)*(COLUMN($C$1:$BJ$1)-COLUMN($C$1)<Controls!$B$7)*$C$23:$BJ$23) -> 0 | BP23: =SUMPRODUCT((YEAR(EDATE(Controls!$B$6,COLUMN($C$1:$BJ$1)-COLUMN($C$1)))=YEAR(Controls!$B$6)+5)*(COLUMN($C$1:$BJ$1)-COLUMN($C$1)<Controls!$B$7)*$C$23:$BJ$23) -> 0
A24: Other G&A (Office, Insurance, HR) | B24: $/mo | C24: 2000 | D24: 2000 | E24: 2000 | F24: 2000 | G24: 2000 | H24: 2000 | I24: 2000 | J24: 2000 | K24: 2000 | L24: 2000 | M24: 2000 | N24: 2000 | O24: =IF(COLUMN()-2<=Controls!$B$7,C24*(1+$C$21),0) -> 2300 | P24: =IF(COLUMN()-2<=Controls!$B$7,D24*(1+$C$21),0) -> 2300 | Q24: =IF(COLUMN()-2<=Controls!$B$7,E24*(1+$C$21),0) -> 2300 | R24: =IF(COLUMN()-2<=Controls!$B$7,F24*(1+$C$21),0) -> 2300 | S24: =IF(COLUMN()-2<=Controls!$B$7,G24*(1+$C$21),0) -> 2300 | T24: =IF(COLUMN()-2<=Controls!$B$7,H24*(1+$C$21),0) -> 2300 | U24: =IF(COLUMN()-2<=Controls!$B$7,I24*(1+$C$21),0) -> 2300 | V24: =IF(COLUMN()-2<=Controls!$B$7,J24*(1+$C$21),0) -> 2300 | ... BJ24: =IF(COLUMN()-2<=Controls!$B$7,AX24*(1+$C$21),0) -> 0 | BK24: =SUMPRODUCT((YEAR(EDATE(Controls!$B$6,COLUMN($C$1:$BJ$1)-COLUMN($C$1)))=YEAR(Controls!$B$6)+0)*(COLUMN($C$1:$BJ$1)-COLUMN($C$1)<Controls!$B$7)*$C$24:$BJ$24) -> 24000 | BL24: =SUMPRODUCT((YEAR(EDATE(Controls!$B$6,COLUMN($C$1:$BJ$1)-COLUMN($C$1)))=YEAR(Controls!$B$6)+1)*(COLUMN($C$1:$BJ$1)-COLUMN($C$1)<Controls!$B$7)*$C$24:$BJ$24) -> 27600 | BM24: =SUMPRODUCT((YEAR(EDATE(Controls!$B$6,COLUMN($C$1:$BJ$1)-COLUMN($C$1)))=YEAR(Controls!$B$6)+2)*(COLUMN($C$1:$BJ$1)-COLUMN($C$1)<Controls!$B$7)*$C$24:$BJ$24) -> 31740 | BN24: =SUMPRODUCT((YEAR(EDATE(Controls!$B$6,COLUMN($C$1:$BJ$1)-COLUMN($C$1)))=YEAR(Controls!$B$6)+3)*(COLUMN($C$1:$BJ$1)-COLUMN($C$1)<Controls!$B$7)*$C$24:$BJ$24) -> 0 | BO24: =SUMPRODUCT((YEAR(EDATE(Controls!$B$6,COLUMN($C$1:$BJ$1)-COLUMN($C$1)))=YEAR(Controls!$B$6)+4)*(COLUMN($C$1:$BJ$1)-COLUMN($C$1)<Controls!$B$7)*$C$24:$BJ$24) -> 0 | BP24: =SUMPRODUCT((YEAR(EDATE(Controls!$B$6,COLUMN($C$1:$BJ$1)-COLUMN($C$1)))=YEAR(Controls!$B$6)+5)*(COLUMN($C$1:$BJ$1)-COLUMN($C$1)<Controls!$B$7)*$C$24:$BJ$24) -> 0
A25: CAPEX (Manual — no auto-growth applied)
A26: Capital Expenditures (Equipment, Etc.) | B26: $/mo | C26: 0 | D26: 0 | E26: 0 | F26: 0 | G26: 0 | H26: 0 | I26: 5000 | J26: 0 | K26: 0 | L26: 0 | M26: 0 | N26: 0 | O26: 0 | P26: 0 | Q26: 0 | R26: 0 | S26: 0 | T26: 0 | U26: 0 | V26: 0 | W26: 0 | X26: 0 | Y26: 0 | Z26: 0 | AA26: 0 | AB26: 0 | AC26: 0 | AD26: 0 | AE26: 0 | AF26: 0 | AG26: 0 | AH26: 0 | AI26: 0 | AJ26: 0 | AK26: 0 | AL26: 0 | AM26: 0 | AN26: 0 | AO26: 0 | AP26: 0 | AQ26: 0 | AR26: 0 | AS26: 0 | AT26: 0 | AU26: 0 | AV26: 0 | AW26: 0 | AX26: 0 | AY26: 0 | AZ26: 0 | BA26: 0 | BB26: 0 | BC26: 0 | BD26: 0 | BE26: 0 | BF26: 0 | BG26: 0 | BH26: 0 | BI26: 0 | BJ26: 0 | BK26: =SUMPRODUCT((YEAR(EDATE(Controls!$B$6,COLUMN($C$1:$BJ$1)-COLUMN($C$1)))=YEAR(Controls!$B$6)+0)*(COLUMN($C$1:$BJ$1)-COLUMN($C$1)<Controls!$B$7)*$C$26:$BJ$26) -> 5000 | BL26: =SUMPRODUCT((YEAR(EDATE(Controls!$B$6,COLUMN($C$1:$BJ$1)-COLUMN($C$1)))=YEAR(Controls!$B$6)+1)*(COLUMN($C$1:$BJ$1)-COLUMN($C$1)<Controls!$B$7)*$C$26:$BJ$26) -> 0 | BM26: =SUMPRODUCT((YEAR(EDATE(Controls!$B$6,COLUMN($C$1:$BJ$1)-COLUMN($C$1)))=YEAR(Controls!$B$6)+2)*(COLUMN($C$1:$BJ$1)-COLUMN($C$1)<Controls!$B$7)*$C$26:$BJ$26) -> 0 | BN26: =SUMPRODUCT((YEAR(EDATE(Controls!$B$6,COLUMN($C$1:$BJ$1)-COLUMN($C$1)))=YEAR(Controls!$B$6)+3)*(COLUMN($C$1:$BJ$1)-COLUMN($C$1)<Controls!$B$7)*$C$26:$BJ$26) -> 0 | BO26: =SUMPRODUCT((YEAR(EDATE(Controls!$B$6,COLUMN($C$1:$BJ$1)-COLUMN($C$1)))=YEAR(Controls!$B$6)+4)*(COLUMN($C$1:$BJ$1)-COLUMN($C$1)<Controls!$B$7)*$C$26:$BJ$26) -> 0 | BP26: =SUMPRODUCT((YEAR(EDATE(Controls!$B$6,COLUMN($C$1:$BJ$1)-COLUMN($C$1)))=YEAR(Controls!$B$6)+5)*(COLUMN($C$1:$BJ$1)-COLUMN($C$1)<Controls!$B$7)*$C$26:$BJ$26) -> 0
A27: Depreciation (straight-line from CapEx above) | B27: $/mo | C27: =IFERROR(C26/Controls!$B$26/12,0) -> 0 | D27: =IFERROR(D26/Controls!$B$26/12,0) -> 0 | E27: =IFERROR(E26/Controls!$B$26/12,0) -> 0 | F27: =IFERROR(F26/Controls!$B$26/12,0) -> 0 | G27: =IFERROR(G26/Controls!$B$26/12,0) -> 0 | H27: =IFERROR(H26/Controls!$B$26/12,0) -> 0 | I27: =IFERROR(I26/Controls!$B$26/12,0) -> 138.88889 | J27: =IFERROR(J26/Controls!$B$26/12,0) -> 0 | ... BJ27: =IFERROR(BJ26/Controls!$B$26/12,0) -> 0 | BK27: =SUMPRODUCT((YEAR(EDATE(Controls!$B$6,COLUMN($C$1:$BJ$1)-COLUMN($C$1)))=YEAR(Controls!$B$6)+0)*(COLUMN($C$1:$BJ$1)-COLUMN($C$1)<Controls!$B$7)*$C$27:$BJ$27) -> 138.88889 | BL27: =SUMPRODUCT((YEAR(EDATE(Controls!$B$6,COLUMN($C$1:$BJ$1)-COLUMN($C$1)))=YEAR(Controls!$B$6)+1)*(COLUMN($C$1:$BJ$1)-COLUMN($C$1)<Controls!$B$7)*$C$27:$BJ$27) -> 0 | BM27: =SUMPRODUCT((YEAR(EDATE(Controls!$B$6,COLUMN($C$1:$BJ$1)-COLUMN($C$1)))=YEAR(Controls!$B$6)+2)*(COLUMN($C$1:$BJ$1)-COLUMN($C$1)<Controls!$B$7)*$C$27:$BJ$27) -> 0 | BN27: =SUMPRODUCT((YEAR(EDATE(Controls!$B$6,COLUMN($C$1:$BJ$1)-COLUMN($C$1)))=YEAR(Controls!$B$6)+3)*(COLUMN($C$1:$BJ$1)-COLUMN($C$1)<Controls!$B$7)*$C$27:$BJ$27) -> 0 | BO27: =SUMPRODUCT((YEAR(EDATE(Controls!$B$6,COLUMN($C$1:$BJ$1)-COLUMN($C$1)))=YEAR(Controls!$B$6)+4)*(COLUMN($C$1:$BJ$1)-COLUMN($C$1)<Controls!$B$7)*$C$27:$BJ$27) -> 0 | BP27: =SUMPRODUCT((YEAR(EDATE(Controls!$B$6,COLUMN($C$1:$BJ$1)-COLUMN($C$1)))=YEAR(Controls!$B$6)+5)*(COLUMN($C$1:$BJ$1)-COLUMN($C$1)<Controls!$B$7)*$C$27:$BJ$27) -> 0

Sheet P&L
A1: INCOME STATEMENT · SaaS P&L with Gross Margin, EBITDA, EBIT, Net Income
A3: Label | B3: Unit | C3: =TEXT(EDATE(Controls!$B$6,0),"mmm-yy") -> Jan-26 | D3: =TEXT(EDATE(Controls!$B$6,1),"mmm-yy") -> Feb-26 | E3: =TEXT(EDATE(Controls!$B$6,2),"mmm-yy") -> Mar-26 | F3: =TEXT(EDATE(Controls!$B$6,3),"mmm-yy") -> Apr-26 | G3: =TEXT(EDATE(Controls!$B$6,4),"mmm-yy") -> May-26 | H3: =TEXT(EDATE(Controls!$B$6,5),"mmm-yy") -> Jun-26 | I3: =TEXT(EDATE(Controls!$B$6,6),"mmm-yy") -> Jul-26 | J3: =TEXT(EDATE(Controls!$B$6,7),"mmm-yy") -> Aug-26 | K3: =TEXT(EDATE(Controls!$B$6,8),"mmm-yy") -> Sep-26 | L3: =TEXT(EDATE(Controls!$B$6,9),"mmm-yy") -> Oct-26 | M3: =TEXT(EDATE(Controls!$B$6,10),"mmm-yy") -> Nov-26 | N3: =TEXT(EDATE(Controls!$B$6,11),"mmm-yy") -> Dec-26 | O3: =TEXT(EDATE(Controls!$B$6,12),"mmm-yy") -> Jan-27 | P3: =TEXT(EDATE(Controls!$B$6,13),"mmm-yy") -> Feb-27 | Q3: =TEXT(EDATE(Controls!$B$6,14),"mmm-yy") -> Mar-27 | R3: =TEXT(EDATE(Controls!$B$6,15),"mmm-yy") -> Apr-27 | S3: =TEXT(EDATE(Controls!$B$6,16),"mmm-yy") -> May-27 | T3: =TEXT(EDATE(Controls!$B$6,17),"mmm-yy") -> Jun-27 | U3: =TEXT(EDATE(Controls!$B$6,18),"mmm-yy") -> Jul-27 | V3: =TEXT(EDATE(Controls!$B$6,19),"mmm-yy") -> Aug-27 | W3: =TEXT(EDATE(Controls!$B$6,20),"mmm-yy") -> Sep-27 | X3: =TEXT(EDATE(Controls!$B$6,21),"mmm-yy") -> Oct-27 | Y3: =TEXT(EDATE(Controls!$B$6,22),"mmm-yy") -> Nov-27 | Z3: =TEXT(EDATE(Controls!$B$6,23),"mmm-yy") -> Dec-27 | AA3: =TEXT(EDATE(Controls!$B$6,24),"mmm-yy") -> Jan-28 | AB3: =TEXT(EDATE(Controls!$B$6,25),"mmm-yy") -> Feb-28 | AC3: =TEXT(EDATE(Controls!$B$6,26),"mmm-yy") -> Mar-28 | AD3: =TEXT(EDATE(Controls!$B$6,27),"mmm-yy") -> Apr-28 | AE3: =TEXT(EDATE(Controls!$B$6,28),"mmm-yy") -> May-28 | AF3: =TEXT(EDATE(Controls!$B$6,29),"mmm-yy") -> Jun-28 | AG3: =TEXT(EDATE(Controls!$B$6,30),"mmm-yy") -> Jul-28 | AH3: =TEXT(EDATE(Controls!$B$6,31),"mmm-yy") -> Aug-28 | AI3: =TEXT(EDATE(Controls!$B$6,32),"mmm-yy") -> Sep-28 | AJ3: =TEXT(EDATE(Controls!$B$6,33),"mmm-yy") -> Oct-28 | AK3: =TEXT(EDATE(Controls!$B$6,34),"mmm-yy") -> Nov-28 | AL3: =TEXT(EDATE(Controls!$B$6,35),"mmm-yy") -> Dec-28 | AM3: =TEXT(EDATE(Controls!$B$6,36),"mmm-yy") -> Jan-29 | AN3: =TEXT(EDATE(Controls!$B$6,37),"mmm-yy") -> Feb-29 | AO3: =TEXT(EDATE(Controls!$B$6,38),"mmm-yy") -> Mar-29 | AP3: =TEXT(EDATE(Controls!$B$6,39),"mmm-yy") -> Apr-29 | AQ3: =TEXT(EDATE(Controls!$B$6,40),"mmm-yy") -> May-29 | AR3: =TEXT(EDATE(Controls!$B$6,41),"mmm-yy") -> Jun-29 | AS3: =TEXT(EDATE(Controls!$B$6,42),"mmm-yy") -> Jul-29 | AT3: =TEXT(EDATE(Controls!$B$6,43),"mmm-yy") -> Aug-29 | AU3: =TEXT(EDATE(Controls!$B$6,44),"mmm-yy") -> Sep-29 | AV3: =TEXT(EDATE(Controls!$B$6,45),"mmm-yy") -> Oct-29 | AW3: =TEXT(EDATE(Controls!$B$6,46),"mmm-yy") -> Nov-29 | AX3: =TEXT(EDATE(Controls!$B$6,47),"mmm-yy") -> Dec-29 | AY3: =TEXT(EDATE(Controls!$B$6,48),"mmm-yy") -> Jan-30 | AZ3: =TEXT(EDATE(Controls!$B$6,49),"mmm-yy") -> Feb-30 | BA3: =TEXT(EDATE(Controls!$B$6,50),"mmm-yy") -> Mar-30 | BB3: =TEXT(EDATE(Controls!$B$6,51),"mmm-yy") -> Apr-30 | BC3: =TEXT(EDATE(Controls!$B$6,52),"mmm-yy") -> May-30 | BD3: =TEXT(EDATE(Controls!$B$6,53),"mmm-yy") -> Jun-30 | BE3: =TEXT(EDATE(Controls!$B$6,54),"mmm-yy") -> Jul-30 | BF3: =TEXT(EDATE(Controls!$B$6,55),"mmm-yy") -> Aug-30 | BG3: =TEXT(EDATE(Controls!$B$6,56),"mmm-yy") -> Sep-30 | BH3: =TEXT(EDATE(Controls!$B$6,57),"mmm-yy") -> Oct-30 | BI3: =TEXT(EDATE(Controls!$B$6,58),"mmm-yy") -> Nov-30 | BJ3: =TEXT(EDATE(Controls!$B$6,59),"mmm-yy") -> Dec-30 | BK3: ="FY "&(YEAR(Controls!$B$6)+0) -> FY 2026 | BL3: ="FY "&(YEAR(Controls!$B$6)+1) -> FY 2027 | BM3: ="FY "&(YEAR(Controls!$B$6)+2) -> FY 2028 | BN3: ="FY "&(YEAR(Controls!$B$6)+3) -> FY 2029 | BO3: ="FY "&(YEAR(Controls!$B$6)+4) -> FY 2030 | BP3: ="FY "&(YEAR(Controls!$B$6)+5) -> FY 2031
A5: REVENUE
A6: Subscription Revenue | B6: $ | C6: =Revenue!C102 -> 8691.094 | D6: =Revenue!D102 -> 20722.069 | E6: =Revenue!E102 -> 36114.149 | F6: =Revenue!F102 -> 54776.382 | G6: =Revenue!G102 -> 77092.71 | H6: =Revenue!H102 -> 102733.2 | I6: =Revenue!I102 -> 131901.31 | J6: =Revenue!J102 -> 163969.82 | ... BJ6: =Revenue!BJ102 -> 5231473.9 | BK6: =SUMPRODUCT((YEAR(EDATE(Controls!$B$6,COLUMN($C$1:$BJ$1)-COLUMN($C$1)))=YEAR(Controls!$B$6)+0)*(COLUMN($C$1:$BJ$1)-COLUMN($C$1)<Controls!$B$7)*$C$6:$BJ$6) -> 1643273.9 | BL6: =SUMPRODUCT((YEAR(EDATE(Controls!$B$6,COLUMN($C$1:$BJ$1)-COLUMN($C$1)))=YEAR(Controls!$B$6)+1)*(COLUMN($C$1:$BJ$1)-COLUMN($C$1)<Controls!$B$7)*$C$6:$BJ$6) -> 9205123.1 | BM6: =SUMPRODUCT((YEAR(EDATE(Controls!$B$6,COLUMN($C$1:$BJ$1)-COLUMN($C$1)))=YEAR(Controls!$B$6)+2)*(COLUMN($C$1:$BJ$1)-COLUMN($C$1)<Controls!$B$7)*$C$6:$BJ$6) -> 26869393 | BN6: =SUMPRODUCT((YEAR(EDATE(Controls!$B$6,COLUMN($C$1:$BJ$1)-COLUMN($C$1)))=YEAR(Controls!$B$6)+3)*(COLUMN($C$1:$BJ$1)-COLUMN($C$1)<Controls!$B$7)*$C$6:$BJ$6) -> 0 | BO6: =SUMPRODUCT((YEAR(EDATE(Controls!$B$6,COLUMN($C$1:$BJ$1)-COLUMN($C$1)))=YEAR(Controls!$B$6)+4)*(COLUMN($C$1:$BJ$1)-COLUMN($C$1)<Controls!$B$7)*$C$6:$BJ$6) -> 0 | BP6: =SUMPRODUCT((YEAR(EDATE(Controls!$B$6,COLUMN($C$1:$BJ$1)-COLUMN($C$1)))=YEAR(Controls!$B$6)+5)*(COLUMN($C$1:$BJ$1)-COLUMN($C$1)<Controls!$B$7)*$C$6:$BJ$6) -> 0
A7: Professional Services | B7: $ | C7: =Revenue!C104 -> 5000 | D7: =Revenue!D104 -> 5500 | E7: =Revenue!E104 -> 6000 | F7: =Revenue!F104 -> 6500 | G7: =Revenue!G104 -> 7000 | H7: =Revenue!H104 -> 7500 | I7: =Revenue!I104 -> 8000 | J7: =Revenue!J104 -> 8500 | ... BJ7: =Revenue!BJ104 -> 32000 | BK7: =SUMPRODUCT((YEAR(EDATE(Controls!$B$6,COLUMN($C$1:$BJ$1)-COLUMN($C$1)))=YEAR(Controls!$B$6)+0)*(COLUMN($C$1:$BJ$1)-COLUMN($C$1)<Controls!$B$7)*$C$7:$BJ$7) -> 92500 | BL7: =SUMPRODUCT((YEAR(EDATE(Controls!$B$6,COLUMN($C$1:$BJ$1)-COLUMN($C$1)))=YEAR(Controls!$B$6)+1)*(COLUMN($C$1:$BJ$1)-COLUMN($C$1)<Controls!$B$7)*$C$7:$BJ$7) -> 152000 | BM7: =SUMPRODUCT((YEAR(EDATE(Controls!$B$6,COLUMN($C$1:$BJ$1)-COLUMN($C$1)))=YEAR(Controls!$B$6)+2)*(COLUMN($C$1:$BJ$1)-COLUMN($C$1)<Controls!$B$7)*$C$7:$BJ$7) -> 215000 | BN7: =SUMPRODUCT((YEAR(EDATE(Controls!$B$6,COLUMN($C$1:$BJ$1)-COLUMN($C$1)))=YEAR(Controls!$B$6)+3)*(COLUMN($C$1:$BJ$1)-COLUMN($C$1)<Controls!$B$7)*$C$7:$BJ$7) -> 0 | BO7: =SUMPRODUCT((YEAR(EDATE(Controls!$B$6,COLUMN($C$1:$BJ$1)-COLUMN($C$1)))=YEAR(Controls!$B$6)+4)*(COLUMN($C$1:$BJ$1)-COLUMN($C$1)<Controls!$B$7)*$C$7:$BJ$7) -> 0 | BP7: =SUMPRODUCT((YEAR(EDATE(Controls!$B$6,COLUMN($C$1:$BJ$1)-COLUMN($C$1)))=YEAR(Controls!$B$6)+5)*(COLUMN($C$1:$BJ$1)-COLUMN($C$1)<Controls!$B$7)*$C$7:$BJ$7) -> 0
A8: Total Revenue | B8: $ | C8: =C6+C7 -> 13691.094 | D8: =D6+D7 -> 26222.069 | E8: =E6+E7 -> 42114.149 | F8: =F6+F7 -> 61276.382 | G8: =G6+G7 -> 84092.71 | H8: =H6+H7 -> 110233.2 | I8: =I6+I7 -> 139901.31 | J8: =J6+J7 -> 172469.82 | ... BJ8: =BJ6+BJ7 -> 5263473.9 | BK8: =SUMPRODUCT((YEAR(EDATE(Controls!$B$6,COLUMN($C$1:$BJ$1)-COLUMN($C$1)))=YEAR(Controls!$B$6)+0)*(COLUMN($C$1:$BJ$1)-COLUMN($C$1)<Controls!$B$7)*$C$8:$BJ$8) -> 1735773.9 | BL8: =SUMPRODUCT((YEAR(EDATE(Controls!$B$6,COLUMN($C$1:$BJ$1)-COLUMN($C$1)))=YEAR(Controls!$B$6)+1)*(COLUMN($C$1:$BJ$1)-COLUMN($C$1)<Controls!$B$7)*$C$8:$BJ$8) -> 9357123.1 | BM8: =SUMPRODUCT((YEAR(EDATE(Controls!$B$6,COLUMN($C$1:$BJ$1)-COLUMN($C$1)))=YEAR(Controls!$B$6)+2)*(COLUMN($C$1:$BJ$1)-COLUMN($C$1)<Controls!$B$7)*$C$8:$BJ$8) -> 27084393 | BN8: =SUMPRODUCT((YEAR(EDATE(Controls!$B$6,COLUMN($C$1:$BJ$1)-COLUMN($C$1)))=YEAR(Controls!$B$6)+3)*(COLUMN($C$1:$BJ$1)-COLUMN($C$1)<Controls!$B$7)*$C$8:$BJ$8) -> 0 | BO8: =SUMPRODUCT((YEAR(EDATE(Controls!$B$6,COLUMN($C$1:$BJ$1)-COLUMN($C$1)))=YEAR(Controls!$B$6)+4)*(COLUMN($C$1:$BJ$1)-COLUMN($C$1)<Controls!$B$7)*$C$8:$BJ$8) -> 0 | BP8: =SUMPRODUCT((YEAR(EDATE(Controls!$B$6,COLUMN($C$1:$BJ$1)-COLUMN($C$1)))=YEAR(Controls!$B$6)+5)*(COLUMN($C$1:$BJ$1)-COLUMN($C$1)<Controls!$B$7)*$C$8:$BJ$8) -> 0
A10: COST OF REVENUE (COGS)
A11: Cloud Hosting & Infra | B11: $ | C11: =OpEx!C8 -> 3000 | D11: =OpEx!D8 -> 3000 | E11: =OpEx!E8 -> 3000 | F11: =OpEx!F8 -> 3000 | G11: =OpEx!G8 -> 3000 | H11: =OpEx!H8 -> 3000 | I11: =OpEx!I8 -> 3000 | J11: =OpEx!J8 -> 3000 | ... BJ11: =OpEx!BJ8 -> 0 | BK11: =SUMPRODUCT((YEAR(EDATE(Controls!$B$6,COLUMN($C$1:$BJ$1)-COLUMN($C$1)))=YEAR(Controls!$B$6)+0)*(COLUMN($C$1:$BJ$1)-COLUMN($C$1)<Controls!$B$7)*$C$11:$BJ$11) -> 36000 | BL11: =SUMPRODUCT((YEAR(EDATE(Controls!$B$6,COLUMN($C$1:$BJ$1)-COLUMN($C$1)))=YEAR(Controls!$B$6)+1)*(COLUMN($C$1:$BJ$1)-COLUMN($C$1)<Controls!$B$7)*$C$11:$BJ$11) -> 43200 | BM11: =SUMPRODUCT((YEAR(EDATE(Controls!$B$6,COLUMN($C$1:$BJ$1)-COLUMN($C$1)))=YEAR(Controls!$B$6)+2)*(COLUMN($C$1:$BJ$1)-COLUMN($C$1)<Controls!$B$7)*$C$11:$BJ$11) -> 51840 | BN11: =SUMPRODUCT((YEAR(EDATE(Controls!$B$6,COLUMN($C$1:$BJ$1)-COLUMN($C$1)))=YEAR(Controls!$B$6)+3)*(COLUMN($C$1:$BJ$1)-COLUMN($C$1)<Controls!$B$7)*$C$11:$BJ$11) -> 0 | BO11: =SUMPRODUCT((YEAR(EDATE(Controls!$B$6,COLUMN($C$1:$BJ$1)-COLUMN($C$1)))=YEAR(Controls!$B$6)+4)*(COLUMN($C$1:$BJ$1)-COLUMN($C$1)<Controls!$B$7)*$C$11:$BJ$11) -> 0 | BP11: =SUMPRODUCT((YEAR(EDATE(Controls!$B$6,COLUMN($C$1:$BJ$1)-COLUMN($C$1)))=YEAR(Controls!$B$6)+5)*(COLUMN($C$1:$BJ$1)-COLUMN($C$1)<Controls!$B$7)*$C$11:$BJ$11) -> 0
A12: Other COGS | B12: $ | C12: =OpEx!C9 -> 1000 | D12: =OpEx!D9 -> 1000 | E12: =OpEx!E9 -> 1000 | F12: =OpEx!F9 -> 1000 | G12: =OpEx!G9 -> 1000 | H12: =OpEx!H9 -> 1000 | I12: =OpEx!I9 -> 1000 | J12: =OpEx!J9 -> 1000 | ... BJ12: =OpEx!BJ9 -> 0 | BK12: =SUMPRODUCT((YEAR(EDATE(Controls!$B$6,COLUMN($C$1:$BJ$1)-COLUMN($C$1)))=YEAR(Controls!$B$6)+0)*(COLUMN($C$1:$BJ$1)-COLUMN($C$1)<Controls!$B$7)*$C$12:$BJ$12) -> 12000 | BL12: =SUMPRODUCT((YEAR(EDATE(Controls!$B$6,COLUMN($C$1:$BJ$1)-COLUMN($C$1)))=YEAR(Controls!$B$6)+1)*(COLUMN($C$1:$BJ$1)-COLUMN($C$1)<Controls!$B$7)*$C$12:$BJ$12) -> 14400 | BM12: =SUMPRODUCT((YEAR(EDATE(Controls!$B$6,COLUMN($C$1:$BJ$1)-COLUMN($C$1)))=YEAR(Controls!$B$6)+2)*(COLUMN($C$1:$BJ$1)-COLUMN($C$1)<Controls!$B$7)*$C$12:$BJ$12) -> 17280 | BN12: =SUMPRODUCT((YEAR(EDATE(Controls!$B$6,COLUMN($C$1:$BJ$1)-COLUMN($C$1)))=YEAR(Controls!$B$6)+3)*(COLUMN($C$1:$BJ$1)-COLUMN($C$1)<Controls!$B$7)*$C$12:$BJ$12) -> 0 | BO12: =SUMPRODUCT((YEAR(EDATE(Controls!$B$6,COLUMN($C$1:$BJ$1)-COLUMN($C$1)))=YEAR(Controls!$B$6)+4)*(COLUMN($C$1:$BJ$1)-COLUMN($C$1)<Controls!$B$7)*$C$12:$BJ$12) -> 0 | BP12: =SUMPRODUCT((YEAR(EDATE(Controls!$B$6,COLUMN($C$1:$BJ$1)-COLUMN($C$1)))=YEAR(Controls!$B$6)+5)*(COLUMN($C$1:$BJ$1)-COLUMN($C$1)<Controls!$B$7)*$C$12:$BJ$12) -> 0
A13: CS Team Wages (Loaded) | B13: $ | C13: =Headcount!C10 -> 10052 | D13: =Headcount!D10 -> 10052 | E13: =Headcount!E10 -> 10052 | F13: =Headcount!F10 -> 10052 | G13: =Headcount!G10 -> 10052 | H13: =Headcount!H10 -> 10052 | I13: =Headcount!I10 -> 10052 | J13: =Headcount!J10 -> 10052 | ... BJ13: =Headcount!BJ10 -> 0 | BK13: =SUMPRODUCT((YEAR(EDATE(Controls!$B$6,COLUMN($C$1:$BJ$1)-COLUMN($C$1)))=YEAR(Controls!$B$6)+0)*(COLUMN($C$1:$BJ$1)-COLUMN($C$1)<Controls!$B$7)*$C$13:$BJ$13) -> 120624 | BL13: =SUMPRODUCT((YEAR(EDATE(Controls!$B$6,COLUMN($C$1:$BJ$1)-COLUMN($C$1)))=YEAR(Controls!$B$6)+1)*(COLUMN($C$1:$BJ$1)-COLUMN($C$1)<Controls!$B$7)*$C$13:$BJ$13) -> 144748.8 | BM13: =SUMPRODUCT((YEAR(EDATE(Controls!$B$6,COLUMN($C$1:$BJ$1)-COLUMN($C$1)))=YEAR(Controls!$B$6)+2)*(COLUMN($C$1:$BJ$1)-COLUMN($C$1)<Controls!$B$7)*$C$13:$BJ$13) -> 173698.56 | BN13: =SUMPRODUCT((YEAR(EDATE(Controls!$B$6,COLUMN($C$1:$BJ$1)-COLUMN($C$1)))=YEAR(Controls!$B$6)+3)*(COLUMN($C$1:$BJ$1)-COLUMN($C$1)<Controls!$B$7)*$C$13:$BJ$13) -> 0 | BO13: =SUMPRODUCT((YEAR(EDATE(Controls!$B$6,COLUMN($C$1:$BJ$1)-COLUMN($C$1)))=YEAR(Controls!$B$6)+4)*(COLUMN($C$1:$BJ$1)-COLUMN($C$1)<Controls!$B$7)*$C$13:$BJ$13) -> 0 | BP13: =SUMPRODUCT((YEAR(EDATE(Controls!$B$6,COLUMN($C$1:$BJ$1)-COLUMN($C$1)))=YEAR(Controls!$B$6)+5)*(COLUMN($C$1:$BJ$1)-COLUMN($C$1)<Controls!$B$7)*$C$13:$BJ$13) -> 0
A14: Services Delivery Cost | B14: $ | C14: =C7*0.35 -> 1750 | D14: =D7*0.35 -> 1925 | E14: =E7*0.35 -> 2100 | F14: =F7*0.35 -> 2275 | G14: =G7*0.35 -> 2450 | H14: =H7*0.35 -> 2625 | I14: =I7*0.35 -> 2800 | J14: =J7*0.35 -> 2975 | ... BJ14: =BJ7*0.35 -> 11200 | BK14: =SUMPRODUCT((YEAR(EDATE(Controls!$B$6,COLUMN($C$1:$BJ$1)-COLUMN($C$1)))=YEAR(Controls!$B$6)+0)*(COLUMN($C$1:$BJ$1)-COLUMN($C$1)<Controls!$B$7)*$C$14:$BJ$14) -> 32375 | BL14: =SUMPRODUCT((YEAR(EDATE(Controls!$B$6,COLUMN($C$1:$BJ$1)-COLUMN($C$1)))=YEAR(Controls!$B$6)+1)*(COLUMN($C$1:$BJ$1)-COLUMN($C$1)<Controls!$B$7)*$C$14:$BJ$14) -> 53200 | BM14: =SUMPRODUCT((YEAR(EDATE(Controls!$B$6,COLUMN($C$1:$BJ$1)-COLUMN($C$1)))=YEAR(Controls!$B$6)+2)*(COLUMN($C$1:$BJ$1)-COLUMN($C$1)<Controls!$B$7)*$C$14:$BJ$14) -> 75250 | BN14: =SUMPRODUCT((YEAR(EDATE(Controls!$B$6,COLUMN($C$1:$BJ$1)-COLUMN($C$1)))=YEAR(Controls!$B$6)+3)*(COLUMN($C$1:$BJ$1)-COLUMN($C$1)<Controls!$B$7)*$C$14:$BJ$14) -> 0 | BO14: =SUMPRODUCT((YEAR(EDATE(Controls!$B$6,COLUMN($C$1:$BJ$1)-COLUMN($C$1)))=YEAR(Controls!$B$6)+4)*(COLUMN($C$1:$BJ$1)-COLUMN($C$1)<Controls!$B$7)*$C$14:$BJ$14) -> 0 | BP14: =SUMPRODUCT((YEAR(EDATE(Controls!$B$6,COLUMN($C$1:$BJ$1)-COLUMN($C$1)))=YEAR(Controls!$B$6)+5)*(COLUMN($C$1:$BJ$1)-COLUMN($C$1)<Controls!$B$7)*$C$14:$BJ$14) -> 0
A15: Total COGS | B15: $ | C15: =C11+C12+C13+C14 -> 15802 | D15: =D11+D12+D13+D14 -> 15977 | E15: =E11+E12+E13+E14 -> 16152 | F15: =F11+F12+F13+F14 -> 16327 | G15: =G11+G12+G13+G14 -> 16502 | H15: =H11+H12+H13+H14 -> 16677 | I15: =I11+I12+I13+I14 -> 16852 | J15: =J11+J12+J13+J14 -> 17027 | ... BJ15: =BJ11+BJ12+BJ13+BJ14 -> 11200 | BK15: =SUMPRODUCT((YEAR(EDATE(Controls!$B$6,COLUMN($C$1:$BJ$1)-COLUMN($C$1)))=YEAR(Controls!$B$6)+0)*(COLUMN($C$1:$BJ$1)-COLUMN($C$1)<Controls!$B$7)*$C$15:$BJ$15) -> 200999 | BL15: =SUMPRODUCT((YEAR(EDATE(Controls!$B$6,COLUMN($C$1:$BJ$1)-COLUMN($C$1)))=YEAR(Controls!$B$6)+1)*(COLUMN($C$1:$BJ$1)-COLUMN($C$1)<Controls!$B$7)*$C$15:$BJ$15) -> 255548.8 | BM15: =SUMPRODUCT((YEAR(EDATE(Controls!$B$6,COLUMN($C$1:$BJ$1)-COLUMN($C$1)))=YEAR(Controls!$B$6)+2)*(COLUMN($C$1:$BJ$1)-COLUMN($C$1)<Controls!$B$7)*$C$15:$BJ$15) -> 318068.56 | BN15: =SUMPRODUCT((YEAR(EDATE(Controls!$B$6,COLUMN($C$1:$BJ$1)-COLUMN($C$1)))=YEAR(Controls!$B$6)+3)*(COLUMN($C$1:$BJ$1)-COLUMN($C$1)<Controls!$B$7)*$C$15:$BJ$15) -> 0 | BO15: =SUMPRODUCT((YEAR(EDATE(Controls!$B$6,COLUMN($C$1:$BJ$1)-COLUMN($C$1)))=YEAR(Controls!$B$6)+4)*(COLUMN($C$1:$BJ$1)-COLUMN($C$1)<Controls!$B$7)*$C$15:$BJ$15) -> 0 | BP15: =SUMPRODUCT((YEAR(EDATE(Controls!$B$6,COLUMN($C$1:$BJ$1)-COLUMN($C$1)))=YEAR(Controls!$B$6)+5)*(COLUMN($C$1:$BJ$1)-COLUMN($C$1)<Controls!$B$7)*$C$15:$BJ$15) -> 0
A16: Gross Profit | B16: $ | C16: =C8-C15 -> -2110.906 | D16: =D8-D15 -> 10245.069 | E16: =E8-E15 -> 25962.149 | F16: =F8-F15 -> 44949.382 | G16: =G8-G15 -> 67590.71 | H16: =H8-H15 -> 93556.197 | I16: =I8-I15 -> 123049.31 | J16: =J8-J15 -> 155442.82 | ... BJ16: =BJ8-BJ15 -> 5252273.9 | BK16: =SUMPRODUCT((YEAR(EDATE(Controls!$B$6,COLUMN($C$1:$BJ$1)-COLUMN($C$1)))=YEAR(Controls!$B$6)+0)*(COLUMN($C$1:$BJ$1)-COLUMN($C$1)<Controls!$B$7)*$C$16:$BJ$16) -> 1534774.9 | BL16: =SUMPRODUCT((YEAR(EDATE(Controls!$B$6,COLUMN($C$1:$BJ$1)-COLUMN($C$1)))=YEAR(Controls!$B$6)+1)*(COLUMN($C$1:$BJ$1)-COLUMN($C$1)<Controls!$B$7)*$C$16:$BJ$16) -> 9101574.3 | BM16: =SUMPRODUCT((YEAR(EDATE(Controls!$B$6,COLUMN($C$1:$BJ$1)-COLUMN($C$1)))=YEAR(Controls!$B$6)+2)*(COLUMN($C$1:$BJ$1)-COLUMN($C$1)<Controls!$B$7)*$C$16:$BJ$16) -> 26766325 | BN16: =SUMPRODUCT((YEAR(EDATE(Controls!$B$6,COLUMN($C$1:$BJ$1)-COLUMN($C$1)))=YEAR(Controls!$B$6)+3)*(COLUMN($C$1:$BJ$1)-COLUMN($C$1)<Controls!$B$7)*$C$16:$BJ$16) -> 0 | BO16: =SUMPRODUCT((YEAR(EDATE(Controls!$B$6,COLUMN($C$1:$BJ$1)-COLUMN($C$1)))=YEAR(Controls!$B$6)+4)*(COLUMN($C$1:$BJ$1)-COLUMN($C$1)<Controls!$B$7)*$C$16:$BJ$16) -> 0 | BP16: =SUMPRODUCT((YEAR(EDATE(Controls!$B$6,COLUMN($C$1:$BJ$1)-COLUMN($C$1)))=YEAR(Controls!$B$6)+5)*(COLUMN($C$1:$BJ$1)-COLUMN($C$1)<Controls!$B$7)*$C$16:$BJ$16) -> 0
A17: Gross Margin % | B17: % | C17: =IFERROR(C16/C8,0) -> -0.15418096 | D17: =IFERROR(D16/D8,0) -> 0.39070406 | E17: =IFERROR(E16/E8,0) -> 0.61647094 | F17: =IFERROR(F16/F8,0) -> 0.7335515 | G17: =IFERROR(G16/G8,0) -> 0.8037642 | H17: =IFERROR(H16/H8,0) -> 0.84871164 | I17: =IFERROR(I16/I8,0) -> 0.87954365 | J17: =IFERROR(J16/J8,0) -> 0.90127548 | ... BJ17: =IFERROR(BJ16/BJ8,0) -> 0.99787213 | BK17: =IFERROR(SUMPRODUCT((YEAR(EDATE(Controls!$B$6,COLUMN($C$1:$BJ$1)-COLUMN($C$1)))=YEAR(Controls!$B$6)+0)*(COLUMN($C$1:$BJ$1)-COLUMN($C$1)<Controls!$B$7)*$C$17:$BJ$17)/SUMPRODUCT((YEAR(EDATE(Controls!$B$6,COLUMN($C$1:$BJ$1)-COLUMN($C$1)))=YEAR(Controls!$B$6)+0)*(COLUMN($C$1:$BJ$1)-COLUMN($C$1)<Controls!$B$7)*1),0) -> 0.72959055 | BL17: =IFERROR(SUMPRODUCT((YEAR(EDATE(Controls!$B$6,COLUMN($C$1:$BJ$1)-COLUMN($C$1)))=YEAR(Controls!$B$6)+1)*(COLUMN($C$1:$BJ$1)-COLUMN($C$1)<Controls!$B$7)*$C$17:$BJ$17)/SUMPRODUCT((YEAR(EDATE(Controls!$B$6,COLUMN($C$1:$BJ$1)-COLUMN($C$1)))=YEAR(Controls!$B$6)+1)*(COLUMN($C$1:$BJ$1)-COLUMN($C$1)<Controls!$B$7)*1),0) -> 0.96904014 | BM17: =IFERROR(SUMPRODUCT((YEAR(EDATE(Controls!$B$6,COLUMN($C$1:$BJ$1)-COLUMN($C$1)))=YEAR(Controls!$B$6)+2)*(COLUMN($C$1:$BJ$1)-COLUMN($C$1)<Controls!$B$7)*$C$17:$BJ$17)/SUMPRODUCT((YEAR(EDATE(Controls!$B$6,COLUMN($C$1:$BJ$1)-COLUMN($C$1)))=YEAR(Controls!$B$6)+2)*(COLUMN($C$1:$BJ$1)-COLUMN($C$1)<Controls!$B$7)*1),0) -> 0.98741477 | BN17: =IFERROR(SUMPRODUCT((YEAR(EDATE(Controls!$B$6,COLUMN($C$1:$BJ$1)-COLUMN($C$1)))=YEAR(Controls!$B$6)+3)*(COLUMN($C$1:$BJ$1)-COLUMN($C$1)<Controls!$B$7)*$C$17:$BJ$17)/SUMPRODUCT((YEAR(EDATE(Controls!$B$6,COLUMN($C$1:$BJ$1)-COLUMN($C$1)))=YEAR(Controls!$B$6)+3)*(COLUMN($C$1:$BJ$1)-COLUMN($C$1)<Controls!$B$7)*1),0) -> 0 | BO17: =IFERROR(SUMPRODUCT((YEAR(EDATE(Controls!$B$6,COLUMN($C$1:$BJ$1)-COLUMN($C$1)))=YEAR(Controls!$B$6)+4)*(COLUMN($C$1:$BJ$1)-COLUMN($C$1)<Controls!$B$7)*$C$17:$BJ$17)/SUMPRODUCT((YEAR(EDATE(Controls!$B$6,COLUMN($C$1:$BJ$1)-COLUMN($C$1)))=YEAR(Controls!$B$6)+4)*(COLUMN($C$1:$BJ$1)-COLUMN($C$1)<Controls!$B$7)*1),0) -> 0 | BP17: =IFERROR(SUMPRODUCT((YEAR(EDATE(Controls!$B$6,COLUMN($C$1:$BJ$1)-COLUMN($C$1)))=YEAR(Controls!$B$6)+5)*(COLUMN($C$1:$BJ$1)-COLUMN($C$1)<Controls!$B$7)*$C$17:$BJ$17)/SUMPRODUCT((YEAR(EDATE(Controls!$B$6,COLUMN($C$1:$BJ$1)-COLUMN($C$1)))=YEAR(Controls!$B$6)+5)*(COLUMN($C$1:$BJ$1)-COLUMN($C$1)<Controls!$B$7)*1),0) -> 0
A19: OPERATING EXPENSES
A20: Sales & Marketing
A21: S&M Wages (Loaded) | B21: $ | C21: =Headcount!C15 -> 18847.5 | D21: =Headcount!D15 -> 18847.5 | E21: =Headcount!E15 -> 18847.5 | F21: =Headcount!F15 -> 18847.5 | G21: =Headcount!G15 -> 18847.5 | H21: =Headcount!H15 -> 18847.5 | I21: =Headcount!I15 -> 18847.5 | J21: =Headcount!J15 -> 18847.5 | ... BJ21: =Headcount!BJ15 -> 0 | BK21: =SUMPRODUCT((YEAR(EDATE(Controls!$B$6,COLUMN($C$1:$BJ$1)-COLUMN($C$1)))=YEAR(Controls!$B$6)+0)*(COLUMN($C$1:$BJ$1)-COLUMN($C$1)<Controls!$B$7)*$C$21:$BJ$21) -> 226170 | BL21: =SUMPRODUCT((YEAR(EDATE(Controls!$B$6,COLUMN($C$1:$BJ$1)-COLUMN($C$1)))=YEAR(Controls!$B$6)+1)*(COLUMN($C$1:$BJ$1)-COLUMN($C$1)<Controls!$B$7)*$C$21:$BJ$21) -> 294021 | BM21: =SUMPRODUCT((YEAR(EDATE(Controls!$B$6,COLUMN($C$1:$BJ$1)-COLUMN($C$1)))=YEAR(Controls!$B$6)+2)*(COLUMN($C$1:$BJ$1)-COLUMN($C$1)<Controls!$B$7)*$C$21:$BJ$21) -> 382227.3 | BN21: =SUMPRODUCT((YEAR(EDATE(Controls!$B$6,COLUMN($C$1:$BJ$1)-COLUMN($C$1)))=YEAR(Controls!$B$6)+3)*(COLUMN($C$1:$BJ$1)-COLUMN($C$1)<Controls!$B$7)*$C$21:$BJ$21) -> 0 | BO21: =SUMPRODUCT((YEAR(EDATE(Controls!$B$6,COLUMN($C$1:$BJ$1)-COLUMN($C$1)))=YEAR(Controls!$B$6)+4)*(COLUMN($C$1:$BJ$1)-COLUMN($C$1)<Controls!$B$7)*$C$21:$BJ$21) -> 0 | BP21: =SUMPRODUCT((YEAR(EDATE(Controls!$B$6,COLUMN($C$1:$BJ$1)-COLUMN($C$1)))=YEAR(Controls!$B$6)+5)*(COLUMN($C$1:$BJ$1)-COLUMN($C$1)<Controls!$B$7)*$C$21:$BJ$21) -> 0
A22: Digital Marketing | B22: $ | C22: =OpEx!C12 -> 8000 | D22: =OpEx!D12 -> 8000 | E22: =OpEx!E12 -> 8000 | F22: =OpEx!F12 -> 8000 | G22: =OpEx!G12 -> 8000 | H22: =OpEx!H12 -> 8000 | I22: =OpEx!I12 -> 8000 | J22: =OpEx!J12 -> 8000 | ... BJ22: =OpEx!BJ12 -> 0 | BK22: =SUMPRODUCT((YEAR(EDATE(Controls!$B$6,COLUMN($C$1:$BJ$1)-COLUMN($C$1)))=YEAR(Controls!$B$6)+0)*(COLUMN($C$1:$BJ$1)-COLUMN($C$1)<Controls!$B$7)*$C$22:$BJ$22) -> 96000 | BL22: =SUMPRODUCT((YEAR(EDATE(Controls!$B$6,COLUMN($C$1:$BJ$1)-COLUMN($C$1)))=YEAR(Controls!$B$6)+1)*(COLUMN($C$1:$BJ$1)-COLUMN($C$1)<Controls!$B$7)*$C$22:$BJ$22) -> 129600 | BM22: =SUMPRODUCT((YEAR(EDATE(Controls!$B$6,COLUMN($C$1:$BJ$1)-COLUMN($C$1)))=YEAR(Controls!$B$6)+2)*(COLUMN($C$1:$BJ$1)-COLUMN($C$1)<Controls!$B$7)*$C$22:$BJ$22) -> 174960 | BN22: =SUMPRODUCT((YEAR(EDATE(Controls!$B$6,COLUMN($C$1:$BJ$1)-COLUMN($C$1)))=YEAR(Controls!$B$6)+3)*(COLUMN($C$1:$BJ$1)-COLUMN($C$1)<Controls!$B$7)*$C$22:$BJ$22) -> 0 | BO22: =SUMPRODUCT((YEAR(EDATE(Controls!$B$6,COLUMN($C$1:$BJ$1)-COLUMN($C$1)))=YEAR(Controls!$B$6)+4)*(COLUMN($C$1:$BJ$1)-COLUMN($C$1)<Controls!$B$7)*$C$22:$BJ$22) -> 0 | BP22: =SUMPRODUCT((YEAR(EDATE(Controls!$B$6,COLUMN($C$1:$BJ$1)-COLUMN($C$1)))=YEAR(Controls!$B$6)+5)*(COLUMN($C$1:$BJ$1)-COLUMN($C$1)<Controls!$B$7)*$C$22:$BJ$22) -> 0
A23: Sales Tools | B23: $ | C23: =OpEx!C13 -> 1500 | D23: =OpEx!D13 -> 1500 | E23: =OpEx!E13 -> 1500 | F23: =OpEx!F13 -> 1500 | G23: =OpEx!G13 -> 1500 | H23: =OpEx!H13 -> 1500 | I23: =OpEx!I13 -> 1500 | J23: =OpEx!J13 -> 1500 | ... BJ23: =OpEx!BJ13 -> 0 | BK23: =SUMPRODUCT((YEAR(EDATE(Controls!$B$6,COLUMN($C$1:$BJ$1)-COLUMN($C$1)))=YEAR(Controls!$B$6)+0)*(COLUMN($C$1:$BJ$1)-COLUMN($C$1)<Controls!$B$7)*$C$23:$BJ$23) -> 18000 | BL23: =SUMPRODUCT((YEAR(EDATE(Controls!$B$6,COLUMN($C$1:$BJ$1)-COLUMN($C$1)))=YEAR(Controls!$B$6)+1)*(COLUMN($C$1:$BJ$1)-COLUMN($C$1)<Controls!$B$7)*$C$23:$BJ$23) -> 24300 | BM23: =SUMPRODUCT((YEAR(EDATE(Controls!$B$6,COLUMN($C$1:$BJ$1)-COLUMN($C$1)))=YEAR(Controls!$B$6)+2)*(COLUMN($C$1:$BJ$1)-COLUMN($C$1)<Controls!$B$7)*$C$23:$BJ$23) -> 32805 | BN23: =SUMPRODUCT((YEAR(EDATE(Controls!$B$6,COLUMN($C$1:$BJ$1)-COLUMN($C$1)))=YEAR(Controls!$B$6)+3)*(COLUMN($C$1:$BJ$1)-COLUMN($C$1)<Controls!$B$7)*$C$23:$BJ$23) -> 0 | BO23: =SUMPRODUCT((YEAR(EDATE(Controls!$B$6,COLUMN($C$1:$BJ$1)-COLUMN($C$1)))=YEAR(Controls!$B$6)+4)*(COLUMN($C$1:$BJ$1)-COLUMN($C$1)<Controls!$B$7)*$C$23:$BJ$23) -> 0 | BP23: =SUMPRODUCT((YEAR(EDATE(Controls!$B$6,COLUMN($C$1:$BJ$1)-COLUMN($C$1)))=YEAR(Controls!$B$6)+5)*(COLUMN($C$1:$BJ$1)-COLUMN($C$1)<Controls!$B$7)*$C$23:$BJ$23) -> 0
A24: Other S&M | B24: $ | C24: =OpEx!C14 -> 2000 | D24: =OpEx!D14 -> 2000 | E24: =OpEx!E14 -> 2000 | F24: =OpEx!F14 -> 2000 | G24: =OpEx!G14 -> 2000 | H24: =OpEx!H14 -> 2000 | I24: =OpEx!I14 -> 2000 | J24: =OpEx!J14 -> 2000 | ... BJ24: =OpEx!BJ14 -> 0 | BK24: =SUMPRODUCT((YEAR(EDATE(Controls!$B$6,COLUMN($C$1:$BJ$1)-COLUMN($C$1)))=YEAR(Controls!$B$6)+0)*(COLUMN($C$1:$BJ$1)-COLUMN($C$1)<Controls!$B$7)*$C$24:$BJ$24) -> 24000 | BL24: =SUMPRODUCT((YEAR(EDATE(Controls!$B$6,COLUMN($C$1:$BJ$1)-COLUMN($C$1)))=YEAR(Controls!$B$6)+1)*(COLUMN($C$1:$BJ$1)-COLUMN($C$1)<Controls!$B$7)*$C$24:$BJ$24) -> 32400 | BM24: =SUMPRODUCT((YEAR(EDATE(Controls!$B$6,COLUMN($C$1:$BJ$1)-COLUMN($C$1)))=YEAR(Controls!$B$6)+2)*(COLUMN($C$1:$BJ$1)-COLUMN($C$1)<Controls!$B$7)*$C$24:$BJ$24) -> 43740 | BN24: =SUMPRODUCT((YEAR(EDATE(Controls!$B$6,COLUMN($C$1:$BJ$1)-COLUMN($C$1)))=YEAR(Controls!$B$6)+3)*(COLUMN($C$1:$BJ$1)-COLUMN($C$1)<Controls!$B$7)*$C$24:$BJ$24) -> 0 | BO24: =SUMPRODUCT((YEAR(EDATE(Controls!$B$6,COLUMN($C$1:$BJ$1)-COLUMN($C$1)))=YEAR(Controls!$B$6)+4)*(COLUMN($C$1:$BJ$1)-COLUMN($C$1)<Controls!$B$7)*$C$24:$BJ$24) -> 0 | BP24: =SUMPRODUCT((YEAR(EDATE(Controls!$B$6,COLUMN($C$1:$BJ$1)-COLUMN($C$1)))=YEAR(Controls!$B$6)+5)*(COLUMN($C$1:$BJ$1)-COLUMN($C$1)<Controls!$B$7)*$C$24:$BJ$24) -> 0
A25: Total Sales & Marketing | B25: $ | C25: =C21+C22+C23+C24 -> 30347.5 | D25: =D21+D22+D23+D24 -> 30347.5 | E25: =E21+E22+E23+E24 -> 30347.5 | F25: =F21+F22+F23+F24 -> 30347.5 | G25: =G21+G22+G23+G24 -> 30347.5 | H25: =H21+H22+H23+H24 -> 30347.5 | I25: =I21+I22+I23+I24 -> 30347.5 | J25: =J21+J22+J23+J24 -> 30347.5 | ... BJ25: =BJ21+BJ22+BJ23+BJ24 -> 0 | BK25: =SUMPRODUCT((YEAR(EDATE(Controls!$B$6,COLUMN($C$1:$BJ$1)-COLUMN($C$1)))=YEAR(Controls!$B$6)+0)*(COLUMN($C$1:$BJ$1)-COLUMN($C$1)<Controls!$B$7)*$C$25:$BJ$25) -> 364170 | BL25: =SUMPRODUCT((YEAR(EDATE(Controls!$B$6,COLUMN($C$1:$BJ$1)-COLUMN($C$1)))=YEAR(Controls!$B$6)+1)*(COLUMN($C$1:$BJ$1)-COLUMN($C$1)<Controls!$B$7)*$C$25:$BJ$25) -> 480321 | BM25: =SUMPRODUCT((YEAR(EDATE(Controls!$B$6,COLUMN($C$1:$BJ$1)-COLUMN($C$1)))=YEAR(Controls!$B$6)+2)*(COLUMN($C$1:$BJ$1)-COLUMN($C$1)<Controls!$B$7)*$C$25:$BJ$25) -> 633732.3 | BN25: =SUMPRODUCT((YEAR(EDATE(Controls!$B$6,COLUMN($C$1:$BJ$1)-COLUMN($C$1)))=YEAR(Controls!$B$6)+3)*(COLUMN($C$1:$BJ$1)-COLUMN($C$1)<Controls!$B$7)*$C$25:$BJ$25) -> 0 | BO25: =SUMPRODUCT((YEAR(EDATE(Controls!$B$6,COLUMN($C$1:$BJ$1)-COLUMN($C$1)))=YEAR(Controls!$B$6)+4)*(COLUMN($C$1:$BJ$1)-COLUMN($C$1)<Controls!$B$7)*$C$25:$BJ$25) -> 0 | BP25: =SUMPRODUCT((YEAR(EDATE(Controls!$B$6,COLUMN($C$1:$BJ$1)-COLUMN($C$1)))=YEAR(Controls!$B$6)+5)*(COLUMN($C$1:$BJ$1)-COLUMN($C$1)<Controls!$B$7)*$C$25:$BJ$25) -> 0
A27: R&D / Engineering
A28: R&D Wages (Loaded) | B28: $ | C28: =Headcount!C20 -> 25130 | D28: =Headcount!D20 -> 25130 | E28: =Headcount!E20 -> 25130 | F28: =Headcount!F20 -> 25130 | G28: =Headcount!G20 -> 25130 | H28: =Headcount!H20 -> 25130 | I28: =Headcount!I20 -> 25130 | J28: =Headcount!J20 -> 25130 | ... BJ28: =Headcount!BJ20 -> 0 | BK28: =SUMPRODUCT((YEAR(EDATE(Controls!$B$6,COLUMN($C$1:$BJ$1)-COLUMN($C$1)))=YEAR(Controls!$B$6)+0)*(COLUMN($C$1:$BJ$1)-COLUMN($C$1)<Controls!$B$7)*$C$28:$BJ$28) -> 301560 | BL28: =SUMPRODUCT((YEAR(EDATE(Controls!$B$6,COLUMN($C$1:$BJ$1)-COLUMN($C$1)))=YEAR(Controls!$B$6)+1)*(COLUMN($C$1:$BJ$1)-COLUMN($C$1)<Controls!$B$7)*$C$28:$BJ$28) -> 376950 | BM28: =SUMPRODUCT((YEAR(EDATE(Controls!$B$6,COLUMN($C$1:$BJ$1)-COLUMN($C$1)))=YEAR(Controls!$B$6)+2)*(COLUMN($C$1:$BJ$1)-COLUMN($C$1)<Controls!$B$7)*$C$28:$BJ$28) -> 471187.5 | BN28: =SUMPRODUCT((YEAR(EDATE(Controls!$B$6,COLUMN($C$1:$BJ$1)-COLUMN($C$1)))=YEAR(Controls!$B$6)+3)*(COLUMN($C$1:$BJ$1)-COLUMN($C$1)<Controls!$B$7)*$C$28:$BJ$28) -> 0 | BO28: =SUMPRODUCT((YEAR(EDATE(Controls!$B$6,COLUMN($C$1:$BJ$1)-COLUMN($C$1)))=YEAR(Controls!$B$6)+4)*(COLUMN($C$1:$BJ$1)-COLUMN($C$1)<Controls!$B$7)*$C$28:$BJ$28) -> 0 | BP28: =SUMPRODUCT((YEAR(EDATE(Controls!$B$6,COLUMN($C$1:$BJ$1)-COLUMN($C$1)))=YEAR(Controls!$B$6)+5)*(COLUMN($C$1:$BJ$1)-COLUMN($C$1)<Controls!$B$7)*$C$28:$BJ$28) -> 0
A29: Cloud Compute | B29: $ | C29: =OpEx!C17 -> 2000 | D29: =OpEx!D17 -> 2000 | E29: =OpEx!E17 -> 2000 | F29: =OpEx!F17 -> 2000 | G29: =OpEx!G17 -> 2000 | H29: =OpEx!H17 -> 2000 | I29: =OpEx!I17 -> 2000 | J29: =OpEx!J17 -> 2000 | ... BJ29: =OpEx!BJ17 -> 0 | BK29: =SUMPRODUCT((YEAR(EDATE(Controls!$B$6,COLUMN($C$1:$BJ$1)-COLUMN($C$1)))=YEAR(Controls!$B$6)+0)*(COLUMN($C$1:$BJ$1)-COLUMN($C$1)<Controls!$B$7)*$C$29:$BJ$29) -> 24000 | BL29: =SUMPRODUCT((YEAR(EDATE(Controls!$B$6,COLUMN($C$1:$BJ$1)-COLUMN($C$1)))=YEAR(Controls!$B$6)+1)*(COLUMN($C$1:$BJ$1)-COLUMN($C$1)<Controls!$B$7)*$C$29:$BJ$29) -> 30000 | BM29: =SUMPRODUCT((YEAR(EDATE(Controls!$B$6,COLUMN($C$1:$BJ$1)-COLUMN($C$1)))=YEAR(Controls!$B$6)+2)*(COLUMN($C$1:$BJ$1)-COLUMN($C$1)<Controls!$B$7)*$C$29:$BJ$29) -> 37500 | BN29: =SUMPRODUCT((YEAR(EDATE(Controls!$B$6,COLUMN($C$1:$BJ$1)-COLUMN($C$1)))=YEAR(Controls!$B$6)+3)*(COLUMN($C$1:$BJ$1)-COLUMN($C$1)<Controls!$B$7)*$C$29:$BJ$29) -> 0 | BO29: =SUMPRODUCT((YEAR(EDATE(Controls!$B$6,COLUMN($C$1:$BJ$1)-COLUMN($C$1)))=YEAR(Controls!$B$6)+4)*(COLUMN($C$1:$BJ$1)-COLUMN($C$1)<Controls!$B$7)*$C$29:$BJ$29) -> 0 | BP29: =SUMPRODUCT((YEAR(EDATE(Controls!$B$6,COLUMN($C$1:$BJ$1)-COLUMN($C$1)))=YEAR(Controls!$B$6)+5)*(COLUMN($C$1:$BJ$1)-COLUMN($C$1)<Controls!$B$7)*$C$29:$BJ$29) -> 0
A30: Dev Tools | B30: $ | C30: =OpEx!C18 -> 1000 | D30: =OpEx!D18 -> 1000 | E30: =OpEx!E18 -> 1000 | F30: =OpEx!F18 -> 1000 | G30: =OpEx!G18 -> 1000 | H30: =OpEx!H18 -> 1000 | I30: =OpEx!I18 -> 1000 | J30: =OpEx!J18 -> 1000 | ... BJ30: =OpEx!BJ18 -> 0 | BK30: =SUMPRODUCT((YEAR(EDATE(Controls!$B$6,COLUMN($C$1:$BJ$1)-COLUMN($C$1)))=YEAR(Controls!$B$6)+0)*(COLUMN($C$1:$BJ$1)-COLUMN($C$1)<Controls!$B$7)*$C$30:$BJ$30) -> 12000 | BL30: =SUMPRODUCT((YEAR(EDATE(Controls!$B$6,COLUMN($C$1:$BJ$1)-COLUMN($C$1)))=YEAR(Controls!$B$6)+1)*(COLUMN($C$1:$BJ$1)-COLUMN($C$1)<Controls!$B$7)*$C$30:$BJ$30) -> 15000 | BM30: =SUMPRODUCT((YEAR(EDATE(Controls!$B$6,COLUMN($C$1:$BJ$1)-COLUMN($C$1)))=YEAR(Controls!$B$6)+2)*(COLUMN($C$1:$BJ$1)-COLUMN($C$1)<Controls!$B$7)*$C$30:$BJ$30) -> 18750 | BN30: =SUMPRODUCT((YEAR(EDATE(Controls!$B$6,COLUMN($C$1:$BJ$1)-COLUMN($C$1)))=YEAR(Controls!$B$6)+3)*(COLUMN($C$1:$BJ$1)-COLUMN($C$1)<Controls!$B$7)*$C$30:$BJ$30) -> 0 | BO30: =SUMPRODUCT((YEAR(EDATE(Controls!$B$6,COLUMN($C$1:$BJ$1)-COLUMN($C$1)))=YEAR(Controls!$B$6)+4)*(COLUMN($C$1:$BJ$1)-COLUMN($C$1)<Controls!$B$7)*$C$30:$BJ$30) -> 0 | BP30: =SUMPRODUCT((YEAR(EDATE(Controls!$B$6,COLUMN($C$1:$BJ$1)-COLUMN($C$1)))=YEAR(Controls!$B$6)+5)*(COLUMN($C$1:$BJ$1)-COLUMN($C$1)<Controls!$B$7)*$C$30:$BJ$30) -> 0
A31: Other R&D | B31: $ | C31: =OpEx!C19 -> 500 | D31: =OpEx!D19 -> 500 | E31: =OpEx!E19 -> 500 | F31: =OpEx!F19 -> 500 | G31: =OpEx!G19 -> 500 | H31: =OpEx!H19 -> 500 | I31: =OpEx!I19 -> 500 | J31: =OpEx!J19 -> 500 | ... BJ31: =OpEx!BJ19 -> 0 | BK31: =SUMPRODUCT((YEAR(EDATE(Controls!$B$6,COLUMN($C$1:$BJ$1)-COLUMN($C$1)))=YEAR(Controls!$B$6)+0)*(COLUMN($C$1:$BJ$1)-COLUMN($C$1)<Controls!$B$7)*$C$31:$BJ$31) -> 6000 | BL31: =SUMPRODUCT((YEAR(EDATE(Controls!$B$6,COLUMN($C$1:$BJ$1)-COLUMN($C$1)))=YEAR(Controls!$B$6)+1)*(COLUMN($C$1:$BJ$1)-COLUMN($C$1)<Controls!$B$7)*$C$31:$BJ$31) -> 7500 | BM31: =SUMPRODUCT((YEAR(EDATE(Controls!$B$6,COLUMN($C$1:$BJ$1)-COLUMN($C$1)))=YEAR(Controls!$B$6)+2)*(COLUMN($C$1:$BJ$1)-COLUMN($C$1)<Controls!$B$7)*$C$31:$BJ$31) -> 9375 | BN31: =SUMPRODUCT((YEAR(EDATE(Controls!$B$6,COLUMN($C$1:$BJ$1)-COLUMN($C$1)))=YEAR(Controls!$B$6)+3)*(COLUMN($C$1:$BJ$1)-COLUMN($C$1)<Controls!$B$7)*$C$31:$BJ$31) -> 0 | BO31: =SUMPRODUCT((YEAR(EDATE(Controls!$B$6,COLUMN($C$1:$BJ$1)-COLUMN($C$1)))=YEAR(Controls!$B$6)+4)*(COLUMN($C$1:$BJ$1)-COLUMN($C$1)<Controls!$B$7)*$C$31:$BJ$31) -> 0 | BP31: =SUMPRODUCT((YEAR(EDATE(Controls!$B$6,COLUMN($C$1:$BJ$1)-COLUMN($C$1)))=YEAR(Controls!$B$6)+5)*(COLUMN($C$1:$BJ$1)-COLUMN($C$1)<Controls!$B$7)*$C$31:$BJ$31) -> 0
A32: Total R&D / Engineering | B32: $ | C32: =C28+C29+C30+C31 -> 28630 | D32: =D28+D29+D30+D31 -> 28630 | E32: =E28+E29+E30+E31 -> 28630 | F32: =F28+F29+F30+F31 -> 28630 | G32: =G28+G29+G30+G31 -> 28630 | H32: =H28+H29+H30+H31 -> 28630 | I32: =I28+I29+I30+I31 -> 28630 | J32: =J28+J29+J30+J31 -> 28630 | ... BJ32: =BJ28+BJ29+BJ30+BJ31 -> 0 | BK32: =SUMPRODUCT((YEAR(EDATE(Controls!$B$6,COLUMN($C$1:$BJ$1)-COLUMN($C$1)))=YEAR(Controls!$B$6)+0)*(COLUMN($C$1:$BJ$1)-COLUMN($C$1)<Controls!$B$7)*$C$32:$BJ$32) -> 343560 | BL32: =SUMPRODUCT((YEAR(EDATE(Controls!$B$6,COLUMN($C$1:$BJ$1)-COLUMN($C$1)))=YEAR(Controls!$B$6)+1)*(COLUMN($C$1:$BJ$1)-COLUMN($C$1)<Controls!$B$7)*$C$32:$BJ$32) -> 429450 | BM32: =SUMPRODUCT((YEAR(EDATE(Controls!$B$6,COLUMN($C$1:$BJ$1)-COLUMN($C$1)))=YEAR(Controls!$B$6)+2)*(COLUMN($C$1:$BJ$1)-COLUMN($C$1)<Controls!$B$7)*$C$32:$BJ$32) -> 536812.5 | BN32: =SUMPRODUCT((YEAR(EDATE(Controls!$B$6,COLUMN($C$1:$BJ$1)-COLUMN($C$1)))=YEAR(Controls!$B$6)+3)*(COLUMN($C$1:$BJ$1)-COLUMN($C$1)<Controls!$B$7)*$C$32:$BJ$32) -> 0 | BO32: =SUMPRODUCT((YEAR(EDATE(Controls!$B$6,COLUMN($C$1:$BJ$1)-COLUMN($C$1)))=YEAR(Controls!$B$6)+4)*(COLUMN($C$1:$BJ$1)-COLUMN($C$1)<Controls!$B$7)*$C$32:$BJ$32) -> 0 | BP32: =SUMPRODUCT((YEAR(EDATE(Controls!$B$6,COLUMN($C$1:$BJ$1)-COLUMN($C$1)))=YEAR(Controls!$B$6)+5)*(COLUMN($C$1:$BJ$1)-COLUMN($C$1)<Controls!$B$7)*$C$32:$BJ$32) -> 0
A34: G&A
A35: G&A Wages (Loaded) | B35: $ | C35: =Headcount!C25 -> 12565 | D35: =Headcount!D25 -> 12565 | E35: =Headcount!E25 -> 12565 | F35: =Headcount!F25 -> 12565 | G35: =Headcount!G25 -> 12565 | H35: =Headcount!H25 -> 12565 | I35: =Headcount!I25 -> 12565 | J35: =Headcount!J25 -> 12565 | ... BJ35: =Headcount!BJ25 -> 0 | BK35: =SUMPRODUCT((YEAR(EDATE(Controls!$B$6,COLUMN($C$1:$BJ$1)-COLUMN($C$1)))=YEAR(Controls!$B$6)+0)*(COLUMN($C$1:$BJ$1)-COLUMN($C$1)<Controls!$B$7)*$C$35:$BJ$35) -> 150780 | BL35: =SUMPRODUCT((YEAR(EDATE(Controls!$B$6,COLUMN($C$1:$BJ$1)-COLUMN($C$1)))=YEAR(Controls!$B$6)+1)*(COLUMN($C$1:$BJ$1)-COLUMN($C$1)<Controls!$B$7)*$C$35:$BJ$35) -> 173397 | BM35: =SUMPRODUCT((YEAR(EDATE(Controls!$B$6,COLUMN($C$1:$BJ$1)-COLUMN($C$1)))=YEAR(Controls!$B$6)+2)*(COLUMN($C$1:$BJ$1)-COLUMN($C$1)<Controls!$B$7)*$C$35:$BJ$35) -> 199406.55 | BN35: =SUMPRODUCT((YEAR(EDATE(Controls!$B$6,COLUMN($C$1:$BJ$1)-COLUMN($C$1)))=YEAR(Controls!$B$6)+3)*(COLUMN($C$1:$BJ$1)-COLUMN($C$1)<Controls!$B$7)*$C$35:$BJ$35) -> 0 | BO35: =SUMPRODUCT((YEAR(EDATE(Controls!$B$6,COLUMN($C$1:$BJ$1)-COLUMN($C$1)))=YEAR(Controls!$B$6)+4)*(COLUMN($C$1:$BJ$1)-COLUMN($C$1)<Controls!$B$7)*$C$35:$BJ$35) -> 0 | BP35: =SUMPRODUCT((YEAR(EDATE(Controls!$B$6,COLUMN($C$1:$BJ$1)-COLUMN($C$1)))=YEAR(Controls!$B$6)+5)*(COLUMN($C$1:$BJ$1)-COLUMN($C$1)<Controls!$B$7)*$C$35:$BJ$35) -> 0
A36: Legal & Compliance | B36: $ | C36: =OpEx!C22 -> 2500 | D36: =OpEx!D22 -> 2500 | E36: =OpEx!E22 -> 2500 | F36: =OpEx!F22 -> 2500 | G36: =OpEx!G22 -> 2500 | H36: =OpEx!H22 -> 2500 | I36: =OpEx!I22 -> 2500 | J36: =OpEx!J22 -> 2500 | ... BJ36: =OpEx!BJ22 -> 0 | BK36: =SUMPRODUCT((YEAR(EDATE(Controls!$B$6,COLUMN($C$1:$BJ$1)-COLUMN($C$1)))=YEAR(Controls!$B$6)+0)*(COLUMN($C$1:$BJ$1)-COLUMN($C$1)<Controls!$B$7)*$C$36:$BJ$36) -> 30000 | BL36: =SUMPRODUCT((YEAR(EDATE(Controls!$B$6,COLUMN($C$1:$BJ$1)-COLUMN($C$1)))=YEAR(Controls!$B$6)+1)*(COLUMN($C$1:$BJ$1)-COLUMN($C$1)<Controls!$B$7)*$C$36:$BJ$36) -> 34500 | BM36: =SUMPRODUCT((YEAR(EDATE(Controls!$B$6,COLUMN($C$1:$BJ$1)-COLUMN($C$1)))=YEAR(Controls!$B$6)+2)*(COLUMN($C$1:$BJ$1)-COLUMN($C$1)<Controls!$B$7)*$C$36:$BJ$36) -> 39675 | BN36: =SUMPRODUCT((YEAR(EDATE(Controls!$B$6,COLUMN($C$1:$BJ$1)-COLUMN($C$1)))=YEAR(Controls!$B$6)+3)*(COLUMN($C$1:$BJ$1)-COLUMN($C$1)<Controls!$B$7)*$C$36:$BJ$36) -> 0 | BO36: =SUMPRODUCT((YEAR(EDATE(Controls!$B$6,COLUMN($C$1:$BJ$1)-COLUMN($C$1)))=YEAR(Controls!$B$6)+4)*(COLUMN($C$1:$BJ$1)-COLUMN($C$1)<Controls!$B$7)*$C$36:$BJ$36) -> 0 | BP36: =SUMPRODUCT((YEAR(EDATE(Controls!$B$6,COLUMN($C$1:$BJ$1)-COLUMN($C$1)))=YEAR(Controls!$B$6)+5)*(COLUMN($C$1:$BJ$1)-COLUMN($C$1)<Controls!$B$7)*$C$36:$BJ$36) -> 0
A37: Finance & Accounting | B37: $ | C37: =OpEx!C23 -> 1500 | D37: =OpEx!D23 -> 1500 | E37: =OpEx!E23 -> 1500 | F37: =OpEx!F23 -> 1500 | G37: =OpEx!G23 -> 1500 | H37: =OpEx!H23 -> 1500 | I37: =OpEx!I23 -> 1500 | J37: =OpEx!J23 -> 1500 | ... BJ37: =OpEx!BJ23 -> 0 | BK37: =SUMPRODUCT((YEAR(EDATE(Controls!$B$6,COLUMN($C$1:$BJ$1)-COLUMN($C$1)))=YEAR(Controls!$B$6)+0)*(COLUMN($C$1:$BJ$1)-COLUMN($C$1)<Controls!$B$7)*$C$37:$BJ$37) -> 18000 | BL37: =SUMPRODUCT((YEAR(EDATE(Controls!$B$6,COLUMN($C$1:$BJ$1)-COLUMN($C$1)))=YEAR(Controls!$B$6)+1)*(COLUMN($C$1:$BJ$1)-COLUMN($C$1)<Controls!$B$7)*$C$37:$BJ$37) -> 20700 | BM37: =SUMPRODUCT((YEAR(EDATE(Controls!$B$6,COLUMN($C$1:$BJ$1)-COLUMN($C$1)))=YEAR(Controls!$B$6)+2)*(COLUMN($C$1:$BJ$1)-COLUMN($C$1)<Controls!$B$7)*$C$37:$BJ$37) -> 23805 | BN37: =SUMPRODUCT((YEAR(EDATE(Controls!$B$6,COLUMN($C$1:$BJ$1)-COLUMN($C$1)))=YEAR(Controls!$B$6)+3)*(COLUMN($C$1:$BJ$1)-COLUMN($C$1)<Controls!$B$7)*$C$37:$BJ$37) -> 0 | BO37: =SUMPRODUCT((YEAR(EDATE(Controls!$B$6,COLUMN($C$1:$BJ$1)-COLUMN($C$1)))=YEAR(Controls!$B$6)+4)*(COLUMN($C$1:$BJ$1)-COLUMN($C$1)<Controls!$B$7)*$C$37:$BJ$37) -> 0 | BP37: =SUMPRODUCT((YEAR(EDATE(Controls!$B$6,COLUMN($C$1:$BJ$1)-COLUMN($C$1)))=YEAR(Controls!$B$6)+5)*(COLUMN($C$1:$BJ$1)-COLUMN($C$1)<Controls!$B$7)*$C$37:$BJ$37) -> 0
A38: Other G&A | B38: $ | C38: =OpEx!C24 -> 2000 | D38: =OpEx!D24 -> 2000 | E38: =OpEx!E24 -> 2000 | F38: =OpEx!F24 -> 2000 | G38: =OpEx!G24 -> 2000 | H38: =OpEx!H24 -> 2000 | I38: =OpEx!I24 -> 2000 | J38: =OpEx!J24 -> 2000 | ... BJ38: =OpEx!BJ24 -> 0 | BK38: =SUMPRODUCT((YEAR(EDATE(Controls!$B$6,COLUMN($C$1:$BJ$1)-COLUMN($C$1)))=YEAR(Controls!$B$6)+0)*(COLUMN($C$1:$BJ$1)-COLUMN($C$1)<Controls!$B$7)*$C$38:$BJ$38) -> 24000 | BL38: =SUMPRODUCT((YEAR(EDATE(Controls!$B$6,COLUMN($C$1:$BJ$1)-COLUMN($C$1)))=YEAR(Controls!$B$6)+1)*(COLUMN($C$1:$BJ$1)-COLUMN($C$1)<Controls!$B$7)*$C$38:$BJ$38) -> 27600 | BM38: =SUMPRODUCT((YEAR(EDATE(Controls!$B$6,COLUMN($C$1:$BJ$1)-COLUMN($C$1)))=YEAR(Controls!$B$6)+2)*(COLUMN($C$1:$BJ$1)-COLUMN($C$1)<Controls!$B$7)*$C$38:$BJ$38) -> 31740 | BN38: =SUMPRODUCT((YEAR(EDATE(Controls!$B$6,COLUMN($C$1:$BJ$1)-COLUMN($C$1)))=YEAR(Controls!$B$6)+3)*(COLUMN($C$1:$BJ$1)-COLUMN($C$1)<Controls!$B$7)*$C$38:$BJ$38) -> 0 | BO38: =SUMPRODUCT((YEAR(EDATE(Controls!$B$6,COLUMN($C$1:$BJ$1)-COLUMN($C$1)))=YEAR(Controls!$B$6)+4)*(COLUMN($C$1:$BJ$1)-COLUMN($C$1)<Controls!$B$7)*$C$38:$BJ$38) -> 0 | BP38: =SUMPRODUCT((YEAR(EDATE(Controls!$B$6,COLUMN($C$1:$BJ$1)-COLUMN($C$1)))=YEAR(Controls!$B$6)+5)*(COLUMN($C$1:$BJ$1)-COLUMN($C$1)<Controls!$B$7)*$C$38:$BJ$38) -> 0
A39: Total G&A | B39: $ | C39: =C35+C36+C37+C38 -> 18565 | D39: =D35+D36+D37+D38 -> 18565 | E39: =E35+E36+E37+E38 -> 18565 | F39: =F35+F36+F37+F38 -> 18565 | G39: =G35+G36+G37+G38 -> 18565 | H39: =H35+H36+H37+H38 -> 18565 | I39: =I35+I36+I37+I38 -> 18565 | J39: =J35+J36+J37+J38 -> 18565 | ... BJ39: =BJ35+BJ36+BJ37+BJ38 -> 0 | BK39: =SUMPRODUCT((YEAR(EDATE(Controls!$B$6,COLUMN($C$1:$BJ$1)-COLUMN($C$1)))=YEAR(Controls!$B$6)+0)*(COLUMN($C$1:$BJ$1)-COLUMN($C$1)<Controls!$B$7)*$C$39:$BJ$39) -> 222780 | BL39: =SUMPRODUCT((YEAR(EDATE(Controls!$B$6,COLUMN($C$1:$BJ$1)-COLUMN($C$1)))=YEAR(Controls!$B$6)+1)*(COLUMN($C$1:$BJ$1)-COLUMN($C$1)<Controls!$B$7)*$C$39:$BJ$39) -> 256197 | BM39: =SUMPRODUCT((YEAR(EDATE(Controls!$B$6,COLUMN($C$1:$BJ$1)-COLUMN($C$1)))=YEAR(Controls!$B$6)+2)*(COLUMN($C$1:$BJ$1)-COLUMN($C$1)<Controls!$B$7)*$C$39:$BJ$39) -> 294626.55 | BN39: =SUMPRODUCT((YEAR(EDATE(Controls!$B$6,COLUMN($C$1:$BJ$1)-COLUMN($C$1)))=YEAR(Controls!$B$6)+3)*(COLUMN($C$1:$BJ$1)-COLUMN($C$1)<Controls!$B$7)*$C$39:$BJ$39) -> 0 | BO39: =SUMPRODUCT((YEAR(EDATE(Controls!$B$6,COLUMN($C$1:$BJ$1)-COLUMN($C$1)))=YEAR(Controls!$B$6)+4)*(COLUMN($C$1:$BJ$1)-COLUMN($C$1)<Controls!$B$7)*$C$39:$BJ$39) -> 0 | BP39: =SUMPRODUCT((YEAR(EDATE(Controls!$B$6,COLUMN($C$1:$BJ$1)-COLUMN($C$1)))=YEAR(Controls!$B$6)+5)*(COLUMN($C$1:$BJ$1)-COLUMN($C$1)<Controls!$B$7)*$C$39:$BJ$39) -> 0
A41: Total Operating Expenses | B41: $ | C41: =C25+C32+C39 -> 77542.5 | D41: =D25+D32+D39 -> 77542.5 | E41: =E25+E32+E39 -> 77542.5 | F41: =F25+F32+F39 -> 77542.5 | G41: =G25+G32+G39 -> 77542.5 | H41: =H25+H32+H39 -> 77542.5 | I41: =I25+I32+I39 -> 77542.5 | J41: =J25+J32+J39 -> 77542.5 | ... BJ41: =BJ25+BJ32+BJ39 -> 0 | BK41: =SUMPRODUCT((YEAR(EDATE(Controls!$B$6,COLUMN($C$1:$BJ$1)-COLUMN($C$1)))=YEAR(Controls!$B$6)+0)*(COLUMN($C$1:$BJ$1)-COLUMN($C$1)<Controls!$B$7)*$C$41:$BJ$41) -> 930510 | BL41: =SUMPRODUCT((YEAR(EDATE(Controls!$B$6,COLUMN($C$1:$BJ$1)-COLUMN($C$1)))=YEAR(Controls!$B$6)+1)*(COLUMN($C$1:$BJ$1)-COLUMN($C$1)<Controls!$B$7)*$C$41:$BJ$41) -> 1165968 | BM41: =SUMPRODUCT((YEAR(EDATE(Controls!$B$6,COLUMN($C$1:$BJ$1)-COLUMN($C$1)))=YEAR(Controls!$B$6)+2)*(COLUMN($C$1:$BJ$1)-COLUMN($C$1)<Controls!$B$7)*$C$41:$BJ$41) -> 1465171.4 | BN41: =SUMPRODUCT((YEAR(EDATE(Controls!$B$6,COLUMN($C$1:$BJ$1)-COLUMN($C$1)))=YEAR(Controls!$B$6)+3)*(COLUMN($C$1:$BJ$1)-COLUMN($C$1)<Controls!$B$7)*$C$41:$BJ$41) -> 0 | BO41: =SUMPRODUCT((YEAR(EDATE(Controls!$B$6,COLUMN($C$1:$BJ$1)-COLUMN($C$1)))=YEAR(Controls!$B$6)+4)*(COLUMN($C$1:$BJ$1)-COLUMN($C$1)<Controls!$B$7)*$C$41:$BJ$41) -> 0 | BP41: =SUMPRODUCT((YEAR(EDATE(Controls!$B$6,COLUMN($C$1:$BJ$1)-COLUMN($C$1)))=YEAR(Controls!$B$6)+5)*(COLUMN($C$1:$BJ$1)-COLUMN($C$1)<Controls!$B$7)*$C$41:$BJ$41) -> 0
A42: EBITDA | B42: $ | C42: =C16-C41 -> -79653.406 | D42: =D16-D41 -> -67297.431 | E42: =E16-E41 -> -51580.351 | F42: =F16-F41 -> -32593.118 | G42: =G16-G41 -> -9951.7899 | H42: =H16-H41 -> 16013.697 | I42: =I16-I41 -> 45506.805 | J42: =J16-J41 -> 77900.321 | ... BJ42: =BJ16-BJ41 -> 5252273.9 | BK42: =SUMPRODUCT((YEAR(EDATE(Controls!$B$6,COLUMN($C$1:$BJ$1)-COLUMN($C$1)))=YEAR(Controls!$B$6)+0)*(COLUMN($C$1:$BJ$1)-COLUMN($C$1)<Controls!$B$7)*$C$42:$BJ$42) -> 604264.89 | BL42: =SUMPRODUCT((YEAR(EDATE(Controls!$B$6,COLUMN($C$1:$BJ$1)-COLUMN($C$1)))=YEAR(Controls!$B$6)+1)*(COLUMN($C$1:$BJ$1)-COLUMN($C$1)<Controls!$B$7)*$C$42:$BJ$42) -> 7935606.3 | BM42: =SUMPRODUCT((YEAR(EDATE(Controls!$B$6,COLUMN($C$1:$BJ$1)-COLUMN($C$1)))=YEAR(Controls!$B$6)+2)*(COLUMN($C$1:$BJ$1)-COLUMN($C$1)<Controls!$B$7)*$C$42:$BJ$42) -> 25301153 | BN42: =SUMPRODUCT((YEAR(EDATE(Controls!$B$6,COLUMN($C$1:$BJ$1)-COLUMN($C$1)))=YEAR(Controls!$B$6)+3)*(COLUMN($C$1:$BJ$1)-COLUMN($C$1)<Controls!$B$7)*$C$42:$BJ$42) -> 0 | BO42: =SUMPRODUCT((YEAR(EDATE(Controls!$B$6,COLUMN($C$1:$BJ$1)-COLUMN($C$1)))=YEAR(Controls!$B$6)+4)*(COLUMN($C$1:$BJ$1)-COLUMN($C$1)<Controls!$B$7)*$C$42:$BJ$42) -> 0 | BP42: =SUMPRODUCT((YEAR(EDATE(Controls!$B$6,COLUMN($C$1:$BJ$1)-COLUMN($C$1)))=YEAR(Controls!$B$6)+5)*(COLUMN($C$1:$BJ$1)-COLUMN($C$1)<Controls!$B$7)*$C$42:$BJ$42) -> 0
A43: EBITDA Margin % | B43: % | C43: =IFERROR(C42/C8,0) -> -5.8178993 | D43: =IFERROR(D42/D8,0) -> -2.5664425 | E43: =IFERROR(E42/E8,0) -> -1.2247749 | F43: =IFERROR(F42/F8,0) -> -0.53190342 | G43: =IFERROR(G42/G8,0) -> -0.11834307 | H43: =IFERROR(H42/H8,0) -> 0.14527109 | I43: =IFERROR(I42/I8,0) -> 0.32527792 | J43: =IFERROR(J42/J8,0) -> 0.45167508 | ... BJ43: =IFERROR(BJ42/BJ8,0) -> 0.99787213 | BK43: =IFERROR(SUMPRODUCT((YEAR(EDATE(Controls!$B$6,COLUMN($C$1:$BJ$1)-COLUMN($C$1)))=YEAR(Controls!$B$6)+0)*(COLUMN($C$1:$BJ$1)-COLUMN($C$1)<Controls!$B$7)*$C$43:$BJ$43)/SUMPRODUCT((YEAR(EDATE(Controls!$B$6,COLUMN($C$1:$BJ$1)-COLUMN($C$1)))=YEAR(Controls!$B$6)+0)*(COLUMN($C$1:$BJ$1)-COLUMN($C$1)<Controls!$B$7)*1),0) -> -0.56517301 | BL43: =IFERROR(SUMPRODUCT((YEAR(EDATE(Controls!$B$6,COLUMN($C$1:$BJ$1)-COLUMN($C$1)))=YEAR(Controls!$B$6)+1)*(COLUMN($C$1:$BJ$1)-COLUMN($C$1)<Controls!$B$7)*$C$43:$BJ$43)/SUMPRODUCT((YEAR(EDATE(Controls!$B$6,COLUMN($C$1:$BJ$1)-COLUMN($C$1)))=YEAR(Controls!$B$6)+1)*(COLUMN($C$1:$BJ$1)-COLUMN($C$1)<Controls!$B$7)*1),0) -> 0.8264803 | BM43: =IFERROR(SUMPRODUCT((YEAR(EDATE(Controls!$B$6,COLUMN($C$1:$BJ$1)-COLUMN($C$1)))=YEAR(Controls!$B$6)+2)*(COLUMN($C$1:$BJ$1)-COLUMN($C$1)<Controls!$B$7)*$C$43:$BJ$43)/SUMPRODUCT((YEAR(EDATE(Controls!$B$6,COLUMN($C$1:$BJ$1)-COLUMN($C$1)))=YEAR(Controls!$B$6)+2)*(COLUMN($C$1:$BJ$1)-COLUMN($C$1)<Controls!$B$7)*1),0) -> 0.92909531 | BN43: =IFERROR(SUMPRODUCT((YEAR(EDATE(Controls!$B$6,COLUMN($C$1:$BJ$1)-COLUMN($C$1)))=YEAR(Controls!$B$6)+3)*(COLUMN($C$1:$BJ$1)-COLUMN($C$1)<Controls!$B$7)*$C$43:$BJ$43)/SUMPRODUCT((YEAR(EDATE(Controls!$B$6,COLUMN($C$1:$BJ$1)-COLUMN($C$1)))=YEAR(Controls!$B$6)+3)*(COLUMN($C$1:$BJ$1)-COLUMN($C$1)<Controls!$B$7)*1),0) -> 0 | BO43: =IFERROR(SUMPRODUCT((YEAR(EDATE(Controls!$B$6,COLUMN($C$1:$BJ$1)-COLUMN($C$1)))=YEAR(Controls!$B$6)+4)*(COLUMN($C$1:$BJ$1)-COLUMN($C$1)<Controls!$B$7)*$C$43:$BJ$43)/SUMPRODUCT((YEAR(EDATE(Controls!$B$6,COLUMN($C$1:$BJ$1)-COLUMN($C$1)))=YEAR(Controls!$B$6)+4)*(COLUMN($C$1:$BJ$1)-COLUMN($C$1)<Controls!$B$7)*1),0) -> 0 | BP43: =IFERROR(SUMPRODUCT((YEAR(EDATE(Controls!$B$6,COLUMN($C$1:$BJ$1)-COLUMN($C$1)))=YEAR(Controls!$B$6)+5)*(COLUMN($C$1:$BJ$1)-COLUMN($C$1)<Controls!$B$7)*$C$43:$BJ$43)/SUMPRODUCT((YEAR(EDATE(Controls!$B$6,COLUMN($C$1:$BJ$1)-COLUMN($C$1)))=YEAR(Controls!$B$6)+5)*(COLUMN($C$1:$BJ$1)-COLUMN($C$1)<Controls!$B$7)*1),0) -> 0
A45: Depreciation | B45: $ | C45: =OpEx!C27 -> 0 | D45: =OpEx!D27 -> 0 | E45: =OpEx!E27 -> 0 | F45: =OpEx!F27 -> 0 | G45: =OpEx!G27 -> 0 | H45: =OpEx!H27 -> 0 | I45: =OpEx!I27 -> 138.88889 | J45: =OpEx!J27 -> 0 | ... BJ45: =OpEx!BJ27 -> 0 | BK45: =SUMPRODUCT((YEAR(EDATE(Controls!$B$6,COLUMN($C$1:$BJ$1)-COLUMN($C$1)))=YEAR(Controls!$B$6)+0)*(COLUMN($C$1:$BJ$1)-COLUMN($C$1)<Controls!$B$7)*$C$45:$BJ$45) -> 138.88889 | BL45: =SUMPRODUCT((YEAR(EDATE(Controls!$B$6,COLUMN($C$1:$BJ$1)-COLUMN($C$1)))=YEAR(Controls!$B$6)+1)*(COLUMN($C$1:$BJ$1)-COLUMN($C$1)<Controls!$B$7)*$C$45:$BJ$45) -> 0 | BM45: =SUMPRODUCT((YEAR(EDATE(Controls!$B$6,COLUMN($C$1:$BJ$1)-COLUMN($C$1)))=YEAR(Controls!$B$6)+2)*(COLUMN($C$1:$BJ$1)-COLUMN($C$1)<Controls!$B$7)*$C$45:$BJ$45) -> 0 | BN45: =SUMPRODUCT((YEAR(EDATE(Controls!$B$6,COLUMN($C$1:$BJ$1)-COLUMN($C$1)))=YEAR(Controls!$B$6)+3)*(COLUMN($C$1:$BJ$1)-COLUMN($C$1)<Controls!$B$7)*$C$45:$BJ$45) -> 0 | BO45: =SUMPRODUCT((YEAR(EDATE(Controls!$B$6,COLUMN($C$1:$BJ$1)-COLUMN($C$1)))=YEAR(Controls!$B$6)+4)*(COLUMN($C$1:$BJ$1)-COLUMN($C$1)<Controls!$B$7)*$C$45:$BJ$45) -> 0 | BP45: =SUMPRODUCT((YEAR(EDATE(Controls!$B$6,COLUMN($C$1:$BJ$1)-COLUMN($C$1)))=YEAR(Controls!$B$6)+5)*(COLUMN($C$1:$BJ$1)-COLUMN($C$1)<Controls!$B$7)*$C$45:$BJ$45) -> 0
A46: EBIT (Operating Income) | B46: $ | C46: =C42-C45 -> -79653.406 | D46: =D42-D45 -> -67297.431 | E46: =E42-E45 -> -51580.351 | F46: =F42-F45 -> -32593.118 | G46: =G42-G45 -> -9951.7899 | H46: =H42-H45 -> 16013.697 | I46: =I42-I45 -> 45367.916 | J46: =J42-J45 -> 77900.321 | ... BJ46: =BJ42-BJ45 -> 5252273.9 | BK46: =SUMPRODUCT((YEAR(EDATE(Controls!$B$6,COLUMN($C$1:$BJ$1)-COLUMN($C$1)))=YEAR(Controls!$B$6)+0)*(COLUMN($C$1:$BJ$1)-COLUMN($C$1)<Controls!$B$7)*$C$46:$BJ$46) -> 604126 | BL46: =SUMPRODUCT((YEAR(EDATE(Controls!$B$6,COLUMN($C$1:$BJ$1)-COLUMN($C$1)))=YEAR(Controls!$B$6)+1)*(COLUMN($C$1:$BJ$1)-COLUMN($C$1)<Controls!$B$7)*$C$46:$BJ$46) -> 7935606.3 | BM46: =SUMPRODUCT((YEAR(EDATE(Controls!$B$6,COLUMN($C$1:$BJ$1)-COLUMN($C$1)))=YEAR(Controls!$B$6)+2)*(COLUMN($C$1:$BJ$1)-COLUMN($C$1)<Controls!$B$7)*$C$46:$BJ$46) -> 25301153 | BN46: =SUMPRODUCT((YEAR(EDATE(Controls!$B$6,COLUMN($C$1:$BJ$1)-COLUMN($C$1)))=YEAR(Controls!$B$6)+3)*(COLUMN($C$1:$BJ$1)-COLUMN($C$1)<Controls!$B$7)*$C$46:$BJ$46) -> 0 | BO46: =SUMPRODUCT((YEAR(EDATE(Controls!$B$6,COLUMN($C$1:$BJ$1)-COLUMN($C$1)))=YEAR(Controls!$B$6)+4)*(COLUMN($C$1:$BJ$1)-COLUMN($C$1)<Controls!$B$7)*$C$46:$BJ$46) -> 0 | BP46: =SUMPRODUCT((YEAR(EDATE(Controls!$B$6,COLUMN($C$1:$BJ$1)-COLUMN($C$1)))=YEAR(Controls!$B$6)+5)*(COLUMN($C$1:$BJ$1)-COLUMN($C$1)<Controls!$B$7)*$C$46:$BJ$46) -> 0
A47: Interest Expense | B47: $ | C47: =IFERROR(Controls!$B$20*Controls!$B$21/12,0) -> 0 | D47: =IFERROR(Controls!$B$20*Controls!$B$21/12,0) -> 0 | E47: =IFERROR(Controls!$B$20*Controls!$B$21/12,0) -> 0 | F47: =IFERROR(Controls!$B$20*Controls!$B$21/12,0) -> 0 | G47: =IFERROR(Controls!$B$20*Controls!$B$21/12,0) -> 0 | H47: =IFERROR(Controls!$B$20*Controls!$B$21/12,0) -> 0 | I47: =IFERROR(Controls!$B$20*Controls!$B$21/12,0) -> 0 | J47: =IFERROR(Controls!$B$20*Controls!$B$21/12,0) -> 0 | ... BJ47: =IFERROR(Controls!$B$20*Controls!$B$21/12,0) -> 0 | BK47: =SUMPRODUCT((YEAR(EDATE(Controls!$B$6,COLUMN($C$1:$BJ$1)-COLUMN($C$1)))=YEAR(Controls!$B$6)+0)*(COLUMN($C$1:$BJ$1)-COLUMN($C$1)<Controls!$B$7)*$C$47:$BJ$47) -> 0 | BL47: =SUMPRODUCT((YEAR(EDATE(Controls!$B$6,COLUMN($C$1:$BJ$1)-COLUMN($C$1)))=YEAR(Controls!$B$6)+1)*(COLUMN($C$1:$BJ$1)-COLUMN($C$1)<Controls!$B$7)*$C$47:$BJ$47) -> 0 | BM47: =SUMPRODUCT((YEAR(EDATE(Controls!$B$6,COLUMN($C$1:$BJ$1)-COLUMN($C$1)))=YEAR(Controls!$B$6)+2)*(COLUMN($C$1:$BJ$1)-COLUMN($C$1)<Controls!$B$7)*$C$47:$BJ$47) -> 0 | BN47: =SUMPRODUCT((YEAR(EDATE(Controls!$B$6,COLUMN($C$1:$BJ$1)-COLUMN($C$1)))=YEAR(Controls!$B$6)+3)*(COLUMN($C$1:$BJ$1)-COLUMN($C$1)<Controls!$B$7)*$C$47:$BJ$47) -> 0 | BO47: =SUMPRODUCT((YEAR(EDATE(Controls!$B$6,COLUMN($C$1:$BJ$1)-COLUMN($C$1)))=YEAR(Controls!$B$6)+4)*(COLUMN($C$1:$BJ$1)-COLUMN($C$1)<Controls!$B$7)*$C$47:$BJ$47) -> 0 | BP47: =SUMPRODUCT((YEAR(EDATE(Controls!$B$6,COLUMN($C$1:$BJ$1)-COLUMN($C$1)))=YEAR(Controls!$B$6)+5)*(COLUMN($C$1:$BJ$1)-COLUMN($C$1)<Controls!$B$7)*$C$47:$BJ$47) -> 0
A48: EBT (Pre-Tax Income) | B48: $ | C48: =C46-C47 -> -79653.406 | D48: =D46-D47 -> -67297.431 | E48: =E46-E47 -> -51580.351 | F48: =F46-F47 -> -32593.118 | G48: =G46-G47 -> -9951.7899 | H48: =H46-H47 -> 16013.697 | I48: =I46-I47 -> 45367.916 | J48: =J46-J47 -> 77900.321 | ... BJ48: =BJ46-BJ47 -> 5252273.9 | BK48: =SUMPRODUCT((YEAR(EDATE(Controls!$B$6,COLUMN($C$1:$BJ$1)-COLUMN($C$1)))=YEAR(Controls!$B$6)+0)*(COLUMN($C$1:$BJ$1)-COLUMN($C$1)<Controls!$B$7)*$C$48:$BJ$48) -> 604126 | BL48: =SUMPRODUCT((YEAR(EDATE(Controls!$B$6,COLUMN($C$1:$BJ$1)-COLUMN($C$1)))=YEAR(Controls!$B$6)+1)*(COLUMN($C$1:$BJ$1)-COLUMN($C$1)<Controls!$B$7)*$C$48:$BJ$48) -> 7935606.3 | BM48: =SUMPRODUCT((YEAR(EDATE(Controls!$B$6,COLUMN($C$1:$BJ$1)-COLUMN($C$1)))=YEAR(Controls!$B$6)+2)*(COLUMN($C$1:$BJ$1)-COLUMN($C$1)<Controls!$B$7)*$C$48:$BJ$48) -> 25301153 | BN48: =SUMPRODUCT((YEAR(EDATE(Controls!$B$6,COLUMN($C$1:$BJ$1)-COLUMN($C$1)))=YEAR(Controls!$B$6)+3)*(COLUMN($C$1:$BJ$1)-COLUMN($C$1)<Controls!$B$7)*$C$48:$BJ$48) -> 0 | BO48: =SUMPRODUCT((YEAR(EDATE(Controls!$B$6,COLUMN($C$1:$BJ$1)-COLUMN($C$1)))=YEAR(Controls!$B$6)+4)*(COLUMN($C$1:$BJ$1)-COLUMN($C$1)<Controls!$B$7)*$C$48:$BJ$48) -> 0 | BP48: =SUMPRODUCT((YEAR(EDATE(Controls!$B$6,COLUMN($C$1:$BJ$1)-COLUMN($C$1)))=YEAR(Controls!$B$6)+5)*(COLUMN($C$1:$BJ$1)-COLUMN($C$1)<Controls!$B$7)*$C$48:$BJ$48) -> 0
A49: Income Tax Provision | B49: $ | C49: =MAX(0,C48*Controls!$B$8) -> 0 | D49: =MAX(0,D48*Controls!$B$8) -> 0 | E49: =MAX(0,E48*Controls!$B$8) -> 0 | F49: =MAX(0,F48*Controls!$B$8) -> 0 | G49: =MAX(0,G48*Controls!$B$8) -> 0 | H49: =MAX(0,H48*Controls!$B$8) -> 4003.4243 | I49: =MAX(0,I48*Controls!$B$8) -> 11341.979 | J49: =MAX(0,J48*Controls!$B$8) -> 19475.08 | ... BJ49: =MAX(0,BJ48*Controls!$B$8) -> 1313068.5 | BK49: =SUMPRODUCT((YEAR(EDATE(Controls!$B$6,COLUMN($C$1:$BJ$1)-COLUMN($C$1)))=YEAR(Controls!$B$6)+0)*(COLUMN($C$1:$BJ$1)-COLUMN($C$1)<Controls!$B$7)*$C$49:$BJ$49) -> 211300.52 | BL49: =SUMPRODUCT((YEAR(EDATE(Controls!$B$6,COLUMN($C$1:$BJ$1)-COLUMN($C$1)))=YEAR(Controls!$B$6)+1)*(COLUMN($C$1:$BJ$1)-COLUMN($C$1)<Controls!$B$7)*$C$49:$BJ$49) -> 1983901.6 | BM49: =SUMPRODUCT((YEAR(EDATE(Controls!$B$6,COLUMN($C$1:$BJ$1)-COLUMN($C$1)))=YEAR(Controls!$B$6)+2)*(COLUMN($C$1:$BJ$1)-COLUMN($C$1)<Controls!$B$7)*$C$49:$BJ$49) -> 6325288.4 | BN49: =SUMPRODUCT((YEAR(EDATE(Controls!$B$6,COLUMN($C$1:$BJ$1)-COLUMN($C$1)))=YEAR(Controls!$B$6)+3)*(COLUMN($C$1:$BJ$1)-COLUMN($C$1)<Controls!$B$7)*$C$49:$BJ$49) -> 0 | BO49: =SUMPRODUCT((YEAR(EDATE(Controls!$B$6,COLUMN($C$1:$BJ$1)-COLUMN($C$1)))=YEAR(Controls!$B$6)+4)*(COLUMN($C$1:$BJ$1)-COLUMN($C$1)<Controls!$B$7)*$C$49:$BJ$49) -> 0 | BP49: =SUMPRODUCT((YEAR(EDATE(Controls!$B$6,COLUMN($C$1:$BJ$1)-COLUMN($C$1)))=YEAR(Controls!$B$6)+5)*(COLUMN($C$1:$BJ$1)-COLUMN($C$1)<Controls!$B$7)*$C$49:$BJ$49) -> 0
A50: NET INCOME | B50: $ | C50: =C48-C49 -> -79653.406 | D50: =D48-D49 -> -67297.431 | E50: =E48-E49 -> -51580.351 | F50: =F48-F49 -> -32593.118 | G50: =G48-G49 -> -9951.7899 | H50: =H48-H49 -> 12010.273 | I50: =I48-I49 -> 34025.937 | J50: =J48-J49 -> 58425.24 | ... BJ50: =BJ48-BJ49 -> 3939205.5 | BK50: =SUMPRODUCT((YEAR(EDATE(Controls!$B$6,COLUMN($C$1:$BJ$1)-COLUMN($C$1)))=YEAR(Controls!$B$6)+0)*(COLUMN($C$1:$BJ$1)-COLUMN($C$1)<Controls!$B$7)*$C$50:$BJ$50) -> 392825.48 | BL50: =SUMPRODUCT((YEAR(EDATE(Controls!$B$6,COLUMN($C$1:$BJ$1)-COLUMN($C$1)))=YEAR(Controls!$B$6)+1)*(COLUMN($C$1:$BJ$1)-COLUMN($C$1)<Controls!$B$7)*$C$50:$BJ$50) -> 5951704.7 | BM50: =SUMPRODUCT((YEAR(EDATE(Controls!$B$6,COLUMN($C$1:$BJ$1)-COLUMN($C$1)))=YEAR(Controls!$B$6)+2)*(COLUMN($C$1:$BJ$1)-COLUMN($C$1)<Controls!$B$7)*$C$50:$BJ$50) -> 18975865 | BN50: =SUMPRODUCT((YEAR(EDATE(Controls!$B$6,COLUMN($C$1:$BJ$1)-COLUMN($C$1)))=YEAR(Controls!$B$6)+3)*(COLUMN($C$1:$BJ$1)-COLUMN($C$1)<Controls!$B$7)*$C$50:$BJ$50) -> 0 | BO50: =SUMPRODUCT((YEAR(EDATE(Controls!$B$6,COLUMN($C$1:$BJ$1)-COLUMN($C$1)))=YEAR(Controls!$B$6)+4)*(COLUMN($C$1:$BJ$1)-COLUMN($C$1)<Controls!$B$7)*$C$50:$BJ$50) -> 0 | BP50: =SUMPRODUCT((YEAR(EDATE(Controls!$B$6,COLUMN($C$1:$BJ$1)-COLUMN($C$1)))=YEAR(Controls!$B$6)+5)*(COLUMN($C$1:$BJ$1)-COLUMN($C$1)<Controls!$B$7)*$C$50:$BJ$50) -> 0
A51: Net Margin % | B51: % | C51: =IFERROR(C50/C8,0) -> -5.8178993 | D51: =IFERROR(D50/D8,0) -> -2.5664425 | E51: =IFERROR(E50/E8,0) -> -1.2247749 | F51: =IFERROR(F50/F8,0) -> -0.53190342 | G51: =IFERROR(G50/G8,0) -> -0.11834307 | H51: =IFERROR(H50/H8,0) -> 0.10895332 | I51: =IFERROR(I50/I8,0) -> 0.24321386 | J51: =IFERROR(J50/J8,0) -> 0.33875631 | ... BJ51: =IFERROR(BJ50/BJ8,0) -> 0.7484041 | BK51: =IFERROR(SUMPRODUCT((YEAR(EDATE(Controls!$B$6,COLUMN($C$1:$BJ$1)-COLUMN($C$1)))=YEAR(Controls!$B$6)+0)*(COLUMN($C$1:$BJ$1)-COLUMN($C$1)<Controls!$B$7)*$C$51:$BJ$51)/SUMPRODUCT((YEAR(EDATE(Controls!$B$6,COLUMN($C$1:$BJ$1)-COLUMN($C$1)))=YEAR(Controls!$B$6)+0)*(COLUMN($C$1:$BJ$1)-COLUMN($C$1)<Controls!$B$7)*1),0) -> -0.63767854 | BL51: =IFERROR(SUMPRODUCT((YEAR(EDATE(Controls!$B$6,COLUMN($C$1:$BJ$1)-COLUMN($C$1)))=YEAR(Controls!$B$6)+1)*(COLUMN($C$1:$BJ$1)-COLUMN($C$1)<Controls!$B$7)*$C$51:$BJ$51)/SUMPRODUCT((YEAR(EDATE(Controls!$B$6,COLUMN($C$1:$BJ$1)-COLUMN($C$1)))=YEAR(Controls!$B$6)+1)*(COLUMN($C$1:$BJ$1)-COLUMN($C$1)<Controls!$B$7)*1),0) -> 0.61986022 | BM51: =IFERROR(SUMPRODUCT((YEAR(EDATE(Controls!$B$6,COLUMN($C$1:$BJ$1)-COLUMN($C$1)))=YEAR(Controls!$B$6)+2)*(COLUMN($C$1:$BJ$1)-COLUMN($C$1)<Controls!$B$7)*$C$51:$BJ$51)/SUMPRODUCT((YEAR(EDATE(Controls!$B$6,COLUMN($C$1:$BJ$1)-COLUMN($C$1)))=YEAR(Controls!$B$6)+2)*(COLUMN($C$1:$BJ$1)-COLUMN($C$1)<Controls!$B$7)*1),0) -> 0.69682148 | BN51: =IFERROR(SUMPRODUCT((YEAR(EDATE(Controls!$B$6,COLUMN($C$1:$BJ$1)-COLUMN($C$1)))=YEAR(Controls!$B$6)+3)*(COLUMN($C$1:$BJ$1)-COLUMN($C$1)<Controls!$B$7)*$C$51:$BJ$51)/SUMPRODUCT((YEAR(EDATE(Controls!$B$6,COLUMN($C$1:$BJ$1)-COLUMN($C$1)))=YEAR(Controls!$B$6)+3)*(COLUMN($C$1:$BJ$1)-COLUMN($C$1)<Controls!$B$7)*1),0) -> 0 | BO51: =IFERROR(SUMPRODUCT((YEAR(EDATE(Controls!$B$6,COLUMN($C$1:$BJ$1)-COLUMN($C$1)))=YEAR(Controls!$B$6)+4)*(COLUMN($C$1:$BJ$1)-COLUMN($C$1)<Controls!$B$7)*$C$51:$BJ$51)/SUMPRODUCT((YEAR(EDATE(Controls!$B$6,COLUMN($C$1:$BJ$1)-COLUMN($C$1)))=YEAR(Controls!$B$6)+4)*(COLUMN($C$1:$BJ$1)-COLUMN($C$1)<Controls!$B$7)*1),0) -> 0 | BP51: =IFERROR(SUMPRODUCT((YEAR(EDATE(Controls!$B$6,COLUMN($C$1:$BJ$1)-COLUMN($C$1)))=YEAR(Controls!$B$6)+5)*(COLUMN($C$1:$BJ$1)-COLUMN($C$1)<Controls!$B$7)*$C$51:$BJ$51)/SUMPRODUCT((YEAR(EDATE(Controls!$B$6,COLUMN($C$1:$BJ$1)-COLUMN($C$1)))=YEAR(Controls!$B$6)+5)*(COLUMN($C$1:$BJ$1)-COLUMN($C$1)<Controls!$B$7)*1),0) -> 0

Sheet Cash Flow
A1: CASH FLOW STATEMENT · Operating / Investing / Financing · Burn Rate & Runway
A3: Label | B3: Unit | C3: =TEXT(EDATE(Controls!$B$6,0),"mmm-yy") -> Jan-26 | D3: =TEXT(EDATE(Controls!$B$6,1),"mmm-yy") -> Feb-26 | E3: =TEXT(EDATE(Controls!$B$6,2),"mmm-yy") -> Mar-26 | F3: =TEXT(EDATE(Controls!$B$6,3),"mmm-yy") -> Apr-26 | G3: =TEXT(EDATE(Controls!$B$6,4),"mmm-yy") -> May-26 | H3: =TEXT(EDATE(Controls!$B$6,5),"mmm-yy") -> Jun-26 | I3: =TEXT(EDATE(Controls!$B$6,6),"mmm-yy") -> Jul-26 | J3: =TEXT(EDATE(Controls!$B$6,7),"mmm-yy") -> Aug-26 | K3: =TEXT(EDATE(Controls!$B$6,8),"mmm-yy") -> Sep-26 | L3: =TEXT(EDATE(Controls!$B$6,9),"mmm-yy") -> Oct-26 | M3: =TEXT(EDATE(Controls!$B$6,10),"mmm-yy") -> Nov-26 | N3: =TEXT(EDATE(Controls!$B$6,11),"mmm-yy") -> Dec-26 | O3: =TEXT(EDATE(Controls!$B$6,12),"mmm-yy") -> Jan-27 | P3: =TEXT(EDATE(Controls!$B$6,13),"mmm-yy") -> Feb-27 | Q3: =TEXT(EDATE(Controls!$B$6,14),"mmm-yy") -> Mar-27 | R3: =TEXT(EDATE(Controls!$B$6,15),"mmm-yy") -> Apr-27 | S3: =TEXT(EDATE(Controls!$B$6,16),"mmm-yy") -> May-27 | T3: =TEXT(EDATE(Controls!$B$6,17),"mmm-yy") -> Jun-27 | U3: =TEXT(EDATE(Controls!$B$6,18),"mmm-yy") -> Jul-27 | V3: =TEXT(EDATE(Controls!$B$6,19),"mmm-yy") -> Aug-27 | W3: =TEXT(EDATE(Controls!$B$6,20),"mmm-yy") -> Sep-27 | X3: =TEXT(EDATE(Controls!$B$6,21),"mmm-yy") -> Oct-27 | Y3: =TEXT(EDATE(Controls!$B$6,22),"mmm-yy") -> Nov-27 | Z3: =TEXT(EDATE(Controls!$B$6,23),"mmm-yy") -> Dec-27 | AA3: =TEXT(EDATE(Controls!$B$6,24),"mmm-yy") -> Jan-28 | AB3: =TEXT(EDATE(Controls!$B$6,25),"mmm-yy") -> Feb-28 | AC3: =TEXT(EDATE(Controls!$B$6,26),"mmm-yy") -> Mar-28 | AD3: =TEXT(EDATE(Controls!$B$6,27),"mmm-yy") -> Apr-28 | AE3: =TEXT(EDATE(Controls!$B$6,28),"mmm-yy") -> May-28 | AF3: =TEXT(EDATE(Controls!$B$6,29),"mmm-yy") -> Jun-28 | AG3: =TEXT(EDATE(Controls!$B$6,30),"mmm-yy") -> Jul-28 | AH3: =TEXT(EDATE(Controls!$B$6,31),"mmm-yy") -> Aug-28 | AI3: =TEXT(EDATE(Controls!$B$6,32),"mmm-yy") -> Sep-28 | AJ3: =TEXT(EDATE(Controls!$B$6,33),"mmm-yy") -> Oct-28 | AK3: =TEXT(EDATE(Controls!$B$6,34),"mmm-yy") -> Nov-28 | AL3: =TEXT(EDATE(Controls!$B$6,35),"mmm-yy") -> Dec-28 | AM3: =TEXT(EDATE(Controls!$B$6,36),"mmm-yy") -> Jan-29 | AN3: =TEXT(EDATE(Controls!$B$6,37),"mmm-yy") -> Feb-29 | AO3: =TEXT(EDATE(Controls!$B$6,38),"mmm-yy") -> Mar-29 | AP3: =TEXT(EDATE(Controls!$B$6,39),"mmm-yy") -> Apr-29 | AQ3: =TEXT(EDATE(Controls!$B$6,40),"mmm-yy") -> May-29 | AR3: =TEXT(EDATE(Controls!$B$6,41),"mmm-yy") -> Jun-29 | AS3: =TEXT(EDATE(Controls!$B$6,42),"mmm-yy") -> Jul-29 | AT3: =TEXT(EDATE(Controls!$B$6,43),"mmm-yy") -> Aug-29 | AU3: =TEXT(EDATE(Controls!$B$6,44),"mmm-yy") -> Sep-29 | AV3: =TEXT(EDATE(Controls!$B$6,45),"mmm-yy") -> Oct-29 | AW3: =TEXT(EDATE(Controls!$B$6,46),"mmm-yy") -> Nov-29 | AX3: =TEXT(EDATE(Controls!$B$6,47),"mmm-yy") -> Dec-29 | AY3: =TEXT(EDATE(Controls!$B$6,48),"mmm-yy") -> Jan-30 | AZ3: =TEXT(EDATE(Controls!$B$6,49),"mmm-yy") -> Feb-30 | BA3: =TEXT(EDATE(Controls!$B$6,50),"mmm-yy") -> Mar-30 | BB3: =TEXT(EDATE(Controls!$B$6,51),"mmm-yy") -> Apr-30 | BC3: =TEXT(EDATE(Controls!$B$6,52),"mmm-yy") -> May-30 | BD3: =TEXT(EDATE(Controls!$B$6,53),"mmm-yy") -> Jun-30 | BE3: =TEXT(EDATE(Controls!$B$6,54),"mmm-yy") -> Jul-30 | BF3: =TEXT(EDATE(Controls!$B$6,55),"mmm-yy") -> Aug-30 | BG3: =TEXT(EDATE(Controls!$B$6,56),"mmm-yy") -> Sep-30 | BH3: =TEXT(EDATE(Controls!$B$6,57),"mmm-yy") -> Oct-30 | BI3: =TEXT(EDATE(Controls!$B$6,58),"mmm-yy") -> Nov-30 | BJ3: =TEXT(EDATE(Controls!$B$6,59),"mmm-yy") -> Dec-30 | BK3: ="FY "&(YEAR(Controls!$B$6)+0) -> FY 2026 | BL3: ="FY "&(YEAR(Controls!$B$6)+1) -> FY 2027 | BM3: ="FY "&(YEAR(Controls!$B$6)+2) -> FY 2028 | BN3: ="FY "&(YEAR(Controls!$B$6)+3) -> FY 2029 | BO3: ="FY "&(YEAR(Controls!$B$6)+4) -> FY 2030 | BP3: ="FY "&(YEAR(Controls!$B$6)+5) -> FY 2031
A5: OPERATING ACTIVITIES (Indirect Method)
A6: Net Income | B6: $ | C6: ='P&L'!C50 -> -79653.406 | D6: ='P&L'!D50 -> -67297.431 | E6: ='P&L'!E50 -> -51580.351 | F6: ='P&L'!F50 -> -32593.118 | G6: ='P&L'!G50 -> -9951.7899 | H6: ='P&L'!H50 -> 12010.273 | I6: ='P&L'!I50 -> 34025.937 | J6: ='P&L'!J50 -> 58425.24 | ... BJ6: ='P&L'!BJ50 -> 3939205.5
A7: + Depreciation & Amortization | B7: $ | C7: =OpEx!C27 -> 0 | D7: =OpEx!D27 -> 0 | E7: =OpEx!E27 -> 0 | F7: =OpEx!F27 -> 0 | G7: =OpEx!G27 -> 0 | H7: =OpEx!H27 -> 0 | I7: =OpEx!I27 -> 138.88889 | J7: =OpEx!J27 -> 0 | ... BJ7: =OpEx!BJ27 -> 0
A8: – Change in Accounts Receivable | B8: $ | C8: =-Revenue!C96 -> -5082.9736 | D8: =-(Revenue!D96-Revenue!C96) -> -4869.323 | E8: =-(Revenue!E96-Revenue!D96) -> -4952.9115 | F8: =-(Revenue!F96-Revenue!E96) -> -5134.0275 | G8: =-(Revenue!G96-Revenue!F96) -> -5555.4029 | H8: =-(Revenue!H96-Revenue!G96) -> -5781.8408 | I8: =-(Revenue!I96-Revenue!H96) -> -6112.7565 | J8: =-(Revenue!J96-Revenue!I96) -> -6202.9344 | K8: =-(Revenue!K96-Revenue!J96) -> -6634.0441 | ... BJ8: =-(Revenue!BJ96-Revenue!BI96) -> 643.29855
A9: + Change in Accounts Payable | B9: $ | C9: ='P&L'!C41*0.5 -> 38771.25 | D9: =('P&L'!D41-'P&L'!C41)*0.5 -> 0 | E9: =('P&L'!E41-'P&L'!D41)*0.5 -> 0 | F9: =('P&L'!F41-'P&L'!E41)*0.5 -> 0 | G9: =('P&L'!G41-'P&L'!F41)*0.5 -> 0 | H9: =('P&L'!H41-'P&L'!G41)*0.5 -> 0 | I9: =('P&L'!I41-'P&L'!H41)*0.5 -> 0 | J9: =('P&L'!J41-'P&L'!I41)*0.5 -> 0 | K9: =('P&L'!K41-'P&L'!J41)*0.5 -> 0 | ... BJ9: =('P&L'!BJ41-'P&L'!BI41)*0.5 -> 0
A10: + Change in Deferred Revenue | B10: $ | C10: =Revenue!C101 -> 39689.324 | D10: =Revenue!D101-Revenue!C101 -> 75170.05 | E10: =Revenue!E101-Revenue!D101 -> 107997.21 | F10: =Revenue!F101-Revenue!E101 -> 138992.34 | G10: =Revenue!G101-Revenue!F101 -> 171734.51 | H10: =Revenue!H101-Revenue!G101 -> 202832.88 | I10: =Revenue!I101-Revenue!H101 -> 235169.51 | J10: =Revenue!J101-Revenue!I101 -> 263142.35 | K10: =Revenue!K101-Revenue!J101 -> 293237.54 | ... BJ10: =Revenue!BJ101-Revenue!BI101 -> 349783.84
A11: OPERATING CASH FLOW | B11: $ | C11: =C6+C7+C8+C9+C10 -> -6275.8052 | D11: =D6+D7+D8+D9+D10 -> 3003.296 | E11: =E6+E7+E8+E9+E10 -> 51463.949 | F11: =F6+F7+F8+F9+F10 -> 101265.19 | G11: =G6+G7+G8+G9+G10 -> 156227.31 | H11: =H6+H7+H8+H9+H10 -> 209061.31 | I11: =I6+I7+I8+I9+I10 -> 263221.58 | J11: =J6+J7+J8+J9+J10 -> 315364.65 | ... BJ11: =BJ6+BJ7+BJ8+BJ9+BJ10 -> 4289632.6 | BK11: =SUMPRODUCT((YEAR(EDATE(Controls!$B$6,COLUMN($C$1:$BJ$1)-COLUMN($C$1)))=YEAR(Controls!$B$6)+0)*(COLUMN($C$1:$BJ$1)-COLUMN($C$1)<Controls!$B$7)*$C$11:$BJ$11) -> 2961150.5 | BL11: =SUMPRODUCT((YEAR(EDATE(Controls!$B$6,COLUMN($C$1:$BJ$1)-COLUMN($C$1)))=YEAR(Controls!$B$6)+1)*(COLUMN($C$1:$BJ$1)-COLUMN($C$1)<Controls!$B$7)*$C$11:$BJ$11) -> 13751133 | BM11: =SUMPRODUCT((YEAR(EDATE(Controls!$B$6,COLUMN($C$1:$BJ$1)-COLUMN($C$1)))=YEAR(Controls!$B$6)+2)*(COLUMN($C$1:$BJ$1)-COLUMN($C$1)<Controls!$B$7)*$C$11:$BJ$11) -> 36465789 | BN11: =SUMPRODUCT((YEAR(EDATE(Controls!$B$6,COLUMN($C$1:$BJ$1)-COLUMN($C$1)))=YEAR(Controls!$B$6)+3)*(COLUMN($C$1:$BJ$1)-COLUMN($C$1)<Controls!$B$7)*$C$11:$BJ$11) -> 0 | BO11: =SUMPRODUCT((YEAR(EDATE(Controls!$B$6,COLUMN($C$1:$BJ$1)-COLUMN($C$1)))=YEAR(Controls!$B$6)+4)*(COLUMN($C$1:$BJ$1)-COLUMN($C$1)<Controls!$B$7)*$C$11:$BJ$11) -> 0 | BP11: =SUMPRODUCT((YEAR(EDATE(Controls!$B$6,COLUMN($C$1:$BJ$1)-COLUMN($C$1)))=YEAR(Controls!$B$6)+5)*(COLUMN($C$1:$BJ$1)-COLUMN($C$1)<Controls!$B$7)*$C$11:$BJ$11) -> 0
A13: INVESTING ACTIVITIES
A14: Capital Expenditures | B14: $ | C14: =-OpEx!C26 -> 0 | D14: =-OpEx!D26 -> 0 | E14: =-OpEx!E26 -> 0 | F14: =-OpEx!F26 -> 0 | G14: =-OpEx!G26 -> 0 | H14: =-OpEx!H26 -> 0 | I14: =-OpEx!I26 -> -5000 | J14: =-OpEx!J26 -> 0 | ... BJ14: =-OpEx!BJ26 -> 0
A15: INVESTING CASH FLOW | B15: $ | C15: =C14 -> 0 | D15: =D14 -> 0 | E15: =E14 -> 0 | F15: =F14 -> 0 | G15: =G14 -> 0 | H15: =H14 -> 0 | I15: =I14 -> -5000 | J15: =J14 -> 0 | ... BJ15: =BJ14 -> 0 | BK15: =SUMPRODUCT((YEAR(EDATE(Controls!$B$6,COLUMN($C$1:$BJ$1)-COLUMN($C$1)))=YEAR(Controls!$B$6)+0)*(COLUMN($C$1:$BJ$1)-COLUMN($C$1)<Controls!$B$7)*$C$15:$BJ$15) -> -5000 | BL15: =SUMPRODUCT((YEAR(EDATE(Controls!$B$6,COLUMN($C$1:$BJ$1)-COLUMN($C$1)))=YEAR(Controls!$B$6)+1)*(COLUMN($C$1:$BJ$1)-COLUMN($C$1)<Controls!$B$7)*$C$15:$BJ$15) -> 0 | BM15: =SUMPRODUCT((YEAR(EDATE(Controls!$B$6,COLUMN($C$1:$BJ$1)-COLUMN($C$1)))=YEAR(Controls!$B$6)+2)*(COLUMN($C$1:$BJ$1)-COLUMN($C$1)<Controls!$B$7)*$C$15:$BJ$15) -> 0 | BN15: =SUMPRODUCT((YEAR(EDATE(Controls!$B$6,COLUMN($C$1:$BJ$1)-COLUMN($C$1)))=YEAR(Controls!$B$6)+3)*(COLUMN($C$1:$BJ$1)-COLUMN($C$1)<Controls!$B$7)*$C$15:$BJ$15) -> 0 | BO15: =SUMPRODUCT((YEAR(EDATE(Controls!$B$6,COLUMN($C$1:$BJ$1)-COLUMN($C$1)))=YEAR(Controls!$B$6)+4)*(COLUMN($C$1:$BJ$1)-COLUMN($C$1)<Controls!$B$7)*$C$15:$BJ$15) -> 0 | BP15: =SUMPRODUCT((YEAR(EDATE(Controls!$B$6,COLUMN($C$1:$BJ$1)-COLUMN($C$1)))=YEAR(Controls!$B$6)+5)*(COLUMN($C$1:$BJ$1)-COLUMN($C$1)<Controls!$B$7)*$C$15:$BJ$15) -> 0
A17: FREE CASH FLOW & BURN
A18: FREE CASH FLOW | B18: $ | C18: =C11+C15 -> -6275.8052 | D18: =D11+D15 -> 3003.296 | E18: =E11+E15 -> 51463.949 | F18: =F11+F15 -> 101265.19 | G18: =G11+G15 -> 156227.31 | H18: =H11+H15 -> 209061.31 | I18: =I11+I15 -> 258221.58 | J18: =J11+J15 -> 315364.65 | ... BJ18: =BJ11+BJ15 -> 4289632.6 | BK18: =SUMPRODUCT((YEAR(EDATE(Controls!$B$6,COLUMN($C$1:$BJ$1)-COLUMN($C$1)))=YEAR(Controls!$B$6)+0)*(COLUMN($C$1:$BJ$1)-COLUMN($C$1)<Controls!$B$7)*$C$18:$BJ$18) -> 2956150.5 | BL18: =SUMPRODUCT((YEAR(EDATE(Controls!$B$6,COLUMN($C$1:$BJ$1)-COLUMN($C$1)))=YEAR(Controls!$B$6)+1)*(COLUMN($C$1:$BJ$1)-COLUMN($C$1)<Controls!$B$7)*$C$18:$BJ$18) -> 13751133 | BM18: =SUMPRODUCT((YEAR(EDATE(Controls!$B$6,COLUMN($C$1:$BJ$1)-COLUMN($C$1)))=YEAR(Controls!$B$6)+2)*(COLUMN($C$1:$BJ$1)-COLUMN($C$1)<Controls!$B$7)*$C$18:$BJ$18) -> 36465789 | BN18: =SUMPRODUCT((YEAR(EDATE(Controls!$B$6,COLUMN($C$1:$BJ$1)-COLUMN($C$1)))=YEAR(Controls!$B$6)+3)*(COLUMN($C$1:$BJ$1)-COLUMN($C$1)<Controls!$B$7)*$C$18:$BJ$18) -> 0 | BO18: =SUMPRODUCT((YEAR(EDATE(Controls!$B$6,COLUMN($C$1:$BJ$1)-COLUMN($C$1)))=YEAR(Controls!$B$6)+4)*(COLUMN($C$1:$BJ$1)-COLUMN($C$1)<Controls!$B$7)*$C$18:$BJ$18) -> 0 | BP18: =SUMPRODUCT((YEAR(EDATE(Controls!$B$6,COLUMN($C$1:$BJ$1)-COLUMN($C$1)))=YEAR(Controls!$B$6)+5)*(COLUMN($C$1:$BJ$1)-COLUMN($C$1)<Controls!$B$7)*$C$18:$BJ$18) -> 0
A19: Monthly Burn Rate (if FCF < 0) | B19: $ | C19: =IF(C18<0,-C18,0) -> 6275.8052 | D19: =IF(D18<0,-D18,0) -> 0 | E19: =IF(E18<0,-E18,0) -> 0 | F19: =IF(F18<0,-F18,0) -> 0 | G19: =IF(G18<0,-G18,0) -> 0 | H19: =IF(H18<0,-H18,0) -> 0 | I19: =IF(I18<0,-I18,0) -> 0 | J19: =IF(J18<0,-J18,0) -> 0 | ... BJ19: =IF(BJ18<0,-BJ18,0) -> 0 | BK19: =SUMPRODUCT((YEAR(EDATE(Controls!$B$6,COLUMN($C$1:$BJ$1)-COLUMN($C$1)))=YEAR(Controls!$B$6)+0)*(COLUMN($C$1:$BJ$1)-COLUMN($C$1)<Controls!$B$7)*$C$19:$BJ$19) -> 6275.8052 | BL19: =SUMPRODUCT((YEAR(EDATE(Controls!$B$6,COLUMN($C$1:$BJ$1)-COLUMN($C$1)))=YEAR(Controls!$B$6)+1)*(COLUMN($C$1:$BJ$1)-COLUMN($C$1)<Controls!$B$7)*$C$19:$BJ$19) -> 0 | BM19: =SUMPRODUCT((YEAR(EDATE(Controls!$B$6,COLUMN($C$1:$BJ$1)-COLUMN($C$1)))=YEAR(Controls!$B$6)+2)*(COLUMN($C$1:$BJ$1)-COLUMN($C$1)<Controls!$B$7)*$C$19:$BJ$19) -> 0 | BN19: =SUMPRODUCT((YEAR(EDATE(Controls!$B$6,COLUMN($C$1:$BJ$1)-COLUMN($C$1)))=YEAR(Controls!$B$6)+3)*(COLUMN($C$1:$BJ$1)-COLUMN($C$1)<Controls!$B$7)*$C$19:$BJ$19) -> 0 | BO19: =SUMPRODUCT((YEAR(EDATE(Controls!$B$6,COLUMN($C$1:$BJ$1)-COLUMN($C$1)))=YEAR(Controls!$B$6)+4)*(COLUMN($C$1:$BJ$1)-COLUMN($C$1)<Controls!$B$7)*$C$19:$BJ$19) -> 0 | BP19: =SUMPRODUCT((YEAR(EDATE(Controls!$B$6,COLUMN($C$1:$BJ$1)-COLUMN($C$1)))=YEAR(Controls!$B$6)+5)*(COLUMN($C$1:$BJ$1)-COLUMN($C$1)<Controls!$B$7)*$C$19:$BJ$19) -> 0
A20: FCF Margin % | B20: % | C20: =IFERROR(C18/'P&L'!C8,0) -> -0.45838596 | D20: =IFERROR(D18/'P&L'!D8,0) -> 0.11453314 | E20: =IFERROR(E18/'P&L'!E8,0) -> 1.2220109 | F20: =IFERROR(F18/'P&L'!F8,0) -> 1.6525975 | G20: =IFERROR(G18/'P&L'!G8,0) -> 1.8577985 | H20: =IFERROR(H18/'P&L'!H8,0) -> 1.8965368 | I20: =IFERROR(I18/'P&L'!I8,0) -> 1.8457411 | J20: =IFERROR(J18/'P&L'!J8,0) -> 1.8285208 | ... BJ20: =IFERROR(BJ18/'P&L'!BJ8,0) -> 0.81498126
A22: FINANCING ACTIVITIES
A23: Debt / Equity Raised | B23: $ | C23: =Controls!$B$20 -> 0 | D23: =0 -> 0 | E23: =0 -> 0 | F23: =0 -> 0 | G23: =0 -> 0 | H23: =0 -> 0 | I23: =0 -> 0 | J23: =0 -> 0 | K23: =0 -> 0 | ... BJ23: =0 -> 0
A25: NET CHANGE IN CASH | B25: $ | C25: =C11+C15+C23 -> -6275.8052 | D25: =D11+D15+D23 -> 3003.296 | E25: =E11+E15+E23 -> 51463.949 | F25: =F11+F15+F23 -> 101265.19 | G25: =G11+G15+G23 -> 156227.31 | H25: =H11+H15+H23 -> 209061.31 | I25: =I11+I15+I23 -> 258221.58 | J25: =J11+J15+J23 -> 315364.65 | ... BJ25: =BJ11+BJ15+BJ23 -> 4289632.6 | BK25: =SUMPRODUCT((YEAR(EDATE(Controls!$B$6,COLUMN($C$1:$BJ$1)-COLUMN($C$1)))=YEAR(Controls!$B$6)+0)*(COLUMN($C$1:$BJ$1)-COLUMN($C$1)<Controls!$B$7)*$C$25:$BJ$25) -> 2956150.5 | BL25: =SUMPRODUCT((YEAR(EDATE(Controls!$B$6,COLUMN($C$1:$BJ$1)-COLUMN($C$1)))=YEAR(Controls!$B$6)+1)*(COLUMN($C$1:$BJ$1)-COLUMN($C$1)<Controls!$B$7)*$C$25:$BJ$25) -> 13751133 | BM25: =SUMPRODUCT((YEAR(EDATE(Controls!$B$6,COLUMN($C$1:$BJ$1)-COLUMN($C$1)))=YEAR(Controls!$B$6)+2)*(COLUMN($C$1:$BJ$1)-COLUMN($C$1)<Controls!$B$7)*$C$25:$BJ$25) -> 36465789 | BN25: =SUMPRODUCT((YEAR(EDATE(Controls!$B$6,COLUMN($C$1:$BJ$1)-COLUMN($C$1)))=YEAR(Controls!$B$6)+3)*(COLUMN($C$1:$BJ$1)-COLUMN($C$1)<Controls!$B$7)*$C$25:$BJ$25) -> 0 | BO25: =SUMPRODUCT((YEAR(EDATE(Controls!$B$6,COLUMN($C$1:$BJ$1)-COLUMN($C$1)))=YEAR(Controls!$B$6)+4)*(COLUMN($C$1:$BJ$1)-COLUMN($C$1)<Controls!$B$7)*$C$25:$BJ$25) -> 0 | BP25: =SUMPRODUCT((YEAR(EDATE(Controls!$B$6,COLUMN($C$1:$BJ$1)-COLUMN($C$1)))=YEAR(Controls!$B$6)+5)*(COLUMN($C$1:$BJ$1)-COLUMN($C$1)<Controls!$B$7)*$C$25:$BJ$25) -> 0
A26: Beginning Cash Balance | B26: $ | C26: =Controls!$B$19 -> 1000000 | D26: =C27 -> 993724.19 | E26: =D27 -> 996727.49 | F26: =E27 -> 1048191.4 | G26: =F27 -> 1149456.6 | H26: =G27 -> 1305683.9 | I26: =H27 -> 1514745.3 | J26: =I27 -> 1772966.8 | K26: =J27 -> 2088331.5 | ... BJ26: =BI27 -> 1.5273865e+08
A27: Ending Cash Balance | B27: $ | C27: =C26+C25 -> 993724.19 | D27: =D26+D25 -> 996727.49 | E27: =E26+E25 -> 1048191.4 | F27: =F26+F25 -> 1149456.6 | G27: =G26+G25 -> 1305683.9 | H27: =H26+H25 -> 1514745.3 | I27: =I26+I25 -> 1772966.8 | J27: =J26+J25 -> 2088331.5 | ... BJ27: =BJ26+BJ25 -> 1.5702828e+08 | BK27: =IFERROR(LOOKUP(2,1/((YEAR(EDATE(Controls!$B$6,COLUMN($C$1:$BJ$1)-COLUMN($C$1)))=YEAR(Controls!$B$6)+0)*(COLUMN($C$1:$BJ$1)-COLUMN($C$1)<Controls!$B$7)),$C$27:$BJ$27),0) -> 3956150.5 | BL27: =IFERROR(LOOKUP(2,1/((YEAR(EDATE(Controls!$B$6,COLUMN($C$1:$BJ$1)-COLUMN($C$1)))=YEAR(Controls!$B$6)+1)*(COLUMN($C$1:$BJ$1)-COLUMN($C$1)<Controls!$B$7)),$C$27:$BJ$27),0) -> 17707284 | BM27: =IFERROR(LOOKUP(2,1/((YEAR(EDATE(Controls!$B$6,COLUMN($C$1:$BJ$1)-COLUMN($C$1)))=YEAR(Controls!$B$6)+2)*(COLUMN($C$1:$BJ$1)-COLUMN($C$1)<Controls!$B$7)),$C$27:$BJ$27),0) -> 54173073 | BN27: =IFERROR(LOOKUP(2,1/((YEAR(EDATE(Controls!$B$6,COLUMN($C$1:$BJ$1)-COLUMN($C$1)))=YEAR(Controls!$B$6)+3)*(COLUMN($C$1:$BJ$1)-COLUMN($C$1)<Controls!$B$7)),$C$27:$BJ$27),0) -> 0 | BO27: =IFERROR(LOOKUP(2,1/((YEAR(EDATE(Controls!$B$6,COLUMN($C$1:$BJ$1)-COLUMN($C$1)))=YEAR(Controls!$B$6)+4)*(COLUMN($C$1:$BJ$1)-COLUMN($C$1)<Controls!$B$7)),$C$27:$BJ$27),0) -> 0 | BP27: =IFERROR(LOOKUP(2,1/((YEAR(EDATE(Controls!$B$6,COLUMN($C$1:$BJ$1)-COLUMN($C$1)))=YEAR(Controls!$B$6)+5)*(COLUMN($C$1:$BJ$1)-COLUMN($C$1)<Controls!$B$7)),$C$27:$BJ$27),0) -> 0
A28: Runway (Months at Current Burn) | B28: mo | C28: =IFERROR(IF(C19>0,C27/C19,999),999) -> 158.3421 | D28: =IFERROR(IF(D19>0,D27/D19,999),999) -> 999 | E28: =IFERROR(IF(E19>0,E27/E19,999),999) -> 999 | F28: =IFERROR(IF(F19>0,F27/F19,999),999) -> 999 | G28: =IFERROR(IF(G19>0,G27/G19,999),999) -> 999 | H28: =IFERROR(IF(H19>0,H27/H19,999),999) -> 999 | I28: =IFERROR(IF(I19>0,I27/I19,999),999) -> 999 | J28: =IFERROR(IF(J19>0,J27/J19,999),999) -> 999 | ... BJ28: =IFERROR(IF(BJ19>0,BJ27/BJ19,999),999) -> 999 | BK28: =IFERROR(LOOKUP(2,1/((YEAR(EDATE(Controls!$B$6,COLUMN($C$1:$BJ$1)-COLUMN($C$1)))=YEAR(Controls!$B$6)+0)*(COLUMN($C$1:$BJ$1)-COLUMN($C$1)<Controls!$B$7)),$C$28:$BJ$28),0) -> 999 | BL28: =IFERROR(LOOKUP(2,1/((YEAR(EDATE(Controls!$B$6,COLUMN($C$1:$BJ$1)-COLUMN($C$1)))=YEAR(Controls!$B$6)+1)*(COLUMN($C$1:$BJ$1)-COLUMN($C$1)<Controls!$B$7)),$C$28:$BJ$28),0) -> 999 | BM28: =IFERROR(LOOKUP(2,1/((YEAR(EDATE(Controls!$B$6,COLUMN($C$1:$BJ$1)-COLUMN($C$1)))=YEAR(Controls!$B$6)+2)*(COLUMN($C$1:$BJ$1)-COLUMN($C$1)<Controls!$B$7)),$C$28:$BJ$28),0) -> 999 | BN28: =IFERROR(LOOKUP(2,1/((YEAR(EDATE(Controls!$B$6,COLUMN($C$1:$BJ$1)-COLUMN($C$1)))=YEAR(Controls!$B$6)+3)*(COLUMN($C$1:$BJ$1)-COLUMN($C$1)<Controls!$B$7)),$C$28:$BJ$28),0) -> 0 | BO28: =IFERROR(LOOKUP(2,1/((YEAR(EDATE(Controls!$B$6,COLUMN($C$1:$BJ$1)-COLUMN($C$1)))=YEAR(Controls!$B$6)+4)*(COLUMN($C$1:$BJ$1)-COLUMN($C$1)<Controls!$B$7)),$C$28:$BJ$28),0) -> 0 | BP28: =IFERROR(LOOKUP(2,1/((YEAR(EDATE(Controls!$B$6,COLUMN($C$1:$BJ$1)-COLUMN($C$1)))=YEAR(Controls!$B$6)+5)*(COLUMN($C$1:$BJ$1)-COLUMN($C$1)<Controls!$B$7)),$C$28:$BJ$28),0) -> 0

Sheet Balance Sheet
A1: BALANCE SHEET · End of Period
A3: Label | B3: Unit | C3: =TEXT(EDATE(Controls!$B$6,0),"mmm-yy") -> Jan-26 | D3: =TEXT(EDATE(Controls!$B$6,1),"mmm-yy") -> Feb-26 | E3: =TEXT(EDATE(Controls!$B$6,2),"mmm-yy") -> Mar-26 | F3: =TEXT(EDATE(Controls!$B$6,3),"mmm-yy") -> Apr-26 | G3: =TEXT(EDATE(Controls!$B$6,4),"mmm-yy") -> May-26 | H3: =TEXT(EDATE(Controls!$B$6,5),"mmm-yy") -> Jun-26 | I3: =TEXT(EDATE(Controls!$B$6,6),"mmm-yy") -> Jul-26 | J3: =TEXT(EDATE(Controls!$B$6,7),"mmm-yy") -> Aug-26 | K3: =TEXT(EDATE(Controls!$B$6,8),"mmm-yy") -> Sep-26 | L3: =TEXT(EDATE(Controls!$B$6,9),"mmm-yy") -> Oct-26 | M3: =TEXT(EDATE(Controls!$B$6,10),"mmm-yy") -> Nov-26 | N3: =TEXT(EDATE(Controls!$B$6,11),"mmm-yy") -> Dec-26 | O3: =TEXT(EDATE(Controls!$B$6,12),"mmm-yy") -> Jan-27 | P3: =TEXT(EDATE(Controls!$B$6,13),"mmm-yy") -> Feb-27 | Q3: =TEXT(EDATE(Controls!$B$6,14),"mmm-yy") -> Mar-27 | R3: =TEXT(EDATE(Controls!$B$6,15),"mmm-yy") -> Apr-27 | S3: =TEXT(EDATE(Controls!$B$6,16),"mmm-yy") -> May-27 | T3: =TEXT(EDATE(Controls!$B$6,17),"mmm-yy") -> Jun-27 | U3: =TEXT(EDATE(Controls!$B$6,18),"mmm-yy") -> Jul-27 | V3: =TEXT(EDATE(Controls!$B$6,19),"mmm-yy") -> Aug-27 | W3: =TEXT(EDATE(Controls!$B$6,20),"mmm-yy") -> Sep-27 | X3: =TEXT(EDATE(Controls!$B$6,21),"mmm-yy") -> Oct-27 | Y3: =TEXT(EDATE(Controls!$B$6,22),"mmm-yy") -> Nov-27 | Z3: =TEXT(EDATE(Controls!$B$6,23),"mmm-yy") -> Dec-27 | AA3: =TEXT(EDATE(Controls!$B$6,24),"mmm-yy") -> Jan-28 | AB3: =TEXT(EDATE(Controls!$B$6,25),"mmm-yy") -> Feb-28 | AC3: =TEXT(EDATE(Controls!$B$6,26),"mmm-yy") -> Mar-28 | AD3: =TEXT(EDATE(Controls!$B$6,27),"mmm-yy") -> Apr-28 | AE3: =TEXT(EDATE(Controls!$B$6,28),"mmm-yy") -> May-28 | AF3: =TEXT(EDATE(Controls!$B$6,29),"mmm-yy") -> Jun-28 | AG3: =TEXT(EDATE(Controls!$B$6,30),"mmm-yy") -> Jul-28 | AH3: =TEXT(EDATE(Controls!$B$6,31),"mmm-yy") -> Aug-28 | AI3: =TEXT(EDATE(Controls!$B$6,32),"mmm-yy") -> Sep-28 | AJ3: =TEXT(EDATE(Controls!$B$6,33),"mmm-yy") -> Oct-28 | AK3: =TEXT(EDATE(Controls!$B$6,34),"mmm-yy") -> Nov-28 | AL3: =TEXT(EDATE(Controls!$B$6,35),"mmm-yy") -> Dec-28 | AM3: =TEXT(EDATE(Controls!$B$6,36),"mmm-yy") -> Jan-29 | AN3: =TEXT(EDATE(Controls!$B$6,37),"mmm-yy") -> Feb-29 | AO3: =TEXT(EDATE(Controls!$B$6,38),"mmm-yy") -> Mar-29 | AP3: =TEXT(EDATE(Controls!$B$6,39),"mmm-yy") -> Apr-29 | AQ3: =TEXT(EDATE(Controls!$B$6,40),"mmm-yy") -> May-29 | AR3: =TEXT(EDATE(Controls!$B$6,41),"mmm-yy") -> Jun-29 | AS3: =TEXT(EDATE(Controls!$B$6,42),"mmm-yy") -> Jul-29 | AT3: =TEXT(EDATE(Controls!$B$6,43),"mmm-yy") -> Aug-29 | AU3: =TEXT(EDATE(Controls!$B$6,44),"mmm-yy") -> Sep-29 | AV3: =TEXT(EDATE(Controls!$B$6,45),"mmm-yy") -> Oct-29 | AW3: =TEXT(EDATE(Controls!$B$6,46),"mmm-yy") -> Nov-29 | AX3: =TEXT(EDATE(Controls!$B$6,47),"mmm-yy") -> Dec-29 | AY3: =TEXT(EDATE(Controls!$B$6,48),"mmm-yy") -> Jan-30 | AZ3: =TEXT(EDATE(Controls!$B$6,49),"mmm-yy") -> Feb-30 | BA3: =TEXT(EDATE(Controls!$B$6,50),"mmm-yy") -> Mar-30 | BB3: =TEXT(EDATE(Controls!$B$6,51),"mmm-yy") -> Apr-30 | BC3: =TEXT(EDATE(Controls!$B$6,52),"mmm-yy") -> May-30 | BD3: =TEXT(EDATE(Controls!$B$6,53),"mmm-yy") -> Jun-30 | BE3: =TEXT(EDATE(Controls!$B$6,54),"mmm-yy") -> Jul-30 | BF3: =TEXT(EDATE(Controls!$B$6,55),"mmm-yy") -> Aug-30 | BG3: =TEXT(EDATE(Controls!$B$6,56),"mmm-yy") -> Sep-30 | BH3: =TEXT(EDATE(Controls!$B$6,57),"mmm-yy") -> Oct-30 | BI3: =TEXT(EDATE(Controls!$B$6,58),"mmm-yy") -> Nov-30 | BJ3: =TEXT(EDATE(Controls!$B$6,59),"mmm-yy") -> Dec-30 | BK3: ="FY "&(YEAR(Controls!$B$6)+0) -> FY 2026 | BL3: ="FY "&(YEAR(Controls!$B$6)+1) -> FY 2027 | BM3: ="FY "&(YEAR(Controls!$B$6)+2) -> FY 2028 | BN3: ="FY "&(YEAR(Controls!$B$6)+3) -> FY 2029 | BO3: ="FY "&(YEAR(Controls!$B$6)+4) -> FY 2030 | BP3: ="FY "&(YEAR(Controls!$B$6)+5) -> FY 2031
A5: ASSETS
A6: Cash & Cash Equivalents | B6: $ | C6: ='Cash Flow'!C27 -> 993724.19 | D6: ='Cash Flow'!D27 -> 996727.49 | E6: ='Cash Flow'!E27 -> 1048191.4 | F6: ='Cash Flow'!F27 -> 1149456.6 | G6: ='Cash Flow'!G27 -> 1305683.9 | H6: ='Cash Flow'!H27 -> 1514745.3 | I6: ='Cash Flow'!I27 -> 1772966.8 | J6: ='Cash Flow'!J27 -> 2088331.5 | ... BJ6: ='Cash Flow'!BJ27 -> 1.5702828e+08 | BK6: =IFERROR(LOOKUP(2,1/((YEAR(EDATE(Controls!$B$6,COLUMN($C$1:$BJ$1)-COLUMN($C$1)))=YEAR(Controls!$B$6)+0)*(COLUMN($C$1:$BJ$1)-COLUMN($C$1)<Controls!$B$7)),$C$6:$BJ$6),0) -> 3956150.5 | BL6: =IFERROR(LOOKUP(2,1/((YEAR(EDATE(Controls!$B$6,COLUMN($C$1:$BJ$1)-COLUMN($C$1)))=YEAR(Controls!$B$6)+1)*(COLUMN($C$1:$BJ$1)-COLUMN($C$1)<Controls!$B$7)),$C$6:$BJ$6),0) -> 17707284 | BM6: =IFERROR(LOOKUP(2,1/((YEAR(EDATE(Controls!$B$6,COLUMN($C$1:$BJ$1)-COLUMN($C$1)))=YEAR(Controls!$B$6)+2)*(COLUMN($C$1:$BJ$1)-COLUMN($C$1)<Controls!$B$7)),$C$6:$BJ$6),0) -> 54173073 | BN6: =IFERROR(LOOKUP(2,1/((YEAR(EDATE(Controls!$B$6,COLUMN($C$1:$BJ$1)-COLUMN($C$1)))=YEAR(Controls!$B$6)+3)*(COLUMN($C$1:$BJ$1)-COLUMN($C$1)<Controls!$B$7)),$C$6:$BJ$6),0) -> 0 | BO6: =IFERROR(LOOKUP(2,1/((YEAR(EDATE(Controls!$B$6,COLUMN($C$1:$BJ$1)-COLUMN($C$1)))=YEAR(Controls!$B$6)+4)*(COLUMN($C$1:$BJ$1)-COLUMN($C$1)<Controls!$B$7)),$C$6:$BJ$6),0) -> 0 | BP6: =IFERROR(LOOKUP(2,1/((YEAR(EDATE(Controls!$B$6,COLUMN($C$1:$BJ$1)-COLUMN($C$1)))=YEAR(Controls!$B$6)+5)*(COLUMN($C$1:$BJ$1)-COLUMN($C$1)<Controls!$B$7)),$C$6:$BJ$6),0) -> 0
A7: Accounts Receivable | B7: $ | C7: =Revenue!C96 -> 5082.9736 | D7: =Revenue!D96 -> 9952.2966 | E7: =Revenue!E96 -> 14905.208 | F7: =Revenue!F96 -> 20039.236 | G7: =Revenue!G96 -> 25594.639 | H7: =Revenue!H96 -> 31376.479 | I7: =Revenue!I96 -> 37489.236 | J7: =Revenue!J96 -> 43692.17 | ... BJ7: =Revenue!BJ96 -> 467590.83 | BK7: =IFERROR(LOOKUP(2,1/((YEAR(EDATE(Controls!$B$6,COLUMN($C$1:$BJ$1)-COLUMN($C$1)))=YEAR(Controls!$B$6)+0)*(COLUMN($C$1:$BJ$1)-COLUMN($C$1)<Controls!$B$7)),$C$7:$BJ$7),0) -> 73007.711 | BL7: =IFERROR(LOOKUP(2,1/((YEAR(EDATE(Controls!$B$6,COLUMN($C$1:$BJ$1)-COLUMN($C$1)))=YEAR(Controls!$B$6)+1)*(COLUMN($C$1:$BJ$1)-COLUMN($C$1)<Controls!$B$7)),$C$7:$BJ$7),0) -> 217459.85 | BM7: =IFERROR(LOOKUP(2,1/((YEAR(EDATE(Controls!$B$6,COLUMN($C$1:$BJ$1)-COLUMN($C$1)))=YEAR(Controls!$B$6)+2)*(COLUMN($C$1:$BJ$1)-COLUMN($C$1)<Controls!$B$7)),$C$7:$BJ$7),0) -> 524926.17 | BN7: =IFERROR(LOOKUP(2,1/((YEAR(EDATE(Controls!$B$6,COLUMN($C$1:$BJ$1)-COLUMN($C$1)))=YEAR(Controls!$B$6)+3)*(COLUMN($C$1:$BJ$1)-COLUMN($C$1)<Controls!$B$7)),$C$7:$BJ$7),0) -> 0 | BO7: =IFERROR(LOOKUP(2,1/((YEAR(EDATE(Controls!$B$6,COLUMN($C$1:$BJ$1)-COLUMN($C$1)))=YEAR(Controls!$B$6)+4)*(COLUMN($C$1:$BJ$1)-COLUMN($C$1)<Controls!$B$7)),$C$7:$BJ$7),0) -> 0 | BP7: =IFERROR(LOOKUP(2,1/((YEAR(EDATE(Controls!$B$6,COLUMN($C$1:$BJ$1)-COLUMN($C$1)))=YEAR(Controls!$B$6)+5)*(COLUMN($C$1:$BJ$1)-COLUMN($C$1)<Controls!$B$7)),$C$7:$BJ$7),0) -> 0
A8: Prepaid & Other Current Assets | B8: $ | C8: =0 -> 0 | D8: =0 -> 0 | E8: =0 -> 0 | F8: =0 -> 0 | G8: =0 -> 0 | H8: =0 -> 0 | I8: =0 -> 0 | J8: =0 -> 0 | ... BJ8: =0 -> 0 | BK8: =IFERROR(LOOKUP(2,1/((YEAR(EDATE(Controls!$B$6,COLUMN($C$1:$BJ$1)-COLUMN($C$1)))=YEAR(Controls!$B$6)+0)*(COLUMN($C$1:$BJ$1)-COLUMN($C$1)<Controls!$B$7)),$C$8:$BJ$8),0) -> 0 | BL8: =IFERROR(LOOKUP(2,1/((YEAR(EDATE(Controls!$B$6,COLUMN($C$1:$BJ$1)-COLUMN($C$1)))=YEAR(Controls!$B$6)+1)*(COLUMN($C$1:$BJ$1)-COLUMN($C$1)<Controls!$B$7)),$C$8:$BJ$8),0) -> 0 | BM8: =IFERROR(LOOKUP(2,1/((YEAR(EDATE(Controls!$B$6,COLUMN($C$1:$BJ$1)-COLUMN($C$1)))=YEAR(Controls!$B$6)+2)*(COLUMN($C$1:$BJ$1)-COLUMN($C$1)<Controls!$B$7)),$C$8:$BJ$8),0) -> 0 | BN8: =IFERROR(LOOKUP(2,1/((YEAR(EDATE(Controls!$B$6,COLUMN($C$1:$BJ$1)-COLUMN($C$1)))=YEAR(Controls!$B$6)+3)*(COLUMN($C$1:$BJ$1)-COLUMN($C$1)<Controls!$B$7)),$C$8:$BJ$8),0) -> 0 | BO8: =IFERROR(LOOKUP(2,1/((YEAR(EDATE(Controls!$B$6,COLUMN($C$1:$BJ$1)-COLUMN($C$1)))=YEAR(Controls!$B$6)+4)*(COLUMN($C$1:$BJ$1)-COLUMN($C$1)<Controls!$B$7)),$C$8:$BJ$8),0) -> 0 | BP8: =IFERROR(LOOKUP(2,1/((YEAR(EDATE(Controls!$B$6,COLUMN($C$1:$BJ$1)-COLUMN($C$1)))=YEAR(Controls!$B$6)+5)*(COLUMN($C$1:$BJ$1)-COLUMN($C$1)<Controls!$B$7)),$C$8:$BJ$8),0) -> 0
A9: Total Current Assets | B9: $ | C9: =C6+C7+C8 -> 998807.17 | D9: =D6+D7+D8 -> 1006679.8 | E9: =E6+E7+E8 -> 1063096.6 | F9: =F6+F7+F8 -> 1169495.9 | G9: =G6+G7+G8 -> 1331278.6 | H9: =H6+H7+H8 -> 1546121.7 | I9: =I6+I7+I8 -> 1810456.1 | J9: =J6+J7+J8 -> 2132023.7 | ... BJ9: =BJ6+BJ7+BJ8 -> 1.5749587e+08 | BK9: =IFERROR(LOOKUP(2,1/((YEAR(EDATE(Controls!$B$6,COLUMN($C$1:$BJ$1)-COLUMN($C$1)))=YEAR(Controls!$B$6)+0)*(COLUMN($C$1:$BJ$1)-COLUMN($C$1)<Controls!$B$7)),$C$9:$BJ$9),0) -> 4029158.2 | BL9: =IFERROR(LOOKUP(2,1/((YEAR(EDATE(Controls!$B$6,COLUMN($C$1:$BJ$1)-COLUMN($C$1)))=YEAR(Controls!$B$6)+1)*(COLUMN($C$1:$BJ$1)-COLUMN($C$1)<Controls!$B$7)),$C$9:$BJ$9),0) -> 17924744 | BM9: =IFERROR(LOOKUP(2,1/((YEAR(EDATE(Controls!$B$6,COLUMN($C$1:$BJ$1)-COLUMN($C$1)))=YEAR(Controls!$B$6)+2)*(COLUMN($C$1:$BJ$1)-COLUMN($C$1)<Controls!$B$7)),$C$9:$BJ$9),0) -> 54697999 | BN9: =IFERROR(LOOKUP(2,1/((YEAR(EDATE(Controls!$B$6,COLUMN($C$1:$BJ$1)-COLUMN($C$1)))=YEAR(Controls!$B$6)+3)*(COLUMN($C$1:$BJ$1)-COLUMN($C$1)<Controls!$B$7)),$C$9:$BJ$9),0) -> 0 | BO9: =IFERROR(LOOKUP(2,1/((YEAR(EDATE(Controls!$B$6,COLUMN($C$1:$BJ$1)-COLUMN($C$1)))=YEAR(Controls!$B$6)+4)*(COLUMN($C$1:$BJ$1)-COLUMN($C$1)<Controls!$B$7)),$C$9:$BJ$9),0) -> 0 | BP9: =IFERROR(LOOKUP(2,1/((YEAR(EDATE(Controls!$B$6,COLUMN($C$1:$BJ$1)-COLUMN($C$1)))=YEAR(Controls!$B$6)+5)*(COLUMN($C$1:$BJ$1)-COLUMN($C$1)<Controls!$B$7)),$C$9:$BJ$9),0) -> 0
A11: PP&E, Gross | B11: $ | C11: =OpEx!C26 -> 0 | D11: =C11+OpEx!D26 -> 0 | E11: =D11+OpEx!E26 -> 0 | F11: =E11+OpEx!F26 -> 0 | G11: =F11+OpEx!G26 -> 0 | H11: =G11+OpEx!H26 -> 0 | I11: =H11+OpEx!I26 -> 5000 | J11: =I11+OpEx!J26 -> 5000 | K11: =J11+OpEx!K26 -> 5000 | ... BJ11: =BI11+OpEx!BJ26 -> 5000 | BK11: =IFERROR(LOOKUP(2,1/((YEAR(EDATE(Controls!$B$6,COLUMN($C$1:$BJ$1)-COLUMN($C$1)))=YEAR(Controls!$B$6)+0)*(COLUMN($C$1:$BJ$1)-COLUMN($C$1)<Controls!$B$7)),$C$11:$BJ$11),0) -> 5000 | BL11: =IFERROR(LOOKUP(2,1/((YEAR(EDATE(Controls!$B$6,COLUMN($C$1:$BJ$1)-COLUMN($C$1)))=YEAR(Controls!$B$6)+1)*(COLUMN($C$1:$BJ$1)-COLUMN($C$1)<Controls!$B$7)),$C$11:$BJ$11),0) -> 5000 | BM11: =IFERROR(LOOKUP(2,1/((YEAR(EDATE(Controls!$B$6,COLUMN($C$1:$BJ$1)-COLUMN($C$1)))=YEAR(Controls!$B$6)+2)*(COLUMN($C$1:$BJ$1)-COLUMN($C$1)<Controls!$B$7)),$C$11:$BJ$11),0) -> 5000 | BN11: =IFERROR(LOOKUP(2,1/((YEAR(EDATE(Controls!$B$6,COLUMN($C$1:$BJ$1)-COLUMN($C$1)))=YEAR(Controls!$B$6)+3)*(COLUMN($C$1:$BJ$1)-COLUMN($C$1)<Controls!$B$7)),$C$11:$BJ$11),0) -> 0 | BO11: =IFERROR(LOOKUP(2,1/((YEAR(EDATE(Controls!$B$6,COLUMN($C$1:$BJ$1)-COLUMN($C$1)))=YEAR(Controls!$B$6)+4)*(COLUMN($C$1:$BJ$1)-COLUMN($C$1)<Controls!$B$7)),$C$11:$BJ$11),0) -> 0 | BP11: =IFERROR(LOOKUP(2,1/((YEAR(EDATE(Controls!$B$6,COLUMN($C$1:$BJ$1)-COLUMN($C$1)))=YEAR(Controls!$B$6)+5)*(COLUMN($C$1:$BJ$1)-COLUMN($C$1)<Controls!$B$7)),$C$11:$BJ$11),0) -> 0
A12: Accumulated Depreciation | B12: $ | C12: =-OpEx!C27 -> 0 | D12: =C12-OpEx!D27 -> 0 | E12: =D12-OpEx!E27 -> 0 | F12: =E12-OpEx!F27 -> 0 | G12: =F12-OpEx!G27 -> 0 | H12: =G12-OpEx!H27 -> 0 | I12: =H12-OpEx!I27 -> -138.88889 | J12: =I12-OpEx!J27 -> -138.88889 | K12: =J12-OpEx!K27 -> -138.88889 | ... BJ12: =BI12-OpEx!BJ27 -> -138.88889 | BK12: =IFERROR(LOOKUP(2,1/((YEAR(EDATE(Controls!$B$6,COLUMN($C$1:$BJ$1)-COLUMN($C$1)))=YEAR(Controls!$B$6)+0)*(COLUMN($C$1:$BJ$1)-COLUMN($C$1)<Controls!$B$7)),$C$12:$BJ$12),0) -> -138.88889 | BL12: =IFERROR(LOOKUP(2,1/((YEAR(EDATE(Controls!$B$6,COLUMN($C$1:$BJ$1)-COLUMN($C$1)))=YEAR(Controls!$B$6)+1)*(COLUMN($C$1:$BJ$1)-COLUMN($C$1)<Controls!$B$7)),$C$12:$BJ$12),0) -> -138.88889 | BM12: =IFERROR(LOOKUP(2,1/((YEAR(EDATE(Controls!$B$6,COLUMN($C$1:$BJ$1)-COLUMN($C$1)))=YEAR(Controls!$B$6)+2)*(COLUMN($C$1:$BJ$1)-COLUMN($C$1)<Controls!$B$7)),$C$12:$BJ$12),0) -> -138.88889 | BN12: =IFERROR(LOOKUP(2,1/((YEAR(EDATE(Controls!$B$6,COLUMN($C$1:$BJ$1)-COLUMN($C$1)))=YEAR(Controls!$B$6)+3)*(COLUMN($C$1:$BJ$1)-COLUMN($C$1)<Controls!$B$7)),$C$12:$BJ$12),0) -> 0 | BO12: =IFERROR(LOOKUP(2,1/((YEAR(EDATE(Controls!$B$6,COLUMN($C$1:$BJ$1)-COLUMN($C$1)))=YEAR(Controls!$B$6)+4)*(COLUMN($C$1:$BJ$1)-COLUMN($C$1)<Controls!$B$7)),$C$12:$BJ$12),0) -> 0 | BP12: =IFERROR(LOOKUP(2,1/((YEAR(EDATE(Controls!$B$6,COLUMN($C$1:$BJ$1)-COLUMN($C$1)))=YEAR(Controls!$B$6)+5)*(COLUMN($C$1:$BJ$1)-COLUMN($C$1)<Controls!$B$7)),$C$12:$BJ$12),0) -> 0
A13: PP&E, Net | B13: $ | C13: =C11+C12 -> 0 | D13: =D11+D12 -> 0 | E13: =E11+E12 -> 0 | F13: =F11+F12 -> 0 | G13: =G11+G12 -> 0 | H13: =H11+H12 -> 0 | I13: =I11+I12 -> 4861.1111 | J13: =J11+J12 -> 4861.1111 | ... BJ13: =BJ11+BJ12 -> 4861.1111 | BK13: =IFERROR(LOOKUP(2,1/((YEAR(EDATE(Controls!$B$6,COLUMN($C$1:$BJ$1)-COLUMN($C$1)))=YEAR(Controls!$B$6)+0)*(COLUMN($C$1:$BJ$1)-COLUMN($C$1)<Controls!$B$7)),$C$13:$BJ$13),0) -> 4861.1111 | BL13: =IFERROR(LOOKUP(2,1/((YEAR(EDATE(Controls!$B$6,COLUMN($C$1:$BJ$1)-COLUMN($C$1)))=YEAR(Controls!$B$6)+1)*(COLUMN($C$1:$BJ$1)-COLUMN($C$1)<Controls!$B$7)),$C$13:$BJ$13),0) -> 4861.1111 | BM13: =IFERROR(LOOKUP(2,1/((YEAR(EDATE(Controls!$B$6,COLUMN($C$1:$BJ$1)-COLUMN($C$1)))=YEAR(Controls!$B$6)+2)*(COLUMN($C$1:$BJ$1)-COLUMN($C$1)<Controls!$B$7)),$C$13:$BJ$13),0) -> 4861.1111 | BN13: =IFERROR(LOOKUP(2,1/((YEAR(EDATE(Controls!$B$6,COLUMN($C$1:$BJ$1)-COLUMN($C$1)))=YEAR(Controls!$B$6)+3)*(COLUMN($C$1:$BJ$1)-COLUMN($C$1)<Controls!$B$7)),$C$13:$BJ$13),0) -> 0 | BO13: =IFERROR(LOOKUP(2,1/((YEAR(EDATE(Controls!$B$6,COLUMN($C$1:$BJ$1)-COLUMN($C$1)))=YEAR(Controls!$B$6)+4)*(COLUMN($C$1:$BJ$1)-COLUMN($C$1)<Controls!$B$7)),$C$13:$BJ$13),0) -> 0 | BP13: =IFERROR(LOOKUP(2,1/((YEAR(EDATE(Controls!$B$6,COLUMN($C$1:$BJ$1)-COLUMN($C$1)))=YEAR(Controls!$B$6)+5)*(COLUMN($C$1:$BJ$1)-COLUMN($C$1)<Controls!$B$7)),$C$13:$BJ$13),0) -> 0
A14: TOTAL ASSETS | B14: $ | C14: =C9+C13 -> 998807.17 | D14: =D9+D13 -> 1006679.8 | E14: =E9+E13 -> 1063096.6 | F14: =F9+F13 -> 1169495.9 | G14: =G9+G13 -> 1331278.6 | H14: =H9+H13 -> 1546121.7 | I14: =I9+I13 -> 1815317.2 | J14: =J9+J13 -> 2136884.8 | ... BJ14: =BJ9+BJ13 -> 1.5750073e+08 | BK14: =IFERROR(LOOKUP(2,1/((YEAR(EDATE(Controls!$B$6,COLUMN($C$1:$BJ$1)-COLUMN($C$1)))=YEAR(Controls!$B$6)+0)*(COLUMN($C$1:$BJ$1)-COLUMN($C$1)<Controls!$B$7)),$C$14:$BJ$14),0) -> 4034019.3 | BL14: =IFERROR(LOOKUP(2,1/((YEAR(EDATE(Controls!$B$6,COLUMN($C$1:$BJ$1)-COLUMN($C$1)))=YEAR(Controls!$B$6)+1)*(COLUMN($C$1:$BJ$1)-COLUMN($C$1)<Controls!$B$7)),$C$14:$BJ$14),0) -> 17929605 | BM14: =IFERROR(LOOKUP(2,1/((YEAR(EDATE(Controls!$B$6,COLUMN($C$1:$BJ$1)-COLUMN($C$1)))=YEAR(Controls!$B$6)+2)*(COLUMN($C$1:$BJ$1)-COLUMN($C$1)<Controls!$B$7)),$C$14:$BJ$14),0) -> 54702860 | BN14: =IFERROR(LOOKUP(2,1/((YEAR(EDATE(Controls!$B$6,COLUMN($C$1:$BJ$1)-COLUMN($C$1)))=YEAR(Controls!$B$6)+3)*(COLUMN($C$1:$BJ$1)-COLUMN($C$1)<Controls!$B$7)),$C$14:$BJ$14),0) -> 0 | BO14: =IFERROR(LOOKUP(2,1/((YEAR(EDATE(Controls!$B$6,COLUMN($C$1:$BJ$1)-COLUMN($C$1)))=YEAR(Controls!$B$6)+4)*(COLUMN($C$1:$BJ$1)-COLUMN($C$1)<Controls!$B$7)),$C$14:$BJ$14),0) -> 0 | BP14: =IFERROR(LOOKUP(2,1/((YEAR(EDATE(Controls!$B$6,COLUMN($C$1:$BJ$1)-COLUMN($C$1)))=YEAR(Controls!$B$6)+5)*(COLUMN($C$1:$BJ$1)-COLUMN($C$1)<Controls!$B$7)),$C$14:$BJ$14),0) -> 0
A16: LIABILITIES
